Workbook
Name _Hlk318882101: 'ACS Tariff classes & tariffs'!#REF!
Name current_pricing_year: '[1]Model builder'!$E$23
Name JS_final_round: [1]JS!$C$25:$L$34
Name JS_final_round_C: [1]JS!$C$24:$L$24
Name ProdCodes: 'ACS Price List'!$D$13:$G$180

Sheet ACS Price List
B7: Ergon Energy Corporation Limited
B8: 2017-18 Price List for Alternative Control Services | H8: Key: | J8: These services are subject to an additional layer of price regulation at the jurisdictional level, through Schedule 8 of the Electricity Regulation 2006. Even though the national economic regulator (the AER) has approved a higher price that EECL can charge for this service, the Queensland Government has stipulated a (lower) maximum price EECL is able to charge customers in EECL's supply area for these services.
B9: Release 2.0 - 1 December 2017 | D9: Release 0.0 - 1 July 2017 | F9: Release 0.0 - 1 July 2017 | J9: These services are subject to an additional layer of price regulation at the jurisdictional level, through Schedule 8 of the Electricity Regulation 2006. Even though the national economic regulator (the AER) has approved a higher price that EECL can charge for this service, the Queensland Government has stipulated that long rural / isolated customers in EECL's supply area are only able to be charged for these services at the same rate as an urban / short rural customer.
A12: Ref | B12: Service | C12: Service description | D12: Product Codes | H12: Ellipse Cost Code | I12: Urban/short rural feeder price | K12: Long rural/isolated feeder price | M12: AER classification | N12: Notes | O12: B2B Retailer only | P12: Form "A" Required | Q12: B2B Service Order Type
D13: Urban | E13: Short rural | F13: Long rural | G13: Isolated | I13: GST Excl | J13: GST Incl | K13: GST Excl | L13: GST Incl | O13: Customer
A14: Fee Based and Quoted Services
B15: Pre-Connection Services
A16: 1 | B16: Application fee - Basic or standard connection | C16: Services associated with assessing an application requesting a connection to be made (or altered) between Ergon Energy's network and the customer’s installation, and the preparation of a compliant basic or standard connection offer. Applies to small customers classified as a Standard Asset Customer (SAC), as per Ergon Energy's pricing proposal. | D16: APFSAC | H16: 8000 | I16: 888.4 | J16: =I16*1.1 -> 977.24 | K16: =I16 -> 888.4 | L16: =J16 -> 977.24 | M16: Fee Based Service | N16: Fixed fee applies | O16: Customer | P16: No | Q16: N/A
A17: 2 | B17: Application fee - Basic or standard connection - Micro-embedded generators | C17: Services associated with assessing a micro-embedded generator application requesting a connection to be made (or altered) between Ergon Energy's network and the customer’s installation, and the preparation of a compliant basic or standard connection offer. Applies to micro-embedded generators only (a subset of Standard Asset Customers, as per Ergon Energy's pricing proposal). No technical assessment required. | D17: APFMEG | H17: 8001 | I17: 48.6 | J17: =I17*1.1 -> 53.46 | K17: =I17 -> 48.6 | L17: =J17 -> 53.46 | M17: Fee Based Service | N17: Fixed fee applies | O17: Customer | P17: No | Q17: N/A
A18: 3 | B18: Application fee - Basic or standard connection - Micro-embedded generators - Technical assessment required | C18: Services associated with assessing a micro-embedded generator application requesting a connection to be made (or altered) between Ergon Energy's network and the customer’s installation, and the preparation of a compliant basic or standard connection offer. Applies to micro-embedded generators only (a subset of Standard Asset Customers, as per Ergon Energy's pricing proposal), where a technical assessment is required to be undertaken by Ergon Energy. | D18: APFMTA | H18: 8002 | I18: 220.7 | J18: =I18*1.1 -> 242.77 | K18: =I18 -> 220.7 | L18: =J18 -> 242.77 | M18: Fee Based Service | N18: Fixed fee applies | O18: Customer | P18: No | Q18: N/A
A19: 4 | B19: Application fee - Real estate development connection | C19: Services associated with assessing an application requesting a connection to be made between Ergon Energy's network and a real estate developer's installation, and the preparation of a compliant connection offer. Includes works carried out by contractors and/or Ergon Energy. | D19: APFRED | H19: 8003 | I19: 930.2 | J19: =I19*1.1 -> 1023.22 | K19: =I19 -> 930.2 | L19: =J19 -> 1023.22 | M19: Fee Based Service | N19: Fixed fee applies | O19: Customer | P19: No | Q19: N/A
A20: 5 | B20: Protection and Power Quality assessment prior to connection | C20: Evaluation of application protection design for completeness against engineering connection standard. Study of Power Quality issues including Flicker, Harmonics and DC voltage injection. | D20: PPQA | H20: 8004 | I20: 1376.7 | J20: =I20*1.1 -> 1514.37 | K20: =I20 -> 1376.7 | L20: =J20 -> 1514.37 | M20: Fee Based Service | N20: Fixed fee applies | O20: Customer | P20: No | Q20: N/A
A21: 40 | B21: Application fee - Negotiated connection | C21: Services associated with assessing an application requesting a connection to be made (or altered) between Ergon Energy's network and the customer’s installation, and the costs associated with negotiating and preparing a negotiated connection offer. Applies to small customers classified as a Standard Asset Customer (SAC), as per Ergon Energy's pricing proposal, with the exception of micro-embedded generators. | D21: As Quoted | H21: 8005 | I21: POA | K21: POA | M21: Quoted Service | N21: Price on application | O21: Customer | P21: No | Q21: N/A
A22: 41 | B22: Application fee - Negotiated connection - Micro-embedded generators | C22: Services associated with assessing a micro-embedded generator application requesting a connection to be made (or altered) between Ergon Energy's network and the customer’s installation, and the costs associated with negotiating and preparing a negotiated connection offer. Applies to micro-embedded generators only (a subset of SAC, as per Ergon Energy's pricing proposal). | D22: As Quoted | H22: 8006 | I22: POA | K22: POA | M22: Quoted Service | N22: Price on application | O22: Customer | P22: No | Q22: N/A
A23: 42 | B23: Application fee - Negotiated - Major customer connection | C23: Services associated with assessing a major customer connection application requesting a connection to be made (or altered) between Ergon Energy's network and the customer’s installation, and the costs associated with negotiating and preparing a compliant negotiated connection offer. Applies to major customers classified as an Individually Calculated Customer (ICC), Connection Asset Customer (CAC) or Embedded Generator (EG), as per Ergon Energy's pricing proposal. | D23: As Quoted | H23: 8007 | I23: POA | K23: POA | M23: Quoted Service | N23: Price on application | O23: Customer | P23: No | Q23: N/A
A24: 43 | B24: Carrying out planning studies and analysis relating to connection applications | C24: Services associated with carrying out additional planning studies and analysis on the distribution system which are reasonably required to assess a small customer or real estate development connection application. Excludes planning studies and analysis that would otherwise be required for distributor purposes or for the efficient management of the shared network. Applies to small customers classified as a Standard Asset Customer, as per Ergon Energy's pricing proposal (including micro-embedded generators), and real estate developers. | D24: As Quoted | H24: 8008 | I24: POA | K24: POA | M24: Quoted Service | N24: Price on application | O24: Customer | P24: No | Q24: N/A
A25: 44 | B25: Feasibility and concept scoping, including planning and design, for major customer connections | C25: Detailed design and advice for major customer connections for the selected (preferred) connection option. This includes shared network planning and design works incurred during the feasibility and concept scoping phases (i.e. before the connection offer has been accepted) (where applicable). | D25: As Quoted | H25: 8009 | I25: POA | K25: POA | M25: Quoted Service | N25: Price on application | O25: Customer | P25: No | Q25: N/A
A26: 45 | B26: Tender process | C26: Applies where Ergon Energy conducts a tender process on behalf of a connection applicant to procure connection services that can be provided by a third party, or where the connection applicant conducts a tender process and requires assistance from Ergon Energy | D26: As Quoted | H26: 8010 | I26: POA | K26: POA | M26: Quoted Service | N26: Price on application | O26: Customer | P26: No | Q26: N/A
A27: 46 | B27: Pre-connection site inspection | C27: Site inspection in order to determine nature of connection being sought | D27: As Quoted | H27: 8011 | I27: POA | K27: POA | M27: Quoted Service | N27: Price on application | O27: Customer | P27: No | Q27: N/A
A28: 47 | B28: Provision of site-specific connection information and advice | C28: Provision of site-specific connection advice, data and/or information on request (during the connection enquiry and/or connection application stage only). For example: - advice on project feasibility - advice on whether augmentation would likely be required - capacity information, including specific network capacity - load profiles for load flow studies - requests to review reports and designs prepared by external consultants, prior to lodgement of connection application - additional or more detailed specification and design options. Excludes information provided in planning reports/studies and project scopes. | D28: As Quoted | H28: 8012 | I28: POA | K28: POA | M28: Quoted Service | N28: Price on application | O28: Customer | P28: No | Q28: N/A
A29: 48 | B29: Preparation of preliminary designs and planning reports for major customer connections, including project scopes and estimates | C29: Initial specification and design outline for major customer connections. Includes general evaluation and advice on asset ownership options, indicative estimates of viable connection options, and recommendation on the most suitable option. | D29: As Quoted | H29: 8013 | I29: POA | K29: POA | M29: Quoted Service | N29: Price on application | O29: Customer | P29: No | Q29: N/A
A30: 49 | B30: Customer build, own and operate consultation services | C30: Provision of advice, design and specification on request to an applicant considering a build-own-operate asset ownership option for connection assets. | D30: As Quoted | H30: 8014 | I30: POA | K30: POA | M30: Quoted Service | N30: Price on application | O30: Customer | P30: No | Q30: N/A
A31: 50 | B31: Detailed enquiry response fee - embedded generation | C31: Costs associated with preparing a detailed enquiry response pursuant to Chapter 5 of the NER. Applies to any embedded generation connection applicant that submits an enquiry under the connection process set out in Chapter 5 of the NER and seeks a detailed enquiry response. | D31: As Quoted | H31: 8015 | I31: POA | K31: POA | M31: Quoted Service | N31: Price on application | O31: Customer | P31: No | Q31: N/A
B32: Connection Services
A33: 6 | B33: Temporary connection, not in permanent position - single phase metered - urban/short rural feeders | C33: Connection of a single phase supply to a meter location that is not permanent (i.e. short term supply). Excludes work on metering equipment. | D33: TBSSPU | E33: TBSSPS | H33: 8020 | I33: 330.2 | J33: =I33*1.1 -> 363.22 | M33: Fee Based Service | N33: Fixed fee applies. Aggregate of this service and #161-M capped to maximum specified in Schedule 8 of Electricity Regulation 2006 | O33: B2B Retailer only | P33: Yes | Q33: Supply Service Works (SSW) - Establish Temporary Supply
A34: 6-CF | B34: Call out fee for temporary connection, not in permanent position - single phase metered - urban/short rural feeders | C34: Travel time to perform a temporary connection, requested by a retailer or customer, and the service is unable to be performed due to customer/retailer fault. | D34: CFTBSSPU | E34: CFTBSSPS | H34: 8021 | I34: 116.9 | J34: =I34*1.1 -> 128.59 | M34: Fee Based Service | N34: Fixed fee applies | O34: B2B Retailer only | P34: N/A | Q34: N/A
A35: 7 | B35: Temporary connection, not in permanent position - single phase metered - long rural/isolated feeders | C35: Connection of a single phase supply to a meter location that is not permanent (i.e. short term supply). Excludes work on metering equipment. | F35: TBSSPL | G35: TBSSPI | H35: 8022 | K35: 330.2 | L35: =K35*1.1 -> 363.22 | M35: Fee Based Service | N35: Fixed fee applies. Aggregate of this service and #161-M capped to maximum specified in Schedule 8 of Electricity Regulation 2006 | O35: B2B Retailer only | P35: Yes | Q35: Supply Service Works (SSW) - Establish Temporary Supply
A36: 7-CF | B36: Call out fee for temporary connection, not in permanent position - single phase metered - long rural/isolated feeders | C36: Travel time to perform a temporary connection requested by a retailer or customer, and the service is unable to be performed due to customer/retailer fault. | F36: CFTBSSPL | G36: CFTBSSPI | H36: 8023 | K36: 330.2 | L36: =K36*1.1 -> 363.22 | M36: Fee Based Service | N36: Fixed fee applies, capped to the maximum price of the associated service (to be consistent with Schedule 8 of Electricity Regulation 2006) | O36: B2B Retailer only | P36: N/A | Q36: N/A
A37: 8 | B37: Temporary connection, not in permanent position - multi phase metered - urban/short rural feeders | C37: Connection of a multi phase supply to a meter location that is not permanent (i.e. short term supply). Excludes work on metering equipment. | D37: TBSMPU | E37: TBSMPS | H37: 8024 | I37: 330.2 | J37: =I37*1.1 -> 363.22 | M37: Fee Based Service | N37: Fixed fee applies. Aggregate of this service and #161-M capped to maximum specified in Schedule 8 of Electricity Regulation 2006 | O37: B2B Retailer only | P37: Yes | Q37: Supply Service Works (SSW) - Establish Temporary Supply
A38: 8-CF | B38: Call out fee for temporary connection, not in permanent position - multi-phase metered - urban/short rural feeders | C38: Travel time to perform a temporary connection requested by a retailer or customer, and the service is unable to be performed due to customer/retailer fault. | D38: CFTBSMPU | E38: CFTBSMPS | H38: 8025 | I38: 116.9 | J38: =I38*1.1 -> 128.59 | M38: Fee Based Service | N38: Fixed fee applies | O38: B2B Retailer only | P38: N/A | Q38: N/A
A39: 9 | B39: Temporary connection, not in permanent position - multi phase metered - long rural/isolated feeders | C39: Connection of a multi phase supply to a meter location that is not permanent (i.e. short term supply). Excludes work on metering equipment. | F39: TBSMPL | G39: TBSMPI | H39: 8026 | K39: 330.2 | L39: =K39*1.1 -> 363.22 | M39: Fee Based Service | N39: Fixed fee applies. Aggregate of this service and #161-M capped to maximum specified in Schedule 8 of Electricity Regulation 2006 | O39: B2B Retailer only | P39: Yes | Q39: Supply Service Works (SSW) - Establish Temporary Supply
A40: 9-CF | B40: Call out fee for temporary connection, not in permanent position - multi-phase metered - long rural/isolated feeders | C40: Travel time to perform a temporary connection requested by a retailer or customer, and the service is unable to be performed due to customer/retailer fault. | F40: CFTBSMPL | G40: CFTBSMPI | H40: 8027 | K40: 330.2 | L40: =K40*1.1 -> 363.22 | M40: Fee Based Service | N40: Fixed fee applies, capped to the maximum price of the associated service (to be consistent with Schedule 8 of Electricity Regulation 2006) | O40: B2B Retailer only | P40: N/A | Q40: N/A
A41: 161-M | B41: Work on metering equipment for temporary connection, not in permanent position - single phase or multi phase metered | C41: Work on metering equipment undertaken by Ergon Energy to accommodate a temporary connection. Note: this service is only available for non-grid connected areas of our network (isolated feeders and the Mount Isa-Cloncurry supply network). | D41: MTBSU | E41: MTBSS | F41: MTBSL | G41: MTBSI | H41: 8033 | I41: 82.5 | J41: =I41*1.1 -> 90.75 | K41: 82.5 | L41: =K41*1.1 -> 90.75 | M41: Fee Based Service | N41: Fixed fee applies. Aggregate of this service and relevant temporary connection service capped to maximum specified in Schedule 8 of Electricity Regulation 2006 | O41: B2B Retailer only | P41: Yes | Q41: Supply Service Works (SSW) - Establish Temporary Supply
A42: 51 | B42: Design and construction of connection assets for major customers | C42: Detailed design work and construction of connection assets after a connection offer has been made. Applies to major customers classified as an Individually Calculated Customer (ICC), Connection Asset Customer (CAC) or Embedded Generator (EG) as per Ergon Energy's pricing proposal. | D42: As Quoted | H42: 8028 | I42: POA | K42: POA | M42: Quoted Service | N42: Price on application | O42: Customer | P42: No | Q42: N/A
A43: 52 | B43: Commissioning and energisation of major customer connections | C43: Includes: - inspection and testing of connection assets prior to physical connection to the network - physical connection and energisation of electricity equipment to allow conveyance of electricity - administration services involved in reconciling the financials of a connection project, and processing and finalising network information and contracts in relation to a connection - generation required (if any) to supply existing customers while equipment is de-energised to allow testing and commissioning Applies to major customers classified as an Individually Calculated Customer (ICC), Connection Asset Customer (CAC) or Embedded Generator (EG) as per Ergon Energy's pricing proposal. | D43: As Quoted | H43: 8029 | I43: POA | K43: POA | M43: Quoted Service | N43: Price on application | O43: Customer | P43: No | Q43: N/A
A44: 53 | B44: Design and construction for real estate developments | C44: Detailed design work and construction for a real estate development connection after a connection offer has been made. Includes work associated with augmentation to the shared network which is directly attributable to the establishment or alteration of the real estate development connection | D44: As Quoted | H44: 8030 | I44: POA | K44: POA | M44: Quoted Service | N44: Price on application | O44: Customer | P44: No | Q44: N/A
A45: 54 | B45: Commissioning and energisation of real estate development connections | C45: Includes: - inspection and testing prior to physical connection to the network - physical connection and energisation of electricity equipment to allow conveyance of electricity - administration services involved in reconciling the financials of a connection project, and processing and finalising network information and contracts in relation to a connection - generation required (if any) to supply existing customers while equipment is de-energised to allow testing and commissioning | D45: As Quoted | H45: 8031 | I45: POA | K45: POA | M45: Quoted Service | N45: Price on application | O45: Customer | P45: Yes | Q45: N/A
A46: 55 | B46: Removal of network constraint for embedded generator | C46: Augmenting the network to remove a constraint faced by an embedded generator | D46: As Quoted | H46: 8032 | I46: POA | K46: POA | M46: Quoted Service | N46: Price on application | O46: Customer | P46: No | Q46: N/A
B47: Post Connection Services
A48: 10 | B48: Supply abolishment during business hours - urban/short rural feeders | C48: Retailer requests Ergon Energy to abolish supply at a connection point and decommission a NMI. May be used where a property is to be demolished; supply is no longer required; an alternative connection point is to be used; or a redundant supply is to be removed. Excludes decommissioning of metering undertaken by Ergon Energy or an alternative provider. | D48: SUPABOLU | E48: SUPABOLS | H48: 8040 | I48: 292.4 | J48: =I48*1.1 -> 321.64 | M48: Fee Based Service | N48: Fixed fee applies | O48: B2B Retailer only | P48: No | Q48: Supply Service Works (SSW) - Supply Abolishment
A49: 10-CF | B49: Call out fee for supply abolishment during business hours - urban/short rural feeders | C49: Travel time to perform a supply abolishment requested by a retailer or customer, and the service is unable to be performed due to customer/retailer fault. | D49: CFSUPABOLU | E49: CFSUPABOLS | H49: 8041 | I49: 116.9 | J49: =I49*1.1 -> 128.59 | M49: Fee Based Service | N49: Fixed fee applies | O49: B2B Retailer only | P49: N/A | Q49: N/A
A50: 11 | B50: Supply abolishment during business hours - long rural/isolated feeders | C50: Retailer requests Ergon Energy to abolish supply at a connection point and decommission a NMI. May be used where a property is to be demolished; supply is no longer required; an alternative connection point is to be used; or a redundant supply is to be removed. Excludes decommissioning of metering undertaken by Ergon Energy or an alternative provider. | F50: SUPABOLL | G50: SUPABOLI | H50: 8042 | K50: 292.4 | L50: =K50*1.1 -> 321.64 | M50: Fee Based Service | N50: Fixed fee applies, capped to UR/SR price as per Schedule 8 of Electricity Regulation 2006 | O50: B2B Retailer only | P50: No | Q50: Supply Service Works (SSW) - Supply Abolishment
A51: 11-CF | B51: Call out fee for supply abolishment during business hours - long rural/isolated feeders | C51: Travel time to perform a supply abolishment requested by a retailer or customer, and the service is unable to be performed due to customer/retailer fault. | F51: CFSUPABOLL | G51: CFSUPABOLI | H51: 8043 | K51: 116.9 | L51: =K51*1.1 -> 128.59 | M51: Fee Based Service | N51: Fixed fee applies, capped to UR/SR price (to be consistent with Schedule 8 of Electricity Regulation 2006) | O51: B2B Retailer only | P51: N/A | Q51: N/A
A52: 162-M | B52: Decommissioning of metering equipment for supply abolishment | C52: Decommissioning of metering associated with a retailer request to abolish supply at a connection point. Note: this service is only available where Ergon Energy is the default Metering Co-ordinator or Responsible Person for the premises. | D52: MSUPABOLU | E52: MSUPABOLS | F52: MSUPABOLL | G52: MSUPABOLI | H52: 8039 | I52: 58.4 | J52: =I52*1.1 -> 64.24 | K52: 58.4 | L52: =K52*1.1 -> 64.24 | M52: Fee Based Service | N52: Fixed fee applies, capped to UR/SR price as per Schedule 8 of Electricity Regulation 2006 | O52: B2B Retailer only | P52: N/A | Q52: Supply Service Works (SSW) - Supply Abolishment
A53: 12 | B53: De-energisation during business hours - urban/short rural feeders | C53: Retailer requests de-energisation of the customer's premises during business hours: - where the de-energisation can be performed (e.g. pole, pillar or meter) - Main switch sticker | D53: DEENBHU | E53: DEENBHS | H53: 8044 | I53: 0 | J53: =I53*1.1 -> 0 | M53: Fee Based Service | N53: Fixed fee applies, capped to maximum specified in Schedule 8 of Electricity Regulation 2006 | O53: B2B Retailer only | P53: No | Q53: De-energisation
A54: 12-CF | B54: Call out fee for de-energisation during business hours - urban/short rural feeders | C54: Travel time to perform a de-energisation during business hours requested by a retailer or customer , and the service is unable to be performed due to customer/retailer fault. | D54: CFDEENBHU | E54: CFDEENBHS | H54: 8045 | I54: 0 | J54: =I54*1.1 -> 0 | M54: Fee Based Service | N54: Fixed fee applies, capped to the maximum price of the associated service (to be consistent with Schedule 8 of Electricity Regulation 2006) | O54: B2B Retailer only | P54: N/A | Q54: N/A
A55: 13 | B55: De-energisation during business hours - long rural/isolated feeders | C55: Retailer requests de-energisation of the customer's premises during business hours: - where the de-energisation can be performed (e.g. pole, pillar or meter) - Main switch sticker | F55: DEENBHL | G55: DEENBHI | H55: 8046 | K55: 0 | L55: =K55*1.1 -> 0 | M55: Fee Based Service | N55: Fixed fee applies, capped to maximum specified in Schedule 8 of Electricity Regulation 2006 | O55: B2B Retailer only | P55: No | Q55: De-energisation
A56: 13-CF | B56: Call out fee for de-energisation during business hours - long rural/isolated feeders | C56: Travel time to perform a de-energisation during business hours requested by a retailer or customer , and the service is unable to be performed due to customer/retailer fault. | F56: CFDEENBHL | G56: CFDEENBHI | H56: 8047 | K56: 0 | L56: =K56*1.1 -> 0 | M56: Fee Based Service | N56: Fixed fee applies, capped to the maximum price of the associated service (to be consistent with Schedule 8 of Electricity Regulation 2006) | O56: B2B Retailer only | P56: N/A | Q56: N/A
A57: 14 | B57: Re-energisation during business hours - urban/short rural feeders | C57: Retailer requests re-energisation of customer's premises during business hours: - after a physical disconnection and premises requires a visual examination - following a main switch sticker | D57: REENBHU | E57: REENBHS | H57: 8048 | I57: 0 | J57: =I57*1.1 -> 0 | M57: Fee Based Service | N57: Fixed fee applies, capped to maximum specified in Schedule 8 of Electricity Regulation 2006 | O57: B2B Retailer only | P57: No | Q57: Re-energisation
A58: 14-VE | B58: Visual examination during business hours for remote re-energisation - urban/short rural feeders | C58: Retailer or Metering Co-ordinator requests visual examination during business hours, prior to performing a remote re-energisation. | D58: VEREENBHU | E58: VEREENBHS | H58: 2050 | I58: 0 | J58: =I58*1.1 -> 0 | M58: Fee Based Service | N58: Fixed fee applies, capped to maximum specified in Schedule 8 of Electricity Regulation 2006 | O58: B2B Retailer only | P58: No | Q58: Re-energisation
A59: 14-CF | B59: Call out fee for re-energisation during business hours - urban/short rural feeders | C59: Travel time to perform a re-energisation or visual inspection during business hours requested by a retailer or customer , and the service is unable to be performed due to customer/retailer fault. | D59: CFREENBHU | E59: CFREENBHS | H59: 8049 | I59: 0 | J59: =I59*1.1 -> 0 | M59: Fee Based Service | N59: Fixed fee applies, capped to the maximum price of the associated service (to be consistent with Schedule 8 of Electricity Regulation 2006) | O59: B2B Retailer only | P59: N/A | Q59: N/A
A60: 15 | B60: Re-energisation during business hours - long rural/isolated feeders | C60: Retailer requests re-energisation of customer's premises during business hours: - after a physical disconnection and premises requires a visual examination - following a main switch sticker | F60: REENBHL | G60: REENBHI | H60: 8050 | K60: 0 | L60: =K60*1.1 -> 0 | M60: Fee Based Service | N60: Fixed fee applies, capped to maximum specified in Schedule 8 of Electricity Regulation 2006 | O60: B2B Retailer only | P60: No | Q60: Re-energisation
A61: 15-VE | B61: Visual examination during business hours for remote re-energisation - long rural/isolated feeders | C61: Retailer or Metering Co-ordinator requests visual examination during business hours, prior to performing a remote re-energisation. | F61: VEREENBHL | G61: VEREENBHI | H61: 2051 | K61: 0 | L61: =K61*1.1 -> 0 | M61: Fee Based Service | N61: Fixed fee applies, capped to maximum specified in Schedule 8 of Electricity Regulation 2006 | O61: B2B Retailer only | P61: No | Q61: Re-energisation
A62: 15-CF | B62: Call out fee for re-energisation during business hours - long rural/isolated feeders | C62: Travel time to perform a re-energisation or visual inspection during business hours requested by a retailer or customer, and the service is unable to be performed due to customer/retailer fault. | F62: CFREENBHL | G62: CFREENBHI | H62: 8051 | K62: 0 | L62: =K62*1.1 -> 0 | M62: Fee Based Service | N62: Fixed fee applies, capped to the maximum price of the associated service (to be consistent with Schedule 8 of Electricity Regulation 2006) | O62: B2B Retailer only | P62: N/A | Q62: N/A
A63: 16 | B63: Re-energisation during business hours - after de-energisation for debt - urban/short rural feeders | C63: Retailer requests re-energisation of customer's premises during business hours where the customer was previously de-energised for non-payment of their electricity account | D63: REDDBHU | E63: REDDBHS | H63: 8052 | I63: 45.5 | J63: =I63*1.1 -> 50.05 | M63: Fee Based Service | N63: Fixed fee applies, capped to maximum specified in Schedule 8 of Electricity Regulation 2006 | O63: B2B Retailer only | P63: No | Q63: Re-energisation after disconnection for non-payment
A64: 16-VE | B64: Visual examination during business hours for remote re-energisation - after de-energisation for debt - urban/short rural feeders | C64: Retailer or Metering Co-ordinator requests visual examination during business hours, prior to performing a remote re-energisation. Applies where the customer was previously de-energised for non-payment of their electricity account | D64: VEREDDBHU | E64: VEREDDBHS | H64: 2052 | I64: 45.5 | J64: =I64*1.1 -> 50.05 | M64: Fee Based Service | N64: Fixed fee applies, capped to maximum specified in Schedule 8 of Electricity Regulation 2006 | O64: B2B Retailer only | P64: No | Q64: Re-energisation after disconnection for non-payment
A65: 16-CF | B65: Call out fee for re-energisation during business hours - after de-energisation for debt - urban/short rural feeders | C65: Travel time to perform a re-energisation or visual inspection during business hours requested by a retailer or customer, and the service is unable to be performed due to customer/retailer fault. | D65: CFREDDBHU | E65: CFREDDBHS | H65: 8053 | I65: 38.9 | J65: =I65*1.1 -> 42.79 | M65: Fee Based Service | N65: Fixed fee applies | O65: B2B Retailer only | P65: N/A | Q65: N/A
A66: 17 | B66: Re-energisation during business hours - after de-energisation for debt - long rural/isolated feeders | C66: Retailer requests re-energisation of customer's premises during business hours where the customer was previously de-energised for non-payment of their electricity account | F66: REDDBHL | G66: REDDBHI | H66: 8054 | K66: 45.5 | L66: =K66*1.1 -> 50.05 | M66: Fee Based Service | N66: Fixed fee applies, capped to maximum specified in Schedule 8 of Electricity Regulation 2006 | O66: B2B Retailer only | P66: No | Q66: Re-energisation after disconnection for non-payment
A67: 17-VE | B67: Visual examination during business hours for remote re-energisation - after de-energisation for debt - long rural/isolated feeders | C67: Retailer or Metering Co-ordinator requests visual examination during business hours, prior to performing a remote re-energisation. Applies where the customer was previously de-energised for non-payment of their electricity account | F67: VEREDDBHL | G67: VEREDDBHI | H67: 2053 | K67: 45.5 | L67: =K67*1.1 -> 50.05 | M67: Fee Based Service | N67: Fixed fee applies, capped to maximum specified in Schedule 8 of Electricity Regulation 2006 | O67: B2B Retailer only | P67: No | Q67: Re-energisation after disconnection for non-payment
A68: 17-CF | B68: Call out fee for re-energisation during business hours - after de-energisation for debt - long rural/isolated feeders | C68: Travel time to perform a re-energisation or visual inspection during business hours requested by a retailer or customer , and the service is unable to be performed due to customer/retailer fault. | F68: CFREDDBHL | G68: CFREDDBHI | H68: 8055 | K68: 45.5 | L68: =K68*1.1 -> 50.05 | M68: Fee Based Service | N68: Fixed fee applies, capped to the maximum price of the associated service (to be consistent with Schedule 8 of Electricity Regulation 2006) | O68: B2B Retailer only | P68: N/A | Q68: N/A
A69: 56 | B69: Move point of attachment - single/multi phase | C69: De-energisation, followed by physical dismantling then reattachment of service and re-energisation. Excludes work on metering equipment (if required). | D69: MPOAU | E69: MPOAS | F69: MPOAL | G69: MPOAI | H69: 8056 | I69: POA | K69: POA | M69: Quoted Service | N69: Price on application | O69: B2B Retailer only | P69: Yes | Q69: Supply Service Works (SSW) - Supply Alteration
A70: 57 | B70: Re-arrange connection assets at customer's request | C70: Removal, relocation or rearrangement of connection assets at customer request. Excludes work on metering equipment (if required). | D70: As Quoted | H70: 8057 | I70: POA | K70: POA | M70: Quoted Service | N70: Price on application | O70: B2B Retailer only | P70: Yes | Q70: Supply Service Works (SSW) - Supply Alteration
A71: 58 | B71: Protection and Power Quality assessment after connection | C71: Investigation into Power Quality issues including Flicker, Harmonics and DC voltage injection. | D71: As Quoted | H71: 8058 | I71: POA | K71: POA | M71: Quoted Service | N71: Price on application | O71: Customer | P71: No | Q71: N/A
A72: 59 | B72: Temporary de-energisation - no dismantling | C72: Temporary de-energisation and re-energisation of supply at the service fuse to allow customer or contractor to work close - no dismantling of service required (i.e. no service line drop). | D72: TEMPDEENU | E72: TEMPDEENS | F72: TEMPDEENL | G72: TEMPDEENI | H72: 8059 | I72: POA | K72: POA | M72: Quoted Service | N72: Price on application | O72: B2B Retailer only | P72: No | Q72: Supply Service Works (SSW) - Temporary Isolation
A73: 60 | B73: LV Service line drop and replace - physical dismantling | C73: Temporary de-energisation and re-energisation of supply to allow customer or contractor to work close - the service will be physically dismantled or disconnected (e.g. overhead service dropped). | D73: LVSLDU | E73: LVSLDS | F73: LVSLDL | G73: LVSLDI | H73: 8060 | I73: POA | K73: POA | M73: Quoted Service | N73: Price on application | O73: B2B Retailer only | P73: No | Q73: Supply Service Works (SSW) - Temporary Isolation
A74: 61 | B74: HV Service line drop and replace | C74: Temporary de-energisation and re-energisation of supply to allow customer or contractor to work close - Isolate and earth | D74: HVSLDU | E74: HVSLDS | F74: HVSLDL | G74: HVSLDI | H74: 8061 | I74: POA | K74: POA | M74: Quoted Service | N74: Price on application | O74: B2B Retailer only | P74: No | Q74: Supply Service Works (SSW) - Temporary Isolation
A75: 62 | B75: Supply enhancement | C75: For example, an upgrade from single phase to multi phase and/or increase capacity. Applies to underground and overhead service upgrades. Excludes work on metering equipment (if required) | D75: SUPENHU | E75: SUPENHS | F75: SUPENHL | G75: SUPENHI | H75: 8062 | I75: POA | K75: POA | M75: Quoted Service | N75: Price on application | O75: B2B Retailer only | P75: Yes | Q75: Supply Service Works (SSW) - Supply Alteration
A76: 63 | B76: Provision of connection services above minimum requirements | C76: Customer requests increase in reliability or quality of supply beyond the standard, and/or above minimum regulatory requirements (e.g. reserve feeder). Excludes work on metering equipment (if required) | D76: As Quoted | H76: 8063 | I76: POA | K76: POA | M76: Quoted Service | N76: Price on application | O76: Customer | P76: No | Q76: N/A
A77: 64 | B77: Upgrade from overhead to underground service | C77: Requests to convert an existing overhead service to an underground service. Excludes work on metering equipment (if required) | D77: As Quoted | H77: 8064 | I77: POA | K77: POA | M77: Quoted Service | N77: Price on application | O77: Customer | P77: Yes | Q77: Supply Service Works (SSW) - Supply Alteration
A78: 65 | B78: Rectification of illegal connections or damage to overhead or underground service cables | C78: Repair works to re-establish a safe and legal connection due to customer or third party action. Excludes work on metering equipment (if required) | D78: As Quoted | H78: 8065 | I78: POA | K78: POA | M78: Quoted Service | N78: Price on application | O78: Customer | P78: No | Q78: N/A
A79: 163-M | B79: Work on metering equipment for a post connection service, not covered by another metering service. | C79: Work on metering equipment undertaken by Ergon Energy in conjunction with a post connection quoted service. Only applies where this work is not covered by another metering service. Note: this service is only available where Ergon Energy is the Default Metering Co-ordinator or Responsible Person for the premises. | D79: GENMU | E79: GENMS | F79: GENML | G79: GENMI | H79: 8077 | I79: POA | K79: POA | M79: Quoted Service | N79: Price on application | O79: Depends on activity requested | P79: Depends on activity requested | Q79: Depends on activity requested
A80: 66 | B80: De-energisation after business hours | C80: Retailer requests de-energisation of the customer's premises after business hours: - where the de-energisation can be performed (e.g. pole, pillar or meter). - Main switch sticker | D80: DEENAHU | E80: DEENAHS | F80: DEENAHL | G80: DEENAHI | H80: 8066 | I80: 0 | J80: =I80*1.1 -> 0 | K80: 0 | L80: =K80*1.1 -> 0 | M80: Quoted Service | N80: Fixed fee applies, capped to maximum specified in Schedule 8 of Electricity Regulation 2006 | O80: B2B Retailer only | P80: No | Q80: De-energisation after Business Hours
A81: 66-CF | B81: Call out fee for de-energisations after business hours | C81: Travel time to perform a de-energisation after business hours requested by a retailer, and the service is unable to be performed due to customer/retailer fault. | D81: CFDEENAHU | E81: CFDEENAHS | F81: CFDEENAHL | G81: CFDEENAHI | H81: 8075 | I81: 0 | J81: =I81*1.1 -> 0 | K81: 0 | L81: =K81*1.1 -> 0 | M81: Quoted Service | N81: Fixed fee applies, capped to the maximum price of the associated service (to be consistent with Schedule 8 of Electricity Regulation 2006) | O81: B2B Retailer only | P81: N/A | Q81: N/A
A82: 67 | B82: Re-energisation after business hours | C82: Retailer requests re-energisation of a customer's premises after business hours: - after a physical disconnection and premises requires a visual examination - following a main switch sticker - where the customer was previously de-energised for non-payment of their electricity account | D82: REENAHU | E82: REENAHS | F82: REENAHL | G82: REENAHI | H82: 8067 | I82: 109.9 | J82: =I82*1.1 -> 120.89 | K82: 109.9 | L82: =K82*1.1 -> 120.89 | M82: Quoted Service | N82: Fixed fee applies, capped to maximum specified in Schedule 8 of Electricity Regulation 2006 | O82: B2B Retailer only | P82: No | Q82: Re-energisation after Business Hours
A83: 67-VE | B83: Visual examination after business hours for remote re-energisation | C83: Retailer or Metering Co-ordinator requests visual examination during business hours, prior to performing a remote re-energisation. Applies all instances, including where the customer was previously de-energised for non-payment of their electricity account. | D83: VEREENAHU | E83: VEREENAHS | F83: VEREENAHL | G83: VEREENAHI | H83: 8254 | I83: 109.9 | J83: =I83*1.1 -> 120.89 | K83: 109.9 | L83: =K83*1.1 -> 120.89 | M83: Quoted Service | N83: Fixed fee applies (to be consistent with Schedule 8 of Electricity Regulation 2006) | O83: B2B Retailer only | P83: No | Q83: Re-energisation after Business Hours
A84: 67-CF | B84: Call out fee for re-energisations after business hours | C84: Travel time to perform a re-energisation or visual examination after business hours requested by a retailer, and the service is unable to be performed due to customer/retailer fault. | D84: CFREENAHU | E84: CFREENAHS | F84: CFREENAHL | G84: CFREENAHI | H84: 8076 | I84: 58.4 | J84: =I84*1.1 -> 64.24 | K84: 58.4 | L84: =K84*1.1 -> 64.24 | M84: Quoted Service | N84: Fixed fee applies (to be consistent with Schedule 8 of Electricity Regulation 2006) | O84: B2B Retailer only | P84: N/A | Q84: N/A
A85: 68 | B85: Accreditation of alternative service providers - major customer connections | C85: Accreditation of service providers that meet competency criteria. Applies to major customers classified as an Individually Calculated Customer (ICC), Connection Asset Customer (CAC) or Embedded Generator (EG) as per Ergon Energy's pricing proposal. | D85: As Quoted | H85: 8068 | I85: POA | K85: POA | M85: Quoted Service | N85: Price on application | O85: Customer | P85: No | Q85: N/A
A86: 18 | B86: Accreditation of alternative service providers - real estate developments | C86: Accreditation of service providers that meet competency criteria. Applies to real estate developments. | D86: ASPRED | H86: 8069 | I86: 903.5 | J86: =I86*1.1 -> 993.85 | K86: =I86 -> 903.5 | L86: =J86 -> 993.85 | M86: Fee Based Service | N86: Fixed fee applies | O86: Customer | P86: No | Q86: N/A
A87: 69 | B87: Approval of third party design - major customer connections | C87: Review, inspection and auditing of design carried out by an alternative service provider prior to energisation. Applies to major customers classified as an Individually Calculated Customer (ICC), Connection Asset Customer (CAC) or Embedded Generator (EG) as per Ergon Energy's pricing proposal. | D87: As Quoted | H87: 8070 | I87: POA | K87: POA | M87: Quoted Service | N87: Price on application | O87: Customer | P87: No | Q87: N/A
A88: 70 | B88: Approval of third party design - real estate developments | C88: Review, inspection and auditing of design carried out by an alternative service provider prior to energisation. Applies to real estate developments. | D88: As Quoted | H88: 8071 | I88: POA | K88: POA | M88: Quoted Service | N88: Price on application | O88: Customer | P88: No | Q88: N/A
A89: 71 | B89: Construction audit - major customer connections | C89: Review, inspection and auditing of construction works carried out by an alternative service provider prior to energisation. Applies to major customers classified as an Individually Calculated Customer (ICC), Connection Asset Customer (CAC) or Embedded Generator (EG) as per Ergon Energy's pricing proposal. | D89: As Quoted | H89: 8072 | I89: POA | K89: POA | M89: Quoted Service | N89: Price on application | O89: Customer | P89: No | Q89: N/A
A90: 72 | B90: Construction audit - real estate developments | C90: Review, inspection and auditing of construction works carried out by an alternative service provider prior to energisation. Applies to real estate developments. | D90: As Quoted | H90: 8073 | I90: POA | K90: POA | M90: Quoted Service | N90: Price on application | O90: Customer | P90: No | Q90: N/A
A91: 73 | B91: Approval of third party materials | C91: Certification of non-approved materials (i.e. approval of non-approved materials to be used on Ergon Energy's network). | D91: As Quoted | H91: 8074 | I91: POA | K91: POA | M91: Quoted Service | N91: Price on application | O91: Customer | P91: No | Q91: N/A
B92: Metering Services
B93: Meter replacements
A94: 19 | B94: Install replacement meter (Type 5 and 6) – Single phase – urban/short rural feeder | C94: Installation and provision during business hours of a single phase replacement meter, where allowed by regulation. Note: this service is only available in non-grid connected areas of our network (isolated feeders and feeders in Mount Isa-Cloncurry supply network). | D94: MSNGLU | E94: MSNGLS | H94: 8193 | I94: 344.4 | J94: =I94*1.1 -> 378.84 | M94: Fee Based Service | N94: Fixed fee applies | O94: B2B Retailer only | P94: Depends on activity requested | Q94: Metering Service Works - Exchange Meter
A95: 19-CF | B95: Call out fee for installation of a replacement meter (Type 5 and 6) – Single phase – urban/short rural feeder | C95: Travel time to perform the installation of a replacement meter (Type 5 and 6) requested by a retailer or customer, and the service is unable to be performed due to customer/retailer fault. Note: Call out fees for replacement meters are only applicable in non-grid connected areas of our network (isolated feeders and feeders in Mount Isa-Cloncurry supply network) | D95: CFMSNGLU | E95: CFMSNGLS | H95: 8194 | I95: 63.4 | J95: =I95*1.1 -> 69.74 | M95: Fee Based Service | N95: Fixed fee applies | O95: B2B Retailer only | P95: N/A | Q95: N/A
A96: 20 | B96: Install replacement meter (Type 5 and 6) – Single phase – long rural/isolated feeder | C96: Installation and provision during business hours of a single phase replacement meter, where allowed by regulation. Note: this service is only available in non-grid connected areas of our network (isolated feeders and feeders in Mount Isa-Cloncurry supply network). | F96: MSNGLL | G96: MSNGLI | H96: 8195 | K96: 344.4 | L96: =K96*1.1 -> 378.84 | M96: Fee Based Service | N96: Fixed fee applies, capped to UR/SR price as per Schedule 8 of Electricity Regulation 2006 | O96: B2B Retailer only | P96: Depends on activity requested | Q96: Metering Service Works - Exchange Meter
A97: 20-CF | B97: Call out fee for installation of a replacement meter (Type 5 and 6) – Single phase – long rural/isolated feeder | C97: Travel time to perform the installation of a replacement meter (Type 5 and 6) requested by a retailer or customer, and the service is unable to be performed due to customer/retailer fault. Note: Call out fees for replacement meters are only applicable in non-grid connected areas of our network (isolated feeders and feeders in Mount Isa-Cloncurry supply network) | F97: CFMSNGLL | G97: CFMSNGLI | H97: 8196 | K97: 63.4 | L97: =K97*1.1 -> 69.74 | M97: Fee Based Service | N97: Fixed fee applies, capped to UR/SR price (to be consistent with Schedule 8 of Electricity Regulation 2006) | O97: B2B Retailer only | P97: N/A | Q97: N/A
A98: 21 | B98: Install replacement meter (Type 5 and 6) – Dual element – urban/short rural feeder | C98: Installation and provision during business hours of a dual element replacement meter, where allowed by regulation. Note: this service is only available in non-grid connected areas of our network (isolated feeders and feeders in Mount Isa-Cloncurry supply network). | D98: MDUALU | E98: MDUALS | H98: 8197 | I98: 421.8 | J98: =I98*1.1 -> 463.98 | M98: Fee Based Service | N98: Fixed fee applies | O98: B2B Retailer only | P98: Depends on activity requested | Q98: Metering Service Works - Exchange Meter
A99: 21-CF | B99: Call out fee for installation of a replacement meter (Type 5 and 6) – Dual element – urban/short rural feeder | C99: Travel time to perform the installation of a replacement meter (Type 5 and 6) requested by a retailer or customer, and the service is unable to be performed due to customer/retailer fault. Note: Call out fees for replacement meters are only applicable in non-grid connected areas of our network (isolated feeders and feeders in Mount Isa-Cloncurry supply network) | D99: CFMDUALU | E99: CFMDUALS | H99: 8198 | I99: 63.4 | J99: =I99*1.1 -> 69.74 | M99: Fee Based Service | N99: Fixed fee applies | O99: B2B Retailer only | P99: N/A | Q99: N/A
A100: 22 | B100: Install replacement meter (Type 5 and 6) – Dual element – long rural/isolated feeder | C100: Installation and provision during business hours of a dual element replacement meter, where allowed by regulation. Note: this service is only available in non-grid connected areas of our network (isolated feeders and feeders in Mount Isa-Cloncurry supply network). | F100: MDUALL | G100: MDUALI | H100: 8199 | K100: 421.8 | L100: =K100*1.1 -> 463.98 | M100: Fee Based Service | N100: Fixed fee applies, capped to UR/SR price as per Schedule 8 of Electricity Regulation 2006 | O100: B2B Retailer only | P100: Depends on activity requested | Q100: Metering Service Works - Exchange Meter
A101: 22-CF | B101: Call out fee for installation of a replacement meter (Type 5 and 6) – Dual element – long rural/isolated feeder | C101: Travel time to perform the installation of a replacement meter (Type 5 and 6) requested by a retailer or customer, and the service is unable to be performed due to customer/retailer fault. Note: Call out fees for replacement meters are only applicable in non-grid connected areas of our network (isolated feeders and feeders in Mount Isa-Cloncurry supply network) | F101: CFMDUALL | G101: CFMDUALI | H101: 8200 | K101: 63.4 | L101: =K101*1.1 -> 69.74 | M101: Fee Based Service | N101: Fixed fee applies, capped to UR/SR price (to be consistent with Schedule 8 of Electricity Regulation 2006) | O101: B2B Retailer only | P101: N/A | Q101: N/A
A102: 23 | B102: Install replacement meter (Type 5 and 6) – Polyphase – urban/short rural feeder | C102: Installation and provision during business hours of a polyphase replacement meter, where allowed by regulation. Note: this service is only available in non-grid connected areas of our network (isolated feeders and feeders in Mount Isa-Cloncurry supply network). | D102: MTHREU | E102: MTHRES | H102: 8201 | I102: 530.2 | J102: =I102*1.1 -> 583.22 | M102: Fee Based Service | N102: Fixed fee applies | O102: B2B Retailer only | P102: Depends on activity requested | Q102: Metering Service Works - Exchange Meter
A103: 23-CF | B103: Call out fee for installation of a replacement meter (Type 5 and 6) – Polyphase – urban/short rural feeder | C103: Travel time to perform the installation of a replacement meter requested by a retailer or customer, and the service is unable to be performed due to customer/retailer fault. Note: Call out fees for replacement meters are only applicable in non-grid connected areas of our network (isolated feeders and feeders in Mount Isa-Cloncurry supply network). | D103: CFMTHREU | E103: CFMTHRES | H103: 8202 | I103: 63.4 | J103: =I103*1.1 -> 69.74 | M103: Fee Based Service | N103: Fixed fee applies | O103: B2B Retailer only | P103: N/A | Q103: N/A
A104: 24 | B104: Install replacement meter (Type 5 and 6) – Polyphase – long rural/isolated feeder | C104: Installation and provision during business hours of a polyphase replacement meter, where allowed by regulation. Note: this service is only available in non-grid connected areas of our network (isolated feeders and feeders in Mount Isa-Cloncurry supply network). | F104: MTHREL | G104: MTHREI | H104: 8203 | K104: 530.2 | L104: =K104*1.1 -> 583.22 | M104: Fee Based Service | N104: Fixed fee applies, capped to UR/SR price as per Schedule 8 of Electricity Regulation 2006 | O104: B2B Retailer only | P104: Depends on activity requested | Q104: Metering Service Works - Exchange Meter
A105: 24-CF | B105: Call out fee for installation of a replacement meter (Type 5 and 6) – Polyphase – long rural/isolated feeder | C105: Travel time to perform the installation of a replacement meter requested by a retailer or customer, and the service is unable to be performed due to customer/retailer fault. Note: Call out fees for replacement meters are only applicable in non-grid connected areas of our network (isolated feeders and feeders in Mount Isa-Cloncurry supply network). | F105: CFMTHREL | G105: CFMTHREI | H105: 8204 | K105: 63.4 | L105: =K105*1.1 -> 69.74 | M105: Fee Based Service | N105: Fixed fee applies, capped to UR/SR price (to be consistent with Schedule 8 of Electricity Regulation 2006) | O105: B2B Retailer only | P105: N/A | Q105: N/A
A106: 25 | B106: Install replacement meter (CT) – urban/short rural feeder | C106: Installation and provision during business hours of a CT replacement meter, where allowed by regulation. Note: this service is only available in non-grid connected areas of our network (isolated feeders and feeders in Mount Isa-Cloncurry supply network). | D106: MCTU | E106: MCTS | H106: 8205 | I106: 2519.1 | J106: =I106*1.1 -> 2771.01 | M106: Fee Based Service | N106: Fixed fee applies | O106: B2B Retailer only | P106: Depends on activity requested | Q106: Metering Service Works - Exchange Meter
A107: 25-CF | B107: Call out fee for installation of a replacement meter (CT) – urban/short rural feeder | C107: Travel time to perform the installation of a replacement meter requested by a retailer or customer, and the service is unable to be performed due to customer/retailer fault. Note: Call out fees for replacement meters are only applicable in non-grid connected areas of our network (isolated feeders and feeders in Mount Isa-Cloncurry supply network). | D107: CFMCTU | E107: CFMCTS | H107: 8206 | I107: 121.3 | J107: =I107*1.1 -> 133.43 | M107: Fee Based Service | N107: Fixed fee applies | O107: B2B Retailer only | P107: N/A | Q107: N/A
A108: 26 | B108: Install replacement meter (CT) – long rural/isolated feeder | C108: Installation and provision during business hours of a CT replacement meter, where allowed by regulation. Note: this service is only available in non-grid connected areas of our network (isolated feeders and feeders in Mount Isa-Cloncurry supply network). | F108: MCTL | G108: MCTI | H108: 8207 | K108: 2519.1 | L108: =K108*1.1 -> 2771.01 | M108: Fee Based Service | N108: Fixed fee applies, capped to UR/SR price as per Schedule 8 of Electricity Regulation 2006 | O108: B2B Retailer only | P108: Depends on activity requested | Q108: Metering Service Works - Exchange Meter
...

Sheet ACS Tariff classes & tariffs
G1: 4 | H1: 5 | I1: 6 | J1: 7
E3: Ergon Energy Corporation Limited
E4: 2017-18 ACS tariffs by tariff class
E8: Tariff class | F8: Tariff | G8: Product Codes
G9: Service undertaken | O9: No service undertaken due to fault of another party (Call out fee)
G10: Primary Service | K10: Metering Component (MC Fee) | O10: (Call out fee)
B11: 1 | E11: Fee based services (urban/short rural) | F11: =VLOOKUP(B11,'ACS Price List'!$A$12:$P$180,2,FALSE) -> Application fee - Basic or standard connection | G11: =IF(VLOOKUP($B11,'ACS Price List'!$A$12:$P$180,G$1,FALSE)=0,"",VLOOKUP($B11,'ACS Price List'!$A$12:$P$180,G$1,FALSE)) -> APFSAC | H11: =IF(VLOOKUP($B11,'ACS Price List'!$A$12:$P$180,H$1,FALSE)=0,"",VLOOKUP($B11,'ACS Price List'!$A$12:$P$180,H$1,FALSE)) | K11: =IFERROR(IF(VLOOKUP($C11,'ACS Price List'!$A$12:$P$180,G$1,FALSE)=0,"",VLOOKUP($C11,'ACS Price List'!$A$12:$P$180,G$1,FALSE)),"") | L11: =IFERROR(IF(VLOOKUP($C11,'ACS Price List'!$A$12:$P$180,H$1,FALSE)=0,"",VLOOKUP($C11,'ACS Price List'!$A$12:$P$180,H$1,FALSE)),"") | O11: =IFERROR(IF(VLOOKUP($D11,'ACS Price List'!$A$12:$P$180,G$1,FALSE)=0,"",VLOOKUP($D11,'ACS Price List'!$A$12:$P$180,G$1,FALSE)),"") | P11: =IFERROR(IF(VLOOKUP($D11,'ACS Price List'!$A$12:$P$180,H$1,FALSE)=0,"",VLOOKUP($D11,'ACS Price List'!$A$12:$P$180,H$1,FALSE)),"") | U11: =COUNTA(G11:G45,H16:H23,K16:K18,L16:L18,O16:P23,O25:P45,H25:H45) -> 128
B12: 2 | F12: =VLOOKUP(B12,'ACS Price List'!$A$12:$P$180,2,FALSE) -> Application fee - Basic or standard connection - Micro-embedded generators | G12: =IF(VLOOKUP($B12,'ACS Price List'!$A$12:$P$180,G$1,FALSE)=0,"",VLOOKUP($B12,'ACS Price List'!$A$12:$P$180,G$1,FALSE)) -> APFMEG | H12: =IF(VLOOKUP($B12,'ACS Price List'!$A$12:$P$180,H$1,FALSE)=0,"",VLOOKUP($B12,'ACS Price List'!$A$12:$P$180,H$1,FALSE)) | K12: =IFERROR(IF(VLOOKUP($C12,'ACS Price List'!$A$12:$P$180,G$1,FALSE)=0,"",VLOOKUP($C12,'ACS Price List'!$A$12:$P$180,G$1,FALSE)),"") | L12: =IFERROR(IF(VLOOKUP($C12,'ACS Price List'!$A$12:$P$180,H$1,FALSE)=0,"",VLOOKUP($C12,'ACS Price List'!$A$12:$P$180,H$1,FALSE)),"") | O12: =IFERROR(IF(VLOOKUP($D12,'ACS Price List'!$A$12:$P$180,G$1,FALSE)=0,"",VLOOKUP($D12,'ACS Price List'!$A$12:$P$180,G$1,FALSE)),"") | P12: =IFERROR(IF(VLOOKUP($D12,'ACS Price List'!$A$12:$P$180,H$1,FALSE)=0,"",VLOOKUP($D12,'ACS Price List'!$A$12:$P$180,H$1,FALSE)),"")
B13: 3 | F13: =VLOOKUP(B13,'ACS Price List'!$A$12:$P$180,2,FALSE) -> Application fee - Basic or standard connection - Micro-embedded generators - Technical assessment required | G13: =IF(VLOOKUP($B13,'ACS Price List'!$A$12:$P$180,G$1,FALSE)=0,"",VLOOKUP($B13,'ACS Price List'!$A$12:$P$180,G$1,FALSE)) -> APFMTA | H13: =IF(VLOOKUP($B13,'ACS Price List'!$A$12:$P$180,H$1,FALSE)=0,"",VLOOKUP($B13,'ACS Price List'!$A$12:$P$180,H$1,FALSE)) | K13: =IFERROR(IF(VLOOKUP($C13,'ACS Price List'!$A$12:$P$180,G$1,FALSE)=0,"",VLOOKUP($C13,'ACS Price List'!$A$12:$P$180,G$1,FALSE)),"") | L13: =IFERROR(IF(VLOOKUP($C13,'ACS Price List'!$A$12:$P$180,H$1,FALSE)=0,"",VLOOKUP($C13,'ACS Price List'!$A$12:$P$180,H$1,FALSE)),"") | O13: =IFERROR(IF(VLOOKUP($D13,'ACS Price List'!$A$12:$P$180,G$1,FALSE)=0,"",VLOOKUP($D13,'ACS Price List'!$A$12:$P$180,G$1,FALSE)),"") | P13: =IFERROR(IF(VLOOKUP($D13,'ACS Price List'!$A$12:$P$180,H$1,FALSE)=0,"",VLOOKUP($D13,'ACS Price List'!$A$12:$P$180,H$1,FALSE)),"")
B14: 4 | F14: =VLOOKUP(B14,'ACS Price List'!$A$12:$P$180,2,FALSE) -> Application fee - Real estate development connection | G14: =IF(VLOOKUP($B14,'ACS Price List'!$A$12:$P$180,G$1,FALSE)=0,"",VLOOKUP($B14,'ACS Price List'!$A$12:$P$180,G$1,FALSE)) -> APFRED | H14: =IF(VLOOKUP($B14,'ACS Price List'!$A$12:$P$180,H$1,FALSE)=0,"",VLOOKUP($B14,'ACS Price List'!$A$12:$P$180,H$1,FALSE)) | K14: =IFERROR(IF(VLOOKUP($C14,'ACS Price List'!$A$12:$P$180,G$1,FALSE)=0,"",VLOOKUP($C14,'ACS Price List'!$A$12:$P$180,G$1,FALSE)),"") | L14: =IFERROR(IF(VLOOKUP($C14,'ACS Price List'!$A$12:$P$180,H$1,FALSE)=0,"",VLOOKUP($C14,'ACS Price List'!$A$12:$P$180,H$1,FALSE)),"") | O14: =IFERROR(IF(VLOOKUP($D14,'ACS Price List'!$A$12:$P$180,G$1,FALSE)=0,"",VLOOKUP($D14,'ACS Price List'!$A$12:$P$180,G$1,FALSE)),"") | P14: =IFERROR(IF(VLOOKUP($D14,'ACS Price List'!$A$12:$P$180,H$1,FALSE)=0,"",VLOOKUP($D14,'ACS Price List'!$A$12:$P$180,H$1,FALSE)),"")
B15: 5 | F15: =VLOOKUP(B15,'ACS Price List'!$A$12:$P$180,2,FALSE) -> Protection and Power Quality assessment prior to connection | G15: =IF(VLOOKUP($B15,'ACS Price List'!$A$12:$P$180,G$1,FALSE)=0,"",VLOOKUP($B15,'ACS Price List'!$A$12:$P$180,G$1,FALSE)) -> PPQA | H15: =IF(VLOOKUP($B15,'ACS Price List'!$A$12:$P$180,H$1,FALSE)=0,"",VLOOKUP($B15,'ACS Price List'!$A$12:$P$180,H$1,FALSE)) | K15: =IFERROR(IF(VLOOKUP($C15,'ACS Price List'!$A$12:$P$180,G$1,FALSE)=0,"",VLOOKUP($C15,'ACS Price List'!$A$12:$P$180,G$1,FALSE)),"") | L15: =IFERROR(IF(VLOOKUP($C15,'ACS Price List'!$A$12:$P$180,H$1,FALSE)=0,"",VLOOKUP($C15,'ACS Price List'!$A$12:$P$180,H$1,FALSE)),"") | O15: =IFERROR(IF(VLOOKUP($D15,'ACS Price List'!$A$12:$P$180,G$1,FALSE)=0,"",VLOOKUP($D15,'ACS Price List'!$A$12:$P$180,G$1,FALSE)),"") | P15: =IFERROR(IF(VLOOKUP($D15,'ACS Price List'!$A$12:$P$180,H$1,FALSE)=0,"",VLOOKUP($D15,'ACS Price List'!$A$12:$P$180,H$1,FALSE)),"")
B16: 6 | C16: 161-M | D16: 6-CF | F16: =VLOOKUP(B16,'ACS Price List'!$A$12:$P$180,2,FALSE) -> Temporary connection, not in permanent position - single phase metered - urban/short rural feeders | G16: =IF(VLOOKUP($B16,'ACS Price List'!$A$12:$P$180,G$1,FALSE)=0,"",VLOOKUP($B16,'ACS Price List'!$A$12:$P$180,G$1,FALSE)) -> TBSSPU | H16: =IF(VLOOKUP($B16,'ACS Price List'!$A$12:$P$180,H$1,FALSE)=0,"",VLOOKUP($B16,'ACS Price List'!$A$12:$P$180,H$1,FALSE)) -> TBSSPS | K16: =IFERROR(IF(VLOOKUP($C16,'ACS Price List'!$A$12:$P$180,G$1,FALSE)=0,"",VLOOKUP($C16,'ACS Price List'!$A$12:$P$180,G$1,FALSE)),"") -> MTBSU | L16: =IFERROR(IF(VLOOKUP($C16,'ACS Price List'!$A$12:$P$180,H$1,FALSE)=0,"",VLOOKUP($C16,'ACS Price List'!$A$12:$P$180,H$1,FALSE)),"") -> MTBSS | O16: =IFERROR(IF(VLOOKUP($D16,'ACS Price List'!$A$12:$P$180,G$1,FALSE)=0,"",VLOOKUP($D16,'ACS Price List'!$A$12:$P$180,G$1,FALSE)),"") -> CFTBSSPU | P16: =IFERROR(IF(VLOOKUP($D16,'ACS Price List'!$A$12:$P$180,H$1,FALSE)=0,"",VLOOKUP($D16,'ACS Price List'!$A$12:$P$180,H$1,FALSE)),"") -> CFTBSSPS
B17: 8 | C17: 161-M | D17: 8-CF | F17: =VLOOKUP(B17,'ACS Price List'!$A$12:$P$180,2,FALSE) -> Temporary connection, not in permanent position - multi phase metered - urban/short rural feeders | G17: =IF(VLOOKUP($B17,'ACS Price List'!$A$12:$P$180,G$1,FALSE)=0,"",VLOOKUP($B17,'ACS Price List'!$A$12:$P$180,G$1,FALSE)) -> TBSMPU | H17: =IF(VLOOKUP($B17,'ACS Price List'!$A$12:$P$180,H$1,FALSE)=0,"",VLOOKUP($B17,'ACS Price List'!$A$12:$P$180,H$1,FALSE)) -> TBSMPS | K17: =IFERROR(IF(VLOOKUP($C17,'ACS Price List'!$A$12:$P$180,G$1,FALSE)=0,"",VLOOKUP($C17,'ACS Price List'!$A$12:$P$180,G$1,FALSE)),"") -> MTBSU | L17: =IFERROR(IF(VLOOKUP($C17,'ACS Price List'!$A$12:$P$180,H$1,FALSE)=0,"",VLOOKUP($C17,'ACS Price List'!$A$12:$P$180,H$1,FALSE)),"") -> MTBSS | O17: =IFERROR(IF(VLOOKUP($D17,'ACS Price List'!$A$12:$P$180,G$1,FALSE)=0,"",VLOOKUP($D17,'ACS Price List'!$A$12:$P$180,G$1,FALSE)),"") -> CFTBSMPU | P17: =IFERROR(IF(VLOOKUP($D17,'ACS Price List'!$A$12:$P$180,H$1,FALSE)=0,"",VLOOKUP($D17,'ACS Price List'!$A$12:$P$180,H$1,FALSE)),"") -> CFTBSMPS
B18: 10 | C18: 162-M | D18: 10-CF | F18: =VLOOKUP(B18,'ACS Price List'!$A$12:$P$180,2,FALSE) -> Supply abolishment during business hours - urban/short rural feeders | G18: =IF(VLOOKUP($B18,'ACS Price List'!$A$12:$P$180,G$1,FALSE)=0,"",VLOOKUP($B18,'ACS Price List'!$A$12:$P$180,G$1,FALSE)) -> SUPABOLU | H18: =IF(VLOOKUP($B18,'ACS Price List'!$A$12:$P$180,H$1,FALSE)=0,"",VLOOKUP($B18,'ACS Price List'!$A$12:$P$180,H$1,FALSE)) -> SUPABOLS | K18: =IFERROR(IF(VLOOKUP($C18,'ACS Price List'!$A$12:$P$180,G$1,FALSE)=0,"",VLOOKUP($C18,'ACS Price List'!$A$12:$P$180,G$1,FALSE)),"") -> MSUPABOLU | L18: =IFERROR(IF(VLOOKUP($C18,'ACS Price List'!$A$12:$P$180,H$1,FALSE)=0,"",VLOOKUP($C18,'ACS Price List'!$A$12:$P$180,H$1,FALSE)),"") -> MSUPABOLS | O18: =IFERROR(IF(VLOOKUP($D18,'ACS Price List'!$A$12:$P$180,G$1,FALSE)=0,"",VLOOKUP($D18,'ACS Price List'!$A$12:$P$180,G$1,FALSE)),"") -> CFSUPABOLU | P18: =IFERROR(IF(VLOOKUP($D18,'ACS Price List'!$A$12:$P$180,H$1,FALSE)=0,"",VLOOKUP($D18,'ACS Price List'!$A$12:$P$180,H$1,FALSE)),"") -> CFSUPABOLS
B19: 12 | D19: 12-CF | F19: =VLOOKUP(B19,'ACS Price List'!$A$12:$P$180,2,FALSE) -> De-energisation during business hours - urban/short rural feeders | G19: =IF(VLOOKUP($B19,'ACS Price List'!$A$12:$P$180,G$1,FALSE)=0,"",VLOOKUP($B19,'ACS Price List'!$A$12:$P$180,G$1,FALSE)) -> DEENBHU | H19: =IF(VLOOKUP($B19,'ACS Price List'!$A$12:$P$180,H$1,FALSE)=0,"",VLOOKUP($B19,'ACS Price List'!$A$12:$P$180,H$1,FALSE)) -> DEENBHS | K19: =IFERROR(IF(VLOOKUP($C19,'ACS Price List'!$A$12:$P$180,G$1,FALSE)=0,"",VLOOKUP($C19,'ACS Price List'!$A$12:$P$180,G$1,FALSE)),"") | L19: =IFERROR(IF(VLOOKUP($C19,'ACS Price List'!$A$12:$P$180,H$1,FALSE)=0,"",VLOOKUP($C19,'ACS Price List'!$A$12:$P$180,H$1,FALSE)),"") | O19: =IFERROR(IF(VLOOKUP($D19,'ACS Price List'!$A$12:$P$180,G$1,FALSE)=0,"",VLOOKUP($D19,'ACS Price List'!$A$12:$P$180,G$1,FALSE)),"") -> CFDEENBHU | P19: =IFERROR(IF(VLOOKUP($D19,'ACS Price List'!$A$12:$P$180,H$1,FALSE)=0,"",VLOOKUP($D19,'ACS Price List'!$A$12:$P$180,H$1,FALSE)),"") -> CFDEENBHS
B20: 14 | D20: 14-CF | F20: =VLOOKUP(B20,'ACS Price List'!$A$12:$P$180,2,FALSE) -> Re-energisation during business hours - urban/short rural feeders | G20: =IF(VLOOKUP($B20,'ACS Price List'!$A$12:$P$180,G$1,FALSE)=0,"",VLOOKUP($B20,'ACS Price List'!$A$12:$P$180,G$1,FALSE)) -> REENBHU | H20: =IF(VLOOKUP($B20,'ACS Price List'!$A$12:$P$180,H$1,FALSE)=0,"",VLOOKUP($B20,'ACS Price List'!$A$12:$P$180,H$1,FALSE)) -> REENBHS | K20: =IFERROR(IF(VLOOKUP($C20,'ACS Price List'!$A$12:$P$180,G$1,FALSE)=0,"",VLOOKUP($C20,'ACS Price List'!$A$12:$P$180,G$1,FALSE)),"") | L20: =IFERROR(IF(VLOOKUP($C20,'ACS Price List'!$A$12:$P$180,H$1,FALSE)=0,"",VLOOKUP($C20,'ACS Price List'!$A$12:$P$180,H$1,FALSE)),"") | O20: =IFERROR(IF(VLOOKUP($D20,'ACS Price List'!$A$12:$P$180,G$1,FALSE)=0,"",VLOOKUP($D20,'ACS Price List'!$A$12:$P$180,G$1,FALSE)),"") -> CFREENBHU | P20: =IFERROR(IF(VLOOKUP($D20,'ACS Price List'!$A$12:$P$180,H$1,FALSE)=0,"",VLOOKUP($D20,'ACS Price List'!$A$12:$P$180,H$1,FALSE)),"") -> CFREENBHS
B21: 14-VE | D21: 14-CF | F21: =VLOOKUP(B21,'ACS Price List'!$A$12:$P$180,2,FALSE) -> Visual examination during business hours for remote re-energisation - urban/short rural feeders | G21: =IF(VLOOKUP($B21,'ACS Price List'!$A$12:$P$180,G$1,FALSE)=0,"",VLOOKUP($B21,'ACS Price List'!$A$12:$P$180,G$1,FALSE)) -> VEREENBHU | H21: =IF(VLOOKUP($B21,'ACS Price List'!$A$12:$P$180,H$1,FALSE)=0,"",VLOOKUP($B21,'ACS Price List'!$A$12:$P$180,H$1,FALSE)) -> VEREENBHS | K21: =IFERROR(IF(VLOOKUP($C21,'ACS Price List'!$A$12:$P$180,G$1,FALSE)=0,"",VLOOKUP($C21,'ACS Price List'!$A$12:$P$180,G$1,FALSE)),"") | L21: =IFERROR(IF(VLOOKUP($C21,'ACS Price List'!$A$12:$P$180,H$1,FALSE)=0,"",VLOOKUP($C21,'ACS Price List'!$A$12:$P$180,H$1,FALSE)),"") | O21: =IFERROR(IF(VLOOKUP($D21,'ACS Price List'!$A$12:$P$180,G$1,FALSE)=0,"",VLOOKUP($D21,'ACS Price List'!$A$12:$P$180,G$1,FALSE)),"") -> CFREENBHU | P21: =IFERROR(IF(VLOOKUP($D21,'ACS Price List'!$A$12:$P$180,H$1,FALSE)=0,"",VLOOKUP($D21,'ACS Price List'!$A$12:$P$180,H$1,FALSE)),"") -> CFREENBHS
B22: 16 | D22: 16-CF | F22: =VLOOKUP(B22,'ACS Price List'!$A$12:$P$180,2,FALSE) -> Re-energisation during business hours - after de-energisation for debt - urban/short rural feeders | G22: =IF(VLOOKUP($B22,'ACS Price List'!$A$12:$P$180,G$1,FALSE)=0,"",VLOOKUP($B22,'ACS Price List'!$A$12:$P$180,G$1,FALSE)) -> REDDBHU | H22: =IF(VLOOKUP($B22,'ACS Price List'!$A$12:$P$180,H$1,FALSE)=0,"",VLOOKUP($B22,'ACS Price List'!$A$12:$P$180,H$1,FALSE)) -> REDDBHS | K22: =IFERROR(IF(VLOOKUP($C22,'ACS Price List'!$A$12:$P$180,G$1,FALSE)=0,"",VLOOKUP($C22,'ACS Price List'!$A$12:$P$180,G$1,FALSE)),"") | L22: =IFERROR(IF(VLOOKUP($C22,'ACS Price List'!$A$12:$P$180,H$1,FALSE)=0,"",VLOOKUP($C22,'ACS Price List'!$A$12:$P$180,H$1,FALSE)),"") | O22: =IFERROR(IF(VLOOKUP($D22,'ACS Price List'!$A$12:$P$180,G$1,FALSE)=0,"",VLOOKUP($D22,'ACS Price List'!$A$12:$P$180,G$1,FALSE)),"") -> CFREDDBHU | P22: =IFERROR(IF(VLOOKUP($D22,'ACS Price List'!$A$12:$P$180,H$1,FALSE)=0,"",VLOOKUP($D22,'ACS Price List'!$A$12:$P$180,H$1,FALSE)),"") -> CFREDDBHS
B23: 16-VE | D23: 16-CF | F23: =VLOOKUP(B23,'ACS Price List'!$A$12:$P$180,2,FALSE) -> Visual examination during business hours for remote re-energisation - after de-energisation for debt - urban/short rural feeders | G23: =IF(VLOOKUP($B23,'ACS Price List'!$A$12:$P$180,G$1,FALSE)=0,"",VLOOKUP($B23,'ACS Price List'!$A$12:$P$180,G$1,FALSE)) -> VEREDDBHU | H23: =IF(VLOOKUP($B23,'ACS Price List'!$A$12:$P$180,H$1,FALSE)=0,"",VLOOKUP($B23,'ACS Price List'!$A$12:$P$180,H$1,FALSE)) -> VEREDDBHS | K23: =IFERROR(IF(VLOOKUP($C23,'ACS Price List'!$A$12:$P$180,G$1,FALSE)=0,"",VLOOKUP($C23,'ACS Price List'!$A$12:$P$180,G$1,FALSE)),"") | L23: =IFERROR(IF(VLOOKUP($C23,'ACS Price List'!$A$12:$P$180,H$1,FALSE)=0,"",VLOOKUP($C23,'ACS Price List'!$A$12:$P$180,H$1,FALSE)),"") | O23: =IFERROR(IF(VLOOKUP($D23,'ACS Price List'!$A$12:$P$180,G$1,FALSE)=0,"",VLOOKUP($D23,'ACS Price List'!$A$12:$P$180,G$1,FALSE)),"") -> CFREDDBHU | P23: =IFERROR(IF(VLOOKUP($D23,'ACS Price List'!$A$12:$P$180,H$1,FALSE)=0,"",VLOOKUP($D23,'ACS Price List'!$A$12:$P$180,H$1,FALSE)),"") -> CFREDDBHS
B24: 18 | F24: =VLOOKUP(B24,'ACS Price List'!$A$12:$P$180,2,FALSE) -> Accreditation of alternative service providers - real estate developments | G24: =IF(VLOOKUP($B24,'ACS Price List'!$A$12:$P$180,G$1,FALSE)=0,"",VLOOKUP($B24,'ACS Price List'!$A$12:$P$180,G$1,FALSE)) -> ASPRED | H24: =IF(VLOOKUP($B24,'ACS Price List'!$A$12:$P$180,H$1,FALSE)=0,"",VLOOKUP($B24,'ACS Price List'!$A$12:$P$180,H$1,FALSE)) | K24: =IFERROR(IF(VLOOKUP($C24,'ACS Price List'!$A$12:$P$180,G$1,FALSE)=0,"",VLOOKUP($C24,'ACS Price List'!$A$12:$P$180,G$1,FALSE)),"") | L24: =IFERROR(IF(VLOOKUP($C24,'ACS Price List'!$A$12:$P$180,H$1,FALSE)=0,"",VLOOKUP($C24,'ACS Price List'!$A$12:$P$180,H$1,FALSE)),"") | O24: =IFERROR(IF(VLOOKUP($D24,'ACS Price List'!$A$12:$P$180,G$1,FALSE)=0,"",VLOOKUP($D24,'ACS Price List'!$A$12:$P$180,G$1,FALSE)),"") | P24: =IFERROR(IF(VLOOKUP($D24,'ACS Price List'!$A$12:$P$180,H$1,FALSE)=0,"",VLOOKUP($D24,'ACS Price List'!$A$12:$P$180,H$1,FALSE)),"")
B25: 19 | D25: 19-CF | F25: =VLOOKUP(B25,'ACS Price List'!$A$12:$P$180,2,FALSE) -> Install replacement meter (Type 5 and 6) – Single phase – urban/short rural feeder | G25: =IF(VLOOKUP($B25,'ACS Price List'!$A$12:$P$180,G$1,FALSE)=0,"",VLOOKUP($B25,'ACS Price List'!$A$12:$P$180,G$1,FALSE)) -> MSNGLU | H25: =IF(VLOOKUP($B25,'ACS Price List'!$A$12:$P$180,H$1,FALSE)=0,"",VLOOKUP($B25,'ACS Price List'!$A$12:$P$180,H$1,FALSE)) -> MSNGLS | K25: =IFERROR(IF(VLOOKUP($C25,'ACS Price List'!$A$12:$P$180,G$1,FALSE)=0,"",VLOOKUP($C25,'ACS Price List'!$A$12:$P$180,G$1,FALSE)),"") | L25: =IFERROR(IF(VLOOKUP($C25,'ACS Price List'!$A$12:$P$180,H$1,FALSE)=0,"",VLOOKUP($C25,'ACS Price List'!$A$12:$P$180,H$1,FALSE)),"") | O25: =IFERROR(IF(VLOOKUP($D25,'ACS Price List'!$A$12:$P$180,G$1,FALSE)=0,"",VLOOKUP($D25,'ACS Price List'!$A$12:$P$180,G$1,FALSE)),"") -> CFMSNGLU | P25: =IFERROR(IF(VLOOKUP($D25,'ACS Price List'!$A$12:$P$180,H$1,FALSE)=0,"",VLOOKUP($D25,'ACS Price List'!$A$12:$P$180,H$1,FALSE)),"") -> CFMSNGLS
B26: 21 | D26: 21-CF | F26: =VLOOKUP(B26,'ACS Price List'!$A$12:$P$180,2,FALSE) -> Install replacement meter (Type 5 and 6) – Dual element – urban/short rural feeder | G26: =IF(VLOOKUP($B26,'ACS Price List'!$A$12:$P$180,G$1,FALSE)=0,"",VLOOKUP($B26,'ACS Price List'!$A$12:$P$180,G$1,FALSE)) -> MDUALU | H26: =IF(VLOOKUP($B26,'ACS Price List'!$A$12:$P$180,H$1,FALSE)=0,"",VLOOKUP($B26,'ACS Price List'!$A$12:$P$180,H$1,FALSE)) -> MDUALS | K26: =IFERROR(IF(VLOOKUP($C26,'ACS Price List'!$A$12:$P$180,G$1,FALSE)=0,"",VLOOKUP($C26,'ACS Price List'!$A$12:$P$180,G$1,FALSE)),"") | L26: =IFERROR(IF(VLOOKUP($C26,'ACS Price List'!$A$12:$P$180,H$1,FALSE)=0,"",VLOOKUP($C26,'ACS Price List'!$A$12:$P$180,H$1,FALSE)),"") | O26: =IFERROR(IF(VLOOKUP($D26,'ACS Price List'!$A$12:$P$180,G$1,FALSE)=0,"",VLOOKUP($D26,'ACS Price List'!$A$12:$P$180,G$1,FALSE)),"") -> CFMDUALU | P26: =IFERROR(IF(VLOOKUP($D26,'ACS Price List'!$A$12:$P$180,H$1,FALSE)=0,"",VLOOKUP($D26,'ACS Price List'!$A$12:$P$180,H$1,FALSE)),"") -> CFMDUALS
B27: 23 | D27: 23-CF | F27: =VLOOKUP(B27,'ACS Price List'!$A$12:$P$180,2,FALSE) -> Install replacement meter (Type 5 and 6) – Polyphase – urban/short rural feeder | G27: =IF(VLOOKUP($B27,'ACS Price List'!$A$12:$P$180,G$1,FALSE)=0,"",VLOOKUP($B27,'ACS Price List'!$A$12:$P$180,G$1,FALSE)) -> MTHREU | H27: =IF(VLOOKUP($B27,'ACS Price List'!$A$12:$P$180,H$1,FALSE)=0,"",VLOOKUP($B27,'ACS Price List'!$A$12:$P$180,H$1,FALSE)) -> MTHRES | K27: =IFERROR(IF(VLOOKUP($C27,'ACS Price List'!$A$12:$P$180,G$1,FALSE)=0,"",VLOOKUP($C27,'ACS Price List'!$A$12:$P$180,G$1,FALSE)),"") | L27: =IFERROR(IF(VLOOKUP($C27,'ACS Price List'!$A$12:$P$180,H$1,FALSE)=0,"",VLOOKUP($C27,'ACS Price List'!$A$12:$P$180,H$1,FALSE)),"") | O27: =IFERROR(IF(VLOOKUP($D27,'ACS Price List'!$A$12:$P$180,G$1,FALSE)=0,"",VLOOKUP($D27,'ACS Price List'!$A$12:$P$180,G$1,FALSE)),"") -> CFMTHREU | P27: =IFERROR(IF(VLOOKUP($D27,'ACS Price List'!$A$12:$P$180,H$1,FALSE)=0,"",VLOOKUP($D27,'ACS Price List'!$A$12:$P$180,H$1,FALSE)),"") -> CFMTHRES
B28: 25 | D28: 25-CF | F28: =VLOOKUP(B28,'ACS Price List'!$A$12:$P$180,2,FALSE) -> Install replacement meter (CT) – urban/short rural feeder | G28: =IF(VLOOKUP($B28,'ACS Price List'!$A$12:$P$180,G$1,FALSE)=0,"",VLOOKUP($B28,'ACS Price List'!$A$12:$P$180,G$1,FALSE)) -> MCTU | H28: =IF(VLOOKUP($B28,'ACS Price List'!$A$12:$P$180,H$1,FALSE)=0,"",VLOOKUP($B28,'ACS Price List'!$A$12:$P$180,H$1,FALSE)) -> MCTS | K28: =IFERROR(IF(VLOOKUP($C28,'ACS Price List'!$A$12:$P$180,G$1,FALSE)=0,"",VLOOKUP($C28,'ACS Price List'!$A$12:$P$180,G$1,FALSE)),"") | L28: =IFERROR(IF(VLOOKUP($C28,'ACS Price List'!$A$12:$P$180,H$1,FALSE)=0,"",VLOOKUP($C28,'ACS Price List'!$A$12:$P$180,H$1,FALSE)),"") | O28: =IFERROR(IF(VLOOKUP($D28,'ACS Price List'!$A$12:$P$180,G$1,FALSE)=0,"",VLOOKUP($D28,'ACS Price List'!$A$12:$P$180,G$1,FALSE)),"") -> CFMCTU | P28: =IFERROR(IF(VLOOKUP($D28,'ACS Price List'!$A$12:$P$180,H$1,FALSE)=0,"",VLOOKUP($D28,'ACS Price List'!$A$12:$P$180,H$1,FALSE)),"") -> CFMCTS
B29: 140 | D29: 157-CF | F29: =VLOOKUP(B29,'ACS Price List'!$A$12:$P$180,2,FALSE) -> Install new meter (Type 5 and 6) – Single phase – Primary | G29: =IF(VLOOKUP($B29,'ACS Price List'!$A$12:$P$180,G$1,FALSE)=0,"",VLOOKUP($B29,'ACS Price List'!$A$12:$P$180,G$1,FALSE)) -> NMSPU | H29: =IF(VLOOKUP($B29,'ACS Price List'!$A$12:$P$180,H$1,FALSE)=0,"",VLOOKUP($B29,'ACS Price List'!$A$12:$P$180,H$1,FALSE)) -> NMSPS | K29: =IFERROR(IF(VLOOKUP($C29,'ACS Price List'!$A$12:$P$180,G$1,FALSE)=0,"",VLOOKUP($C29,'ACS Price List'!$A$12:$P$180,G$1,FALSE)),"") | L29: =IFERROR(IF(VLOOKUP($C29,'ACS Price List'!$A$12:$P$180,H$1,FALSE)=0,"",VLOOKUP($C29,'ACS Price List'!$A$12:$P$180,H$1,FALSE)),"") | O29: =IFERROR(IF(VLOOKUP($D29,'ACS Price List'!$A$12:$P$180,G$1,FALSE)=0,"",VLOOKUP($D29,'ACS Price List'!$A$12:$P$180,G$1,FALSE)),"") -> CFNMSPU | P29: =IFERROR(IF(VLOOKUP($D29,'ACS Price List'!$A$12:$P$180,H$1,FALSE)=0,"",VLOOKUP($D29,'ACS Price List'!$A$12:$P$180,H$1,FALSE)),"") -> CFNMSPS
B30: 141 | D30: 157-CF | F30: =VLOOKUP(B30,'ACS Price List'!$A$12:$P$180,2,FALSE) -> Install new meter (Type 5 and 6) – Single phase – Primary plus embedded generation | G30: =IF(VLOOKUP($B30,'ACS Price List'!$A$12:$P$180,G$1,FALSE)=0,"",VLOOKUP($B30,'ACS Price List'!$A$12:$P$180,G$1,FALSE)) -> NMSPEGU | H30: =IF(VLOOKUP($B30,'ACS Price List'!$A$12:$P$180,H$1,FALSE)=0,"",VLOOKUP($B30,'ACS Price List'!$A$12:$P$180,H$1,FALSE)) -> NMSPEGS | K30: =IFERROR(IF(VLOOKUP($C30,'ACS Price List'!$A$12:$P$180,G$1,FALSE)=0,"",VLOOKUP($C30,'ACS Price List'!$A$12:$P$180,G$1,FALSE)),"") | L30: =IFERROR(IF(VLOOKUP($C30,'ACS Price List'!$A$12:$P$180,H$1,FALSE)=0,"",VLOOKUP($C30,'ACS Price List'!$A$12:$P$180,H$1,FALSE)),"") | O30: =IFERROR(IF(VLOOKUP($D30,'ACS Price List'!$A$12:$P$180,G$1,FALSE)=0,"",VLOOKUP($D30,'ACS Price List'!$A$12:$P$180,G$1,FALSE)),"") -> CFNMSPU | P30: =IFERROR(IF(VLOOKUP($D30,'ACS Price List'!$A$12:$P$180,H$1,FALSE)=0,"",VLOOKUP($D30,'ACS Price List'!$A$12:$P$180,H$1,FALSE)),"") -> CFNMSPS
B31: 142 | D31: 158-CF | F31: =VLOOKUP(B31,'ACS Price List'!$A$12:$P$180,2,FALSE) -> Install new meter (Type 5 and 6) – Dual element – Primary plus controlled load | G31: =IF(VLOOKUP($B31,'ACS Price List'!$A$12:$P$180,G$1,FALSE)=0,"",VLOOKUP($B31,'ACS Price List'!$A$12:$P$180,G$1,FALSE)) -> NMDPCLU | H31: =IF(VLOOKUP($B31,'ACS Price List'!$A$12:$P$180,H$1,FALSE)=0,"",VLOOKUP($B31,'ACS Price List'!$A$12:$P$180,H$1,FALSE)) -> NMDPCLS | K31: =IFERROR(IF(VLOOKUP($C31,'ACS Price List'!$A$12:$P$180,G$1,FALSE)=0,"",VLOOKUP($C31,'ACS Price List'!$A$12:$P$180,G$1,FALSE)),"") | L31: =IFERROR(IF(VLOOKUP($C31,'ACS Price List'!$A$12:$P$180,H$1,FALSE)=0,"",VLOOKUP($C31,'ACS Price List'!$A$12:$P$180,H$1,FALSE)),"") | O31: =IFERROR(IF(VLOOKUP($D31,'ACS Price List'!$A$12:$P$180,G$1,FALSE)=0,"",VLOOKUP($D31,'ACS Price List'!$A$12:$P$180,G$1,FALSE)),"") -> CFNMDUALU | P31: =IFERROR(IF(VLOOKUP($D31,'ACS Price List'!$A$12:$P$180,H$1,FALSE)=0,"",VLOOKUP($D31,'ACS Price List'!$A$12:$P$180,H$1,FALSE)),"") -> CFNMDUALS
B32: 143 | D32: 158-CF | F32: =VLOOKUP(B32,'ACS Price List'!$A$12:$P$180,2,FALSE) -> Install new meter (Type 5 and 6) – Dual element – Primary plus controlled load plus embedded generation | G32: =IF(VLOOKUP($B32,'ACS Price List'!$A$12:$P$180,G$1,FALSE)=0,"",VLOOKUP($B32,'ACS Price List'!$A$12:$P$180,G$1,FALSE)) -> NMDPCLEGU | H32: =IF(VLOOKUP($B32,'ACS Price List'!$A$12:$P$180,H$1,FALSE)=0,"",VLOOKUP($B32,'ACS Price List'!$A$12:$P$180,H$1,FALSE)) -> NMDPCLEGS | K32: =IFERROR(IF(VLOOKUP($C32,'ACS Price List'!$A$12:$P$180,G$1,FALSE)=0,"",VLOOKUP($C32,'ACS Price List'!$A$12:$P$180,G$1,FALSE)),"") | L32: =IFERROR(IF(VLOOKUP($C32,'ACS Price List'!$A$12:$P$180,H$1,FALSE)=0,"",VLOOKUP($C32,'ACS Price List'!$A$12:$P$180,H$1,FALSE)),"") | O32: =IFERROR(IF(VLOOKUP($D32,'ACS Price List'!$A$12:$P$180,G$1,FALSE)=0,"",VLOOKUP($D32,'ACS Price List'!$A$12:$P$180,G$1,FALSE)),"") -> CFNMDUALU | P32: =IFERROR(IF(VLOOKUP($D32,'ACS Price List'!$A$12:$P$180,H$1,FALSE)=0,"",VLOOKUP($D32,'ACS Price List'!$A$12:$P$180,H$1,FALSE)),"") -> CFNMDUALS
B33: 144 | D33: 159-CF | F33: =VLOOKUP(B33,'ACS Price List'!$A$12:$P$180,2,FALSE) -> Install new meter (Type 5 and 6) – Polyphase – Primary | G33: =IF(VLOOKUP($B33,'ACS Price List'!$A$12:$P$180,G$1,FALSE)=0,"",VLOOKUP($B33,'ACS Price List'!$A$12:$P$180,G$1,FALSE)) -> NMPPU | H33: =IF(VLOOKUP($B33,'ACS Price List'!$A$12:$P$180,H$1,FALSE)=0,"",VLOOKUP($B33,'ACS Price List'!$A$12:$P$180,H$1,FALSE)) -> NMPPS | K33: =IFERROR(IF(VLOOKUP($C33,'ACS Price List'!$A$12:$P$180,G$1,FALSE)=0,"",VLOOKUP($C33,'ACS Price List'!$A$12:$P$180,G$1,FALSE)),"") | L33: =IFERROR(IF(VLOOKUP($C33,'ACS Price List'!$A$12:$P$180,H$1,FALSE)=0,"",VLOOKUP($C33,'ACS Price List'!$A$12:$P$180,H$1,FALSE)),"") | O33: =IFERROR(IF(VLOOKUP($D33,'ACS Price List'!$A$12:$P$180,G$1,FALSE)=0,"",VLOOKUP($D33,'ACS Price List'!$A$12:$P$180,G$1,FALSE)),"") -> CFNMTHREU | P33: =IFERROR(IF(VLOOKUP($D33,'ACS Price List'!$A$12:$P$180,H$1,FALSE)=0,"",VLOOKUP($D33,'ACS Price List'!$A$12:$P$180,H$1,FALSE)),"") -> CFNMTHRES
B34: 145 | D34: 159-CF | F34: =VLOOKUP(B34,'ACS Price List'!$A$12:$P$180,2,FALSE) -> Install new meter (Type 5 and 6) – Polyphase – Primary plus embedded generation | G34: =IF(VLOOKUP($B34,'ACS Price List'!$A$12:$P$180,G$1,FALSE)=0,"",VLOOKUP($B34,'ACS Price List'!$A$12:$P$180,G$1,FALSE)) -> NMPPEGU | H34: =IF(VLOOKUP($B34,'ACS Price List'!$A$12:$P$180,H$1,FALSE)=0,"",VLOOKUP($B34,'ACS Price List'!$A$12:$P$180,H$1,FALSE)) -> NMPPEGS | K34: =IFERROR(IF(VLOOKUP($C34,'ACS Price List'!$A$12:$P$180,G$1,FALSE)=0,"",VLOOKUP($C34,'ACS Price List'!$A$12:$P$180,G$1,FALSE)),"") | L34: =IFERROR(IF(VLOOKUP($C34,'ACS Price List'!$A$12:$P$180,H$1,FALSE)=0,"",VLOOKUP($C34,'ACS Price List'!$A$12:$P$180,H$1,FALSE)),"") | O34: =IFERROR(IF(VLOOKUP($D34,'ACS Price List'!$A$12:$P$180,G$1,FALSE)=0,"",VLOOKUP($D34,'ACS Price List'!$A$12:$P$180,G$1,FALSE)),"") -> CFNMTHREU | P34: =IFERROR(IF(VLOOKUP($D34,'ACS Price List'!$A$12:$P$180,H$1,FALSE)=0,"",VLOOKUP($D34,'ACS Price List'!$A$12:$P$180,H$1,FALSE)),"") -> CFNMTHRES
B35: 146 | D35: 160-CF | F35: =VLOOKUP(B35,'ACS Price List'!$A$12:$P$180,2,FALSE) -> Install new meter (CT) – Primary | G35: =IF(VLOOKUP($B35,'ACS Price List'!$A$12:$P$180,G$1,FALSE)=0,"",VLOOKUP($B35,'ACS Price List'!$A$12:$P$180,G$1,FALSE)) -> NMCTPU | H35: =IF(VLOOKUP($B35,'ACS Price List'!$A$12:$P$180,H$1,FALSE)=0,"",VLOOKUP($B35,'ACS Price List'!$A$12:$P$180,H$1,FALSE)) -> NMCTPS | K35: =IFERROR(IF(VLOOKUP($C35,'ACS Price List'!$A$12:$P$180,G$1,FALSE)=0,"",VLOOKUP($C35,'ACS Price List'!$A$12:$P$180,G$1,FALSE)),"") | L35: =IFERROR(IF(VLOOKUP($C35,'ACS Price List'!$A$12:$P$180,H$1,FALSE)=0,"",VLOOKUP($C35,'ACS Price List'!$A$12:$P$180,H$1,FALSE)),"") | O35: =IFERROR(IF(VLOOKUP($D35,'ACS Price List'!$A$12:$P$180,G$1,FALSE)=0,"",VLOOKUP($D35,'ACS Price List'!$A$12:$P$180,G$1,FALSE)),"") -> CFNMCTU | P35: =IFERROR(IF(VLOOKUP($D35,'ACS Price List'!$A$12:$P$180,H$1,FALSE)=0,"",VLOOKUP($D35,'ACS Price List'!$A$12:$P$180,H$1,FALSE)),"") -> CFNMCTS
B36: 147 | D36: 160-CF | F36: =VLOOKUP(B36,'ACS Price List'!$A$12:$P$180,2,FALSE) -> Install new meter (CT) – Primary plus embedded generation | G36: =IF(VLOOKUP($B36,'ACS Price List'!$A$12:$P$180,G$1,FALSE)=0,"",VLOOKUP($B36,'ACS Price List'!$A$12:$P$180,G$1,FALSE)) -> NMCTPEGU | H36: =IF(VLOOKUP($B36,'ACS Price List'!$A$12:$P$180,H$1,FALSE)=0,"",VLOOKUP($B36,'ACS Price List'!$A$12:$P$180,H$1,FALSE)) -> NMCTPEGS | K36: =IFERROR(IF(VLOOKUP($C36,'ACS Price List'!$A$12:$P$180,G$1,FALSE)=0,"",VLOOKUP($C36,'ACS Price List'!$A$12:$P$180,G$1,FALSE)),"") | L36: =IFERROR(IF(VLOOKUP($C36,'ACS Price List'!$A$12:$P$180,H$1,FALSE)=0,"",VLOOKUP($C36,'ACS Price List'!$A$12:$P$180,H$1,FALSE)),"") | O36: =IFERROR(IF(VLOOKUP($D36,'ACS Price List'!$A$12:$P$180,G$1,FALSE)=0,"",VLOOKUP($D36,'ACS Price List'!$A$12:$P$180,G$1,FALSE)),"") -> CFNMCTU | P36: =IFERROR(IF(VLOOKUP($D36,'ACS Price List'!$A$12:$P$180,H$1,FALSE)=0,"",VLOOKUP($D36,'ACS Price List'!$A$12:$P$180,H$1,FALSE)),"") -> CFNMCTS
... B45: 156 | D45: 160-CF | F45: =VLOOKUP(B45,'ACS Price List'!$A$12:$P$180,2,FALSE) -> Install new meter (CT) to accommodate embedded generation installation | G45: =IF(VLOOKUP($B45,'ACS Price List'!$A$12:$P$180,G$1,FALSE)=0,"",VLOOKUP($B45,'ACS Price List'!$A$12:$P$180,G$1,FALSE)) -> NCTAEGU | H45: =IF(VLOOKUP($B45,'ACS Price List'!$A$12:$P$180,H$1,FALSE)=0,"",VLOOKUP($B45,'ACS Price List'!$A$12:$P$180,H$1,FALSE)) -> NCTAEGS | K45: =IFERROR(IF(VLOOKUP($C45,'ACS Price List'!$A$12:$P$180,G$1,FALSE)=0,"",VLOOKUP($C45,'ACS Price List'!$A$12:$P$180,G$1,FALSE)),"") | L45: =IFERROR(IF(VLOOKUP($C45,'ACS Price List'!$A$12:$P$180,H$1,FALSE)=0,"",VLOOKUP($C45,'ACS Price List'!$A$12:$P$180,H$1,FALSE)),"") | O45: =IFERROR(IF(VLOOKUP($D45,'ACS Price List'!$A$12:$P$180,G$1,FALSE)=0,"",VLOOKUP($D45,'ACS Price List'!$A$12:$P$180,G$1,FALSE)),"") -> CFNMCTU | P45: =IFERROR(IF(VLOOKUP($D45,'ACS Price List'!$A$12:$P$180,H$1,FALSE)=0,"",VLOOKUP($D45,'ACS Price List'!$A$12:$P$180,H$1,FALSE)),"") -> CFNMCTS
B46: 1 | E46: Fee based services (long rural/isolated) | F46: =VLOOKUP(B46,'ACS Price List'!$A$12:$P$180,2,FALSE) -> Application fee - Basic or standard connection | G46: =IF(VLOOKUP($B46,'ACS Price List'!$A$12:$P$180,G$1,FALSE)=0,"",VLOOKUP($B46,'ACS Price List'!$A$12:$P$180,G$1,FALSE)) -> APFSAC | H46: =IF(VLOOKUP($B46,'ACS Price List'!$A$12:$P$180,J$1,FALSE)=0,"",VLOOKUP($B46,'ACS Price List'!$A$12:$P$180,J$1,FALSE)) | K46: =IFERROR(IF(VLOOKUP($C46,'ACS Price List'!$A$12:$P$180,I$1,FALSE)=0,"",VLOOKUP($C46,'ACS Price List'!$A$12:$P$180,I$1,FALSE)),"") | L46: =IFERROR(IF(VLOOKUP($C46,'ACS Price List'!$A$12:$P$180,J$1,FALSE)=0,"",VLOOKUP($C46,'ACS Price List'!$A$12:$P$180,J$1,FALSE)),"") | U46: =COUNTA(G46:G80,H51:H58,H60:H80,K51:K53,L51:L53,O51:O58,P51:P58,O60:O80,P60:P80) -> 128
B47: 2 | F47: =VLOOKUP(B47,'ACS Price List'!$A$12:$P$180,2,FALSE) -> Application fee - Basic or standard connection - Micro-embedded generators | G47: =IF(VLOOKUP($B47,'ACS Price List'!$A$12:$P$180,G$1,FALSE)=0,"",VLOOKUP($B47,'ACS Price List'!$A$12:$P$180,G$1,FALSE)) -> APFMEG | H47: =IF(VLOOKUP($B47,'ACS Price List'!$A$12:$P$180,J$1,FALSE)=0,"",VLOOKUP($B47,'ACS Price List'!$A$12:$P$180,J$1,FALSE)) | K47: =IFERROR(IF(VLOOKUP($C47,'ACS Price List'!$A$12:$P$180,I$1,FALSE)=0,"",VLOOKUP($C47,'ACS Price List'!$A$12:$P$180,I$1,FALSE)),"") | L47: =IFERROR(IF(VLOOKUP($C47,'ACS Price List'!$A$12:$P$180,J$1,FALSE)=0,"",VLOOKUP($C47,'ACS Price List'!$A$12:$P$180,J$1,FALSE)),"")
B48: 3 | F48: =VLOOKUP(B48,'ACS Price List'!$A$12:$P$180,2,FALSE) -> Application fee - Basic or standard connection - Micro-embedded generators - Technical assessment required | G48: =IF(VLOOKUP($B48,'ACS Price List'!$A$12:$P$180,G$1,FALSE)=0,"",VLOOKUP($B48,'ACS Price List'!$A$12:$P$180,G$1,FALSE)) -> APFMTA | H48: =IF(VLOOKUP($B48,'ACS Price List'!$A$12:$P$180,J$1,FALSE)=0,"",VLOOKUP($B48,'ACS Price List'!$A$12:$P$180,J$1,FALSE)) | K48: =IFERROR(IF(VLOOKUP($C48,'ACS Price List'!$A$12:$P$180,I$1,FALSE)=0,"",VLOOKUP($C48,'ACS Price List'!$A$12:$P$180,I$1,FALSE)),"") | L48: =IFERROR(IF(VLOOKUP($C48,'ACS Price List'!$A$12:$P$180,J$1,FALSE)=0,"",VLOOKUP($C48,'ACS Price List'!$A$12:$P$180,J$1,FALSE)),"")
B49: 4 | F49: =VLOOKUP(B49,'ACS Price List'!$A$12:$P$180,2,FALSE) -> Application fee - Real estate development connection | G49: =IF(VLOOKUP($B49,'ACS Price List'!$A$12:$P$180,G$1,FALSE)=0,"",VLOOKUP($B49,'ACS Price List'!$A$12:$P$180,G$1,FALSE)) -> APFRED | H49: =IF(VLOOKUP($B49,'ACS Price List'!$A$12:$P$180,J$1,FALSE)=0,"",VLOOKUP($B49,'ACS Price List'!$A$12:$P$180,J$1,FALSE)) | K49: =IFERROR(IF(VLOOKUP($C49,'ACS Price List'!$A$12:$P$180,I$1,FALSE)=0,"",VLOOKUP($C49,'ACS Price List'!$A$12:$P$180,I$1,FALSE)),"") | L49: =IFERROR(IF(VLOOKUP($C49,'ACS Price List'!$A$12:$P$180,J$1,FALSE)=0,"",VLOOKUP($C49,'ACS Price List'!$A$12:$P$180,J$1,FALSE)),"")
B50: 5 | F50: =VLOOKUP(B50,'ACS Price List'!$A$12:$P$180,2,FALSE) -> Protection and Power Quality assessment prior to connection | G50: =IF(VLOOKUP($B50,'ACS Price List'!$A$12:$P$180,G$1,FALSE)=0,"",VLOOKUP($B50,'ACS Price List'!$A$12:$P$180,G$1,FALSE)) -> PPQA | H50: =IF(VLOOKUP($B50,'ACS Price List'!$A$12:$P$180,J$1,FALSE)=0,"",VLOOKUP($B50,'ACS Price List'!$A$12:$P$180,J$1,FALSE)) | K50: =IFERROR(IF(VLOOKUP($C50,'ACS Price List'!$A$12:$P$180,I$1,FALSE)=0,"",VLOOKUP($C50,'ACS Price List'!$A$12:$P$180,I$1,FALSE)),"") | L50: =IFERROR(IF(VLOOKUP($C50,'ACS Price List'!$A$12:$P$180,J$1,FALSE)=0,"",VLOOKUP($C50,'ACS Price List'!$A$12:$P$180,J$1,FALSE)),"")
B51: 7 | C51: 161-M | D51: 7-CF | F51: =VLOOKUP(B51,'ACS Price List'!$A$12:$P$180,2,FALSE) -> Temporary connection, not in permanent position - single phase metered - long rural/isolated feeders | G51: =IF(VLOOKUP($B51,'ACS Price List'!$A$12:$P$180,I$1,FALSE)=0,"",VLOOKUP($B51,'ACS Price List'!$A$12:$P$180,I$1,FALSE)) -> TBSSPL | H51: =IF(VLOOKUP($B51,'ACS Price List'!$A$12:$P$180,J$1,FALSE)=0,"",VLOOKUP($B51,'ACS Price List'!$A$12:$P$180,J$1,FALSE)) -> TBSSPI | K51: =IFERROR(IF(VLOOKUP($C51,'ACS Price List'!$A$12:$P$180,I$1,FALSE)=0,"",VLOOKUP($C51,'ACS Price List'!$A$12:$P$180,I$1,FALSE)),"") -> MTBSL | L51: =IFERROR(IF(VLOOKUP($C51,'ACS Price List'!$A$12:$P$180,J$1,FALSE)=0,"",VLOOKUP($C51,'ACS Price List'!$A$12:$P$180,J$1,FALSE)),"") -> MTBSI | O51: =IFERROR(IF(VLOOKUP($D51,'ACS Price List'!$A$12:$P$180,I$1,FALSE)=0,"",VLOOKUP($D51,'ACS Price List'!$A$12:$P$180,I$1,FALSE)),"") -> CFTBSSPL | P51: =IFERROR(IF(VLOOKUP($D51,'ACS Price List'!$A$12:$P$180,J$1,FALSE)=0,"",VLOOKUP($D51,'ACS Price List'!$A$12:$P$180,J$1,FALSE)),"") -> CFTBSSPI
B52: 9 | C52: 161-M | D52: 9-CF | F52: =VLOOKUP(B52,'ACS Price List'!$A$12:$P$180,2,FALSE) -> Temporary connection, not in permanent position - multi phase metered - long rural/isolated feeders | G52: =IF(VLOOKUP($B52,'ACS Price List'!$A$12:$P$180,I$1,FALSE)=0,"",VLOOKUP($B52,'ACS Price List'!$A$12:$P$180,I$1,FALSE)) -> TBSMPL | H52: =IF(VLOOKUP($B52,'ACS Price List'!$A$12:$P$180,J$1,FALSE)=0,"",VLOOKUP($B52,'ACS Price List'!$A$12:$P$180,J$1,FALSE)) -> TBSMPI | K52: =IFERROR(IF(VLOOKUP($C52,'ACS Price List'!$A$12:$P$180,I$1,FALSE)=0,"",VLOOKUP($C52,'ACS Price List'!$A$12:$P$180,I$1,FALSE)),"") -> MTBSL | L52: =IFERROR(IF(VLOOKUP($C52,'ACS Price List'!$A$12:$P$180,J$1,FALSE)=0,"",VLOOKUP($C52,'ACS Price List'!$A$12:$P$180,J$1,FALSE)),"") -> MTBSI | O52: =IFERROR(IF(VLOOKUP($D52,'ACS Price List'!$A$12:$P$180,I$1,FALSE)=0,"",VLOOKUP($D52,'ACS Price List'!$A$12:$P$180,I$1,FALSE)),"") -> CFTBSMPL | P52: =IFERROR(IF(VLOOKUP($D52,'ACS Price List'!$A$12:$P$180,J$1,FALSE)=0,"",VLOOKUP($D52,'ACS Price List'!$A$12:$P$180,J$1,FALSE)),"") -> CFTBSMPI
B53: 11 | C53: 162-M | D53: 11-CF | F53: =VLOOKUP(B53,'ACS Price List'!$A$12:$P$180,2,FALSE) -> Supply abolishment during business hours - long rural/isolated feeders | G53: =IF(VLOOKUP($B53,'ACS Price List'!$A$12:$P$180,I$1,FALSE)=0,"",VLOOKUP($B53,'ACS Price List'!$A$12:$P$180,I$1,FALSE)) -> SUPABOLL | H53: =IF(VLOOKUP($B53,'ACS Price List'!$A$12:$P$180,J$1,FALSE)=0,"",VLOOKUP($B53,'ACS Price List'!$A$12:$P$180,J$1,FALSE)) -> SUPABOLI | K53: =IFERROR(IF(VLOOKUP($C53,'ACS Price List'!$A$12:$P$180,I$1,FALSE)=0,"",VLOOKUP($C53,'ACS Price List'!$A$12:$P$180,I$1,FALSE)),"") -> MSUPABOLL | L53: =IFERROR(IF(VLOOKUP($C53,'ACS Price List'!$A$12:$P$180,J$1,FALSE)=0,"",VLOOKUP($C53,'ACS Price List'!$A$12:$P$180,J$1,FALSE)),"") -> MSUPABOLI | O53: =IFERROR(IF(VLOOKUP($D53,'ACS Price List'!$A$12:$P$180,I$1,FALSE)=0,"",VLOOKUP($D53,'ACS Price List'!$A$12:$P$180,I$1,FALSE)),"") -> CFSUPABOLL | P53: =IFERROR(IF(VLOOKUP($D53,'ACS Price List'!$A$12:$P$180,J$1,FALSE)=0,"",VLOOKUP($D53,'ACS Price List'!$A$12:$P$180,J$1,FALSE)),"") -> CFSUPABOLI
B54: 13 | D54: 13-CF | F54: =VLOOKUP(B54,'ACS Price List'!$A$12:$P$180,2,FALSE) -> De-energisation during business hours - long rural/isolated feeders | G54: =IF(VLOOKUP($B54,'ACS Price List'!$A$12:$P$180,I$1,FALSE)=0,"",VLOOKUP($B54,'ACS Price List'!$A$12:$P$180,I$1,FALSE)) -> DEENBHL | H54: =IF(VLOOKUP($B54,'ACS Price List'!$A$12:$P$180,J$1,FALSE)=0,"",VLOOKUP($B54,'ACS Price List'!$A$12:$P$180,J$1,FALSE)) -> DEENBHI | K54: =IFERROR(IF(VLOOKUP($C54,'ACS Price List'!$A$12:$P$180,I$1,FALSE)=0,"",VLOOKUP($C54,'ACS Price List'!$A$12:$P$180,I$1,FALSE)),"") | L54: =IFERROR(IF(VLOOKUP($C54,'ACS Price List'!$A$12:$P$180,J$1,FALSE)=0,"",VLOOKUP($C54,'ACS Price List'!$A$12:$P$180,J$1,FALSE)),"") | O54: =IFERROR(IF(VLOOKUP($D54,'ACS Price List'!$A$12:$P$180,I$1,FALSE)=0,"",VLOOKUP($D54,'ACS Price List'!$A$12:$P$180,I$1,FALSE)),"") -> CFDEENBHL | P54: =IFERROR(IF(VLOOKUP($D54,'ACS Price List'!$A$12:$P$180,J$1,FALSE)=0,"",VLOOKUP($D54,'ACS Price List'!$A$12:$P$180,J$1,FALSE)),"") -> CFDEENBHI
B55: 15 | D55: 15-CF | F55: =VLOOKUP(B55,'ACS Price List'!$A$12:$P$180,2,FALSE) -> Re-energisation during business hours - long rural/isolated feeders | G55: =IF(VLOOKUP($B55,'ACS Price List'!$A$12:$P$180,I$1,FALSE)=0,"",VLOOKUP($B55,'ACS Price List'!$A$12:$P$180,I$1,FALSE)) -> REENBHL | H55: =IF(VLOOKUP($B55,'ACS Price List'!$A$12:$P$180,J$1,FALSE)=0,"",VLOOKUP($B55,'ACS Price List'!$A$12:$P$180,J$1,FALSE)) -> REENBHI | K55: =IFERROR(IF(VLOOKUP($C55,'ACS Price List'!$A$12:$P$180,I$1,FALSE)=0,"",VLOOKUP($C55,'ACS Price List'!$A$12:$P$180,I$1,FALSE)),"") | L55: =IFERROR(IF(VLOOKUP($C55,'ACS Price List'!$A$12:$P$180,J$1,FALSE)=0,"",VLOOKUP($C55,'ACS Price List'!$A$12:$P$180,J$1,FALSE)),"") | O55: =IFERROR(IF(VLOOKUP($D55,'ACS Price List'!$A$12:$P$180,I$1,FALSE)=0,"",VLOOKUP($D55,'ACS Price List'!$A$12:$P$180,I$1,FALSE)),"") -> CFREENBHL | P55: =IFERROR(IF(VLOOKUP($D55,'ACS Price List'!$A$12:$P$180,J$1,FALSE)=0,"",VLOOKUP($D55,'ACS Price List'!$A$12:$P$180,J$1,FALSE)),"") -> CFREENBHI
B56: 15-VE | D56: 15-CF | F56: =VLOOKUP(B56,'ACS Price List'!$A$12:$P$180,2,FALSE) -> Visual examination during business hours for remote re-energisation - long rural/isolated feeders | G56: =IF(VLOOKUP($B56,'ACS Price List'!$A$12:$P$180,I$1,FALSE)=0,"",VLOOKUP($B56,'ACS Price List'!$A$12:$P$180,I$1,FALSE)) -> VEREENBHL | H56: =IF(VLOOKUP($B56,'ACS Price List'!$A$12:$P$180,J$1,FALSE)=0,"",VLOOKUP($B56,'ACS Price List'!$A$12:$P$180,J$1,FALSE)) -> VEREENBHI | K56: =IFERROR(IF(VLOOKUP($C56,'ACS Price List'!$A$12:$P$180,I$1,FALSE)=0,"",VLOOKUP($C56,'ACS Price List'!$A$12:$P$180,I$1,FALSE)),"") | L56: =IFERROR(IF(VLOOKUP($C56,'ACS Price List'!$A$12:$P$180,J$1,FALSE)=0,"",VLOOKUP($C56,'ACS Price List'!$A$12:$P$180,J$1,FALSE)),"") | O56: =IFERROR(IF(VLOOKUP($D56,'ACS Price List'!$A$12:$P$180,I$1,FALSE)=0,"",VLOOKUP($D56,'ACS Price List'!$A$12:$P$180,I$1,FALSE)),"") -> CFREENBHL | P56: =IFERROR(IF(VLOOKUP($D56,'ACS Price List'!$A$12:$P$180,J$1,FALSE)=0,"",VLOOKUP($D56,'ACS Price List'!$A$12:$P$180,J$1,FALSE)),"") -> CFREENBHI
B57: 17 | D57: 17-CF | F57: =VLOOKUP(B57,'ACS Price List'!$A$12:$P$180,2,FALSE) -> Re-energisation during business hours - after de-energisation for debt - long rural/isolated feeders | G57: =IF(VLOOKUP($B57,'ACS Price List'!$A$12:$P$180,I$1,FALSE)=0,"",VLOOKUP($B57,'ACS Price List'!$A$12:$P$180,I$1,FALSE)) -> REDDBHL | H57: =IF(VLOOKUP($B57,'ACS Price List'!$A$12:$P$180,J$1,FALSE)=0,"",VLOOKUP($B57,'ACS Price List'!$A$12:$P$180,J$1,FALSE)) -> REDDBHI | K57: =IFERROR(IF(VLOOKUP($C57,'ACS Price List'!$A$12:$P$180,I$1,FALSE)=0,"",VLOOKUP($C57,'ACS Price List'!$A$12:$P$180,I$1,FALSE)),"") | L57: =IFERROR(IF(VLOOKUP($C57,'ACS Price List'!$A$12:$P$180,J$1,FALSE)=0,"",VLOOKUP($C57,'ACS Price List'!$A$12:$P$180,J$1,FALSE)),"") | O57: =IFERROR(IF(VLOOKUP($D57,'ACS Price List'!$A$12:$P$180,I$1,FALSE)=0,"",VLOOKUP($D57,'ACS Price List'!$A$12:$P$180,I$1,FALSE)),"") -> CFREDDBHL | P57: =IFERROR(IF(VLOOKUP($D57,'ACS Price List'!$A$12:$P$180,J$1,FALSE)=0,"",VLOOKUP($D57,'ACS Price List'!$A$12:$P$180,J$1,FALSE)),"") -> CFREDDBHI
B58: 17-VE | D58: 17-CF | F58: =VLOOKUP(B58,'ACS Price List'!$A$12:$P$180,2,FALSE) -> Visual examination during business hours for remote re-energisation - after de-energisation for debt - long rural/isolated feeders | G58: =IF(VLOOKUP($B58,'ACS Price List'!$A$12:$P$180,I$1,FALSE)=0,"",VLOOKUP($B58,'ACS Price List'!$A$12:$P$180,I$1,FALSE)) -> VEREDDBHL | H58: =IF(VLOOKUP($B58,'ACS Price List'!$A$12:$P$180,J$1,FALSE)=0,"",VLOOKUP($B58,'ACS Price List'!$A$12:$P$180,J$1,FALSE)) -> VEREDDBHI | K58: =IFERROR(IF(VLOOKUP($C58,'ACS Price List'!$A$12:$P$180,I$1,FALSE)=0,"",VLOOKUP($C58,'ACS Price List'!$A$12:$P$180,I$1,FALSE)),"") | L58: =IFERROR(IF(VLOOKUP($C58,'ACS Price List'!$A$12:$P$180,J$1,FALSE)=0,"",VLOOKUP($C58,'ACS Price List'!$A$12:$P$180,J$1,FALSE)),"") | O58: =IFERROR(IF(VLOOKUP($D58,'ACS Price List'!$A$12:$P$180,I$1,FALSE)=0,"",VLOOKUP($D58,'ACS Price List'!$A$12:$P$180,I$1,FALSE)),"") -> CFREDDBHL | P58: =IFERROR(IF(VLOOKUP($D58,'ACS Price List'!$A$12:$P$180,J$1,FALSE)=0,"",VLOOKUP($D58,'ACS Price List'!$A$12:$P$180,J$1,FALSE)),"") -> CFREDDBHI
B59: 18 | F59: =VLOOKUP(B59,'ACS Price List'!$A$12:$P$180,2,FALSE) -> Accreditation of alternative service providers - real estate developments | G59: =IF(VLOOKUP($B59,'ACS Price List'!$A$12:$P$180,G$1,FALSE)=0,"",VLOOKUP($B59,'ACS Price List'!$A$12:$P$180,G$1,FALSE)) -> ASPRED | H59: =IF(VLOOKUP($B59,'ACS Price List'!$A$12:$P$180,J$1,FALSE)=0,"",VLOOKUP($B59,'ACS Price List'!$A$12:$P$180,J$1,FALSE)) | K59: =IFERROR(IF(VLOOKUP($C59,'ACS Price List'!$A$12:$P$180,I$1,FALSE)=0,"",VLOOKUP($C59,'ACS Price List'!$A$12:$P$180,I$1,FALSE)),"") | L59: =IFERROR(IF(VLOOKUP($C59,'ACS Price List'!$A$12:$P$180,J$1,FALSE)=0,"",VLOOKUP($C59,'ACS Price List'!$A$12:$P$180,J$1,FALSE)),"") | O59: =IFERROR(IF(VLOOKUP($D59,'ACS Price List'!$A$12:$P$180,I$1,FALSE)=0,"",VLOOKUP($D59,'ACS Price List'!$A$12:$P$180,I$1,FALSE)),"") | P59: =IFERROR(IF(VLOOKUP($D59,'ACS Price List'!$A$12:$P$180,J$1,FALSE)=0,"",VLOOKUP($D59,'ACS Price List'!$A$12:$P$180,J$1,FALSE)),"")
B60: 20 | D60: 20-CF | F60: =VLOOKUP(B60,'ACS Price List'!$A$12:$P$180,2,FALSE) -> Install replacement meter (Type 5 and 6) – Single phase – long rural/isolated feeder | G60: =IF(VLOOKUP($B60,'ACS Price List'!$A$12:$P$180,I$1,FALSE)=0,"",VLOOKUP($B60,'ACS Price List'!$A$12:$P$180,I$1,FALSE)) -> MSNGLL | H60: =IF(VLOOKUP($B60,'ACS Price List'!$A$12:$P$180,J$1,FALSE)=0,"",VLOOKUP($B60,'ACS Price List'!$A$12:$P$180,J$1,FALSE)) -> MSNGLI | K60: =IFERROR(IF(VLOOKUP($C60,'ACS Price List'!$A$12:$P$180,I$1,FALSE)=0,"",VLOOKUP($C60,'ACS Price List'!$A$12:$P$180,I$1,FALSE)),"") | L60: =IFERROR(IF(VLOOKUP($C60,'ACS Price List'!$A$12:$P$180,J$1,FALSE)=0,"",VLOOKUP($C60,'ACS Price List'!$A$12:$P$180,J$1,FALSE)),"") | O60: =IFERROR(IF(VLOOKUP($D60,'ACS Price List'!$A$12:$P$180,I$1,FALSE)=0,"",VLOOKUP($D60,'ACS Price List'!$A$12:$P$180,I$1,FALSE)),"") -> CFMSNGLL | P60: =IFERROR(IF(VLOOKUP($D60,'ACS Price List'!$A$12:$P$180,J$1,FALSE)=0,"",VLOOKUP($D60,'ACS Price List'!$A$12:$P$180,J$1,FALSE)),"") -> CFMSNGLI
B61: 22 | D61: 22-CF | F61: =VLOOKUP(B61,'ACS Price List'!$A$12:$P$180,2,FALSE) -> Install replacement meter (Type 5 and 6) – Dual element – long rural/isolated feeder | G61: =IF(VLOOKUP($B61,'ACS Price List'!$A$12:$P$180,I$1,FALSE)=0,"",VLOOKUP($B61,'ACS Price List'!$A$12:$P$180,I$1,FALSE)) -> MDUALL | H61: =IF(VLOOKUP($B61,'ACS Price List'!$A$12:$P$180,J$1,FALSE)=0,"",VLOOKUP($B61,'ACS Price List'!$A$12:$P$180,J$1,FALSE)) -> MDUALI | K61: =IFERROR(IF(VLOOKUP($C61,'ACS Price List'!$A$12:$P$180,I$1,FALSE)=0,"",VLOOKUP($C61,'ACS Price List'!$A$12:$P$180,I$1,FALSE)),"") | L61: =IFERROR(IF(VLOOKUP($C61,'ACS Price List'!$A$12:$P$180,J$1,FALSE)=0,"",VLOOKUP($C61,'ACS Price List'!$A$12:$P$180,J$1,FALSE)),"") | O61: =IFERROR(IF(VLOOKUP($D61,'ACS Price List'!$A$12:$P$180,I$1,FALSE)=0,"",VLOOKUP($D61,'ACS Price List'!$A$12:$P$180,I$1,FALSE)),"") -> CFMDUALL | P61: =IFERROR(IF(VLOOKUP($D61,'ACS Price List'!$A$12:$P$180,J$1,FALSE)=0,"",VLOOKUP($D61,'ACS Price List'!$A$12:$P$180,J$1,FALSE)),"") -> CFMDUALI
B62: 24 | D62: 24-CF | F62: =VLOOKUP(B62,'ACS Price List'!$A$12:$P$180,2,FALSE) -> Install replacement meter (Type 5 and 6) – Polyphase – long rural/isolated feeder | G62: =IF(VLOOKUP($B62,'ACS Price List'!$A$12:$P$180,I$1,FALSE)=0,"",VLOOKUP($B62,'ACS Price List'!$A$12:$P$180,I$1,FALSE)) -> MTHREL | H62: =IF(VLOOKUP($B62,'ACS Price List'!$A$12:$P$180,J$1,FALSE)=0,"",VLOOKUP($B62,'ACS Price List'!$A$12:$P$180,J$1,FALSE)) -> MTHREI | K62: =IFERROR(IF(VLOOKUP($C62,'ACS Price List'!$A$12:$P$180,I$1,FALSE)=0,"",VLOOKUP($C62,'ACS Price List'!$A$12:$P$180,I$1,FALSE)),"") | L62: =IFERROR(IF(VLOOKUP($C62,'ACS Price List'!$A$12:$P$180,J$1,FALSE)=0,"",VLOOKUP($C62,'ACS Price List'!$A$12:$P$180,J$1,FALSE)),"") | O62: =IFERROR(IF(VLOOKUP($D62,'ACS Price List'!$A$12:$P$180,I$1,FALSE)=0,"",VLOOKUP($D62,'ACS Price List'!$A$12:$P$180,I$1,FALSE)),"") -> CFMTHREL | P62: =IFERROR(IF(VLOOKUP($D62,'ACS Price List'!$A$12:$P$180,J$1,FALSE)=0,"",VLOOKUP($D62,'ACS Price List'!$A$12:$P$180,J$1,FALSE)),"") -> CFMTHREI
B63: 26 | D63: 26-CF | F63: =VLOOKUP(B63,'ACS Price List'!$A$12:$P$180,2,FALSE) -> Install replacement meter (CT) – long rural/isolated feeder | G63: =IF(VLOOKUP($B63,'ACS Price List'!$A$12:$P$180,I$1,FALSE)=0,"",VLOOKUP($B63,'ACS Price List'!$A$12:$P$180,I$1,FALSE)) -> MCTL | H63: =IF(VLOOKUP($B63,'ACS Price List'!$A$12:$P$180,J$1,FALSE)=0,"",VLOOKUP($B63,'ACS Price List'!$A$12:$P$180,J$1,FALSE)) -> MCTI | K63: =IFERROR(IF(VLOOKUP($C63,'ACS Price List'!$A$12:$P$180,I$1,FALSE)=0,"",VLOOKUP($C63,'ACS Price List'!$A$12:$P$180,I$1,FALSE)),"") | L63: =IFERROR(IF(VLOOKUP($C63,'ACS Price List'!$A$12:$P$180,J$1,FALSE)=0,"",VLOOKUP($C63,'ACS Price List'!$A$12:$P$180,J$1,FALSE)),"") | O63: =IFERROR(IF(VLOOKUP($D63,'ACS Price List'!$A$12:$P$180,I$1,FALSE)=0,"",VLOOKUP($D63,'ACS Price List'!$A$12:$P$180,I$1,FALSE)),"") -> CFMCTL | P63: =IFERROR(IF(VLOOKUP($D63,'ACS Price List'!$A$12:$P$180,J$1,FALSE)=0,"",VLOOKUP($D63,'ACS Price List'!$A$12:$P$180,J$1,FALSE)),"") -> CFMCTI
B64: 140 | D64: 157-CF | F64: =VLOOKUP(B64,'ACS Price List'!$A$12:$P$180,2,FALSE) -> Install new meter (Type 5 and 6) – Single phase – Primary | G64: =IF(VLOOKUP($B64,'ACS Price List'!$A$12:$P$180,I$1,FALSE)=0,"",VLOOKUP($B64,'ACS Price List'!$A$12:$P$180,I$1,FALSE)) -> NMSPL | H64: =IF(VLOOKUP($B64,'ACS Price List'!$A$12:$P$180,J$1,FALSE)=0,"",VLOOKUP($B64,'ACS Price List'!$A$12:$P$180,J$1,FALSE)) -> NMSPI | K64: =IFERROR(IF(VLOOKUP($C64,'ACS Price List'!$A$12:$P$180,I$1,FALSE)=0,"",VLOOKUP($C64,'ACS Price List'!$A$12:$P$180,I$1,FALSE)),"") | L64: =IFERROR(IF(VLOOKUP($C64,'ACS Price List'!$A$12:$P$180,J$1,FALSE)=0,"",VLOOKUP($C64,'ACS Price List'!$A$12:$P$180,J$1,FALSE)),"") | O64: =IFERROR(IF(VLOOKUP($D64,'ACS Price List'!$A$12:$P$180,I$1,FALSE)=0,"",VLOOKUP($D64,'ACS Price List'!$A$12:$P$180,I$1,FALSE)),"") -> CFNMSPL | P64: =IFERROR(IF(VLOOKUP($D64,'ACS Price List'!$A$12:$P$180,J$1,FALSE)=0,"",VLOOKUP($D64,'ACS Price List'!$A$12:$P$180,J$1,FALSE)),"") -> CFNMSPI
B65: 141 | D65: 157-CF | F65: =VLOOKUP(B65,'ACS Price List'!$A$12:$P$180,2,FALSE) -> Install new meter (Type 5 and 6) – Single phase – Primary plus embedded generation | G65: =IF(VLOOKUP($B65,'ACS Price List'!$A$12:$P$180,I$1,FALSE)=0,"",VLOOKUP($B65,'ACS Price List'!$A$12:$P$180,I$1,FALSE)) -> NMSPEGL | H65: =IF(VLOOKUP($B65,'ACS Price List'!$A$12:$P$180,J$1,FALSE)=0,"",VLOOKUP($B65,'ACS Price List'!$A$12:$P$180,J$1,FALSE)) -> NMSPEGI | K65: =IFERROR(IF(VLOOKUP($C65,'ACS Price List'!$A$12:$P$180,I$1,FALSE)=0,"",VLOOKUP($C65,'ACS Price List'!$A$12:$P$180,I$1,FALSE)),"") | L65: =IFERROR(IF(VLOOKUP($C65,'ACS Price List'!$A$12:$P$180,J$1,FALSE)=0,"",VLOOKUP($C65,'ACS Price List'!$A$12:$P$180,J$1,FALSE)),"") | O65: =IFERROR(IF(VLOOKUP($D65,'ACS Price List'!$A$12:$P$180,I$1,FALSE)=0,"",VLOOKUP($D65,'ACS Price List'!$A$12:$P$180,I$1,FALSE)),"") -> CFNMSPL | P65: =IFERROR(IF(VLOOKUP($D65,'ACS Price List'!$A$12:$P$180,J$1,FALSE)=0,"",VLOOKUP($D65,'ACS Price List'!$A$12:$P$180,J$1,FALSE)),"") -> CFNMSPI
B66: 142 | D66: 158-CF | F66: =VLOOKUP(B66,'ACS Price List'!$A$12:$P$180,2,FALSE) -> Install new meter (Type 5 and 6) – Dual element – Primary plus controlled load | G66: =IF(VLOOKUP($B66,'ACS Price List'!$A$12:$P$180,I$1,FALSE)=0,"",VLOOKUP($B66,'ACS Price List'!$A$12:$P$180,I$1,FALSE)) -> NMDPCLL | H66: =IF(VLOOKUP($B66,'ACS Price List'!$A$12:$P$180,J$1,FALSE)=0,"",VLOOKUP($B66,'ACS Price List'!$A$12:$P$180,J$1,FALSE)) -> NMDPCLI | K66: =IFERROR(IF(VLOOKUP($C66,'ACS Price List'!$A$12:$P$180,I$1,FALSE)=0,"",VLOOKUP($C66,'ACS Price List'!$A$12:$P$180,I$1,FALSE)),"") | L66: =IFERROR(IF(VLOOKUP($C66,'ACS Price List'!$A$12:$P$180,J$1,FALSE)=0,"",VLOOKUP($C66,'ACS Price List'!$A$12:$P$180,J$1,FALSE)),"") | O66: =IFERROR(IF(VLOOKUP($D66,'ACS Price List'!$A$12:$P$180,I$1,FALSE)=0,"",VLOOKUP($D66,'ACS Price List'!$A$12:$P$180,I$1,FALSE)),"") -> CFNMDUALL | P66: =IFERROR(IF(VLOOKUP($D66,'ACS Price List'!$A$12:$P$180,J$1,FALSE)=0,"",VLOOKUP($D66,'ACS Price List'!$A$12:$P$180,J$1,FALSE)),"") -> CFNMDUALI
B67: 143 | D67: 158-CF | F67: =VLOOKUP(B67,'ACS Price List'!$A$12:$P$180,2,FALSE) -> Install new meter (Type 5 and 6) – Dual element – Primary plus controlled load plus embedded generation | G67: =IF(VLOOKUP($B67,'ACS Price List'!$A$12:$P$180,I$1,FALSE)=0,"",VLOOKUP($B67,'ACS Price List'!$A$12:$P$180,I$1,FALSE)) -> NMDPCLEGL | H67: =IF(VLOOKUP($B67,'ACS Price List'!$A$12:$P$180,J$1,FALSE)=0,"",VLOOKUP($B67,'ACS Price List'!$A$12:$P$180,J$1,FALSE)) -> NMDPCLEGI | K67: =IFERROR(IF(VLOOKUP($C67,'ACS Price List'!$A$12:$P$180,I$1,FALSE)=0,"",VLOOKUP($C67,'ACS Price List'!$A$12:$P$180,I$1,FALSE)),"") | L67: =IFERROR(IF(VLOOKUP($C67,'ACS Price List'!$A$12:$P$180,J$1,FALSE)=0,"",VLOOKUP($C67,'ACS Price List'!$A$12:$P$180,J$1,FALSE)),"") | O67: =IFERROR(IF(VLOOKUP($D67,'ACS Price List'!$A$12:$P$180,I$1,FALSE)=0,"",VLOOKUP($D67,'ACS Price List'!$A$12:$P$180,I$1,FALSE)),"") -> CFNMDUALL | P67: =IFERROR(IF(VLOOKUP($D67,'ACS Price List'!$A$12:$P$180,J$1,FALSE)=0,"",VLOOKUP($D67,'ACS Price List'!$A$12:$P$180,J$1,FALSE)),"") -> CFNMDUALI
B68: 144 | D68: 159-CF | F68: =VLOOKUP(B68,'ACS Price List'!$A$12:$P$180,2,FALSE) -> Install new meter (Type 5 and 6) – Polyphase – Primary | G68: =IF(VLOOKUP($B68,'ACS Price List'!$A$12:$P$180,I$1,FALSE)=0,"",VLOOKUP($B68,'ACS Price List'!$A$12:$P$180,I$1,FALSE)) -> NMPPL | H68: =IF(VLOOKUP($B68,'ACS Price List'!$A$12:$P$180,J$1,FALSE)=0,"",VLOOKUP($B68,'ACS Price List'!$A$12:$P$180,J$1,FALSE)) -> NMPPI | K68: =IFERROR(IF(VLOOKUP($C68,'ACS Price List'!$A$12:$P$180,I$1,FALSE)=0,"",VLOOKUP($C68,'ACS Price List'!$A$12:$P$180,I$1,FALSE)),"") | L68: =IFERROR(IF(VLOOKUP($C68,'ACS Price List'!$A$12:$P$180,J$1,FALSE)=0,"",VLOOKUP($C68,'ACS Price List'!$A$12:$P$180,J$1,FALSE)),"") | O68: =IFERROR(IF(VLOOKUP($D68,'ACS Price List'!$A$12:$P$180,I$1,FALSE)=0,"",VLOOKUP($D68,'ACS Price List'!$A$12:$P$180,I$1,FALSE)),"") -> CFNMTHREL | P68: =IFERROR(IF(VLOOKUP($D68,'ACS Price List'!$A$12:$P$180,J$1,FALSE)=0,"",VLOOKUP($D68,'ACS Price List'!$A$12:$P$180,J$1,FALSE)),"") -> CFNMTHREI
B69: 145 | D69: 159-CF | F69: =VLOOKUP(B69,'ACS Price List'!$A$12:$P$180,2,FALSE) -> Install new meter (Type 5 and 6) – Polyphase – Primary plus embedded generation | G69: =IF(VLOOKUP($B69,'ACS Price List'!$A$12:$P$180,I$1,FALSE)=0,"",VLOOKUP($B69,'ACS Price List'!$A$12:$P$180,I$1,FALSE)) -> NMPPEGL | H69: =IF(VLOOKUP($B69,'ACS Price List'!$A$12:$P$180,J$1,FALSE)=0,"",VLOOKUP($B69,'ACS Price List'!$A$12:$P$180,J$1,FALSE)) -> NMPPEGI | K69: =IFERROR(IF(VLOOKUP($C69,'ACS Price List'!$A$12:$P$180,I$1,FALSE)=0,"",VLOOKUP($C69,'ACS Price List'!$A$12:$P$180,I$1,FALSE)),"") | L69: =IFERROR(IF(VLOOKUP($C69,'ACS Price List'!$A$12:$P$180,J$1,FALSE)=0,"",VLOOKUP($C69,'ACS Price List'!$A$12:$P$180,J$1,FALSE)),"") | O69: =IFERROR(IF(VLOOKUP($D69,'ACS Price List'!$A$12:$P$180,I$1,FALSE)=0,"",VLOOKUP($D69,'ACS Price List'!$A$12:$P$180,I$1,FALSE)),"") -> CFNMTHREL | P69: =IFERROR(IF(VLOOKUP($D69,'ACS Price List'!$A$12:$P$180,J$1,FALSE)=0,"",VLOOKUP($D69,'ACS Price List'!$A$12:$P$180,J$1,FALSE)),"") -> CFNMTHREI
B70: 146 | D70: 160-CF | F70: =VLOOKUP(B70,'ACS Price List'!$A$12:$P$180,2,FALSE) -> Install new meter (CT) – Primary | G70: =IF(VLOOKUP($B70,'ACS Price List'!$A$12:$P$180,I$1,FALSE)=0,"",VLOOKUP($B70,'ACS Price List'!$A$12:$P$180,I$1,FALSE)) -> NMCTPL | H70: =IF(VLOOKUP($B70,'ACS Price List'!$A$12:$P$180,J$1,FALSE)=0,"",VLOOKUP($B70,'ACS Price List'!$A$12:$P$180,J$1,FALSE)) -> NMCTPI | K70: =IFERROR(IF(VLOOKUP($C70,'ACS Price List'!$A$12:$P$180,I$1,FALSE)=0,"",VLOOKUP($C70,'ACS Price List'!$A$12:$P$180,I$1,FALSE)),"") | L70: =IFERROR(IF(VLOOKUP($C70,'ACS Price List'!$A$12:$P$180,J$1,FALSE)=0,"",VLOOKUP($C70,'ACS Price List'!$A$12:$P$180,J$1,FALSE)),"") | O70: =IFERROR(IF(VLOOKUP($D70,'ACS Price List'!$A$12:$P$180,I$1,FALSE)=0,"",VLOOKUP($D70,'ACS Price List'!$A$12:$P$180,I$1,FALSE)),"") -> CFNMCTL | P70: =IFERROR(IF(VLOOKUP($D70,'ACS Price List'!$A$12:$P$180,J$1,FALSE)=0,"",VLOOKUP($D70,'ACS Price List'!$A$12:$P$180,J$1,FALSE)),"") -> CFNMCTI
B71: 147 | D71: 160-CF | F71: =VLOOKUP(B71,'ACS Price List'!$A$12:$P$180,2,FALSE) -> Install new meter (CT) – Primary plus embedded generation | G71: =IF(VLOOKUP($B71,'ACS Price List'!$A$12:$P$180,I$1,FALSE)=0,"",VLOOKUP($B71,'ACS Price List'!$A$12:$P$180,I$1,FALSE)) -> NMCTPEGL | H71: =IF(VLOOKUP($B71,'ACS Price List'!$A$12:$P$180,J$1,FALSE)=0,"",VLOOKUP($B71,'ACS Price List'!$A$12:$P$180,J$1,FALSE)) -> NMCTPEGI | K71: =IFERROR(IF(VLOOKUP($C71,'ACS Price List'!$A$12:$P$180,I$1,FALSE)=0,"",VLOOKUP($C71,'ACS Price List'!$A$12:$P$180,I$1,FALSE)),"") | L71: =IFERROR(IF(VLOOKUP($C71,'ACS Price List'!$A$12:$P$180,J$1,FALSE)=0,"",VLOOKUP($C71,'ACS Price List'!$A$12:$P$180,J$1,FALSE)),"") | O71: =IFERROR(IF(VLOOKUP($D71,'ACS Price List'!$A$12:$P$180,I$1,FALSE)=0,"",VLOOKUP($D71,'ACS Price List'!$A$12:$P$180,I$1,FALSE)),"") -> CFNMCTL | P71: =IFERROR(IF(VLOOKUP($D71,'ACS Price List'!$A$12:$P$180,J$1,FALSE)=0,"",VLOOKUP($D71,'ACS Price List'!$A$12:$P$180,J$1,FALSE)),"") -> CFNMCTI
... B80: 156 | D80: 160-CF | F80: =VLOOKUP(B80,'ACS Price List'!$A$12:$P$180,2,FALSE) -> Install new meter (CT) to accommodate embedded generation installation | G80: =IF(VLOOKUP($B80,'ACS Price List'!$A$12:$P$180,I$1,FALSE)=0,"",VLOOKUP($B80,'ACS Price List'!$A$12:$P$180,I$1,FALSE)) -> NCTAEGL | H80: =IF(VLOOKUP($B80,'ACS Price List'!$A$12:$P$180,J$1,FALSE)=0,"",VLOOKUP($B80,'ACS Price List'!$A$12:$P$180,J$1,FALSE)) -> NCTAEGI | K80: =IFERROR(IF(VLOOKUP($C80,'ACS Price List'!$A$12:$P$180,I$1,FALSE)=0,"",VLOOKUP($C80,'ACS Price List'!$A$12:$P$180,I$1,FALSE)),"") | L80: =IFERROR(IF(VLOOKUP($C80,'ACS Price List'!$A$12:$P$180,J$1,FALSE)=0,"",VLOOKUP($C80,'ACS Price List'!$A$12:$P$180,J$1,FALSE)),"") | O80: =IFERROR(IF(VLOOKUP($D80,'ACS Price List'!$A$12:$P$180,I$1,FALSE)=0,"",VLOOKUP($D80,'ACS Price List'!$A$12:$P$180,I$1,FALSE)),"") -> CFNMCTL | P80: =IFERROR(IF(VLOOKUP($D80,'ACS Price List'!$A$12:$P$180,J$1,FALSE)=0,"",VLOOKUP($D80,'ACS Price List'!$A$12:$P$180,J$1,FALSE)),"") -> CFNMCTI
B81: 40 | E81: Quoted Services | F81: =VLOOKUP(B81,'ACS Price List'!$A$12:$P$180,2,FALSE) -> Application fee - Negotiated connection | G81: =IF(VLOOKUP($B81,'ACS Price List'!$A$12:$P$180,G$1,FALSE)=0,"",VLOOKUP($B81,'ACS Price List'!$A$12:$P$180,G$1,FALSE)) -> As Quoted | H81: =IF(VLOOKUP($B81,'ACS Price List'!$A$12:$P$180,H$1,FALSE)=0,"",VLOOKUP($B81,'ACS Price List'!$A$12:$P$180,H$1,FALSE)) | I81: =IF(VLOOKUP($B81,'ACS Price List'!$A$12:$P$180,I$1,FALSE)=0,"",VLOOKUP($B81,'ACS Price List'!$A$12:$P$180,I$1,FALSE)) | J81: =IF(VLOOKUP($B81,'ACS Price List'!$A$12:$P$180,J$1,FALSE)=0,"",VLOOKUP($B81,'ACS Price List'!$A$12:$P$180,J$1,FALSE)) | K81: =IF(C81="163-M","GENM or applicable Metering Service product code**","") | O81: GENCF* | P81: GENCFMC* | Q81: =IFERROR(IF(VLOOKUP($D81,'ACS Price List'!$A$12:$P$180,I$1,FALSE)=0,"",VLOOKUP($D81,'ACS Price List'!$A$12:$P$180,I$1,FALSE)),"") | R81: =IFERROR(IF(VLOOKUP($D81,'ACS Price List'!$A$12:$P$180,J$1,FALSE)=0,"",VLOOKUP($D81,'ACS Price List'!$A$12:$P$180,J$1,FALSE)),"") | U81: =COUNTA(G81:G141,H97:J97,H100:J103,,H107:J109,H116:J120,H122:J130,H133:J135,O107:R109,O116:R117) -> 157
B82: 41 | F82: =VLOOKUP(B82,'ACS Price List'!$A$12:$P$180,2,FALSE) -> Application fee - Negotiated connection - Micro-embedded generators | G82: =IF(VLOOKUP($B82,'ACS Price List'!$A$12:$P$180,G$1,FALSE)=0,"",VLOOKUP($B82,'ACS Price List'!$A$12:$P$180,G$1,FALSE)) -> As Quoted | H82: =IF(VLOOKUP($B82,'ACS Price List'!$A$12:$P$180,H$1,FALSE)=0,"",VLOOKUP($B82,'ACS Price List'!$A$12:$P$180,H$1,FALSE)) | I82: =IF(VLOOKUP($B82,'ACS Price List'!$A$12:$P$180,I$1,FALSE)=0,"",VLOOKUP($B82,'ACS Price List'!$A$12:$P$180,I$1,FALSE)) | J82: =IF(VLOOKUP($B82,'ACS Price List'!$A$12:$P$180,J$1,FALSE)=0,"",VLOOKUP($B82,'ACS Price List'!$A$12:$P$180,J$1,FALSE)) | K82: =IF(C82="163-M","GENM or applicable Metering Service product code**","") | O82: GENCF* | P82: GENCFMC* | Q82: =IFERROR(IF(VLOOKUP($D82,'ACS Price List'!$A$12:$P$180,I$1,FALSE)=0,"",VLOOKUP($D82,'ACS Price List'!$A$12:$P$180,I$1,FALSE)),"") | R82: =IFERROR(IF(VLOOKUP($D82,'ACS Price List'!$A$12:$P$180,J$1,FALSE)=0,"",VLOOKUP($D82,'ACS Price List'!$A$12:$P$180,J$1,FALSE)),"")
B83: 42 | F83: =VLOOKUP(B83,'ACS Price List'!$A$12:$P$180,2,FALSE) -> Application fee - Negotiated - Major customer connection | G83: =IF(VLOOKUP($B83,'ACS Price List'!$A$12:$P$180,G$1,FALSE)=0,"",VLOOKUP($B83,'ACS Price List'!$A$12:$P$180,G$1,FALSE)) -> As Quoted | H83: =IF(VLOOKUP($B83,'ACS Price List'!$A$12:$P$180,H$1,FALSE)=0,"",VLOOKUP($B83,'ACS Price List'!$A$12:$P$180,H$1,FALSE)) | I83: =IF(VLOOKUP($B83,'ACS Price List'!$A$12:$P$180,I$1,FALSE)=0,"",VLOOKUP($B83,'ACS Price List'!$A$12:$P$180,I$1,FALSE)) | J83: =IF(VLOOKUP($B83,'ACS Price List'!$A$12:$P$180,J$1,FALSE)=0,"",VLOOKUP($B83,'ACS Price List'!$A$12:$P$180,J$1,FALSE)) | K83: =IF(C83="163-M","GENM or applicable Metering Service product code**","") | O83: GENCF* | P83: GENCFMC* | Q83: =IFERROR(IF(VLOOKUP($D83,'ACS Price List'!$A$12:$P$180,I$1,FALSE)=0,"",VLOOKUP($D83,'ACS Price List'!$A$12:$P$180,I$1,FALSE)),"") | R83: =IFERROR(IF(VLOOKUP($D83,'ACS Price List'!$A$12:$P$180,J$1,FALSE)=0,"",VLOOKUP($D83,'ACS Price List'!$A$12:$P$180,J$1,FALSE)),"")
B84: 43 | F84: =VLOOKUP(B84,'ACS Price List'!$A$12:$P$180,2,FALSE) -> Carrying out planning studies and analysis relating to connection applications | G84: =IF(VLOOKUP($B84,'ACS Price List'!$A$12:$P$180,G$1,FALSE)=0,"",VLOOKUP($B84,'ACS Price List'!$A$12:$P$180,G$1,FALSE)) -> As Quoted | H84: =IF(VLOOKUP($B84,'ACS Price List'!$A$12:$P$180,H$1,FALSE)=0,"",VLOOKUP($B84,'ACS Price List'!$A$12:$P$180,H$1,FALSE)) | I84: =IF(VLOOKUP($B84,'ACS Price List'!$A$12:$P$180,I$1,FALSE)=0,"",VLOOKUP($B84,'ACS Price List'!$A$12:$P$180,I$1,FALSE)) | J84: =IF(VLOOKUP($B84,'ACS Price List'!$A$12:$P$180,J$1,FALSE)=0,"",VLOOKUP($B84,'ACS Price List'!$A$12:$P$180,J$1,FALSE)) | K84: =IF(C84="163-M","GENM or applicable Metering Service product code**","") | O84: GENCF* | P84: GENCFMC* | Q84: =IFERROR(IF(VLOOKUP($D84,'ACS Price List'!$A$12:$P$180,I$1,FALSE)=0,"",VLOOKUP($D84,'ACS Price List'!$A$12:$P$180,I$1,FALSE)),"") | R84: =IFERROR(IF(VLOOKUP($D84,'ACS Price List'!$A$12:$P$180,J$1,FALSE)=0,"",VLOOKUP($D84,'ACS Price List'!$A$12:$P$180,J$1,FALSE)),"")
B85: 44 | F85: =VLOOKUP(B85,'ACS Price List'!$A$12:$P$180,2,FALSE) -> Feasibility and concept scoping, including planning and design, for major customer connections | G85: =IF(VLOOKUP($B85,'ACS Price List'!$A$12:$P$180,G$1,FALSE)=0,"",VLOOKUP($B85,'ACS Price List'!$A$12:$P$180,G$1,FALSE)) -> As Quoted | H85: =IF(VLOOKUP($B85,'ACS Price List'!$A$12:$P$180,H$1,FALSE)=0,"",VLOOKUP($B85,'ACS Price List'!$A$12:$P$180,H$1,FALSE)) | I85: =IF(VLOOKUP($B85,'ACS Price List'!$A$12:$P$180,I$1,FALSE)=0,"",VLOOKUP($B85,'ACS Price List'!$A$12:$P$180,I$1,FALSE)) | J85: =IF(VLOOKUP($B85,'ACS Price List'!$A$12:$P$180,J$1,FALSE)=0,"",VLOOKUP($B85,'ACS Price List'!$A$12:$P$180,J$1,FALSE)) | K85: =IF(C85="163-M","GENM or applicable Metering Service product code**","") | O85: GENCF* | P85: GENCFMC* | Q85: =IFERROR(IF(VLOOKUP($D85,'ACS Price List'!$A$12:$P$180,I$1,FALSE)=0,"",VLOOKUP($D85,'ACS Price List'!$A$12:$P$180,I$1,FALSE)),"") | R85: =IFERROR(IF(VLOOKUP($D85,'ACS Price List'!$A$12:$P$180,J$1,FALSE)=0,"",VLOOKUP($D85,'ACS Price List'!$A$12:$P$180,J$1,FALSE)),"")
B86: 45 | F86: =VLOOKUP(B86,'ACS Price List'!$A$12:$P$180,2,FALSE) -> Tender process | G86: =IF(VLOOKUP($B86,'ACS Price List'!$A$12:$P$180,G$1,FALSE)=0,"",VLOOKUP($B86,'ACS Price List'!$A$12:$P$180,G$1,FALSE)) -> As Quoted | H86: =IF(VLOOKUP($B86,'ACS Price List'!$A$12:$P$180,H$1,FALSE)=0,"",VLOOKUP($B86,'ACS Price List'!$A$12:$P$180,H$1,FALSE)) | I86: =IF(VLOOKUP($B86,'ACS Price List'!$A$12:$P$180,I$1,FALSE)=0,"",VLOOKUP($B86,'ACS Price List'!$A$12:$P$180,I$1,FALSE)) | J86: =IF(VLOOKUP($B86,'ACS Price List'!$A$12:$P$180,J$1,FALSE)=0,"",VLOOKUP($B86,'ACS Price List'!$A$12:$P$180,J$1,FALSE)) | K86: =IF(C86="163-M","GENM or applicable Metering Service product code**","") | O86: GENCF* | P86: GENCFMC* | Q86: =IFERROR(IF(VLOOKUP($D86,'ACS Price List'!$A$12:$P$180,I$1,FALSE)=0,"",VLOOKUP($D86,'ACS Price List'!$A$12:$P$180,I$1,FALSE)),"") | R86: =IFERROR(IF(VLOOKUP($D86,'ACS Price List'!$A$12:$P$180,J$1,FALSE)=0,"",VLOOKUP($D86,'ACS Price List'!$A$12:$P$180,J$1,FALSE)),"")
B87: 46 | F87: =VLOOKUP(B87,'ACS Price List'!$A$12:$P$180,2,FALSE) -> Pre-connection site inspection | G87: =IF(VLOOKUP($B87,'ACS Price List'!$A$12:$P$180,G$1,FALSE)=0,"",VLOOKUP($B87,'ACS Price List'!$A$12:$P$180,G$1,FALSE)) -> As Quoted | H87: =IF(VLOOKUP($B87,'ACS Price List'!$A$12:$P$180,H$1,FALSE)=0,"",VLOOKUP($B87,'ACS Price List'!$A$12:$P$180,H$1,FALSE)) | I87: =IF(VLOOKUP($B87,'ACS Price List'!$A$12:$P$180,I$1,FALSE)=0,"",VLOOKUP($B87,'ACS Price List'!$A$12:$P$180,I$1,FALSE)) | J87: =IF(VLOOKUP($B87,'ACS Price List'!$A$12:$P$180,J$1,FALSE)=0,"",VLOOKUP($B87,'ACS Price List'!$A$12:$P$180,J$1,FALSE)) | K87: =IF(C87="163-M","GENM or applicable Metering Service product code**","") | O87: GENCF* | P87: GENCFMC* | Q87: =IFERROR(IF(VLOOKUP($D87,'ACS Price List'!$A$12:$P$180,I$1,FALSE)=0,"",VLOOKUP($D87,'ACS Price List'!$A$12:$P$180,I$1,FALSE)),"") | R87: =IFERROR(IF(VLOOKUP($D87,'ACS Price List'!$A$12:$P$180,J$1,FALSE)=0,"",VLOOKUP($D87,'ACS Price List'!$A$12:$P$180,J$1,FALSE)),"")
B88: 47 | F88: =VLOOKUP(B88,'ACS Price List'!$A$12:$P$180,2,FALSE) -> Provision of site-specific connection information and advice | G88: =IF(VLOOKUP($B88,'ACS Price List'!$A$12:$P$180,G$1,FALSE)=0,"",VLOOKUP($B88,'ACS Price List'!$A$12:$P$180,G$1,FALSE)) -> As Quoted | H88: =IF(VLOOKUP($B88,'ACS Price List'!$A$12:$P$180,H$1,FALSE)=0,"",VLOOKUP($B88,'ACS Price List'!$A$12:$P$180,H$1,FALSE)) | I88: =IF(VLOOKUP($B88,'ACS Price List'!$A$12:$P$180,I$1,FALSE)=0,"",VLOOKUP($B88,'ACS Price List'!$A$12:$P$180,I$1,FALSE)) | J88: =IF(VLOOKUP($B88,'ACS Price List'!$A$12:$P$180,J$1,FALSE)=0,"",VLOOKUP($B88,'ACS Price List'!$A$12:$P$180,J$1,FALSE)) | K88: =IF(C88="163-M","GENM or applicable Metering Service product code**","") | O88: GENCF* | P88: GENCFMC* | Q88: =IFERROR(IF(VLOOKUP($D88,'ACS Price List'!$A$12:$P$180,I$1,FALSE)=0,"",VLOOKUP($D88,'ACS Price List'!$A$12:$P$180,I$1,FALSE)),"") | R88: =IFERROR(IF(VLOOKUP($D88,'ACS Price List'!$A$12:$P$180,J$1,FALSE)=0,"",VLOOKUP($D88,'ACS Price List'!$A$12:$P$180,J$1,FALSE)),"")
B89: 48 | F89: =VLOOKUP(B89,'ACS Price List'!$A$12:$P$180,2,FALSE) -> Preparation of preliminary designs and planning reports for major customer connections, including project scopes and estimates | G89: =IF(VLOOKUP($B89,'ACS Price List'!$A$12:$P$180,G$1,FALSE)=0,"",VLOOKUP($B89,'ACS Price List'!$A$12:$P$180,G$1,FALSE)) -> As Quoted | H89: =IF(VLOOKUP($B89,'ACS Price List'!$A$12:$P$180,H$1,FALSE)=0,"",VLOOKUP($B89,'ACS Price List'!$A$12:$P$180,H$1,FALSE)) | I89: =IF(VLOOKUP($B89,'ACS Price List'!$A$12:$P$180,I$1,FALSE)=0,"",VLOOKUP($B89,'ACS Price List'!$A$12:$P$180,I$1,FALSE)) | J89: =IF(VLOOKUP($B89,'ACS Price List'!$A$12:$P$180,J$1,FALSE)=0,"",VLOOKUP($B89,'ACS Price List'!$A$12:$P$180,J$1,FALSE)) | K89: =IF(C89="163-M","GENM or applicable Metering Service product code**","") | O89: GENCF* | P89: GENCFMC* | Q89: =IFERROR(IF(VLOOKUP($D89,'ACS Price List'!$A$12:$P$180,I$1,FALSE)=0,"",VLOOKUP($D89,'ACS Price List'!$A$12:$P$180,I$1,FALSE)),"") | R89: =IFERROR(IF(VLOOKUP($D89,'ACS Price List'!$A$12:$P$180,J$1,FALSE)=0,"",VLOOKUP($D89,'ACS Price List'!$A$12:$P$180,J$1,FALSE)),"")
B90: 49 | F90: =VLOOKUP(B90,'ACS Price List'!$A$12:$P$180,2,FALSE) -> Customer build, own and operate consultation services | G90: =IF(VLOOKUP($B90,'ACS Price List'!$A$12:$P$180,G$1,FALSE)=0,"",VLOOKUP($B90,'ACS Price List'!$A$12:$P$180,G$1,FALSE)) -> As Quoted | H90: =IF(VLOOKUP($B90,'ACS Price List'!$A$12:$P$180,H$1,FALSE)=0,"",VLOOKUP($B90,'ACS Price List'!$A$12:$P$180,H$1,FALSE)) | I90: =IF(VLOOKUP($B90,'ACS Price List'!$A$12:$P$180,I$1,FALSE)=0,"",VLOOKUP($B90,'ACS Price List'!$A$12:$P$180,I$1,FALSE)) | J90: =IF(VLOOKUP($B90,'ACS Price List'!$A$12:$P$180,J$1,FALSE)=0,"",VLOOKUP($B90,'ACS Price List'!$A$12:$P$180,J$1,FALSE)) | K90: =IF(C90="163-M","GENM or applicable Metering Service product code**","") | O90: GENCF* | P90: GENCFMC* | Q90: =IFERROR(IF(VLOOKUP($D90,'ACS Price List'!$A$12:$P$180,I$1,FALSE)=0,"",VLOOKUP($D90,'ACS Price List'!$A$12:$P$180,I$1,FALSE)),"") | R90: =IFERROR(IF(VLOOKUP($D90,'ACS Price List'!$A$12:$P$180,J$1,FALSE)=0,"",VLOOKUP($D90,'ACS Price List'!$A$12:$P$180,J$1,FALSE)),"")
B91: 50 | F91: =VLOOKUP(B91,'ACS Price List'!$A$12:$P$180,2,FALSE) -> Detailed enquiry response fee - embedded generation | G91: =IF(VLOOKUP($B91,'ACS Price List'!$A$12:$P$180,G$1,FALSE)=0,"",VLOOKUP($B91,'ACS Price List'!$A$12:$P$180,G$1,FALSE)) -> As Quoted | H91: =IF(VLOOKUP($B91,'ACS Price List'!$A$12:$P$180,H$1,FALSE)=0,"",VLOOKUP($B91,'ACS Price List'!$A$12:$P$180,H$1,FALSE)) | I91: =IF(VLOOKUP($B91,'ACS Price List'!$A$12:$P$180,I$1,FALSE)=0,"",VLOOKUP($B91,'ACS Price List'!$A$12:$P$180,I$1,FALSE)) | J91: =IF(VLOOKUP($B91,'ACS Price List'!$A$12:$P$180,J$1,FALSE)=0,"",VLOOKUP($B91,'ACS Price List'!$A$12:$P$180,J$1,FALSE)) | K91: =IF(C91="163-M","GENM or applicable Metering Service product code**","") | O91: GENCF* | P91: GENCFMC* | Q91: =IFERROR(IF(VLOOKUP($D91,'ACS Price List'!$A$12:$P$180,I$1,FALSE)=0,"",VLOOKUP($D91,'ACS Price List'!$A$12:$P$180,I$1,FALSE)),"") | R91: =IFERROR(IF(VLOOKUP($D91,'ACS Price List'!$A$12:$P$180,J$1,FALSE)=0,"",VLOOKUP($D91,'ACS Price List'!$A$12:$P$180,J$1,FALSE)),"")
B92: 51 | F92: =VLOOKUP(B92,'ACS Price List'!$A$12:$P$180,2,FALSE) -> Design and construction of connection assets for major customers | G92: =IF(VLOOKUP($B92,'ACS Price List'!$A$12:$P$180,G$1,FALSE)=0,"",VLOOKUP($B92,'ACS Price List'!$A$12:$P$180,G$1,FALSE)) -> As Quoted | H92: =IF(VLOOKUP($B92,'ACS Price List'!$A$12:$P$180,H$1,FALSE)=0,"",VLOOKUP($B92,'ACS Price List'!$A$12:$P$180,H$1,FALSE)) | I92: =IF(VLOOKUP($B92,'ACS Price List'!$A$12:$P$180,I$1,FALSE)=0,"",VLOOKUP($B92,'ACS Price List'!$A$12:$P$180,I$1,FALSE)) | J92: =IF(VLOOKUP($B92,'ACS Price List'!$A$12:$P$180,J$1,FALSE)=0,"",VLOOKUP($B92,'ACS Price List'!$A$12:$P$180,J$1,FALSE)) | K92: =IF(C92="163-M","GENM or applicable Metering Service product code**","") | O92: GENCF* | P92: GENCFMC* | Q92: =IFERROR(IF(VLOOKUP($D92,'ACS Price List'!$A$12:$P$180,I$1,FALSE)=0,"",VLOOKUP($D92,'ACS Price List'!$A$12:$P$180,I$1,FALSE)),"") | R92: =IFERROR(IF(VLOOKUP($D92,'ACS Price List'!$A$12:$P$180,J$1,FALSE)=0,"",VLOOKUP($D92,'ACS Price List'!$A$12:$P$180,J$1,FALSE)),"")
B93: 52 | F93: =VLOOKUP(B93,'ACS Price List'!$A$12:$P$180,2,FALSE) -> Commissioning and energisation of major customer connections | G93: =IF(VLOOKUP($B93,'ACS Price List'!$A$12:$P$180,G$1,FALSE)=0,"",VLOOKUP($B93,'ACS Price List'!$A$12:$P$180,G$1,FALSE)) -> As Quoted | H93: =IF(VLOOKUP($B93,'ACS Price List'!$A$12:$P$180,H$1,FALSE)=0,"",VLOOKUP($B93,'ACS Price List'!$A$12:$P$180,H$1,FALSE)) | I93: =IF(VLOOKUP($B93,'ACS Price List'!$A$12:$P$180,I$1,FALSE)=0,"",VLOOKUP($B93,'ACS Price List'!$A$12:$P$180,I$1,FALSE)) | J93: =IF(VLOOKUP($B93,'ACS Price List'!$A$12:$P$180,J$1,FALSE)=0,"",VLOOKUP($B93,'ACS Price List'!$A$12:$P$180,J$1,FALSE)) | K93: =IF(C93="163-M","GENM or applicable Metering Service product code**","") | O93: GENCF* | P93: GENCFMC* | Q93: =IFERROR(IF(VLOOKUP($D93,'ACS Price List'!$A$12:$P$180,I$1,FALSE)=0,"",VLOOKUP($D93,'ACS Price List'!$A$12:$P$180,I$1,FALSE)),"") | R93: =IFERROR(IF(VLOOKUP($D93,'ACS Price List'!$A$12:$P$180,J$1,FALSE)=0,"",VLOOKUP($D93,'ACS Price List'!$A$12:$P$180,J$1,FALSE)),"")
... B96: 55 | F96: =VLOOKUP(B96,'ACS Price List'!$A$12:$P$180,2,FALSE) -> Removal of network constraint for embedded generator | G96: =IF(VLOOKUP($B96,'ACS Price List'!$A$12:$P$180,G$1,FALSE)=0,"",VLOOKUP($B96,'ACS Price List'!$A$12:$P$180,G$1,FALSE)) -> As Quoted | H96: =IF(VLOOKUP($B96,'ACS Price List'!$A$12:$P$180,H$1,FALSE)=0,"",VLOOKUP($B96,'ACS Price List'!$A$12:$P$180,H$1,FALSE)) | I96: =IF(VLOOKUP($B96,'ACS Price List'!$A$12:$P$180,I$1,FALSE)=0,"",VLOOKUP($B96,'ACS Price List'!$A$12:$P$180,I$1,FALSE)) | J96: =IF(VLOOKUP($B96,'ACS Price List'!$A$12:$P$180,J$1,FALSE)=0,"",VLOOKUP($B96,'ACS Price List'!$A$12:$P$180,J$1,FALSE)) | K96: =IF(C96="163-M","GENM or applicable Metering Service product code**","") | O96: GENCF* | P96: GENCFMC* | Q96: =IFERROR(IF(VLOOKUP($D96,'ACS Price List'!$A$12:$P$180,I$1,FALSE)=0,"",VLOOKUP($D96,'ACS Price List'!$A$12:$P$180,I$1,FALSE)),"") | R96: =IFERROR(IF(VLOOKUP($D96,'ACS Price List'!$A$12:$P$180,J$1,FALSE)=0,"",VLOOKUP($D96,'ACS Price List'!$A$12:$P$180,J$1,FALSE)),"")
B97: 56 | C97: 163-M | F97: =VLOOKUP(B97,'ACS Price List'!$A$12:$P$180,2,FALSE) -> Move point of attachment - single/multi phase | G97: =IF(VLOOKUP($B97,'ACS Price List'!$A$12:$P$180,G$1,FALSE)=0,"",VLOOKUP($B97,'ACS Price List'!$A$12:$P$180,G$1,FALSE)) -> MPOAU | H97: =IF(VLOOKUP($B97,'ACS Price List'!$A$12:$P$180,H$1,FALSE)=0,"",VLOOKUP($B97,'ACS Price List'!$A$12:$P$180,H$1,FALSE)) -> MPOAS | I97: =IF(VLOOKUP($B97,'ACS Price List'!$A$12:$P$180,I$1,FALSE)=0,"",VLOOKUP($B97,'ACS Price List'!$A$12:$P$180,I$1,FALSE)) -> MPOAL | J97: =IF(VLOOKUP($B97,'ACS Price List'!$A$12:$P$180,J$1,FALSE)=0,"",VLOOKUP($B97,'ACS Price List'!$A$12:$P$180,J$1,FALSE)) -> MPOAI | K97: =IF(C97="163-M","GENM series or applicable Metering Service product code**","") -> GENM series or applicable Metering Service product code** | O97: GENCF* | P97: GENCFMC* | Q97: =IFERROR(IF(VLOOKUP($D97,'ACS Price List'!$A$12:$P$180,I$1,FALSE)=0,"",VLOOKUP($D97,'ACS Price List'!$A$12:$P$180,I$1,FALSE)),"") | R97: =IFERROR(IF(VLOOKUP($D97,'ACS Price List'!$A$12:$P$180,J$1,FALSE)=0,"",VLOOKUP($D97,'ACS Price List'!$A$12:$P$180,J$1,FALSE)),"")
B98: 57 | C98: 163-M | F98: =VLOOKUP(B98,'ACS Price List'!$A$12:$P$180,2,FALSE) -> Re-arrange connection assets at customer's request | G98: =IF(VLOOKUP($B98,'ACS Price List'!$A$12:$P$180,G$1,FALSE)=0,"",VLOOKUP($B98,'ACS Price List'!$A$12:$P$180,G$1,FALSE)) -> As Quoted | H98: =IF(VLOOKUP($B98,'ACS Price List'!$A$12:$P$180,H$1,FALSE)=0,"",VLOOKUP($B98,'ACS Price List'!$A$12:$P$180,H$1,FALSE)) | I98: =IF(VLOOKUP($B98,'ACS Price List'!$A$12:$P$180,I$1,FALSE)=0,"",VLOOKUP($B98,'ACS Price List'!$A$12:$P$180,I$1,FALSE)) | J98: =IF(VLOOKUP($B98,'ACS Price List'!$A$12:$P$180,J$1,FALSE)=0,"",VLOOKUP($B98,'ACS Price List'!$A$12:$P$180,J$1,FALSE)) | K98: =IF(C98="163-M","GENM series or applicable Metering Service product code**","") -> GENM series or applicable Metering Service product code** | O98: GENCF* | P98: GENCFMC* | Q98: =IFERROR(IF(VLOOKUP($D98,'ACS Price List'!$A$12:$P$180,I$1,FALSE)=0,"",VLOOKUP($D98,'ACS Price List'!$A$12:$P$180,I$1,FALSE)),"") | R98: =IFERROR(IF(VLOOKUP($D98,'ACS Price List'!$A$12:$P$180,J$1,FALSE)=0,"",VLOOKUP($D98,'ACS Price List'!$A$12:$P$180,J$1,FALSE)),"")
B99: 58 | C99: 163-M | F99: =VLOOKUP(B99,'ACS Price List'!$A$12:$P$180,2,FALSE) -> Protection and Power Quality assessment after connection | G99: =IF(VLOOKUP($B99,'ACS Price List'!$A$12:$P$180,G$1,FALSE)=0,"",VLOOKUP($B99,'ACS Price List'!$A$12:$P$180,G$1,FALSE)) -> As Quoted | H99: =IF(VLOOKUP($B99,'ACS Price List'!$A$12:$P$180,H$1,FALSE)=0,"",VLOOKUP($B99,'ACS Price List'!$A$12:$P$180,H$1,FALSE)) | I99: =IF(VLOOKUP($B99,'ACS Price List'!$A$12:$P$180,I$1,FALSE)=0,"",VLOOKUP($B99,'ACS Price List'!$A$12:$P$180,I$1,FALSE)) | J99: =IF(VLOOKUP($B99,'ACS Price List'!$A$12:$P$180,J$1,FALSE)=0,"",VLOOKUP($B99,'ACS Price List'!$A$12:$P$180,J$1,FALSE)) | K99: =IF(C99="163-M","GENM series or applicable Metering Service product code**","") -> GENM series or applicable Metering Service product code** | O99: GENCF* | P99: GENCFMC* | Q99: =IFERROR(IF(VLOOKUP($D99,'ACS Price List'!$A$12:$P$180,I$1,FALSE)=0,"",VLOOKUP($D99,'ACS Price List'!$A$12:$P$180,I$1,FALSE)),"") | R99: =IFERROR(IF(VLOOKUP($D99,'ACS Price List'!$A$12:$P$180,J$1,FALSE)=0,"",VLOOKUP($D99,'ACS Price List'!$A$12:$P$180,J$1,FALSE)),"")
B100: 59 | C100: 163-M | F100: =VLOOKUP(B100,'ACS Price List'!$A$12:$P$180,2,FALSE) -> Temporary de-energisation - no dismantling | G100: =IF(VLOOKUP($B100,'ACS Price List'!$A$12:$P$180,G$1,FALSE)=0,"",VLOOKUP($B100,'ACS Price List'!$A$12:$P$180,G$1,FALSE)) -> TEMPDEENU | H100: =IF(VLOOKUP($B100,'ACS Price List'!$A$12:$P$180,H$1,FALSE)=0,"",VLOOKUP($B100,'ACS Price List'!$A$12:$P$180,H$1,FALSE)) -> TEMPDEENS | I100: =IF(VLOOKUP($B100,'ACS Price List'!$A$12:$P$180,I$1,FALSE)=0,"",VLOOKUP($B100,'ACS Price List'!$A$12:$P$180,I$1,FALSE)) -> TEMPDEENL | J100: =IF(VLOOKUP($B100,'ACS Price List'!$A$12:$P$180,J$1,FALSE)=0,"",VLOOKUP($B100,'ACS Price List'!$A$12:$P$180,J$1,FALSE)) -> TEMPDEENI | K100: =IF(C100="163-M","GENM series or applicable Metering Service product code**","") -> GENM series or applicable Metering Service product code** | O100: GENCF* | P100: GENCFMC* | Q100: =IFERROR(IF(VLOOKUP($D100,'ACS Price List'!$A$12:$P$180,I$1,FALSE)=0,"",VLOOKUP($D100,'ACS Price List'!$A$12:$P$180,I$1,FALSE)),"") | R100: =IFERROR(IF(VLOOKUP($D100,'ACS Price List'!$A$12:$P$180,J$1,FALSE)=0,"",VLOOKUP($D100,'ACS Price List'!$A$12:$P$180,J$1,FALSE)),"")
B101: 60 | C101: 163-M | F101: =VLOOKUP(B101,'ACS Price List'!$A$12:$P$180,2,FALSE) -> LV Service line drop and replace - physical dismantling | G101: =IF(VLOOKUP($B101,'ACS Price List'!$A$12:$P$180,G$1,FALSE)=0,"",VLOOKUP($B101,'ACS Price List'!$A$12:$P$180,G$1,FALSE)) -> LVSLDU | H101: =IF(VLOOKUP($B101,'ACS Price List'!$A$12:$P$180,H$1,FALSE)=0,"",VLOOKUP($B101,'ACS Price List'!$A$12:$P$180,H$1,FALSE)) -> LVSLDS | I101: =IF(VLOOKUP($B101,'ACS Price List'!$A$12:$P$180,I$1,FALSE)=0,"",VLOOKUP($B101,'ACS Price List'!$A$12:$P$180,I$1,FALSE)) -> LVSLDL | J101: =IF(VLOOKUP($B101,'ACS Price List'!$A$12:$P$180,J$1,FALSE)=0,"",VLOOKUP($B101,'ACS Price List'!$A$12:$P$180,J$1,FALSE)) -> LVSLDI | K101: =IF(C101="163-M","GENM series or applicable Metering Service product code**","") -> GENM series or applicable Metering Service product code** | O101: GENCF* | P101: GENCFMC* | Q101: =IFERROR(IF(VLOOKUP($D101,'ACS Price List'!$A$12:$P$180,I$1,FALSE)=0,"",VLOOKUP($D101,'ACS Price List'!$A$12:$P$180,I$1,FALSE)),"") | R101: =IFERROR(IF(VLOOKUP($D101,'ACS Price List'!$A$12:$P$180,J$1,FALSE)=0,"",VLOOKUP($D101,'ACS Price List'!$A$12:$P$180,J$1,FALSE)),"")
B102: 61 | C102: 163-M | F102: =VLOOKUP(B102,'ACS Price List'!$A$12:$P$180,2,FALSE) -> HV Service line drop and replace | G102: =IF(VLOOKUP($B102,'ACS Price List'!$A$12:$P$180,G$1,FALSE)=0,"",VLOOKUP($B102,'ACS Price List'!$A$12:$P$180,G$1,FALSE)) -> HVSLDU | H102: =IF(VLOOKUP($B102,'ACS Price List'!$A$12:$P$180,H$1,FALSE)=0,"",VLOOKUP($B102,'ACS Price List'!$A$12:$P$180,H$1,FALSE)) -> HVSLDS | I102: =IF(VLOOKUP($B102,'ACS Price List'!$A$12:$P$180,I$1,FALSE)=0,"",VLOOKUP($B102,'ACS Price List'!$A$12:$P$180,I$1,FALSE)) -> HVSLDL | J102: =IF(VLOOKUP($B102,'ACS Price List'!$A$12:$P$180,J$1,FALSE)=0,"",VLOOKUP($B102,'ACS Price List'!$A$12:$P$180,J$1,FALSE)) -> HVSLDI | K102: =IF(C102="163-M","GENM series or applicable Metering Service product code**","") -> GENM series or applicable Metering Service product code** | O102: GENCF* | P102: GENCFMC* | Q102: =IFERROR(IF(VLOOKUP($D102,'ACS Price List'!$A$12:$P$180,I$1,FALSE)=0,"",VLOOKUP($D102,'ACS Price List'!$A$12:$P$180,I$1,FALSE)),"") | R102: =IFERROR(IF(VLOOKUP($D102,'ACS Price List'!$A$12:$P$180,J$1,FALSE)=0,"",VLOOKUP($D102,'ACS Price List'!$A$12:$P$180,J$1,FALSE)),"")
B103: 62 | C103: 163-M | F103: =VLOOKUP(B103,'ACS Price List'!$A$12:$P$180,2,FALSE) -> Supply enhancement | G103: =IF(VLOOKUP($B103,'ACS Price List'!$A$12:$P$180,G$1,FALSE)=0,"",VLOOKUP($B103,'ACS Price List'!$A$12:$P$180,G$1,FALSE)) -> SUPENHU | H103: =IF(VLOOKUP($B103,'ACS Price List'!$A$12:$P$180,H$1,FALSE)=0,"",VLOOKUP($B103,'ACS Price List'!$A$12:$P$180,H$1,FALSE)) -> SUPENHS | I103: =IF(VLOOKUP($B103,'ACS Price List'!$A$12:$P$180,I$1,FALSE)=0,"",VLOOKUP($B103,'ACS Price List'!$A$12:$P$180,I$1,FALSE)) -> SUPENHL | J103: =IF(VLOOKUP($B103,'ACS Price List'!$A$12:$P$180,J$1,FALSE)=0,"",VLOOKUP($B103,'ACS Price List'!$A$12:$P$180,J$1,FALSE)) -> SUPENHI | K103: =IF(C103="163-M","GENM series or applicable Metering Service product code**","") -> GENM series or applicable Metering Service product code** | O103: GENCF* | P103: GENCFMC* | Q103: =IFERROR(IF(VLOOKUP($D103,'ACS Price List'!$A$12:$P$180,I$1,FALSE)=0,"",VLOOKUP($D103,'ACS Price List'!$A$12:$P$180,I$1,FALSE)),"") | R103: =IFERROR(IF(VLOOKUP($D103,'ACS Price List'!$A$12:$P$180,J$1,FALSE)=0,"",VLOOKUP($D103,'ACS Price List'!$A$12:$P$180,J$1,FALSE)),"")
B104: 63 | C104: 163-M | F104: =VLOOKUP(B104,'ACS Price List'!$A$12:$P$180,2,FALSE) -> Provision of connection services above minimum requirements | G104: =IF(VLOOKUP($B104,'ACS Price List'!$A$12:$P$180,G$1,FALSE)=0,"",VLOOKUP($B104,'ACS Price List'!$A$12:$P$180,G$1,FALSE)) -> As Quoted | H104: =IF(VLOOKUP($B104,'ACS Price List'!$A$12:$P$180,H$1,FALSE)=0,"",VLOOKUP($B104,'ACS Price List'!$A$12:$P$180,H$1,FALSE)) | I104: =IF(VLOOKUP($B104,'ACS Price List'!$A$12:$P$180,I$1,FALSE)=0,"",VLOOKUP($B104,'ACS Price List'!$A$12:$P$180,I$1,FALSE)) | J104: =IF(VLOOKUP($B104,'ACS Price List'!$A$12:$P$180,J$1,FALSE)=0,"",VLOOKUP($B104,'ACS Price List'!$A$12:$P$180,J$1,FALSE)) | K104: =IF(C104="163-M","GENM series or applicable Metering Service product code**","") -> GENM series or applicable Metering Service product code** | O104: GENCF* | P104: GENCFMC* | Q104: =IFERROR(IF(VLOOKUP($D104,'ACS Price List'!$A$12:$P$180,I$1,FALSE)=0,"",VLOOKUP($D104,'ACS Price List'!$A$12:$P$180,I$1,FALSE)),"") | R104: =IFERROR(IF(VLOOKUP($D104,'ACS Price List'!$A$12:$P$180,J$1,FALSE)=0,"",VLOOKUP($D104,'ACS Price List'!$A$12:$P$180,J$1,FALSE)),"")
B105: 64 | C105: 163-M | F105: =VLOOKUP(B105,'ACS Price List'!$A$12:$P$180,2,FALSE) -> Upgrade from overhead to underground service | G105: =IF(VLOOKUP($B105,'ACS Price List'!$A$12:$P$180,G$1,FALSE)=0,"",VLOOKUP($B105,'ACS Price List'!$A$12:$P$180,G$1,FALSE)) -> As Quoted | H105: =IF(VLOOKUP($B105,'ACS Price List'!$A$12:$P$180,H$1,FALSE)=0,"",VLOOKUP($B105,'ACS Price List'!$A$12:$P$180,H$1,FALSE)) | I105: =IF(VLOOKUP($B105,'ACS Price List'!$A$12:$P$180,I$1,FALSE)=0,"",VLOOKUP($B105,'ACS Price List'!$A$12:$P$180,I$1,FALSE)) | J105: =IF(VLOOKUP($B105,'ACS Price List'!$A$12:$P$180,J$1,FALSE)=0,"",VLOOKUP($B105,'ACS Price List'!$A$12:$P$180,J$1,FALSE)) | K105: =IF(C105="163-M","GENM series or applicable Metering Service product code**","") -> GENM series or applicable Metering Service product code** | O105: GENCF* | P105: GENCFMC* | Q105: =IFERROR(IF(VLOOKUP($D105,'ACS Price List'!$A$12:$P$180,I$1,FALSE)=0,"",VLOOKUP($D105,'ACS Price List'!$A$12:$P$180,I$1,FALSE)),"") | R105: =IFERROR(IF(VLOOKUP($D105,'ACS Price List'!$A$12:$P$180,J$1,FALSE)=0,"",VLOOKUP($D105,'ACS Price List'!$A$12:$P$180,J$1,FALSE)),"")
B106: 65 | C106: 163-M | F106: =VLOOKUP(B106,'ACS Price List'!$A$12:$P$180,2,FALSE) -> Rectification of illegal connections or damage to overhead or underground service cables | G106: =IF(VLOOKUP($B106,'ACS Price List'!$A$12:$P$180,G$1,FALSE)=0,"",VLOOKUP($B106,'ACS Price List'!$A$12:$P$180,G$1,FALSE)) -> As Quoted | H106: =IF(VLOOKUP($B106,'ACS Price List'!$A$12:$P$180,H$1,FALSE)=0,"",VLOOKUP($B106,'ACS Price List'!$A$12:$P$180,H$1,FALSE)) | I106: =IF(VLOOKUP($B106,'ACS Price List'!$A$12:$P$180,I$1,FALSE)=0,"",VLOOKUP($B106,'ACS Price List'!$A$12:$P$180,I$1,FALSE)) | J106: =IF(VLOOKUP($B106,'ACS Price List'!$A$12:$P$180,J$1,FALSE)=0,"",VLOOKUP($B106,'ACS Price List'!$A$12:$P$180,J$1,FALSE)) | K106: =IF(C106="163-M","GENM series or applicable Metering Service product code**","") -> GENM series or applicable Metering Service product code** | O106: GENCF* | P106: GENCFMC* | Q106: =IFERROR(IF(VLOOKUP($D106,'ACS Price List'!$A$12:$P$180,I$1,FALSE)=0,"",VLOOKUP($D106,'ACS Price List'!$A$12:$P$180,I$1,FALSE)),"") | R106: =IFERROR(IF(VLOOKUP($D106,'ACS Price List'!$A$12:$P$180,J$1,FALSE)=0,"",VLOOKUP($D106,'ACS Price List'!$A$12:$P$180,J$1,FALSE)),"")
B107: 66 | D107: 66-CF | F107: =VLOOKUP(B107,'ACS Price List'!$A$12:$P$180,2,FALSE) -> De-energisation after business hours | G107: =IF(VLOOKUP($B107,'ACS Price List'!$A$12:$P$180,G$1,FALSE)=0,"",VLOOKUP($B107,'ACS Price List'!$A$12:$P$180,G$1,FALSE)) -> DEENAHU | H107: =IF(VLOOKUP($B107,'ACS Price List'!$A$12:$P$180,H$1,FALSE)=0,"",VLOOKUP($B107,'ACS Price List'!$A$12:$P$180,H$1,FALSE)) -> DEENAHS | I107: =IF(VLOOKUP($B107,'ACS Price List'!$A$12:$P$180,I$1,FALSE)=0,"",VLOOKUP($B107,'ACS Price List'!$A$12:$P$180,I$1,FALSE)) -> DEENAHL | J107: =IF(VLOOKUP($B107,'ACS Price List'!$A$12:$P$180,J$1,FALSE)=0,"",VLOOKUP($B107,'ACS Price List'!$A$12:$P$180,J$1,FALSE)) -> DEENAHI | K107: =IF(C107="163-M","GENM or applicable Metering Service product code**","") | O107: =IFERROR(IF(VLOOKUP($D107,'ACS Price List'!$A$12:$P$180,G$1,FALSE)=0,"",VLOOKUP($D107,'ACS Price List'!$A$12:$P$180,G$1,FALSE)),"") -> CFDEENAHU | P107: =IFERROR(IF(VLOOKUP($D107,'ACS Price List'!$A$12:$P$180,H$1,FALSE)=0,"",VLOOKUP($D107,'ACS Price List'!$A$12:$P$180,H$1,FALSE)),"") -> CFDEENAHS | Q107: =IFERROR(IF(VLOOKUP($D107,'ACS Price List'!$A$12:$P$180,I$1,FALSE)=0,"",VLOOKUP($D107,'ACS Price List'!$A$12:$P$180,I$1,FALSE)),"") -> CFDEENAHL | R107: =IFERROR(IF(VLOOKUP($D107,'ACS Price List'!$A$12:$P$180,J$1,FALSE)=0,"",VLOOKUP($D107,'ACS Price List'!$A$12:$P$180,J$1,FALSE)),"") -> CFDEENAHI
B108: 67 | D108: 67-CF | F108: =VLOOKUP(B108,'ACS Price List'!$A$12:$P$180,2,FALSE) -> Re-energisation after business hours | G108: =IF(VLOOKUP($B108,'ACS Price List'!$A$12:$P$180,G$1,FALSE)=0,"",VLOOKUP($B108,'ACS Price List'!$A$12:$P$180,G$1,FALSE)) -> REENAHU | H108: =IF(VLOOKUP($B108,'ACS Price List'!$A$12:$P$180,H$1,FALSE)=0,"",VLOOKUP($B108,'ACS Price List'!$A$12:$P$180,H$1,FALSE)) -> REENAHS | I108: =IF(VLOOKUP($B108,'ACS Price List'!$A$12:$P$180,I$1,FALSE)=0,"",VLOOKUP($B108,'ACS Price List'!$A$12:$P$180,I$1,FALSE)) -> REENAHL | J108: =IF(VLOOKUP($B108,'ACS Price List'!$A$12:$P$180,J$1,FALSE)=0,"",VLOOKUP($B108,'ACS Price List'!$A$12:$P$180,J$1,FALSE)) -> REENAHI | K108: =IF(C108="163-M","GENM or applicable Metering Service product code**","") | O108: =IFERROR(IF(VLOOKUP($D108,'ACS Price List'!$A$12:$P$180,G$1,FALSE)=0,"",VLOOKUP($D108,'ACS Price List'!$A$12:$P$180,G$1,FALSE)),"") -> CFREENAHU | P108: =IFERROR(IF(VLOOKUP($D108,'ACS Price List'!$A$12:$P$180,H$1,FALSE)=0,"",VLOOKUP($D108,'ACS Price List'!$A$12:$P$180,H$1,FALSE)),"") -> CFREENAHS | Q108: =IFERROR(IF(VLOOKUP($D108,'ACS Price List'!$A$12:$P$180,I$1,FALSE)=0,"",VLOOKUP($D108,'ACS Price List'!$A$12:$P$180,I$1,FALSE)),"") -> CFREENAHL | R108: =IFERROR(IF(VLOOKUP($D108,'ACS Price List'!$A$12:$P$180,J$1,FALSE)=0,"",VLOOKUP($D108,'ACS Price List'!$A$12:$P$180,J$1,FALSE)),"") -> CFREENAHI
B109: 67-VE | D109: 67-CF | F109: =VLOOKUP(B109,'ACS Price List'!$A$12:$P$180,2,FALSE) -> Visual examination after business hours for remote re-energisation | G109: =IF(VLOOKUP($B109,'ACS Price List'!$A$12:$P$180,G$1,FALSE)=0,"",VLOOKUP($B109,'ACS Price List'!$A$12:$P$180,G$1,FALSE)) -> VEREENAHU | H109: =IF(VLOOKUP($B109,'ACS Price List'!$A$12:$P$180,H$1,FALSE)=0,"",VLOOKUP($B109,'ACS Price List'!$A$12:$P$180,H$1,FALSE)) -> VEREENAHS | I109: =IF(VLOOKUP($B109,'ACS Price List'!$A$12:$P$180,I$1,FALSE)=0,"",VLOOKUP($B109,'ACS Price List'!$A$12:$P$180,I$1,FALSE)) -> VEREENAHL | J109: =IF(VLOOKUP($B109,'ACS Price List'!$A$12:$P$180,J$1,FALSE)=0,"",VLOOKUP($B109,'ACS Price List'!$A$12:$P$180,J$1,FALSE)) -> VEREENAHI | K109: =IF(C109="163-M","GENM or applicable Metering Service product code**","") | O109: =IFERROR(IF(VLOOKUP($D109,'ACS Price List'!$A$12:$P$180,G$1,FALSE)=0,"",VLOOKUP($D109,'ACS Price List'!$A$12:$P$180,G$1,FALSE)),"") -> CFREENAHU | P109: =IFERROR(IF(VLOOKUP($D109,'ACS Price List'!$A$12:$P$180,H$1,FALSE)=0,"",VLOOKUP($D109,'ACS Price List'!$A$12:$P$180,H$1,FALSE)),"") -> CFREENAHS | Q109: =IFERROR(IF(VLOOKUP($D109,'ACS Price List'!$A$12:$P$180,I$1,FALSE)=0,"",VLOOKUP($D109,'ACS Price List'!$A$12:$P$180,I$1,FALSE)),"") -> CFREENAHL | R109: =IFERROR(IF(VLOOKUP($D109,'ACS Price List'!$A$12:$P$180,J$1,FALSE)=0,"",VLOOKUP($D109,'ACS Price List'!$A$12:$P$180,J$1,FALSE)),"") -> CFREENAHI
B110: 68 | F110: =VLOOKUP(B110,'ACS Price List'!$A$12:$P$180,2,FALSE) -> Accreditation of alternative service providers - major customer connections | G110: =IF(VLOOKUP($B110,'ACS Price List'!$A$12:$P$180,G$1,FALSE)=0,"",VLOOKUP($B110,'ACS Price List'!$A$12:$P$180,G$1,FALSE)) -> As Quoted | H110: =IF(VLOOKUP($B110,'ACS Price List'!$A$12:$P$180,H$1,FALSE)=0,"",VLOOKUP($B110,'ACS Price List'!$A$12:$P$180,H$1,FALSE)) | I110: =IF(VLOOKUP($B110,'ACS Price List'!$A$12:$P$180,I$1,FALSE)=0,"",VLOOKUP($B110,'ACS Price List'!$A$12:$P$180,I$1,FALSE)) | J110: =IF(VLOOKUP($B110,'ACS Price List'!$A$12:$P$180,J$1,FALSE)=0,"",VLOOKUP($B110,'ACS Price List'!$A$12:$P$180,J$1,FALSE)) | K110: =IF(C110="163-M","GENM or applicable Metering Service product code**","") | O110: GENCF* | P110: GENCFMC* | Q110: =IFERROR(IF(VLOOKUP($D110,'ACS Price List'!$A$12:$P$180,I$1,FALSE)=0,"",VLOOKUP($D110,'ACS Price List'!$A$12:$P$180,I$1,FALSE)),"") | R110: =IFERROR(IF(VLOOKUP($D110,'ACS Price List'!$A$12:$P$180,J$1,FALSE)=0,"",VLOOKUP($D110,'ACS Price List'!$A$12:$P$180,J$1,FALSE)),"")
B111: 69 | F111: =VLOOKUP(B111,'ACS Price List'!$A$12:$P$180,2,FALSE) -> Approval of third party design - major customer connections | G111: =IF(VLOOKUP($B111,'ACS Price List'!$A$12:$P$180,G$1,FALSE)=0,"",VLOOKUP($B111,'ACS Price List'!$A$12:$P$180,G$1,FALSE)) -> As Quoted | H111: =IF(VLOOKUP($B111,'ACS Price List'!$A$12:$P$180,H$1,FALSE)=0,"",VLOOKUP($B111,'ACS Price List'!$A$12:$P$180,H$1,FALSE)) | I111: =IF(VLOOKUP($B111,'ACS Price List'!$A$12:$P$180,I$1,FALSE)=0,"",VLOOKUP($B111,'ACS Price List'!$A$12:$P$180,I$1,FALSE)) | J111: =IF(VLOOKUP($B111,'ACS Price List'!$A$12:$P$180,J$1,FALSE)=0,"",VLOOKUP($B111,'ACS Price List'!$A$12:$P$180,J$1,FALSE)) | K111: =IF(C111="163-M","GENM or applicable Metering Service product code**","") | O111: GENCF* | P111: GENCFMC* | Q111: =IFERROR(IF(VLOOKUP($D111,'ACS Price List'!$A$12:$P$180,I$1,FALSE)=0,"",VLOOKUP($D111,'ACS Price List'!$A$12:$P$180,I$1,FALSE)),"") | R111: =IFERROR(IF(VLOOKUP($D111,'ACS Price List'!$A$12:$P$180,J$1,FALSE)=0,"",VLOOKUP($D111,'ACS Price List'!$A$12:$P$180,J$1,FALSE)),"")
B112: 70 | F112: =VLOOKUP(B112,'ACS Price List'!$A$12:$P$180,2,FALSE) -> Approval of third party design - real estate developments | G112: =IF(VLOOKUP($B112,'ACS Price List'!$A$12:$P$180,G$1,FALSE)=0,"",VLOOKUP($B112,'ACS Price List'!$A$12:$P$180,G$1,FALSE)) -> As Quoted | H112: =IF(VLOOKUP($B112,'ACS Price List'!$A$12:$P$180,H$1,FALSE)=0,"",VLOOKUP($B112,'ACS Price List'!$A$12:$P$180,H$1,FALSE)) | I112: =IF(VLOOKUP($B112,'ACS Price List'!$A$12:$P$180,I$1,FALSE)=0,"",VLOOKUP($B112,'ACS Price List'!$A$12:$P$180,I$1,FALSE)) | J112: =IF(VLOOKUP($B112,'ACS Price List'!$A$12:$P$180,J$1,FALSE)=0,"",VLOOKUP($B112,'ACS Price List'!$A$12:$P$180,J$1,FALSE)) | K112: =IF(C112="163-M","GENM or applicable Metering Service product code**","") | O112: GENCF* | P112: GENCFMC* | Q112: =IFERROR(IF(VLOOKUP($D112,'ACS Price List'!$A$12:$P$180,I$1,FALSE)=0,"",VLOOKUP($D112,'ACS Price List'!$A$12:$P$180,I$1,FALSE)),"") | R112: =IFERROR(IF(VLOOKUP($D112,'ACS Price List'!$A$12:$P$180,J$1,FALSE)=0,"",VLOOKUP($D112,'ACS Price List'!$A$12:$P$180,J$1,FALSE)),"")
B113: 71 | F113: =VLOOKUP(B113,'ACS Price List'!$A$12:$P$180,2,FALSE) -> Construction audit - major customer connections | G113: =IF(VLOOKUP($B113,'ACS Price List'!$A$12:$P$180,G$1,FALSE)=0,"",VLOOKUP($B113,'ACS Price List'!$A$12:$P$180,G$1,FALSE)) -> As Quoted | H113: =IF(VLOOKUP($B113,'ACS Price List'!$A$12:$P$180,H$1,FALSE)=0,"",VLOOKUP($B113,'ACS Price List'!$A$12:$P$180,H$1,FALSE)) | I113: =IF(VLOOKUP($B113,'ACS Price List'!$A$12:$P$180,I$1,FALSE)=0,"",VLOOKUP($B113,'ACS Price List'!$A$12:$P$180,I$1,FALSE)) | J113: =IF(VLOOKUP($B113,'ACS Price List'!$A$12:$P$180,J$1,FALSE)=0,"",VLOOKUP($B113,'ACS Price List'!$A$12:$P$180,J$1,FALSE)) | K113: =IF(C113="163-M","GENM or applicable Metering Service product code**","") | O113: GENCF* | P113: GENCFMC* | Q113: =IFERROR(IF(VLOOKUP($D113,'ACS Price List'!$A$12:$P$180,I$1,FALSE)=0,"",VLOOKUP($D113,'ACS Price List'!$A$12:$P$180,I$1,FALSE)),"") | R113: =IFERROR(IF(VLOOKUP($D113,'ACS Price List'!$A$12:$P$180,J$1,FALSE)=0,"",VLOOKUP($D113,'ACS Price List'!$A$12:$P$180,J$1,FALSE)),"")
B114: 72 | F114: =VLOOKUP(B114,'ACS Price List'!$A$12:$P$180,2,FALSE) -> Construction audit - real estate developments | G114: =IF(VLOOKUP($B114,'ACS Price List'!$A$12:$P$180,G$1,FALSE)=0,"",VLOOKUP($B114,'ACS Price List'!$A$12:$P$180,G$1,FALSE)) -> As Quoted | H114: =IF(VLOOKUP($B114,'ACS Price List'!$A$12:$P$180,H$1,FALSE)=0,"",VLOOKUP($B114,'ACS Price List'!$A$12:$P$180,H$1,FALSE)) | I114: =IF(VLOOKUP($B114,'ACS Price List'!$A$12:$P$180,I$1,FALSE)=0,"",VLOOKUP($B114,'ACS Price List'!$A$12:$P$180,I$1,FALSE)) | J114: =IF(VLOOKUP($B114,'ACS Price List'!$A$12:$P$180,J$1,FALSE)=0,"",VLOOKUP($B114,'ACS Price List'!$A$12:$P$180,J$1,FALSE)) | K114: =IF(C114="163-M","GENM or applicable Metering Service product code**","") | O114: GENCF* | P114: GENCFMC* | Q114: =IFERROR(IF(VLOOKUP($D114,'ACS Price List'!$A$12:$P$180,I$1,FALSE)=0,"",VLOOKUP($D114,'ACS Price List'!$A$12:$P$180,I$1,FALSE)),"") | R114: =IFERROR(IF(VLOOKUP($D114,'ACS Price List'!$A$12:$P$180,J$1,FALSE)=0,"",VLOOKUP($D114,'ACS Price List'!$A$12:$P$180,J$1,FALSE)),"")
B115: 73 | F115: =VLOOKUP(B115,'ACS Price List'!$A$12:$P$180,2,FALSE) -> Approval of third party materials | G115: =IF(VLOOKUP($B115,'ACS Price List'!$A$12:$P$180,G$1,FALSE)=0,"",VLOOKUP($B115,'ACS Price List'!$A$12:$P$180,G$1,FALSE)) -> As Quoted | H115: =IF(VLOOKUP($B115,'ACS Price List'!$A$12:$P$180,H$1,FALSE)=0,"",VLOOKUP($B115,'ACS Price List'!$A$12:$P$180,H$1,FALSE)) | I115: =IF(VLOOKUP($B115,'ACS Price List'!$A$12:$P$180,I$1,FALSE)=0,"",VLOOKUP($B115,'ACS Price List'!$A$12:$P$180,I$1,FALSE)) | J115: =IF(VLOOKUP($B115,'ACS Price List'!$A$12:$P$180,J$1,FALSE)=0,"",VLOOKUP($B115,'ACS Price List'!$A$12:$P$180,J$1,FALSE)) | K115: =IF(C115="163-M","GENM or applicable Metering Service product code**","") | O115: GENCF* | P115: GENCFMC* | Q115: =IFERROR(IF(VLOOKUP($D115,'ACS Price List'!$A$12:$P$180,I$1,FALSE)=0,"",VLOOKUP($D115,'ACS Price List'!$A$12:$P$180,I$1,FALSE)),"") | R115: =IFERROR(IF(VLOOKUP($D115,'ACS Price List'!$A$12:$P$180,J$1,FALSE)=0,"",VLOOKUP($D115,'ACS Price List'!$A$12:$P$180,J$1,FALSE)),"")
B116: 74 | D116: 74-CF | F116: =VLOOKUP(B116,'ACS Price List'!$A$12:$P$180,2,FALSE) -> Special meter read | G116: =IF(VLOOKUP($B116,'ACS Price List'!$A$12:$P$180,G$1,FALSE)=0,"",VLOOKUP($B116,'ACS Price List'!$A$12:$P$180,G$1,FALSE)) -> SPMTRRDU | H116: =IF(VLOOKUP($B116,'ACS Price List'!$A$12:$P$180,H$1,FALSE)=0,"",VLOOKUP($B116,'ACS Price List'!$A$12:$P$180,H$1,FALSE)) -> SPMTRRDS | I116: =IF(VLOOKUP($B116,'ACS Price List'!$A$12:$P$180,I$1,FALSE)=0,"",VLOOKUP($B116,'ACS Price List'!$A$12:$P$180,I$1,FALSE)) -> SPMTRRDL | J116: =IF(VLOOKUP($B116,'ACS Price List'!$A$12:$P$180,J$1,FALSE)=0,"",VLOOKUP($B116,'ACS Price List'!$A$12:$P$180,J$1,FALSE)) -> SPMTRRDI | K116: =IF(C116="163-M","GENM or applicable Metering Service product code**","") | O116: =IFERROR(IF(VLOOKUP($D116,'ACS Price List'!$A$12:$P$180,G$1,FALSE)=0,"",VLOOKUP($D116,'ACS Price List'!$A$12:$P$180,G$1,FALSE)),"") -> CFSPMTRRDU | P116: =IFERROR(IF(VLOOKUP($D116,'ACS Price List'!$A$12:$P$180,H$1,FALSE)=0,"",VLOOKUP($D116,'ACS Price List'!$A$12:$P$180,H$1,FALSE)),"") -> CFSPMTRRDS | Q116: =IFERROR(IF(VLOOKUP($D116,'ACS Price List'!$A$12:$P$180,I$1,FALSE)=0,"",VLOOKUP($D116,'ACS Price List'!$A$12:$P$180,I$1,FALSE)),"") -> CFSPMTRRDL | R116: =IFERROR(IF(VLOOKUP($D116,'ACS Price List'!$A$12:$P$180,J$1,FALSE)=0,"",VLOOKUP($D116,'ACS Price List'!$A$12:$P$180,J$1,FALSE)),"") -> CFSPMTRRDI
B117: 75 | D117: 75-CF | F117: =VLOOKUP(B117,'ACS Price List'!$A$12:$P$180,2,FALSE) -> Meter test | G117: =IF(VLOOKUP($B117,'ACS Price List'!$A$12:$P$180,G$1,FALSE)=0,"",VLOOKUP($B117,'ACS Price List'!$A$12:$P$180,G$1,FALSE)) -> MTRTESTU | H117: =IF(VLOOKUP($B117,'ACS Price List'!$A$12:$P$180,H$1,FALSE)=0,"",VLOOKUP($B117,'ACS Price List'!$A$12:$P$180,H$1,FALSE)) -> MTRTESTS | I117: =IF(VLOOKUP($B117,'ACS Price List'!$A$12:$P$180,I$1,FALSE)=0,"",VLOOKUP($B117,'ACS Price List'!$A$12:$P$180,I$1,FALSE)) -> MTRTESTL | J117: =IF(VLOOKUP($B117,'ACS Price List'!$A$12:$P$180,J$1,FALSE)=0,"",VLOOKUP($B117,'ACS Price List'!$A$12:$P$180,J$1,FALSE)) -> MTRTESTI | K117: =IF(C117="163-M","GENM or applicable Metering Service product code**","") | O117: =IFERROR(IF(VLOOKUP($D117,'ACS Price List'!$A$12:$P$180,G$1,FALSE)=0,"",VLOOKUP($D117,'ACS Price List'!$A$12:$P$180,G$1,FALSE)),"") -> CFMTRTESTU | P117: =IFERROR(IF(VLOOKUP($D117,'ACS Price List'!$A$12:$P$180,H$1,FALSE)=0,"",VLOOKUP($D117,'ACS Price List'!$A$12:$P$180,H$1,FALSE)),"") -> CFMTRTESTS | Q117: =IFERROR(IF(VLOOKUP($D117,'ACS Price List'!$A$12:$P$180,I$1,FALSE)=0,"",VLOOKUP($D117,'ACS Price List'!$A$12:$P$180,I$1,FALSE)),"") -> CFMTRTESTL | R117: =IFERROR(IF(VLOOKUP($D117,'ACS Price List'!$A$12:$P$180,J$1,FALSE)=0,"",VLOOKUP($D117,'ACS Price List'!$A$12:$P$180,J$1,FALSE)),"") -> CFMTRTESTI
B118: 76 | F118: =VLOOKUP(B118,'ACS Price List'!$A$12:$P$180,2,FALSE) -> Meter inspection and investigation on request | G118: =IF(VLOOKUP($B118,'ACS Price List'!$A$12:$P$180,G$1,FALSE)=0,"",VLOOKUP($B118,'ACS Price List'!$A$12:$P$180,G$1,FALSE)) -> MTRINSPU | H118: =IF(VLOOKUP($B118,'ACS Price List'!$A$12:$P$180,H$1,FALSE)=0,"",VLOOKUP($B118,'ACS Price List'!$A$12:$P$180,H$1,FALSE)) -> MTRINSPS | I118: =IF(VLOOKUP($B118,'ACS Price List'!$A$12:$P$180,I$1,FALSE)=0,"",VLOOKUP($B118,'ACS Price List'!$A$12:$P$180,I$1,FALSE)) -> MTRINSPL | J118: =IF(VLOOKUP($B118,'ACS Price List'!$A$12:$P$180,J$1,FALSE)=0,"",VLOOKUP($B118,'ACS Price List'!$A$12:$P$180,J$1,FALSE)) -> MTRINSPI | K118: =IF(C118="163-M","GENM or applicable Metering Service product code**","") | O118: GENCF* | P118: GENCFMC* | Q118: =IFERROR(IF(VLOOKUP($D118,'ACS Price List'!$A$12:$P$180,I$1,FALSE)=0,"",VLOOKUP($D118,'ACS Price List'!$A$12:$P$180,I$1,FALSE)),"") | R118: =IFERROR(IF(VLOOKUP($D118,'ACS Price List'!$A$12:$P$180,J$1,FALSE)=0,"",VLOOKUP($D118,'ACS Price List'!$A$12:$P$180,J$1,FALSE)),"")
B119: 77 | F119: =VLOOKUP(B119,'ACS Price List'!$A$12:$P$180,2,FALSE) -> Metering alteration | G119: =IF(VLOOKUP($B119,'ACS Price List'!$A$12:$P$180,G$1,FALSE)=0,"",VLOOKUP($B119,'ACS Price List'!$A$12:$P$180,G$1,FALSE)) -> MOVEMTRU | H119: =IF(VLOOKUP($B119,'ACS Price List'!$A$12:$P$180,H$1,FALSE)=0,"",VLOOKUP($B119,'ACS Price List'!$A$12:$P$180,H$1,FALSE)) -> MOVEMTRS | I119: =IF(VLOOKUP($B119,'ACS Price List'!$A$12:$P$180,I$1,FALSE)=0,"",VLOOKUP($B119,'ACS Price List'!$A$12:$P$180,I$1,FALSE)) -> MOVEMTRL | J119: =IF(VLOOKUP($B119,'ACS Price List'!$A$12:$P$180,J$1,FALSE)=0,"",VLOOKUP($B119,'ACS Price List'!$A$12:$P$180,J$1,FALSE)) -> MOVEMTRI | K119: =IF(C119="163-M","GENM or applicable Metering Service product code**","") | O119: GENCF* | P119: GENCFMC* | Q119: =IFERROR(IF(VLOOKUP($D119,'ACS Price List'!$A$12:$P$180,I$1,FALSE)=0,"",VLOOKUP($D119,'ACS Price List'!$A$12:$P$180,I$1,FALSE)),"") | R119: =IFERROR(IF(VLOOKUP($D119,'ACS Price List'!$A$12:$P$180,J$1,FALSE)=0,"",VLOOKUP($D119,'ACS Price List'!$A$12:$P$180,J$1,FALSE)),"")
B120: 78 | F120: =VLOOKUP(B120,'ACS Price List'!$A$12:$P$180,2,FALSE) -> Exchange meter | G120: =IF(VLOOKUP($B120,'ACS Price List'!$A$12:$P$180,G$1,FALSE)=0,"",VLOOKUP($B120,'ACS Price List'!$A$12:$P$180,G$1,FALSE)) -> MTRREPU | H120: =IF(VLOOKUP($B120,'ACS Price List'!$A$12:$P$180,H$1,FALSE)=0,"",VLOOKUP($B120,'ACS Price List'!$A$12:$P$180,H$1,FALSE)) -> MTRREPS | I120: =IF(VLOOKUP($B120,'ACS Price List'!$A$12:$P$180,I$1,FALSE)=0,"",VLOOKUP($B120,'ACS Price List'!$A$12:$P$180,I$1,FALSE)) -> MTRREPL | J120: =IF(VLOOKUP($B120,'ACS Price List'!$A$12:$P$180,J$1,FALSE)=0,"",VLOOKUP($B120,'ACS Price List'!$A$12:$P$180,J$1,FALSE)) -> MTRREPI | K120: =IF(C120="163-M","GENM or applicable Metering Service product code**","") | O120: GENCF* | P120: GENCFMC* | Q120: =IFERROR(IF(VLOOKUP($D120,'ACS Price List'!$A$12:$P$180,I$1,FALSE)=0,"",VLOOKUP($D120,'ACS Price List'!$A$12:$P$180,I$1,FALSE)),"") | R120: =IFERROR(IF(VLOOKUP($D120,'ACS Price List'!$A$12:$P$180,J$1,FALSE)=0,"",VLOOKUP($D120,'ACS Price List'!$A$12:$P$180,J$1,FALSE)),"")
B121: 79 | F121: =VLOOKUP(B121,'ACS Price List'!$A$12:$P$180,2,FALSE) -> Type 5 to 7 non-standard metering services | G121: =IF(VLOOKUP($B121,'ACS Price List'!$A$12:$P$180,G$1,FALSE)=0,"",VLOOKUP($B121,'ACS Price List'!$A$12:$P$180,G$1,FALSE)) -> As Quoted | H121: =IF(VLOOKUP($B121,'ACS Price List'!$A$12:$P$180,H$1,FALSE)=0,"",VLOOKUP($B121,'ACS Price List'!$A$12:$P$180,H$1,FALSE)) | I121: =IF(VLOOKUP($B121,'ACS Price List'!$A$12:$P$180,I$1,FALSE)=0,"",VLOOKUP($B121,'ACS Price List'!$A$12:$P$180,I$1,FALSE)) | J121: =IF(VLOOKUP($B121,'ACS Price List'!$A$12:$P$180,J$1,FALSE)=0,"",VLOOKUP($B121,'ACS Price List'!$A$12:$P$180,J$1,FALSE)) | K121: =IF(C121="163-M","GENM or applicable Metering Service product code**","") | O121: GENCF* | P121: GENCFMC* | Q121: =IFERROR(IF(VLOOKUP($D121,'ACS Price List'!$A$12:$P$180,I$1,FALSE)=0,"",VLOOKUP($D121,'ACS Price List'!$A$12:$P$180,I$1,FALSE)),"") | R121: =IFERROR(IF(VLOOKUP($D121,'ACS Price List'!$A$12:$P$180,J$1,FALSE)=0,"",VLOOKUP($D121,'ACS Price List'!$A$12:$P$180,J$1,FALSE)),"")
B122: 80 | F122: =VLOOKUP(B122,'ACS Price List'!$A$12:$P$180,2,FALSE) -> Removal of a meter (Type 5 & 6) | G122: =IF(VLOOKUP($B122,'ACS Price List'!$A$12:$P$180,G$1,FALSE)=0,"",VLOOKUP($B122,'ACS Price List'!$A$12:$P$180,G$1,FALSE)) -> RMMTRU | H122: =IF(VLOOKUP($B122,'ACS Price List'!$A$12:$P$180,H$1,FALSE)=0,"",VLOOKUP($B122,'ACS Price List'!$A$12:$P$180,H$1,FALSE)) -> RMMTRS | I122: =IF(VLOOKUP($B122,'ACS Price List'!$A$12:$P$180,I$1,FALSE)=0,"",VLOOKUP($B122,'ACS Price List'!$A$12:$P$180,I$1,FALSE)) -> RMMTRL | J122: =IF(VLOOKUP($B122,'ACS Price List'!$A$12:$P$180,J$1,FALSE)=0,"",VLOOKUP($B122,'ACS Price List'!$A$12:$P$180,J$1,FALSE)) -> RMMTRI | K122: =IF(C122="163-M","GENM or applicable Metering Service product code**","") | O122: GENCF* | P122: GENCFMC* | Q122: =IFERROR(IF(VLOOKUP($D122,'ACS Price List'!$A$12:$P$180,I$1,FALSE)=0,"",VLOOKUP($D122,'ACS Price List'!$A$12:$P$180,I$1,FALSE)),"") | R122: =IFERROR(IF(VLOOKUP($D122,'ACS Price List'!$A$12:$P$180,J$1,FALSE)=0,"",VLOOKUP($D122,'ACS Price List'!$A$12:$P$180,J$1,FALSE)),"")
...

Sheet Rates by ProdCode
J2: Total Unique Prod Codes | K2: =COUNTA('ACS Price List'!D16:G180)+COUNTA('ACS Tariff classes & tariffs'!F160,'ACS Tariff classes & tariffs'!F161) -> 362
D3: Ergon Energy Corporation Limited | J3: No. Prod Codes in this sheet | K3: =COUNTA(C11:C558,O11:O45) -> 362 | L3: =IF(K3=K2,"OK","CHECK") -> OK
D4: 2017-18 ACS tariff rates by product code
I5: revised price or new prod code from 1 December
C8: Table 1: ACS tariffs billed per service | O8: Table 2: ACS tariffs billed as network tariff component
B10: Ref# | C10: Product Code | D10: Feeder Category | E10: Tariff | F10: Ellipse Cost Code | G10: Billing unit | H10: GST Exclusive Rate (effective 1 Jul 2017) | I10: GST Exclusive Rate (effective 1 Dec 2017) | O10: Product Code | P10: Tariff | Q10: Ellipse Cost Code | R10: Billing unit | S10: GST Exclusive Rate (effective 1 Jul 2017) | T10: GST Exclusive Rate (effective 1 Dec 2017)
B11: 1 | C11: APFSAC | D11: N/A | E11: Application fee - Basic or standard connection | F11: =VLOOKUP(B11,'ACS Price List'!$16:$180,8,FALSE) -> 8000 | G11: dollars ($) | H11: 888.4 | I11: =IFERROR(IF(D11="LR",VLOOKUP(B11,'ACS Price List'!$16:$180,11,FALSE),IF(D11="IS",VLOOKUP(B11,'ACS Price List'!$16:$180,11,FALSE),VLOOKUP(B11,'ACS Price List'!$16:$180,9,FALSE))),"POA") -> 888.4 | K11: =IFERROR(IF(I11="POA","OK",IF(I11-H11=0,"OK","CHANGE")),"CHECK") -> OK | N11: 100 | O11: ACSMNCC | P11: Default Metering Services: Primary service - Non-capital | Q11: =VLOOKUP(N11,'ACS Price List'!$16:$180,8,FALSE) -> 8120 | R11: dollars per day per meter ($/day/meter) | T11: =VLOOKUP(N11,'ACS Price List'!$16:$180,9,FALSE) -> 0.1121
B12: 2 | C12: APFMEG | D12: N/A | E12: Application fee - Basic or standard connection - Micro-embedded generators | F12: =VLOOKUP(B12,'ACS Price List'!$16:$180,8,FALSE) -> 8001 | G12: dollars ($) | H12: 48.6 | I12: =IFERROR(IF(D12="LR",VLOOKUP(B12,'ACS Price List'!$16:$180,11,FALSE),IF(D12="IS",VLOOKUP(B12,'ACS Price List'!$16:$180,11,FALSE),VLOOKUP(B12,'ACS Price List'!$16:$180,9,FALSE))),"POA") -> 48.6 | K12: =IFERROR(IF(I12="POA","OK",IF(I12-H12=0,"OK","CHANGE")),"CHECK") -> OK | N12: 101 | O12: ACSMCC | P12: Default Metering Services: Primary service - Capital | Q12: =VLOOKUP(N12,'ACS Price List'!$16:$180,8,FALSE) -> 8121 | R12: dollars per day per meter ($/day/meter) | T12: =VLOOKUP(N12,'ACS Price List'!$16:$180,9,FALSE) -> 0.03128
B13: 3 | C13: APFMTA | D13: N/A | E13: Application fee - Basic or standard connection - Micro-embedded generators - Technical assessment required | F13: =VLOOKUP(B13,'ACS Price List'!$16:$180,8,FALSE) -> 8002 | G13: dollars ($) | H13: 220.7 | I13: =IFERROR(IF(D13="LR",VLOOKUP(B13,'ACS Price List'!$16:$180,11,FALSE),IF(D13="IS",VLOOKUP(B13,'ACS Price List'!$16:$180,11,FALSE),VLOOKUP(B13,'ACS Price List'!$16:$180,9,FALSE))),"POA") -> 220.7 | K13: =IFERROR(IF(I13="POA","OK",IF(I13-H13=0,"OK","CHANGE")),"CHECK") -> OK | N13: 102 | O13: ACSMNCC | P13: Default Metering Services: Controlled load - Non-capital | Q13: =VLOOKUP(N13,'ACS Price List'!$16:$180,8,FALSE) -> 8122 | R13: dollars per day per meter ($/day/meter) | T13: =VLOOKUP(N13,'ACS Price List'!$16:$180,9,FALSE) -> 0.04121
B14: 4 | C14: APFRED | D14: N/A | E14: Application fee - Real estate development connection | F14: =VLOOKUP(B14,'ACS Price List'!$16:$180,8,FALSE) -> 8003 | G14: dollars ($) | H14: 930.2 | I14: =IFERROR(IF(D14="LR",VLOOKUP(B14,'ACS Price List'!$16:$180,11,FALSE),IF(D14="IS",VLOOKUP(B14,'ACS Price List'!$16:$180,11,FALSE),VLOOKUP(B14,'ACS Price List'!$16:$180,9,FALSE))),"POA") -> 930.2 | K14: =IFERROR(IF(I14="POA","OK",IF(I14-H14=0,"OK","CHANGE")),"CHECK") -> OK | N14: 103 | O14: ACSMCC | P14: Default Metering Services: Controlled load - Capital | Q14: =VLOOKUP(N14,'ACS Price List'!$16:$180,8,FALSE) -> 8123 | R14: dollars per day per meter ($/day/meter) | T14: =VLOOKUP(N14,'ACS Price List'!$16:$180,9,FALSE) -> 0.0115
B15: 5 | C15: PPQA | D15: N/A | E15: Protection and Power Quality assessment prior to connection | F15: =VLOOKUP(B15,'ACS Price List'!$16:$180,8,FALSE) -> 8004 | G15: dollars ($) | H15: 1376.7 | I15: =IFERROR(IF(D15="LR",VLOOKUP(B15,'ACS Price List'!$16:$180,11,FALSE),IF(D15="IS",VLOOKUP(B15,'ACS Price List'!$16:$180,11,FALSE),VLOOKUP(B15,'ACS Price List'!$16:$180,9,FALSE))),"POA") -> 1376.7 | K15: =IFERROR(IF(I15="POA","OK",IF(I15-H15=0,"OK","CHANGE")),"CHECK") -> OK | N15: 104 | O15: ACSMNCC | P15: Default Metering Services: Embedded generation - Non-capital | Q15: =VLOOKUP(N15,'ACS Price List'!$16:$180,8,FALSE) -> 8124 | R15: dollars per day per meter ($/day/meter) | T15: =VLOOKUP(N15,'ACS Price List'!$16:$180,9,FALSE) -> 0.02787
B16: 6 | C16: TBSSPU | D16: UR | E16: Temporary connection, not in permanent position - single phase metered - urban/short rural feeders | F16: =VLOOKUP(B16,'ACS Price List'!$16:$180,8,FALSE) -> 8020 | G16: dollars ($) | H16: 412.7 | I16: =IFERROR(IF(D16="LR",VLOOKUP(B16,'ACS Price List'!$16:$180,11,FALSE),IF(D16="IS",VLOOKUP(B16,'ACS Price List'!$16:$180,11,FALSE),VLOOKUP(B16,'ACS Price List'!$16:$180,9,FALSE))),"POA") -> 330.2 | K16: =IFERROR(IF(I16="POA","OK",IF(I16-H16=0,"OK","CHANGE")),"CHECK") -> CHANGE | N16: 105 | O16: ACSMCC | P16: Default Metering Services: Embedded generation - Capital | Q16: =VLOOKUP(N16,'ACS Price List'!$16:$180,8,FALSE) -> 8125 | R16: dollars per day per meter ($/day/meter) | T16: =VLOOKUP(N16,'ACS Price List'!$16:$180,9,FALSE) -> 0.00778
B17: 8 | C17: TBSMPU | D17: UR | E17: Temporary connection, not in permanent position - multi phase metered - urban/short rural feeders | F17: =VLOOKUP(B17,'ACS Price List'!$16:$180,8,FALSE) -> 8024 | G17: dollars ($) | H17: 412.7 | I17: =IFERROR(IF(D17="LR",VLOOKUP(B17,'ACS Price List'!$16:$180,11,FALSE),IF(D17="IS",VLOOKUP(B17,'ACS Price List'!$16:$180,11,FALSE),VLOOKUP(B17,'ACS Price List'!$16:$180,9,FALSE))),"POA") -> 330.2 | K17: =IFERROR(IF(I17="POA","OK",IF(I17-H17=0,"OK","CHANGE")),"CHECK") -> CHANGE | N17: 130 | O17: ACSEOOMA | P17: Public Lighting Services: EO&O - Major | Q17: =VLOOKUP(N17,'ACS Price List'!$16:$180,8,FALSE) -> 8130 | R17: dollars per day per light ($/day/light) | T17: =VLOOKUP(N17,'ACS Price List'!$16:$180,9,FALSE) -> 1.1558
B18: 10 | C18: SUPABOLU | D18: UR | E18: Supply abolishment during business hours - urban/short rural feeders | F18: =VLOOKUP(B18,'ACS Price List'!$16:$180,8,FALSE) -> 8040 | G18: dollars ($) | H18: 350.9 | I18: =IFERROR(IF(D18="LR",VLOOKUP(B18,'ACS Price List'!$16:$180,11,FALSE),IF(D18="IS",VLOOKUP(B18,'ACS Price List'!$16:$180,11,FALSE),VLOOKUP(B18,'ACS Price List'!$16:$180,9,FALSE))),"POA") -> 292.4 | K18: =IFERROR(IF(I18="POA","OK",IF(I18-H18=0,"OK","CHANGE")),"CHECK") -> CHANGE | N18: 131 | O18: ACSEOOMI | P18: Public Lighting Services: EO&O - Minor | Q18: =VLOOKUP(N18,'ACS Price List'!$16:$180,8,FALSE) -> 8131 | R18: dollars per day per light ($/day/light) | T18: =VLOOKUP(N18,'ACS Price List'!$16:$180,9,FALSE) -> 0.6886
B19: 12 | C19: DEENBHU | D19: UR | E19: De-energisation during business hours - urban/short rural feeders | F19: =VLOOKUP(B19,'ACS Price List'!$16:$180,8,FALSE) -> 8044 | G19: dollars ($) | H19: 0 | I19: =IFERROR(IF(D19="LR",VLOOKUP(B19,'ACS Price List'!$16:$180,11,FALSE),IF(D19="IS",VLOOKUP(B19,'ACS Price List'!$16:$180,11,FALSE),VLOOKUP(B19,'ACS Price List'!$16:$180,9,FALSE))),"POA") -> 0 | K19: =IFERROR(IF(I19="POA","OK",IF(I19-H19=0,"OK","CHANGE")),"CHECK") -> OK | N19: 132 | O19: ACSGEOMA | P19: Public Lighting Services: G&EO - Major | Q19: =VLOOKUP(N19,'ACS Price List'!$16:$180,8,FALSE) -> 8132 | R19: dollars per day per light ($/day/light) | T19: =VLOOKUP(N19,'ACS Price List'!$16:$180,9,FALSE) -> 0.4667
B20: 14 | C20: REENBHU | D20: UR | E20: Re-energisation during business hours - urban/short rural feeders | F20: =VLOOKUP(B20,'ACS Price List'!$16:$180,8,FALSE) -> 8048 | G20: dollars ($) | H20: 0 | I20: =IFERROR(IF(D20="LR",VLOOKUP(B20,'ACS Price List'!$16:$180,11,FALSE),IF(D20="IS",VLOOKUP(B20,'ACS Price List'!$16:$180,11,FALSE),VLOOKUP(B20,'ACS Price List'!$16:$180,9,FALSE))),"POA") -> 0 | K20: =IFERROR(IF(I20="POA","OK",IF(I20-H20=0,"OK","CHANGE")),"CHECK") -> OK | N20: 133 | O20: ACSGEOMI | P20: Public Lighting Services: G&EO - Minor | Q20: =VLOOKUP(N20,'ACS Price List'!$16:$180,8,FALSE) -> 8133 | R20: dollars per day per light ($/day/light) | T20: =VLOOKUP(N20,'ACS Price List'!$16:$180,9,FALSE) -> 0.3057
B21: 14-VE | C21: VEREENBHU | D21: UR | E21: Visual examination during business hours for remote re-energisation - urban/short rural feeders | F21: =VLOOKUP(B21,'ACS Price List'!$16:$180,8,FALSE) -> 2050 | G21: dollars ($) | I21: =IFERROR(IF(D21="LR",VLOOKUP(B21,'ACS Price List'!$16:$180,11,FALSE),IF(D21="IS",VLOOKUP(B21,'ACS Price List'!$16:$180,11,FALSE),VLOOKUP(B21,'ACS Price List'!$16:$180,9,FALSE))),"POA") -> 0 | K21: =IFERROR(IF(I21="POA","OK",IF(I21-H21=0,"OK","CHANGE")),"CHECK") -> OK
B22: 16 | C22: REDDBHU | D22: UR | E22: Re-energisation during business hours - after de-energisation for debt - urban/short rural feeders | F22: =VLOOKUP(B22,'ACS Price List'!$16:$180,8,FALSE) -> 8052 | G22: dollars ($) | H22: 45.5 | I22: =IFERROR(IF(D22="LR",VLOOKUP(B22,'ACS Price List'!$16:$180,11,FALSE),IF(D22="IS",VLOOKUP(B22,'ACS Price List'!$16:$180,11,FALSE),VLOOKUP(B22,'ACS Price List'!$16:$180,9,FALSE))),"POA") -> 45.5 | K22: =IFERROR(IF(I22="POA","OK",IF(I22-H22=0,"OK","CHANGE")),"CHECK") -> OK
B23: 16-VE | C23: VEREDDBHU | D23: UR | E23: Visual examination during business hours for remote re-energisation - after de-energisation for debt - urban/short rural feeders | F23: =VLOOKUP(B23,'ACS Price List'!$16:$180,8,FALSE) -> 2052 | G23: dollars ($) | I23: =IFERROR(IF(D23="LR",VLOOKUP(B23,'ACS Price List'!$16:$180,11,FALSE),IF(D23="IS",VLOOKUP(B23,'ACS Price List'!$16:$180,11,FALSE),VLOOKUP(B23,'ACS Price List'!$16:$180,9,FALSE))),"POA") -> 45.5 | K23: =IFERROR(IF(I23="POA","OK",IF(I23-H23=0,"OK","CHANGE")),"CHECK") -> CHANGE
B24: 18 | C24: ASPRED | D24: N/A | E24: Accreditation of alternative service providers - real estate developments | F24: =VLOOKUP(B24,'ACS Price List'!$16:$180,8,FALSE) -> 8069 | G24: dollars ($) | H24: 903.5 | I24: =IFERROR(IF(D24="LR",VLOOKUP(B24,'ACS Price List'!$16:$180,11,FALSE),IF(D24="IS",VLOOKUP(B24,'ACS Price List'!$16:$180,11,FALSE),VLOOKUP(B24,'ACS Price List'!$16:$180,9,FALSE))),"POA") -> 903.5 | K24: =IFERROR(IF(I24="POA","OK",IF(I24-H24=0,"OK","CHANGE")),"CHECK") -> OK
B25: 19 | C25: MSNGLU | D25: UR | E25: Install replacement meter (Type 5 and 6) – Single phase – urban/short rural feeder | F25: =VLOOKUP(B25,'ACS Price List'!$16:$180,8,FALSE) -> 8193 | G25: dollars ($) | H25: 344.4 | I25: =IFERROR(IF(D25="LR",VLOOKUP(B25,'ACS Price List'!$16:$180,11,FALSE),IF(D25="IS",VLOOKUP(B25,'ACS Price List'!$16:$180,11,FALSE),VLOOKUP(B25,'ACS Price List'!$16:$180,9,FALSE))),"POA") -> 344.4 | K25: =IFERROR(IF(I25="POA","OK",IF(I25-H25=0,"OK","CHANGE")),"CHECK") -> OK
B26: 21 | C26: MDUALU | D26: UR | E26: Install replacement meter (Type 5 and 6) – Dual element – urban/short rural feeder | F26: =VLOOKUP(B26,'ACS Price List'!$16:$180,8,FALSE) -> 8197 | G26: dollars ($) | H26: 421.8 | I26: =IFERROR(IF(D26="LR",VLOOKUP(B26,'ACS Price List'!$16:$180,11,FALSE),IF(D26="IS",VLOOKUP(B26,'ACS Price List'!$16:$180,11,FALSE),VLOOKUP(B26,'ACS Price List'!$16:$180,9,FALSE))),"POA") -> 421.8 | K26: =IFERROR(IF(I26="POA","OK",IF(I26-H26=0,"OK","CHANGE")),"CHECK") -> OK
B27: 23 | C27: MTHREU | D27: UR | E27: Install replacement meter (Type 5 and 6) – Polyphase – urban/short rural feeder | F27: =VLOOKUP(B27,'ACS Price List'!$16:$180,8,FALSE) -> 8201 | G27: dollars ($) | H27: 530.2 | I27: =IFERROR(IF(D27="LR",VLOOKUP(B27,'ACS Price List'!$16:$180,11,FALSE),IF(D27="IS",VLOOKUP(B27,'ACS Price List'!$16:$180,11,FALSE),VLOOKUP(B27,'ACS Price List'!$16:$180,9,FALSE))),"POA") -> 530.2 | K27: =IFERROR(IF(I27="POA","OK",IF(I27-H27=0,"OK","CHANGE")),"CHECK") -> OK
B28: 25 | C28: MCTU | D28: UR | E28: Install replacement meter (CT) – urban/short rural feeder | F28: =VLOOKUP(B28,'ACS Price List'!$16:$180,8,FALSE) -> 8205 | G28: dollars ($) | H28: 2519.1 | I28: =IFERROR(IF(D28="LR",VLOOKUP(B28,'ACS Price List'!$16:$180,11,FALSE),IF(D28="IS",VLOOKUP(B28,'ACS Price List'!$16:$180,11,FALSE),VLOOKUP(B28,'ACS Price List'!$16:$180,9,FALSE))),"POA") -> 2519.1 | K28: =IFERROR(IF(I28="POA","OK",IF(I28-H28=0,"OK","CHANGE")),"CHECK") -> OK
B29: 140 | C29: NMSPU | D29: UR | E29: Install new meter (Type 5 and 6) – Single phase – Primary | F29: =VLOOKUP(B29,'ACS Price List'!$16:$180,8,FALSE) -> 8172 | G29: dollars ($) | H29: 344.4 | I29: =IFERROR(IF(D29="LR",VLOOKUP(B29,'ACS Price List'!$16:$180,11,FALSE),IF(D29="IS",VLOOKUP(B29,'ACS Price List'!$16:$180,11,FALSE),VLOOKUP(B29,'ACS Price List'!$16:$180,9,FALSE))),"POA") -> 344.4 | K29: =IFERROR(IF(I29="POA","OK",IF(I29-H29=0,"OK","CHANGE")),"CHECK") -> OK
B30: 141 | C30: NMSPEGU | D30: UR | E30: Install new meter (Type 5 and 6) – Single phase – Primary plus embedded generation | F30: =VLOOKUP(B30,'ACS Price List'!$16:$180,8,FALSE) -> 8173 | G30: dollars ($) | H30: 344.4 | I30: =IFERROR(IF(D30="LR",VLOOKUP(B30,'ACS Price List'!$16:$180,11,FALSE),IF(D30="IS",VLOOKUP(B30,'ACS Price List'!$16:$180,11,FALSE),VLOOKUP(B30,'ACS Price List'!$16:$180,9,FALSE))),"POA") -> 344.4 | K30: =IFERROR(IF(I30="POA","OK",IF(I30-H30=0,"OK","CHANGE")),"CHECK") -> OK
B31: 142 | C31: NMDPCLU | D31: UR | E31: Install new meter (Type 5 and 6) – Dual element – Primary plus controlled load | F31: =VLOOKUP(B31,'ACS Price List'!$16:$180,8,FALSE) -> 8174 | G31: dollars ($) | H31: 421.8 | I31: =IFERROR(IF(D31="LR",VLOOKUP(B31,'ACS Price List'!$16:$180,11,FALSE),IF(D31="IS",VLOOKUP(B31,'ACS Price List'!$16:$180,11,FALSE),VLOOKUP(B31,'ACS Price List'!$16:$180,9,FALSE))),"POA") -> 421.8 | K31: =IFERROR(IF(I31="POA","OK",IF(I31-H31=0,"OK","CHANGE")),"CHECK") -> OK
B32: 143 | C32: NMDPCLEGU | D32: UR | E32: Install new meter (Type 5 and 6) – Dual element – Primary plus controlled load plus embedded generation | F32: =VLOOKUP(B32,'ACS Price List'!$16:$180,8,FALSE) -> 8175 | G32: dollars ($) | H32: 421.8 | I32: =IFERROR(IF(D32="LR",VLOOKUP(B32,'ACS Price List'!$16:$180,11,FALSE),IF(D32="IS",VLOOKUP(B32,'ACS Price List'!$16:$180,11,FALSE),VLOOKUP(B32,'ACS Price List'!$16:$180,9,FALSE))),"POA") -> 421.8 | K32: =IFERROR(IF(I32="POA","OK",IF(I32-H32=0,"OK","CHANGE")),"CHECK") -> OK
B33: 144 | C33: NMPPU | D33: UR | E33: Install new meter (Type 5 and 6) – Polyphase – Primary | F33: =VLOOKUP(B33,'ACS Price List'!$16:$180,8,FALSE) -> 8176 | G33: dollars ($) | H33: 530.2 | I33: =IFERROR(IF(D33="LR",VLOOKUP(B33,'ACS Price List'!$16:$180,11,FALSE),IF(D33="IS",VLOOKUP(B33,'ACS Price List'!$16:$180,11,FALSE),VLOOKUP(B33,'ACS Price List'!$16:$180,9,FALSE))),"POA") -> 530.2 | K33: =IFERROR(IF(I33="POA","OK",IF(I33-H33=0,"OK","CHANGE")),"CHECK") -> OK
B34: 145 | C34: NMPPEGU | D34: UR | E34: Install new meter (Type 5 and 6) – Polyphase – Primary plus embedded generation | F34: =VLOOKUP(B34,'ACS Price List'!$16:$180,8,FALSE) -> 8177 | G34: dollars ($) | H34: 530.2 | I34: =IFERROR(IF(D34="LR",VLOOKUP(B34,'ACS Price List'!$16:$180,11,FALSE),IF(D34="IS",VLOOKUP(B34,'ACS Price List'!$16:$180,11,FALSE),VLOOKUP(B34,'ACS Price List'!$16:$180,9,FALSE))),"POA") -> 530.2 | K34: =IFERROR(IF(I34="POA","OK",IF(I34-H34=0,"OK","CHANGE")),"CHECK") -> OK
B35: 146 | C35: NMCTPU | D35: UR | E35: Install new meter (CT) – Primary | F35: =VLOOKUP(B35,'ACS Price List'!$16:$180,8,FALSE) -> 8178 | G35: dollars ($) | H35: 2519.1 | I35: =IFERROR(IF(D35="LR",VLOOKUP(B35,'ACS Price List'!$16:$180,11,FALSE),IF(D35="IS",VLOOKUP(B35,'ACS Price List'!$16:$180,11,FALSE),VLOOKUP(B35,'ACS Price List'!$16:$180,9,FALSE))),"POA") -> 2519.1 | K35: =IFERROR(IF(I35="POA","OK",IF(I35-H35=0,"OK","CHANGE")),"CHECK") -> OK
... B50: 14 | C50: REENBHS | D50: SR | E50: Re-energisation during business hours - urban/short rural feeders | F50: =VLOOKUP(B50,'ACS Price List'!$16:$180,8,FALSE) -> 8048 | G50: dollars ($) | H50: 0 | I50: =IFERROR(IF(D50="LR",VLOOKUP(B50,'ACS Price List'!$16:$180,11,FALSE),IF(D50="IS",VLOOKUP(B50,'ACS Price List'!$16:$180,11,FALSE),VLOOKUP(B50,'ACS Price List'!$16:$180,9,FALSE))),"POA") -> 0 | K50: =IFERROR(IF(I50="POA","OK",IF(I50-H50=0,"OK","CHANGE")),"CHECK") -> OK
B51: 14-VE | C51: VEREENBHS | D51: SR | E51: Visual examination during business hours for remote re-energisation - urban/short rural feeders | F51: =VLOOKUP(B51,'ACS Price List'!$16:$180,8,FALSE) -> 2050 | G51: dollars ($) | I51: =IFERROR(IF(D51="LR",VLOOKUP(B51,'ACS Price List'!$16:$180,11,FALSE),IF(D51="IS",VLOOKUP(B51,'ACS Price List'!$16:$180,11,FALSE),VLOOKUP(B51,'ACS Price List'!$16:$180,9,FALSE))),"POA") -> 0 | K51: =IFERROR(IF(I51="POA","OK",IF(I51-H51=0,"OK","CHANGE")),"CHECK") -> OK
B52: 16 | C52: REDDBHS | D52: SR | E52: Re-energisation during business hours - after de-energisation for debt - urban/short rural feeders | F52: =VLOOKUP(B52,'ACS Price List'!$16:$180,8,FALSE) -> 8052 | G52: dollars ($) | H52: 45.5 | I52: =IFERROR(IF(D52="LR",VLOOKUP(B52,'ACS Price List'!$16:$180,11,FALSE),IF(D52="IS",VLOOKUP(B52,'ACS Price List'!$16:$180,11,FALSE),VLOOKUP(B52,'ACS Price List'!$16:$180,9,FALSE))),"POA") -> 45.5 | K52: =IFERROR(IF(I52="POA","OK",IF(I52-H52=0,"OK","CHANGE")),"CHECK") -> OK
B53: 16-VE | C53: VEREDDBHS | D53: SR | E53: Visual examination during business hours for remote re-energisation - after de-energisation for debt - urban/short rural feeders | F53: =VLOOKUP(B53,'ACS Price List'!$16:$180,8,FALSE) -> 2052 | G53: dollars ($) | I53: =IFERROR(IF(D53="LR",VLOOKUP(B53,'ACS Price List'!$16:$180,11,FALSE),IF(D53="IS",VLOOKUP(B53,'ACS Price List'!$16:$180,11,FALSE),VLOOKUP(B53,'ACS Price List'!$16:$180,9,FALSE))),"POA") -> 45.5 | K53: =IFERROR(IF(I53="POA","OK",IF(I53-H53=0,"OK","CHANGE")),"CHECK") -> CHANGE
B54: 19 | C54: MSNGLS | D54: SR | E54: Install replacement meter (Type 5 and 6) – Single phase – urban/short rural feeder | F54: =VLOOKUP(B54,'ACS Price List'!$16:$180,8,FALSE) -> 8193 | G54: dollars ($) | H54: 344.4 | I54: =IFERROR(IF(D54="LR",VLOOKUP(B54,'ACS Price List'!$16:$180,11,FALSE),IF(D54="IS",VLOOKUP(B54,'ACS Price List'!$16:$180,11,FALSE),VLOOKUP(B54,'ACS Price List'!$16:$180,9,FALSE))),"POA") -> 344.4 | K54: =IFERROR(IF(I54="POA","OK",IF(I54-H54=0,"OK","CHANGE")),"CHECK") -> OK
B55: 21 | C55: MDUALS | D55: SR | E55: Install replacement meter (Type 5 and 6) – Dual element – urban/short rural feeder | F55: =VLOOKUP(B55,'ACS Price List'!$16:$180,8,FALSE) -> 8197 | G55: dollars ($) | H55: 421.8 | I55: =IFERROR(IF(D55="LR",VLOOKUP(B55,'ACS Price List'!$16:$180,11,FALSE),IF(D55="IS",VLOOKUP(B55,'ACS Price List'!$16:$180,11,FALSE),VLOOKUP(B55,'ACS Price List'!$16:$180,9,FALSE))),"POA") -> 421.8 | K55: =IFERROR(IF(I55="POA","OK",IF(I55-H55=0,"OK","CHANGE")),"CHECK") -> OK
B56: 23 | C56: MTHRES | D56: SR | E56: Install replacement meter (Type 5 and 6) – Polyphase – urban/short rural feeder | F56: =VLOOKUP(B56,'ACS Price List'!$16:$180,8,FALSE) -> 8201 | G56: dollars ($) | H56: 530.2 | I56: =IFERROR(IF(D56="LR",VLOOKUP(B56,'ACS Price List'!$16:$180,11,FALSE),IF(D56="IS",VLOOKUP(B56,'ACS Price List'!$16:$180,11,FALSE),VLOOKUP(B56,'ACS Price List'!$16:$180,9,FALSE))),"POA") -> 530.2 | K56: =IFERROR(IF(I56="POA","OK",IF(I56-H56=0,"OK","CHANGE")),"CHECK") -> OK
B57: 25 | C57: MCTS | D57: SR | E57: Install replacement meter (CT) – urban/short rural feeder | F57: =VLOOKUP(B57,'ACS Price List'!$16:$180,8,FALSE) -> 8205 | G57: dollars ($) | H57: 2519.1 | I57: =IFERROR(IF(D57="LR",VLOOKUP(B57,'ACS Price List'!$16:$180,11,FALSE),IF(D57="IS",VLOOKUP(B57,'ACS Price List'!$16:$180,11,FALSE),VLOOKUP(B57,'ACS Price List'!$16:$180,9,FALSE))),"POA") -> 2519.1 | K57: =IFERROR(IF(I57="POA","OK",IF(I57-H57=0,"OK","CHANGE")),"CHECK") -> OK
B58: 140 | C58: NMSPS | D58: SR | E58: Install new meter (Type 5 and 6) – Single phase – Primary | F58: =VLOOKUP(B58,'ACS Price List'!$16:$180,8,FALSE) -> 8172 | G58: dollars ($) | H58: 344.4 | I58: =IFERROR(IF(D58="LR",VLOOKUP(B58,'ACS Price List'!$16:$180,11,FALSE),IF(D58="IS",VLOOKUP(B58,'ACS Price List'!$16:$180,11,FALSE),VLOOKUP(B58,'ACS Price List'!$16:$180,9,FALSE))),"POA") -> 344.4 | K58: =IFERROR(IF(I58="POA","OK",IF(I58-H58=0,"OK","CHANGE")),"CHECK") -> OK
B59: 141 | C59: NMSPEGS | D59: SR | E59: Install new meter (Type 5 and 6) – Single phase – Primary plus embedded generation | F59: =VLOOKUP(B59,'ACS Price List'!$16:$180,8,FALSE) -> 8173 | G59: dollars ($) | H59: 344.4 | I59: =IFERROR(IF(D59="LR",VLOOKUP(B59,'ACS Price List'!$16:$180,11,FALSE),IF(D59="IS",VLOOKUP(B59,'ACS Price List'!$16:$180,11,FALSE),VLOOKUP(B59,'ACS Price List'!$16:$180,9,FALSE))),"POA") -> 344.4 | K59: =IFERROR(IF(I59="POA","OK",IF(I59-H59=0,"OK","CHANGE")),"CHECK") -> OK
B60: 142 | C60: NMDPCLS | D60: SR | E60: Install new meter (Type 5 and 6) – Dual element – Primary plus controlled load | F60: =VLOOKUP(B60,'ACS Price List'!$16:$180,8,FALSE) -> 8174 | G60: dollars ($) | H60: 421.8 | I60: =IFERROR(IF(D60="LR",VLOOKUP(B60,'ACS Price List'!$16:$180,11,FALSE),IF(D60="IS",VLOOKUP(B60,'ACS Price List'!$16:$180,11,FALSE),VLOOKUP(B60,'ACS Price List'!$16:$180,9,FALSE))),"POA") -> 421.8 | K60: =IFERROR(IF(I60="POA","OK",IF(I60-H60=0,"OK","CHANGE")),"CHECK") -> OK
B61: 143 | C61: NMDPCLEGS | D61: SR | E61: Install new meter (Type 5 and 6) – Dual element – Primary plus controlled load plus embedded generation | F61: =VLOOKUP(B61,'ACS Price List'!$16:$180,8,FALSE) -> 8175 | G61: dollars ($) | H61: 421.8 | I61: =IFERROR(IF(D61="LR",VLOOKUP(B61,'ACS Price List'!$16:$180,11,FALSE),IF(D61="IS",VLOOKUP(B61,'ACS Price List'!$16:$180,11,FALSE),VLOOKUP(B61,'ACS Price List'!$16:$180,9,FALSE))),"POA") -> 421.8 | K61: =IFERROR(IF(I61="POA","OK",IF(I61-H61=0,"OK","CHANGE")),"CHECK") -> OK
B62: 144 | C62: NMPPS | D62: SR | E62: Install new meter (Type 5 and 6) – Polyphase – Primary | F62: =VLOOKUP(B62,'ACS Price List'!$16:$180,8,FALSE) -> 8176 | G62: dollars ($) | H62: 530.2 | I62: =IFERROR(IF(D62="LR",VLOOKUP(B62,'ACS Price List'!$16:$180,11,FALSE),IF(D62="IS",VLOOKUP(B62,'ACS Price List'!$16:$180,11,FALSE),VLOOKUP(B62,'ACS Price List'!$16:$180,9,FALSE))),"POA") -> 530.2 | K62: =IFERROR(IF(I62="POA","OK",IF(I62-H62=0,"OK","CHANGE")),"CHECK") -> OK
B63: 145 | C63: NMPPEGS | D63: SR | E63: Install new meter (Type 5 and 6) – Polyphase – Primary plus embedded generation | F63: =VLOOKUP(B63,'ACS Price List'!$16:$180,8,FALSE) -> 8177 | G63: dollars ($) | H63: 530.2 | I63: =IFERROR(IF(D63="LR",VLOOKUP(B63,'ACS Price List'!$16:$180,11,FALSE),IF(D63="IS",VLOOKUP(B63,'ACS Price List'!$16:$180,11,FALSE),VLOOKUP(B63,'ACS Price List'!$16:$180,9,FALSE))),"POA") -> 530.2 | K63: =IFERROR(IF(I63="POA","OK",IF(I63-H63=0,"OK","CHANGE")),"CHECK") -> OK
B64: 146 | C64: NMCTPS | D64: SR | E64: Install new meter (CT) – Primary | F64: =VLOOKUP(B64,'ACS Price List'!$16:$180,8,FALSE) -> 8178 | G64: dollars ($) | H64: 2519.1 | I64: =IFERROR(IF(D64="LR",VLOOKUP(B64,'ACS Price List'!$16:$180,11,FALSE),IF(D64="IS",VLOOKUP(B64,'ACS Price List'!$16:$180,11,FALSE),VLOOKUP(B64,'ACS Price List'!$16:$180,9,FALSE))),"POA") -> 2519.1 | K64: =IFERROR(IF(I64="POA","OK",IF(I64-H64=0,"OK","CHANGE")),"CHECK") -> OK
B65: 147 | C65: NMCTPEGS | D65: SR | E65: Install new meter (CT) – Primary plus embedded generation | F65: =VLOOKUP(B65,'ACS Price List'!$16:$180,8,FALSE) -> 8179 | G65: dollars ($) | H65: 2519.1 | I65: =IFERROR(IF(D65="LR",VLOOKUP(B65,'ACS Price List'!$16:$180,11,FALSE),IF(D65="IS",VLOOKUP(B65,'ACS Price List'!$16:$180,11,FALSE),VLOOKUP(B65,'ACS Price List'!$16:$180,9,FALSE))),"POA") -> 2519.1 | K65: =IFERROR(IF(I65="POA","OK",IF(I65-H65=0,"OK","CHANGE")),"CHECK") -> OK
... B79: 15 | C79: REENBHL | D79: LR | E79: Re-energisation during business hours - long rural/isolated feeders | F79: =VLOOKUP(B79,'ACS Price List'!$16:$180,8,FALSE) -> 8050 | G79: dollars ($) | H79: 0 | I79: =IFERROR(IF(D79="LR",VLOOKUP(B79,'ACS Price List'!$16:$180,11,FALSE),IF(D79="IS",VLOOKUP(B79,'ACS Price List'!$16:$180,11,FALSE),VLOOKUP(B79,'ACS Price List'!$16:$180,9,FALSE))),"POA") -> 0 | K79: =IFERROR(IF(I79="POA","OK",IF(I79-H79=0,"OK","CHANGE")),"CHECK") -> OK
B80: 15-VE | C80: VEREENBHL | D80: LR | E80: Visual examination during business hours for remote re-energisation - long rural/isolated feeders | F80: =VLOOKUP(B80,'ACS Price List'!$16:$180,8,FALSE) -> 2051 | G80: dollars ($) | I80: =IFERROR(IF(D80="LR",VLOOKUP(B80,'ACS Price List'!$16:$180,11,FALSE),IF(D80="IS",VLOOKUP(B80,'ACS Price List'!$16:$180,11,FALSE),VLOOKUP(B80,'ACS Price List'!$16:$180,9,FALSE))),"POA") -> 0 | K80: =IFERROR(IF(I80="POA","OK",IF(I80-H80=0,"OK","CHANGE")),"CHECK") -> OK
B81: 17 | C81: REDDBHL | D81: LR | E81: Re-energisation during business hours - after de-energisation for debt - long rural/isolated feeders | F81: =VLOOKUP(B81,'ACS Price List'!$16:$180,8,FALSE) -> 8054 | G81: dollars ($) | H81: 45.5 | I81: =IFERROR(IF(D81="LR",VLOOKUP(B81,'ACS Price List'!$16:$180,11,FALSE),IF(D81="IS",VLOOKUP(B81,'ACS Price List'!$16:$180,11,FALSE),VLOOKUP(B81,'ACS Price List'!$16:$180,9,FALSE))),"POA") -> 45.5 | K81: =IFERROR(IF(I81="POA","OK",IF(I81-H81=0,"OK","CHANGE")),"CHECK") -> OK
B82: 17-VE | C82: VEREDDBHL | D82: LR | E82: Visual examination during business hours for remote re-energisation - after de-energisation for debt - long rural/isolated feeders | F82: =VLOOKUP(B82,'ACS Price List'!$16:$180,8,FALSE) -> 2053 | G82: dollars ($) | I82: =IFERROR(IF(D82="LR",VLOOKUP(B82,'ACS Price List'!$16:$180,11,FALSE),IF(D82="IS",VLOOKUP(B82,'ACS Price List'!$16:$180,11,FALSE),VLOOKUP(B82,'ACS Price List'!$16:$180,9,FALSE))),"POA") -> 45.5 | K82: =IFERROR(IF(I82="POA","OK",IF(I82-H82=0,"OK","CHANGE")),"CHECK") -> CHANGE
B83: 20 | C83: MSNGLL | D83: LR | E83: Install replacement meter (Type 5 and 6) – Single phase – long rural/isolated feeder | F83: =VLOOKUP(B83,'ACS Price List'!$16:$180,8,FALSE) -> 8195 | G83: dollars ($) | H83: 344.4 | I83: =IFERROR(IF(D83="LR",VLOOKUP(B83,'ACS Price List'!$16:$180,11,FALSE),IF(D83="IS",VLOOKUP(B83,'ACS Price List'!$16:$180,11,FALSE),VLOOKUP(B83,'ACS Price List'!$16:$180,9,FALSE))),"POA") -> 344.4 | K83: =IFERROR(IF(I83="POA","OK",IF(I83-H83=0,"OK","CHANGE")),"CHECK") -> OK
B84: 22 | C84: MDUALL | D84: LR | E84: Install replacement meter (Type 5 and 6) – Dual element – long rural/isolated feeder | F84: =VLOOKUP(B84,'ACS Price List'!$16:$180,8,FALSE) -> 8199 | G84: dollars ($) | H84: 421.8 | I84: =IFERROR(IF(D84="LR",VLOOKUP(B84,'ACS Price List'!$16:$180,11,FALSE),IF(D84="IS",VLOOKUP(B84,'ACS Price List'!$16:$180,11,FALSE),VLOOKUP(B84,'ACS Price List'!$16:$180,9,FALSE))),"POA") -> 421.8 | K84: =IFERROR(IF(I84="POA","OK",IF(I84-H84=0,"OK","CHANGE")),"CHECK") -> OK
B85: 24 | C85: MTHREL | D85: LR | E85: Install replacement meter (Type 5 and 6) – Polyphase – long rural/isolated feeder | F85: =VLOOKUP(B85,'ACS Price List'!$16:$180,8,FALSE) -> 8203 | G85: dollars ($) | H85: 530.2 | I85: =IFERROR(IF(D85="LR",VLOOKUP(B85,'ACS Price List'!$16:$180,11,FALSE),IF(D85="IS",VLOOKUP(B85,'ACS Price List'!$16:$180,11,FALSE),VLOOKUP(B85,'ACS Price List'!$16:$180,9,FALSE))),"POA") -> 530.2 | K85: =IFERROR(IF(I85="POA","OK",IF(I85-H85=0,"OK","CHANGE")),"CHECK") -> OK
B86: 26 | C86: MCTL | D86: LR | E86: Install replacement meter (CT) – long rural/isolated feeder | F86: =VLOOKUP(B86,'ACS Price List'!$16:$180,8,FALSE) -> 8207 | G86: dollars ($) | H86: 2519.1 | I86: =IFERROR(IF(D86="LR",VLOOKUP(B86,'ACS Price List'!$16:$180,11,FALSE),IF(D86="IS",VLOOKUP(B86,'ACS Price List'!$16:$180,11,FALSE),VLOOKUP(B86,'ACS Price List'!$16:$180,9,FALSE))),"POA") -> 2519.1 | K86: =IFERROR(IF(I86="POA","OK",IF(I86-H86=0,"OK","CHANGE")),"CHECK") -> OK
B87: 140 | C87: NMSPL | D87: LR | E87: Install new meter (Type 5 and 6) – Single phase – Primary | F87: =VLOOKUP(B87,'ACS Price List'!$16:$180,8,FALSE) -> 8172 | G87: dollars ($) | H87: 344.4 | I87: =IFERROR(IF(D87="LR",VLOOKUP(B87,'ACS Price List'!$16:$180,11,FALSE),IF(D87="IS",VLOOKUP(B87,'ACS Price List'!$16:$180,11,FALSE),VLOOKUP(B87,'ACS Price List'!$16:$180,9,FALSE))),"POA") -> 344.4 | K87: =IFERROR(IF(I87="POA","OK",IF(I87-H87=0,"OK","CHANGE")),"CHECK") -> OK
B88: 141 | C88: NMSPEGL | D88: LR | E88: Install new meter (Type 5 and 6) – Single phase – Primary plus embedded generation | F88: =VLOOKUP(B88,'ACS Price List'!$16:$180,8,FALSE) -> 8173 | G88: dollars ($) | H88: 344.4 | I88: =IFERROR(IF(D88="LR",VLOOKUP(B88,'ACS Price List'!$16:$180,11,FALSE),IF(D88="IS",VLOOKUP(B88,'ACS Price List'!$16:$180,11,FALSE),VLOOKUP(B88,'ACS Price List'!$16:$180,9,FALSE))),"POA") -> 344.4 | K88: =IFERROR(IF(I88="POA","OK",IF(I88-H88=0,"OK","CHANGE")),"CHECK") -> OK
B89: 142 | C89: NMDPCLL | D89: LR | E89: Install new meter (Type 5 and 6) – Dual element – Primary plus controlled load | F89: =VLOOKUP(B89,'ACS Price List'!$16:$180,8,FALSE) -> 8174 | G89: dollars ($) | H89: 421.8 | I89: =IFERROR(IF(D89="LR",VLOOKUP(B89,'ACS Price List'!$16:$180,11,FALSE),IF(D89="IS",VLOOKUP(B89,'ACS Price List'!$16:$180,11,FALSE),VLOOKUP(B89,'ACS Price List'!$16:$180,9,FALSE))),"POA") -> 421.8 | K89: =IFERROR(IF(I89="POA","OK",IF(I89-H89=0,"OK","CHANGE")),"CHECK") -> OK
B90: 143 | C90: NMDPCLEGL | D90: LR | E90: Install new meter (Type 5 and 6) – Dual element – Primary plus controlled load plus embedded generation | F90: =VLOOKUP(B90,'ACS Price List'!$16:$180,8,FALSE) -> 8175 | G90: dollars ($) | H90: 421.8 | I90: =IFERROR(IF(D90="LR",VLOOKUP(B90,'ACS Price List'!$16:$180,11,FALSE),IF(D90="IS",VLOOKUP(B90,'ACS Price List'!$16:$180,11,FALSE),VLOOKUP(B90,'ACS Price List'!$16:$180,9,FALSE))),"POA") -> 421.8 | K90: =IFERROR(IF(I90="POA","OK",IF(I90-H90=0,"OK","CHANGE")),"CHECK") -> OK
B91: 144 | C91: NMPPL | D91: LR | E91: Install new meter (Type 5 and 6) – Polyphase – Primary | F91: =VLOOKUP(B91,'ACS Price List'!$16:$180,8,FALSE) -> 8176 | G91: dollars ($) | H91: 530.2 | I91: =IFERROR(IF(D91="LR",VLOOKUP(B91,'ACS Price List'!$16:$180,11,FALSE),IF(D91="IS",VLOOKUP(B91,'ACS Price List'!$16:$180,11,FALSE),VLOOKUP(B91,'ACS Price List'!$16:$180,9,FALSE))),"POA") -> 530.2 | K91: =IFERROR(IF(I91="POA","OK",IF(I91-H91=0,"OK","CHANGE")),"CHECK") -> OK
B92: 145 | C92: NMPPEGL | D92: LR | E92: Install new meter (Type 5 and 6) – Polyphase – Primary plus embedded generation | F92: =VLOOKUP(B92,'ACS Price List'!$16:$180,8,FALSE) -> 8177 | G92: dollars ($) | H92: 530.2 | I92: =IFERROR(IF(D92="LR",VLOOKUP(B92,'ACS Price List'!$16:$180,11,FALSE),IF(D92="IS",VLOOKUP(B92,'ACS Price List'!$16:$180,11,FALSE),VLOOKUP(B92,'ACS Price List'!$16:$180,9,FALSE))),"POA") -> 530.2 | K92: =IFERROR(IF(I92="POA","OK",IF(I92-H92=0,"OK","CHANGE")),"CHECK") -> OK
B93: 146 | C93: NMCTPL | D93: LR | E93: Install new meter (CT) – Primary | F93: =VLOOKUP(B93,'ACS Price List'!$16:$180,8,FALSE) -> 8178 | G93: dollars ($) | H93: 2519.1 | I93: =IFERROR(IF(D93="LR",VLOOKUP(B93,'ACS Price List'!$16:$180,11,FALSE),IF(D93="IS",VLOOKUP(B93,'ACS Price List'!$16:$180,11,FALSE),VLOOKUP(B93,'ACS Price List'!$16:$180,9,FALSE))),"POA") -> 2519.1 | K93: =IFERROR(IF(I93="POA","OK",IF(I93-H93=0,"OK","CHANGE")),"CHECK") -> OK
B94: 147 | C94: NMCTPEGL | D94: LR | E94: Install new meter (CT) – Primary plus embedded generation | F94: =VLOOKUP(B94,'ACS Price List'!$16:$180,8,FALSE) -> 8179 | G94: dollars ($) | H94: 2519.1 | I94: =IFERROR(IF(D94="LR",VLOOKUP(B94,'ACS Price List'!$16:$180,11,FALSE),IF(D94="IS",VLOOKUP(B94,'ACS Price List'!$16:$180,11,FALSE),VLOOKUP(B94,'ACS Price List'!$16:$180,9,FALSE))),"POA") -> 2519.1 | K94: =IFERROR(IF(I94="POA","OK",IF(I94-H94=0,"OK","CHANGE")),"CHECK") -> OK
... B108: 15 | C108: REENBHI | D108: IS | E108: Re-energisation during business hours - long rural/isolated feeders | F108: =VLOOKUP(B108,'ACS Price List'!$16:$180,8,FALSE) -> 8050 | G108: dollars ($) | H108: 0 | I108: =IFERROR(IF(D108="LR",VLOOKUP(B108,'ACS Price List'!$16:$180,11,FALSE),IF(D108="IS",VLOOKUP(B108,'ACS Price List'!$16:$180,11,FALSE),VLOOKUP(B108,'ACS Price List'!$16:$180,9,FALSE))),"POA") -> 0 | K108: =IFERROR(IF(I108="POA","OK",IF(I108-H108=0,"OK","CHANGE")),"CHECK") -> OK
B109: 15-VE | C109: VEREENBHI | D109: IS | E109: Visual examination during business hours for remote re-energisation - long rural/isolated feeders | F109: =VLOOKUP(B109,'ACS Price List'!$16:$180,8,FALSE) -> 2051 | G109: dollars ($) | I109: =IFERROR(IF(D109="LR",VLOOKUP(B109,'ACS Price List'!$16:$180,11,FALSE),IF(D109="IS",VLOOKUP(B109,'ACS Price List'!$16:$180,11,FALSE),VLOOKUP(B109,'ACS Price List'!$16:$180,9,FALSE))),"POA") -> 0 | K109: =IFERROR(IF(I109="POA","OK",IF(I109-H109=0,"OK","CHANGE")),"CHECK") -> OK
B110: 17 | C110: REDDBHI | D110: IS | E110: Re-energisation during business hours - after de-energisation for debt - long rural/isolated feeders | F110: =VLOOKUP(B110,'ACS Price List'!$16:$180,8,FALSE) -> 8054 | G110: dollars ($) | H110: 45.5 | I110: =IFERROR(IF(D110="LR",VLOOKUP(B110,'ACS Price List'!$16:$180,11,FALSE),IF(D110="IS",VLOOKUP(B110,'ACS Price List'!$16:$180,11,FALSE),VLOOKUP(B110,'ACS Price List'!$16:$180,9,FALSE))),"POA") -> 45.5 | K110: =IFERROR(IF(I110="POA","OK",IF(I110-H110=0,"OK","CHANGE")),"CHECK") -> OK
B111: 17-VE | C111: VEREDDBHI | D111: IS | E111: Visual examination during business hours for remote re-energisation - after de-energisation for debt - long rural/isolated feeders | F111: =VLOOKUP(B111,'ACS Price List'!$16:$180,8,FALSE) -> 2053 | G111: dollars ($) | I111: =IFERROR(IF(D111="LR",VLOOKUP(B111,'ACS Price List'!$16:$180,11,FALSE),IF(D111="IS",VLOOKUP(B111,'ACS Price List'!$16:$180,11,FALSE),VLOOKUP(B111,'ACS Price List'!$16:$180,9,FALSE))),"POA") -> 45.5 | K111: =IFERROR(IF(I111="POA","OK",IF(I111-H111=0,"OK","CHANGE")),"CHECK") -> CHANGE
B112: 20 | C112: MSNGLI | D112: IS | E112: Install replacement meter (Type 5 and 6) – Single phase – long rural/isolated feeder | F112: =VLOOKUP(B112,'ACS Price List'!$16:$180,8,FALSE) -> 8195 | G112: dollars ($) | H112: 344.4 | I112: =IFERROR(IF(D112="LR",VLOOKUP(B112,'ACS Price List'!$16:$180,11,FALSE),IF(D112="IS",VLOOKUP(B112,'ACS Price List'!$16:$180,11,FALSE),VLOOKUP(B112,'ACS Price List'!$16:$180,9,FALSE))),"POA") -> 344.4 | K112: =IFERROR(IF(I112="POA","OK",IF(I112-H112=0,"OK","CHANGE")),"CHECK") -> OK
B113: 22 | C113: MDUALI | D113: IS | E113: Install replacement meter (Type 5 and 6) – Dual element – long rural/isolated feeder | F113: =VLOOKUP(B113,'ACS Price List'!$16:$180,8,FALSE) -> 8199 | G113: dollars ($) | H113: 421.8 | I113: =IFERROR(IF(D113="LR",VLOOKUP(B113,'ACS Price List'!$16:$180,11,FALSE),IF(D113="IS",VLOOKUP(B113,'ACS Price List'!$16:$180,11,FALSE),VLOOKUP(B113,'ACS Price List'!$16:$180,9,FALSE))),"POA") -> 421.8 | K113: =IFERROR(IF(I113="POA","OK",IF(I113-H113=0,"OK","CHANGE")),"CHECK") -> OK
B114: 24 | C114: MTHREI | D114: IS | E114: Install replacement meter (Type 5 and 6) – Polyphase – long rural/isolated feeder | F114: =VLOOKUP(B114,'ACS Price List'!$16:$180,8,FALSE) -> 8203 | G114: dollars ($) | H114: 530.2 | I114: =IFERROR(IF(D114="LR",VLOOKUP(B114,'ACS Price List'!$16:$180,11,FALSE),IF(D114="IS",VLOOKUP(B114,'ACS Price List'!$16:$180,11,FALSE),VLOOKUP(B114,'ACS Price List'!$16:$180,9,FALSE))),"POA") -> 530.2 | K114: =IFERROR(IF(I114="POA","OK",IF(I114-H114=0,"OK","CHANGE")),"CHECK") -> OK
B115: 26 | C115: MCTI | D115: IS | E115: Install replacement meter (CT) – long rural/isolated feeder | F115: =VLOOKUP(B115,'ACS Price List'!$16:$180,8,FALSE) -> 8207 | G115: dollars ($) | H115: 2519.1 | I115: =IFERROR(IF(D115="LR",VLOOKUP(B115,'ACS Price List'!$16:$180,11,FALSE),IF(D115="IS",VLOOKUP(B115,'ACS Price List'!$16:$180,11,FALSE),VLOOKUP(B115,'ACS Price List'!$16:$180,9,FALSE))),"POA") -> 2519.1 | K115: =IFERROR(IF(I115="POA","OK",IF(I115-H115=0,"OK","CHANGE")),"CHECK") -> OK
B116: 140 | C116: NMSPI | D116: IS | E116: Install new meter (Type 5 and 6) – Single phase – Primary | F116: =VLOOKUP(B116,'ACS Price List'!$16:$180,8,FALSE) -> 8172 | G116: dollars ($) | H116: 344.4 | I116: =IFERROR(IF(D116="LR",VLOOKUP(B116,'ACS Price List'!$16:$180,11,FALSE),IF(D116="IS",VLOOKUP(B116,'ACS Price List'!$16:$180,11,FALSE),VLOOKUP(B116,'ACS Price List'!$16:$180,9,FALSE))),"POA") -> 344.4 | K116: =IFERROR(IF(I116="POA","OK",IF(I116-H116=0,"OK","CHANGE")),"CHECK") -> OK
B117: 141 | C117: NMSPEGI | D117: IS | E117: Install new meter (Type 5 and 6) – Single phase – Primary plus embedded generation | F117: =VLOOKUP(B117,'ACS Price List'!$16:$180,8,FALSE) -> 8173 | G117: dollars ($) | H117: 344.4 | I117: =IFERROR(IF(D117="LR",VLOOKUP(B117,'ACS Price List'!$16:$180,11,FALSE),IF(D117="IS",VLOOKUP(B117,'ACS Price List'!$16:$180,11,FALSE),VLOOKUP(B117,'ACS Price List'!$16:$180,9,FALSE))),"POA") -> 344.4 | K117: =IFERROR(IF(I117="POA","OK",IF(I117-H117=0,"OK","CHANGE")),"CHECK") -> OK
B118: 142 | C118: NMDPCLI | D118: IS | E118: Install new meter (Type 5 and 6) – Dual element – Primary plus controlled load | F118: =VLOOKUP(B118,'ACS Price List'!$16:$180,8,FALSE) -> 8174 | G118: dollars ($) | H118: 421.8 | I118: =IFERROR(IF(D118="LR",VLOOKUP(B118,'ACS Price List'!$16:$180,11,FALSE),IF(D118="IS",VLOOKUP(B118,'ACS Price List'!$16:$180,11,FALSE),VLOOKUP(B118,'ACS Price List'!$16:$180,9,FALSE))),"POA") -> 421.8 | K118: =IFERROR(IF(I118="POA","OK",IF(I118-H118=0,"OK","CHANGE")),"CHECK") -> OK
B119: 143 | C119: NMDPCLEGI | D119: IS | E119: Install new meter (Type 5 and 6) – Dual element – Primary plus controlled load plus embedded generation | F119: =VLOOKUP(B119,'ACS Price List'!$16:$180,8,FALSE) -> 8175 | G119: dollars ($) | H119: 421.8 | I119: =IFERROR(IF(D119="LR",VLOOKUP(B119,'ACS Price List'!$16:$180,11,FALSE),IF(D119="IS",VLOOKUP(B119,'ACS Price List'!$16:$180,11,FALSE),VLOOKUP(B119,'ACS Price List'!$16:$180,9,FALSE))),"POA") -> 421.8 | K119: =IFERROR(IF(I119="POA","OK",IF(I119-H119=0,"OK","CHANGE")),"CHECK") -> OK
B120: 144 | C120: NMPPI | D120: IS | E120: Install new meter (Type 5 and 6) – Polyphase – Primary | F120: =VLOOKUP(B120,'ACS Price List'!$16:$180,8,FALSE) -> 8176 | G120: dollars ($) | H120: 530.2 | I120: =IFERROR(IF(D120="LR",VLOOKUP(B120,'ACS Price List'!$16:$180,11,FALSE),IF(D120="IS",VLOOKUP(B120,'ACS Price List'!$16:$180,11,FALSE),VLOOKUP(B120,'ACS Price List'!$16:$180,9,FALSE))),"POA") -> 530.2 | K120: =IFERROR(IF(I120="POA","OK",IF(I120-H120=0,"OK","CHANGE")),"CHECK") -> OK
B121: 145 | C121: NMPPEGI | D121: IS | E121: Install new meter (Type 5 and 6) – Polyphase – Primary plus embedded generation | F121: =VLOOKUP(B121,'ACS Price List'!$16:$180,8,FALSE) -> 8177 | G121: dollars ($) | H121: 530.2 | I121: =IFERROR(IF(D121="LR",VLOOKUP(B121,'ACS Price List'!$16:$180,11,FALSE),IF(D121="IS",VLOOKUP(B121,'ACS Price List'!$16:$180,11,FALSE),VLOOKUP(B121,'ACS Price List'!$16:$180,9,FALSE))),"POA") -> 530.2 | K121: =IFERROR(IF(I121="POA","OK",IF(I121-H121=0,"OK","CHANGE")),"CHECK") -> OK
B122: 146 | C122: NMCTPI | D122: IS | E122: Install new meter (CT) – Primary | F122: =VLOOKUP(B122,'ACS Price List'!$16:$180,8,FALSE) -> 8178 | G122: dollars ($) | H122: 2519.1 | I122: =IFERROR(IF(D122="LR",VLOOKUP(B122,'ACS Price List'!$16:$180,11,FALSE),IF(D122="IS",VLOOKUP(B122,'ACS Price List'!$16:$180,11,FALSE),VLOOKUP(B122,'ACS Price List'!$16:$180,9,FALSE))),"POA") -> 2519.1 | K122: =IFERROR(IF(I122="POA","OK",IF(I122-H122=0,"OK","CHANGE")),"CHECK") -> OK
B123: 147 | C123: NMCTPEGI | D123: IS | E123: Install new meter (CT) – Primary plus embedded generation | F123: =VLOOKUP(B123,'ACS Price List'!$16:$180,8,FALSE) -> 8179 | G123: dollars ($) | H123: 2519.1 | I123: =IFERROR(IF(D123="LR",VLOOKUP(B123,'ACS Price List'!$16:$180,11,FALSE),IF(D123="IS",VLOOKUP(B123,'ACS Price List'!$16:$180,11,FALSE),VLOOKUP(B123,'ACS Price List'!$16:$180,9,FALSE))),"POA") -> 2519.1 | K123: =IFERROR(IF(I123="POA","OK",IF(I123-H123=0,"OK","CHANGE")),"CHECK") -> OK
... B132: 156 | C132: NCTAEGI | D132: IS | E132: Install new meter (CT) to accommodate embedded generation installation | F132: =VLOOKUP(B132,'ACS Price List'!$16:$180,8,FALSE) -> 8188 | G132: dollars ($) | H132: 2519.1 | I132: =IFERROR(IF(D132="LR",VLOOKUP(B132,'ACS Price List'!$16:$180,11,FALSE),IF(D132="IS",VLOOKUP(B132,'ACS Price List'!$16:$180,11,FALSE),VLOOKUP(B132,'ACS Price List'!$16:$180,9,FALSE))),"POA") -> 2519.1 | K132: =IFERROR(IF(I132="POA","OK",IF(I132-H132=0,"OK","CHANGE")),"CHECK") -> OK
B133: 161-M | C133: MTBSU | D133: UR | E133: MC Fee: Temporary connection, not in permanent position - single phase or multi phase metered - urban/short rural feeders | F133: =VLOOKUP(B133,'ACS Price List'!$16:$180,8,FALSE) -> 8033 | G133: dollars ($) | I133: =IFERROR(IF(D133="LR",VLOOKUP(B133,'ACS Price List'!$16:$180,11,FALSE),IF(D133="IS",VLOOKUP(B133,'ACS Price List'!$16:$180,11,FALSE),VLOOKUP(B133,'ACS Price List'!$16:$180,9,FALSE))),"POA") -> 82.5 | K133: =IFERROR(IF(I133="POA","OK",IF(I133-H133=0,"OK","CHANGE")),"CHECK") -> CHANGE
B134: 161-M | C134: MTBSS | D134: SR | E134: MC Fee: Temporary connection, not in permanent position - single phase or multi phase metered - urban/short rural feeders | F134: =VLOOKUP(B134,'ACS Price List'!$16:$180,8,FALSE) -> 8033 | G134: dollars ($) | I134: =IFERROR(IF(D134="LR",VLOOKUP(B134,'ACS Price List'!$16:$180,11,FALSE),IF(D134="IS",VLOOKUP(B134,'ACS Price List'!$16:$180,11,FALSE),VLOOKUP(B134,'ACS Price List'!$16:$180,9,FALSE))),"POA") -> 82.5 | K134: =IFERROR(IF(I134="POA","OK",IF(I134-H134=0,"OK","CHANGE")),"CHECK") -> CHANGE
B135: 161-M | C135: MTBSL | D135: LR | E135: MC Fee: Temporary connection, not in permanent position - single phase or multi phase metered - long rural/isolated feeders | F135: =VLOOKUP(B135,'ACS Price List'!$16:$180,8,FALSE) -> 8033 | G135: dollars ($) | I135: =IFERROR(IF(D135="LR",VLOOKUP(B135,'ACS Price List'!$16:$180,11,FALSE),IF(D135="IS",VLOOKUP(B135,'ACS Price List'!$16:$180,11,FALSE),VLOOKUP(B135,'ACS Price List'!$16:$180,9,FALSE))),"POA") -> 82.5 | K135: =IFERROR(IF(I135="POA","OK",IF(I135-H135=0,"OK","CHANGE")),"CHECK") -> CHANGE
B136: 161-M | C136: MTBSI | D136: IS | E136: MC Fee: Temporary connection, not in permanent position - single phase or multi phase metered - long rural/isolated feeders | F136: =VLOOKUP(B136,'ACS Price List'!$16:$180,8,FALSE) -> 8033 | G136: dollars ($) | I136: =IFERROR(IF(D136="LR",VLOOKUP(B136,'ACS Price List'!$16:$180,11,FALSE),IF(D136="IS",VLOOKUP(B136,'ACS Price List'!$16:$180,11,FALSE),VLOOKUP(B136,'ACS Price List'!$16:$180,9,FALSE))),"POA") -> 82.5 | K136: =IFERROR(IF(I136="POA","OK",IF(I136-H136=0,"OK","CHANGE")),"CHECK") -> CHANGE
B137: 162-M | C137: MSUPABOLU | D137: UR | E137: MC Fee: Supply abolishment during business hours - urban/short rural feeders | F137: =VLOOKUP(B137,'ACS Price List'!$16:$180,8,FALSE) -> 8039 | G137: dollars ($) | I137: =IFERROR(IF(D137="LR",VLOOKUP(B137,'ACS Price List'!$16:$180,11,FALSE),IF(D137="IS",VLOOKUP(B137,'ACS Price List'!$16:$180,11,FALSE),VLOOKUP(B137,'ACS Price List'!$16:$180,9,FALSE))),"POA") -> 58.4 | K137: =IFERROR(IF(I137="POA","OK",IF(I137-H137=0,"OK","CHANGE")),"CHECK") -> CHANGE
B138: 162-M | C138: MSUPABOLS | D138: SR | E138: MC Fee: Supply abolishment during business hours - urban/short rural feeders | F138: =VLOOKUP(B138,'ACS Price List'!$16:$180,8,FALSE) -> 8039 | G138: dollars ($) | I138: =IFERROR(IF(D138="LR",VLOOKUP(B138,'ACS Price List'!$16:$180,11,FALSE),IF(D138="IS",VLOOKUP(B138,'ACS Price List'!$16:$180,11,FALSE),VLOOKUP(B138,'ACS Price List'!$16:$180,9,FALSE))),"POA") -> 58.4 | K138: =IFERROR(IF(I138="POA","OK",IF(I138-H138=0,"OK","CHANGE")),"CHECK") -> CHANGE
B139: 162-M | C139: MSUPABOLI | D139: IS | E139: MC Fee: Supply abolishment during business hours - long rural/isolated feeders | F139: =VLOOKUP(B139,'ACS Price List'!$16:$180,8,FALSE) -> 8039 | G139: dollars ($) | I139: =IFERROR(IF(D139="LR",VLOOKUP(B139,'ACS Price List'!$16:$180,11,FALSE),IF(D139="IS",VLOOKUP(B139,'ACS Price List'!$16:$180,11,FALSE),VLOOKUP(B139,'ACS Price List'!$16:$180,9,FALSE))),"POA") -> 58.4 | K139: =IFERROR(IF(I139="POA","OK",IF(I139-H139=0,"OK","CHANGE")),"CHECK") -> CHANGE
B140: 162-M | C140: MSUPABOLL | D140: LR | E140: MC Fee: Supply abolishment during business hours - long rural/isolated feeders | F140: =VLOOKUP(B140,'ACS Price List'!$16:$180,8,FALSE) -> 8039 | G140: dollars ($) | I140: =IFERROR(IF(D140="LR",VLOOKUP(B140,'ACS Price List'!$16:$180,11,FALSE),IF(D140="IS",VLOOKUP(B140,'ACS Price List'!$16:$180,11,FALSE),VLOOKUP(B140,'ACS Price List'!$16:$180,9,FALSE))),"POA") -> 58.4 | K140: =IFERROR(IF(I140="POA","OK",IF(I140-H140=0,"OK","CHANGE")),"CHECK") -> CHANGE
B141: 6-CF | C141: CFTBSSPU | D141: UR | E141: Call out: Temporary connection, not in permanent position - single phase metered - urban/short rural feeders | F141: =VLOOKUP(B141,'ACS Price List'!$16:$180,8,FALSE) -> 8021 | G141: dollars ($) | H141: 116.9 | I141: =IFERROR(IF(D141="LR",VLOOKUP(B141,'ACS Price List'!$16:$180,11,FALSE),IF(D141="IS",VLOOKUP(B141,'ACS Price List'!$16:$180,11,FALSE),VLOOKUP(B141,'ACS Price List'!$16:$180,9,FALSE))),"POA") -> 116.9 | K141: =IFERROR(IF(I141="POA","OK",IF(I141-H141=0,"OK","CHANGE")),"CHECK") -> OK
B142: 8-CF | C142: CFTBSMPU | D142: UR | E142: Call out: Temporary connection, not in permanent position - multi phase metered - urban/short rural feeders | F142: =VLOOKUP(B142,'ACS Price List'!$16:$180,8,FALSE) -> 8025 | G142: dollars ($) | H142: 116.9 | I142: =IFERROR(IF(D142="LR",VLOOKUP(B142,'ACS Price List'!$16:$180,11,FALSE),IF(D142="IS",VLOOKUP(B142,'ACS Price List'!$16:$180,11,FALSE),VLOOKUP(B142,'ACS Price List'!$16:$180,9,FALSE))),"POA") -> 116.9 | K142: =IFERROR(IF(I142="POA","OK",IF(I142-H142=0,"OK","CHANGE")),"CHECK") -> OK
B143: 10-CF | C143: CFSUPABOLU | D143: UR | E143: Call out: Supply abolishment during business hours - urban/short rural feeders | F143: =VLOOKUP(B143,'ACS Price List'!$16:$180,8,FALSE) -> 8041 | G143: dollars ($) | H143: 116.9 | I143: =IFERROR(IF(D143="LR",VLOOKUP(B143,'ACS Price List'!$16:$180,11,FALSE),IF(D143="IS",VLOOKUP(B143,'ACS Price List'!$16:$180,11,FALSE),VLOOKUP(B143,'ACS Price List'!$16:$180,9,FALSE))),"POA") -> 116.9 | K143: =IFERROR(IF(I143="POA","OK",IF(I143-H143=0,"OK","CHANGE")),"CHECK") -> OK
B144: 12-CF | C144: CFDEENBHU | D144: UR | E144: Call out: De-energisation during business hours - urban/short rural feeders | F144: =VLOOKUP(B144,'ACS Price List'!$16:$180,8,FALSE) -> 8045 | G144: dollars ($) | H144: 0 | I144: =IFERROR(IF(D144="LR",VLOOKUP(B144,'ACS Price List'!$16:$180,11,FALSE),IF(D144="IS",VLOOKUP(B144,'ACS Price List'!$16:$180,11,FALSE),VLOOKUP(B144,'ACS Price List'!$16:$180,9,FALSE))),"POA") -> 0 | K144: =IFERROR(IF(I144="POA","OK",IF(I144-H144=0,"OK","CHANGE")),"CHECK") -> OK
B145: 14-CF | C145: CFREENBHU | D145: UR | E145: Call out: Re-energisation during business hours - urban/short rural feeders | F145: =VLOOKUP(B145,'ACS Price List'!$16:$180,8,FALSE) -> 8049 | G145: dollars ($) | H145: 0 | I145: =IFERROR(IF(D145="LR",VLOOKUP(B145,'ACS Price List'!$16:$180,11,FALSE),IF(D145="IS",VLOOKUP(B145,'ACS Price List'!$16:$180,11,FALSE),VLOOKUP(B145,'ACS Price List'!$16:$180,9,FALSE))),"POA") -> 0 | K145: =IFERROR(IF(I145="POA","OK",IF(I145-H145=0,"OK","CHANGE")),"CHECK") -> OK
B146: 16-CF | C146: CFREDDBHU | D146: UR | E146: Call out: Re-energisation during business hours - after de-energisation for debt - urban/short rural feeders | F146: =VLOOKUP(B146,'ACS Price List'!$16:$180,8,FALSE) -> 8053 | G146: dollars ($) | H146: 38.9 | I146: =IFERROR(IF(D146="LR",VLOOKUP(B146,'ACS Price List'!$16:$180,11,FALSE),IF(D146="IS",VLOOKUP(B146,'ACS Price List'!$16:$180,11,FALSE),VLOOKUP(B146,'ACS Price List'!$16:$180,9,FALSE))),"POA") -> 38.9 | K146: =IFERROR(IF(I146="POA","OK",IF(I146-H146=0,"OK","CHANGE")),"CHECK") -> OK
B147: 19-CF | C147: CFMSNGLU | D147: UR | E147: Call out: Install replacement meter (Type 5 and 6) – Single phase – urban/short rural feeder | F147: =VLOOKUP(B147,'ACS Price List'!$16:$180,8,FALSE) -> 8194 | G147: dollars ($) | H147: 63.4 | I147: =IFERROR(IF(D147="LR",VLOOKUP(B147,'ACS Price List'!$16:$180,11,FALSE),IF(D147="IS",VLOOKUP(B147,'ACS Price List'!$16:$180,11,FALSE),VLOOKUP(B147,'ACS Price List'!$16:$180,9,FALSE))),"POA") -> 63.4 | K147: =IFERROR(IF(I147="POA","OK",IF(I147-H147=0,"OK","CHANGE")),"CHECK") -> OK
B148: 21-CF | C148: CFMDUALU | D148: UR | E148: Call out: Install replacement meter (Type 5 and 6) – Dual element – urban/short rural feeder | F148: =VLOOKUP(B148,'ACS Price List'!$16:$180,8,FALSE) -> 8198 | G148: dollars ($) | H148: 63.4 | I148: =IFERROR(IF(D148="LR",VLOOKUP(B148,'ACS Price List'!$16:$180,11,FALSE),IF(D148="IS",VLOOKUP(B148,'ACS Price List'!$16:$180,11,FALSE),VLOOKUP(B148,'ACS Price List'!$16:$180,9,FALSE))),"POA") -> 63.4 | K148: =IFERROR(IF(I148="POA","OK",IF(I148-H148=0,"OK","CHANGE")),"CHECK") -> OK
B149: 23-CF | C149: CFMTHREU | D149: UR | E149: Call out: Install replacement meter (Type 5 and 6) – Polyphase – urban/short rural feeder | F149: =VLOOKUP(B149,'ACS Price List'!$16:$180,8,FALSE) -> 8202 | G149: dollars ($) | H149: 63.4 | I149: =IFERROR(IF(D149="LR",VLOOKUP(B149,'ACS Price List'!$16:$180,11,FALSE),IF(D149="IS",VLOOKUP(B149,'ACS Price List'!$16:$180,11,FALSE),VLOOKUP(B149,'ACS Price List'!$16:$180,9,FALSE))),"POA") -> 63.4 | K149: =IFERROR(IF(I149="POA","OK",IF(I149-H149=0,"OK","CHANGE")),"CHECK") -> OK
B150: 25-CF | C150: CFMCTU | D150: UR | E150: Call out: Install replacement meter (CT) – urban/short rural feeder | F150: =VLOOKUP(B150,'ACS Price List'!$16:$180,8,FALSE) -> 8206 | G150: dollars ($) | H150: 121.3 | I150: =IFERROR(IF(D150="LR",VLOOKUP(B150,'ACS Price List'!$16:$180,11,FALSE),IF(D150="IS",VLOOKUP(B150,'ACS Price List'!$16:$180,11,FALSE),VLOOKUP(B150,'ACS Price List'!$16:$180,9,FALSE))),"POA") -> 121.3 | K150: =IFERROR(IF(I150="POA","OK",IF(I150-H150=0,"OK","CHANGE")),"CHECK") -> OK
