Workbook
Name _Hlk318882101: 'ACS Tariff classes & tariffs'!#REF!
Name current_pricing_year: '[1]Model builder'!$E$23
Name JS_final_round: [1]JS!$C$25:$L$34
Name JS_final_round_C: [1]JS!$C$24:$L$24

Sheet EECL Price List
B7: Ergon Energy Corporation Limited
B8: 2017-18 Price List for Alternative Control Services | H8: Key: | J8: These services are subject to an additional layer of price regulation at the jurisdictional level, through Schedule 8 of the Electricity Regulation 2006. Even though the national economic regulator (the AER) has approved a higher price that EECL can charge for this service, the Queensland Government has stipulated a (lower) maximum price EECL is able to charge customers in EECL's supply area for these services.
B9: Release 1.1 - 1 July 2017 | D9: Release 0.0 - 1 July 2017 | F9: Release 0.0 - 1 July 2017 | J9: These services are subject to an additional layer of price regulation at the jurisdictional level, through Schedule 8 of the Electricity Regulation 2006. Even though the national economic regulator (the AER) has approved a higher price that EECL can charge for this service, the Queensland Government has stipulated that long rural / isolated customers in EECL's supply area are only able to be charged for these services at the same rate as an urban / short rural customer.
A12: Ref | B12: Service | C12: Service description | D12: Product Codes | H12: Ellipse Cost Code | I12: Urban/short rural feeder price | K12: Long rural/isolated feeder price | M12: AER classification | N12: Notes | O12: B2B Retailer only | P12: Form "A" Required
D13: Urban | E13: Short rural | F13: Long rural | G13: Isolated | I13: GST Excl | J13: GST Incl | K13: GST Excl | L13: GST Incl | O13: Customer
B14: Pre-Connection Services
A15: 1 | B15: Application fee - Basic or standard connection | C15: Services associated with assessing an application requesting a connection to be made (or altered) between Ergon Energy's network and the customer’s installation, and the preparation of a compliant basic or standard connection offer. Applies to small customers classified as a Standard Asset Customer (SAC), as per Ergon Energy's pricing proposal. | D15: APFSAC | H15: 8000 | I15: 888.4 | J15: =I15*1.1 -> 977.24 | K15: =I15 -> 888.4 | L15: =J15 -> 977.24 | M15: Fee Based Service | N15: Fixed fee applies | O15: Customer | P15: No
A16: 2 | B16: Application fee - Basic or standard connection - Micro-embedded generators | C16: Services associated with assessing a micro-embedded generator application requesting a connection to be made (or altered) between Ergon Energy's network and the customer’s installation, and the preparation of a compliant basic or standard connection offer. Applies to micro-embedded generators only (a subset of Standard Asset Customers, as per Ergon Energy's pricing proposal). No technical assessment required. | D16: APFMEG | H16: 8001 | I16: 48.6 | J16: =I16*1.1 -> 53.46 | K16: =I16 -> 48.6 | L16: =J16 -> 53.46 | M16: Fee Based Service | N16: Fixed fee applies | O16: Customer | P16: No
A17: 3 | B17: Application fee - Basic or standard connection - Micro-embedded generators - Technical assessment required | C17: Services associated with assessing a micro-embedded generator application requesting a connection to be made (or altered) between Ergon Energy's network and the customer’s installation, and the preparation of a compliant basic or standard connection offer. Applies to micro-embedded generators only (a subset of Standard Asset Customers, as per Ergon Energy's pricing proposal), where a technical assessment is required to be undertaken by Ergon Energy. | D17: APFMTA | H17: 8002 | I17: 220.7 | J17: =I17*1.1 -> 242.77 | K17: =I17 -> 220.7 | L17: =J17 -> 242.77 | M17: Fee Based Service | N17: Fixed fee applies | O17: Customer | P17: No
A18: 4 | B18: Application fee - Real estate development connection | C18: Services associated with assessing an application requesting a connection to be made between Ergon Energy's network and a real estate developer's installation, and the preparation of a compliant connection offer. Includes works carried out by contractors and/or Ergon Energy. | D18: APFRED | H18: 8003 | I18: 930.2 | J18: =I18*1.1 -> 1023.22 | K18: =I18 -> 930.2 | L18: =J18 -> 1023.22 | M18: Fee Based Service | N18: Fixed fee applies | O18: Customer | P18: No
A19: 5 | B19: Protection and Power Quality assessment prior to connection | C19: Evaluation of application protection design for completeness against engineering connection standard. Study of Power Quality issues including Flicker, Harmonics and DC voltage injection. | D19: PPQA | H19: 8004 | I19: 1376.7 | J19: =I19*1.1 -> 1514.37 | K19: =I19 -> 1376.7 | L19: =J19 -> 1514.37 | M19: Fee Based Service | N19: Fixed fee applies | O19: Customer | P19: No
A20: 40 | B20: Application fee - Negotiated connection | C20: Services associated with assessing an application requesting a connection to be made (or altered) between Ergon Energy's network and the customer’s installation, and the costs associated with negotiating and preparing a negotiated connection offer. Applies to small customers classified as a Standard Asset Customer (SAC), as per Ergon Energy's pricing proposal, with the exception of micro-embedded generators. | D20: As Quoted | H20: 8005 | I20: POA | K20: POA | M20: Quoted Service | N20: Price on application | O20: Customer | P20: No
A21: 41 | B21: Application fee - Negotiated connection - Micro-embedded generators | C21: Services associated with assessing a micro-embedded generator application requesting a connection to be made (or altered) between Ergon Energy's network and the customer’s installation, and the costs associated with negotiating and preparing a negotiated connection offer. Applies to micro-embedded generators only (a subset of SAC, as per Ergon Energy's pricing proposal). | D21: As Quoted | H21: 8006 | I21: POA | K21: POA | M21: Quoted Service | N21: Price on application | O21: Customer | P21: No
A22: 42 | B22: Application fee - Negotiated - Major customer connection | C22: Services associated with assessing a major customer connection application requesting a connection to be made (or altered) between Ergon Energy's network and the customer’s installation, and the costs associated with negotiating and preparing a compliant negotiated connection offer. Applies to major customers classified as an Individually Calculated Customer (ICC), Connection Asset Customer (CAC) or Embedded Generator (EG), as per Ergon Energy's pricing proposal. | D22: As Quoted | H22: 8007 | I22: POA | K22: POA | M22: Quoted Service | N22: Price on application | O22: Customer | P22: No
A23: 43 | B23: Carrying out planning studies and analysis relating to connection applications | C23: Services associated with carrying out additional planning studies and analysis on the distribution system which are reasonably required to assess a small customer or real estate development connection application. Excludes planning studies and analysis that would otherwise be required for distributor purposes or for the efficient management of the shared network. Applies to small customers classified as a Standard Asset Customer, as per Ergon Energy's pricing proposal (including micro-embedded generators), and real estate developers. | D23: As Quoted | H23: 8008 | I23: POA | K23: POA | M23: Quoted Service | N23: Price on application | O23: Customer | P23: No
A24: 44 | B24: Feasibility and concept scoping, including planning and design, for major customer connections | C24: Detailed design and advice for major customer connections for the selected (preferred) connection option. This includes shared network planning and design works incurred during the feasibility and concept scoping phases (i.e. before the connection offer has been accepted) (where applicable). | D24: As Quoted | H24: 8009 | I24: POA | K24: POA | M24: Quoted Service | N24: Price on application | O24: Customer | P24: No
A25: 45 | B25: Tender process | C25: Applies where Ergon Energy conducts a tender process on behalf of a connection applicant to procure connection services that can be provided by a third party, or where the connection applicant conducts a tender process and requires assistance from Ergon Energy | D25: As Quoted | H25: 8010 | I25: POA | K25: POA | M25: Quoted Service | N25: Price on application | O25: Customer | P25: No
A26: 46 | B26: Pre-connection site inspection | C26: Site inspection in order to determine nature of connection being sought | D26: As Quoted | H26: 8011 | I26: POA | K26: POA | M26: Quoted Service | N26: Price on application | O26: Customer | P26: No
A27: 47 | B27: Provision of site-specific connection information and advice | C27: Provision of site-specific connection advice, data and/or information on request (during the connection enquiry and/or connection application stage only). For example: - advice on project feasibility - advice on whether augmentation would likely be required - capacity information, including specific network capacity - load profiles for load flow studies - requests to review reports and designs prepared by external consultants, prior to lodgement of connection application - additional or more detailed specification and design options. Excludes information provided in planning reports/studies and project scopes. | D27: As Quoted | H27: 8012 | I27: POA | K27: POA | M27: Quoted Service | N27: Price on application | O27: Customer | P27: No
A28: 48 | B28: Preparation of preliminary designs and planning reports for major customer connections, including project scopes and estimates | C28: Initial specification and design outline for major customer connections. Includes general evaluation and advice on asset ownership options, indicative estimates of viable connection options, and recommendation on the most suitable option. | D28: As Quoted | H28: 8013 | I28: POA | K28: POA | M28: Quoted Service | N28: Price on application | O28: Customer | P28: No
A29: 49 | B29: Customer build, own and operate consultation services | C29: Provision of advice, design and specification on request to an applicant considering a build-own-operate asset ownership option for connection assets. | D29: As Quoted | H29: 8014 | I29: POA | K29: POA | M29: Quoted Service | N29: Price on application | O29: Customer | P29: No
A30: 50 | B30: Detailed enquiry response fee - embedded generation | C30: Costs associated with preparing a detailed enquiry response pursuant to Chapter 5 of the NER. Applies to any embedded generation connection applicant that submits an enquiry under the connection process set out in Chapter 5 of the NER and seeks a detailed enquiry response. | D30: As Quoted | H30: 8015 | I30: POA | K30: POA | M30: Quoted Service | N30: Price on application | O30: Customer | P30: No
B31: Connection Services
A32: 6 | B32: Temporary connection, not in permanent position - single phase metered - urban/short rural feeders | C32: Connection of a single phase supply to a meter location that is not permanent (i.e. short term supply) | D32: TBSSPU | E32: TBSSPS | H32: 8020 | I32: 412.7 | J32: =I32*1.1 -> 453.97 | M32: Fee Based Service | N32: Fixed fee applies, capped to maximum specified in Schedule 8 of Electricity Regulation 2006 | O32: B2B Retailer only | P32: Yes
A33: 6-CF | B33: Call out fee for temporary connection, not in permanent position - single phase metered - urban/short rural feeders | C33: Travel time to perform a fee based service requested by a retailer or customer, and the service is unable to be performed due to customer/retailer fault. Connection of a single phase supply to a meter location that is not permanent (i.e. short term supply) | D33: CFTBSSPU | E33: CFTBSSPS | H33: 8021 | I33: 116.9 | J33: =I33*1.1 -> 128.59 | M33: Fee Based Service | N33: Fixed fee applies | O33: B2B Retailer only | P33: N/A
A34: 7 | B34: Temporary connection, not in permanent position - single phase metered - long rural/isolated feeders | C34: Connection of a single phase supply to a meter location that is not permanent (i.e. short term supply) | F34: TBSSPL | G34: TBSSPI | H34: 8022 | K34: 412.7 | L34: =K34*1.1 -> 453.97 | M34: Fee Based Service | N34: Fixed fee applies, capped to maximum specified in Schedule 8 of Electricity Regulation 2006 | O34: B2B Retailer only | P34: Yes
A35: 7-CF | B35: Call out fee for temporary connection, not in permanent position - single phase metered - long rural/isolated feeders | C35: Travel time to perform a fee based service requested by a retailer or customer, and the service is unable to be performed due to customer/retailer fault. Connection of a single phase supply to a meter location that is not permanent (i.e. short term supply) | F35: CFTBSSPL | G35: CFTBSSPI | H35: 8023 | K35: 412.7 | L35: =K35*1.1 -> 453.97 | M35: Fee Based Service | N35: Fixed fee applies, capped to the maximum price of the associated service (to be consistent with Schedule 8 of Electricity Regulation 2006) | O35: B2B Retailer only | P35: N/A
A36: 8 | B36: Temporary connection, not in permanent position - multi phase metered - urban/short rural feeders | C36: Connection of a multi phase supply to a meter location that is not permanent (i.e. short term supply) | D36: TBSMPU | E36: TBSMPS | H36: 8024 | I36: 412.7 | J36: =I36*1.1 -> 453.97 | M36: Fee Based Service | N36: Fixed fee applies, capped to maximum specified in Schedule 8 of Electricity Regulation 2006 | O36: B2B Retailer only | P36: Yes
A37: 8-CF | B37: Call out fee for temporary connection, not in permanent position - multi-phase metered - urban/short rural feeders | C37: Travel time to perform a fee based service requested by a retailer or customer, and the service is unable to be performed due to customer/retailer fault. Connection of a multi-phase supply to a meter location that is not permanent (i.e. short term supply) | D37: CFTBSMPU | E37: CFTBSMPS | H37: 8025 | I37: 116.9 | J37: =I37*1.1 -> 128.59 | M37: Fee Based Service | N37: Fixed fee applies | O37: B2B Retailer only | P37: N/A
A38: 9 | B38: Temporary connection, not in permanent position - multi phase metered - long rural/isolated feeders | C38: Connection of a multi phase supply to a meter location that is not permanent (i.e. short term supply) | F38: TBSMPL | G38: TBSMPI | H38: 8026 | K38: 412.7 | L38: =K38*1.1 -> 453.97 | M38: Fee Based Service | N38: Fixed fee applies, capped to maximum specified in Schedule 8 of Electricity Regulation 2006 | O38: B2B Retailer only | P38: Yes
A39: 9-CF | B39: Call out fee for temporary connection, not in permanent position - multi-phase metered - long rural/isolated feeders | C39: Travel time to perform a fee based service requested by a retailer or customer, and the service is unable to be performed due to customer/retailer fault. Connection of a multi-phase supply to a meter location that is not permanent (i.e. short term supply) | F39: CFTBSMPL | G39: CFTBSMPI | H39: 8027 | K39: 412.7 | L39: =K39*1.1 -> 453.97 | M39: Fee Based Service | N39: Fixed fee applies, capped to the maximum price of the associated service (to be consistent with Schedule 8 of Electricity Regulation 2006) | O39: B2B Retailer only | P39: N/A
A40: 51 | B40: Design and construction of connection assets for major customers | C40: Detailed design work and construction of connection assets after a connection offer has been made. Applies to major customers classified as an Individually Calculated Customer (ICC), Connection Asset Customer (CAC) or Embedded Generator (EG) as per Ergon Energy's pricing proposal. | D40: As Quoted | H40: 8028 | I40: POA | K40: POA | M40: Quoted Service | N40: Price on application | O40: Customer | P40: No
A41: 52 | B41: Commissioning and energisation of major customer connections | C41: Includes: - inspection and testing of connection assets prior to physical connection to the network - physical connection and energisation of electricity equipment to allow conveyance of electricity - administration services involved in reconciling the financials of a connection project, and processing and finalising network information and contracts in relation to a connection - generation required (if any) to supply existing customers while equipment is de-energised to allow testing and commissioning Applies to major customers classified as an Individually Calculated Customer (ICC), Connection Asset Customer (CAC) or Embedded Generator (EG) as per Ergon Energy's pricing proposal. | D41: As Quoted | H41: 8029 | I41: POA | K41: POA | M41: Quoted Service | N41: Price on application | O41: Customer | P41: Yes
A42: 53 | B42: Design and construction for real estate developments | C42: Detailed design work and construction for a real estate development connection after a connection offer has been made. Includes work associated with augmentation to the shared network which is directly attributable to the establishment or alteration of the real estate development connection | D42: As Quoted | H42: 8030 | I42: POA | K42: POA | M42: Quoted Service | N42: Price on application | O42: Customer | P42: No
A43: 54 | B43: Commissioning and energisation of real estate development connections | C43: Includes: - inspection and testing prior to physical connection to the network - physical connection and energisation of electricity equipment to allow conveyance of electricity - administration services involved in reconciling the financials of a connection project, and processing and finalising network information and contracts in relation to a connection - generation required (if any) to supply existing customers while equipment is de-energised to allow testing and commissioning | D43: As Quoted | H43: 8031 | I43: POA | K43: POA | M43: Quoted Service | N43: Price on application | O43: Customer | P43: Yes
A44: 55 | B44: Removal of network constraint for embedded generator | C44: Augmenting the network to remove a constraint faced by an embedded generator | D44: As Quoted | H44: 8032 | I44: POA | K44: POA | M44: Quoted Service | N44: Price on application | O44: Customer | P44: No
B45: Post Connection Services
A46: 10 | B46: Supply abolishment during business hours - urban/short rural feeders | C46: Decommissioning of a NMI and associated metering when present. May be used where a property is to be demolished; supply is no longer required; an alternative connection point is to be used; or a redundant supply is to be removed | D46: SUPABOLU | E46: SUPABOLS | H46: 8040 | I46: 350.9 | J46: =I46*1.1 -> 385.99 | M46: Fee Based Service | N46: Fixed fee applies | O46: B2B Retailer only | P46: No
A47: 10-CF | B47: Call out fee for supply abolishment during business hours - urban/short rural feeders | C47: Travel time to perform a fee based service requested by a retailer or customer, and the service is unable to be performed due to customer/retailer fault. Decommissioning of a NMI and associated metering when present. May be used where a property is to be demolished; supply is no longer required; an alternative connection point is to be used; or a redundant supply is to be removed | D47: CFSUPABOLU | E47: CFSUPABOLS | H47: 8041 | I47: 116.9 | J47: =I47*1.1 -> 128.59 | M47: Fee Based Service | N47: Fixed fee applies | O47: B2B Retailer only | P47: N/A
A48: 11 | B48: Supply abolishment during business hours - long rural/isolated feeders | C48: Decommissioning of a NMI and associated metering when present. May be used where a property is to be demolished; supply is no longer required; an alternative connection point is to be used; or a redundant supply is to be removed | F48: SUPABOLL | G48: SUPABOLI | H48: 8042 | K48: 350.9 | L48: =K48*1.1 -> 385.99 | M48: Fee Based Service | N48: Fixed fee applies, capped to UR/SR price as per Schedule 8 of Electricity Regulation 2006 | O48: B2B Retailer only | P48: No
A49: 11-CF | B49: Call out fee for supply abolishment during business hours - long rural/isolated feeders | C49: Travel time to perform a fee based service requested by a retailer or customer, and the service is unable to be performed due to customer/retailer fault. Decommissioning of a NMI and associated metering when present. May be used where a property is to be demolished; supply is no longer required; an alternative connection point is to be used; or a redundant supply is to be removed | F49: CFSUPABOLL | G49: CFSUPABOLI | H49: 8043 | K49: 116.9 | L49: =K49*1.1 -> 128.59 | M49: Fee Based Service | N49: Fixed fee applies, capped to UR/SR price (to be consistent with Schedule 8 of Electricity Regulation 2006) | O49: B2B Retailer only | P49: N/A
A50: 12 | B50: De-energisation during business hours - urban/short rural feeders | C50: Retailer requests de-energisation of the customer's premises during business hours: - where the de-energisation can be performed (e.g. pole, pillar or meter) - Main switch sticker | D50: DEENBHU | E50: DEENBHS | H50: 8044 | I50: 0 | J50: =I50*1.1 -> 0 | M50: Fee Based Service | N50: Fixed fee applies, capped to maximum specified in Schedule 8 of Electricity Regulation 2006 | O50: B2B Retailer only | P50: No
A51: 12-CF | B51: Call out fee for de-energisation during business hours - urban/short rural feeders | C51: Travel time to perform a fee based service requested by a retailer or customer, and the service is unable to be performed due to customer/retailer fault. Retailer requests de-energisation of the customer's premises during business hours: - where the de-energisation can be performed (e.g. pole, pillar or meter) - Main switch sticker | D51: CFDEENBHU | E51: CFDEENBHS | H51: 8045 | I51: 0 | J51: =I51*1.1 -> 0 | M51: Fee Based Service | N51: Fixed fee applies, capped to the maximum price of the associated service (to be consistent with Schedule 8 of Electricity Regulation 2006) | O51: B2B Retailer only | P51: N/A
A52: 13 | B52: De-energisation during business hours - long rural/isolated feeders | C52: Retailer requests de-energisation of the customer's premises during business hours: - where the de-energisation can be performed (e.g. pole, pillar or meter) - Main switch sticker | F52: DEENBHL | G52: DEENBHI | H52: 8046 | K52: 0 | L52: =K52*1.1 -> 0 | M52: Fee Based Service | N52: Fixed fee applies, capped to maximum specified in Schedule 8 of Electricity Regulation 2006 | O52: B2B Retailer only | P52: No
A53: 13-CF | B53: Call out fee for de-energisation during business hours - long rural/isolated feeders | C53: Travel time to perform a fee based service requested by a retailer or customer, and the service is unable to be performed due to customer/retailer fault. Retailer requests de-energisation of the customer's premises during business hours: - where the de-energisation can be performed (e.g. pole, pillar or meter) - Main switch sticker | F53: CFDEENBHL | G53: CFDEENBHI | H53: 8047 | K53: 0 | L53: =K53*1.1 -> 0 | M53: Fee Based Service | N53: Fixed fee applies, capped to the maximum price of the associated service (to be consistent with Schedule 8 of Electricity Regulation 2006) | O53: B2B Retailer only | P53: N/A
A54: 14 | B54: Re-energisation during business hours - urban/short rural feeders | C54: Retailer requests re-energisation of customer's premises during business hours: - after a physical disconnection and premises requires a visual examination - following a main switch sticker | D54: REENBHU | E54: REENBHS | H54: 8048 | I54: 0 | J54: =I54*1.1 -> 0 | M54: Fee Based Service | N54: Fixed fee applies, capped to maximum specified in Schedule 8 of Electricity Regulation 2006 | O54: B2B Retailer only | P54: No
A55: 14-CF | B55: Call out fee for re-energisation during business hours - urban/short rural feeders | C55: Travel time to perform a fee based service requested by a retailer or customer, and the service is unable to be performed due to customer/retailer fault. Retailer requests re-energisation of customer's premises during business hours: - after a physical disconnection and premises requires a visual examination - following a main switch sticker | D55: CFREENBHU | E55: CFREENBHS | H55: 8049 | I55: 0 | J55: =I55*1.1 -> 0 | M55: Fee Based Service | N55: Fixed fee applies, capped to the maximum price of the associated service (to be consistent with Schedule 8 of Electricity Regulation 2006) | O55: B2B Retailer only | P55: N/A
A56: 15 | B56: Re-energisation during business hours - long rural/isolated feeders | C56: Retailer requests re-energisation of customer's premises during business hours: - after a physical disconnection and premises requires a visual examination - following a main switch sticker | F56: REENBHL | G56: REENBHI | H56: 8050 | K56: 0 | L56: =K56*1.1 -> 0 | M56: Fee Based Service | N56: Fixed fee applies, capped to maximum specified in Schedule 8 of Electricity Regulation 2006 | O56: B2B Retailer only | P56: No
A57: 15-CF | B57: Call out fee for re-energisation during business hours - long rural/isolated feeders | C57: Travel time to perform a fee based service requested by a retailer or customer, and the service is unable to be performed due to customer/retailer fault. Retailer requests re-energisation of customer's premises during business hours: - after a physical disconnection and premises requires a visual examination - following a main switch sticker | F57: CFREENBHL | G57: CFREENBHI | H57: 8051 | K57: 0 | L57: =K57*1.1 -> 0 | M57: Fee Based Service | N57: Fixed fee applies, capped to the maximum price of the associated service (to be consistent with Schedule 8 of Electricity Regulation 2006) | O57: B2B Retailer only | P57: N/A
A58: 16 | B58: Re-energisation during business hours - after de-energisation for debt - urban/short rural feeders | C58: Retailer requests re-energisation of customer's premises during business hours where the customer has not paid their electricity account | D58: REDDBHU | E58: REDDBHS | H58: 8052 | I58: 45.5 | J58: =I58*1.1 -> 50.05 | M58: Fee Based Service | N58: Fixed fee applies, capped to maximum specified in Schedule 8 of Electricity Regulation 2006 | O58: B2B Retailer only | P58: No
A59: 16-CF | B59: Call out fee for re-energisation during business hours - after de-energisation for debt - urban/short rural feeders | C59: Travel time to perform a fee based service requested by a retailer or customer, and the service is unable to be performed due to customer/retailer fault. Retailer requests re-energisation of customer's premises during business hours where the customer has not paid their electricity account | D59: CFREDDBHU | E59: CFREDDBHS | H59: 8053 | I59: 38.9 | J59: =I59*1.1 -> 42.79 | M59: Fee Based Service | N59: Fixed fee applies | O59: B2B Retailer only | P59: N/A
A60: 17 | B60: Re-energisation during business hours - after de-energisation for debt - long rural/isolated feeders | C60: Retailer requests re-energisation of customer's premises during business hours where the customer has not paid their electricity account | F60: REDDBHL | G60: REDDBHI | H60: 8054 | K60: 45.5 | L60: =K60*1.1 -> 50.05 | M60: Fee Based Service | N60: Fixed fee applies, capped to maximum specified in Schedule 8 of Electricity Regulation 2006 | O60: B2B Retailer only | P60: No
A61: 17-CF | B61: Call out fee for re-energisation during business hours - after de-energisation for debt - long rural/isolated feeders | C61: Travel time to perform a fee based service requested by a retailer or customer, and the service is unable to be performed due to customer/retailer fault. Retailer requests re-energisation of customer's premises during business hours where the customer has not paid their electricity account | F61: CFREDDBHL | G61: CFREDDBHI | H61: 8055 | K61: 45.5 | L61: =K61*1.1 -> 50.05 | M61: Fee Based Service | N61: Fixed fee applies, capped to the maximum price of the associated service (to be consistent with Schedule 8 of Electricity Regulation 2006) | O61: B2B Retailer only | P61: N/A
A62: 56 | B62: Move point of attachment - single/multi phase | C62: De-energisation, followed by physical dismantling then reattachment of service and re-energisation | D62: MPOAU | E62: MPOAS | F62: MPOAL | G62: MPOAI | H62: 8056 | I62: POA | K62: POA | M62: Quoted Service | N62: Price on application | O62: B2B Retailer only | P62: Yes
A63: 57 | B63: Re-arrange connection assets at customer's request | C63: Removal, relocation or rearrangement of connection assets at customer request | D63: As Quoted | H63: 8057 | I63: POA | K63: POA | M63: Quoted Service | N63: Price on application | O63: Customer | P63: Yes
A64: 58 | B64: Protection and Power Quality assessment after connection | C64: Investigation into Power Quality issues including Flicker, Harmonics and DC voltage injection. | D64: As Quoted | H64: 8058 | I64: POA | K64: POA | M64: Quoted Service | N64: Price on application | O64: Customer | P64: No
A65: 59 | B65: Temporary de-energisation - no dismantling | C65: Temporary de-energisation and re-energisation of supply at the service fuse to allow customer or contractor to work close - no dismantling of service required (i.e. no service line drop). | D65: TEMPDEENU | E65: TEMPDEENS | F65: TEMPDEENL | G65: TEMPDEENI | H65: 8059 | I65: POA | K65: POA | M65: Quoted Service | N65: Price on application | O65: B2B Retailer only | P65: No
A66: 60 | B66: LV Service line drop and replace - physical dismantling | C66: Temporary de-energisation and re-energisation of supply to allow customer or contractor to work close - the service will be physically dismantled or disconnected (e.g. overhead service dropped). | D66: LVSLDU | E66: LVSLDS | F66: LVSLDL | G66: LVSLDI | H66: 8060 | I66: POA | K66: POA | M66: Quoted Service | N66: Price on application | O66: B2B Retailer only | P66: No
A67: 61 | B67: HV Service line drop and replace | C67: Temporary de-energisation and re-energisation of supply to allow customer or contractor to work close - Isolate and earth | D67: HVSLDU | E67: HVSLDS | F67: HVSLDL | G67: HVSLDI | H67: 8061 | I67: POA | K67: POA | M67: Quoted Service | N67: Price on application | O67: B2B Retailer only | P67: No
A68: 62 | B68: Supply enhancement | C68: For example, an upgrade from single phase to multi phase and/or increase capacity. Applies to underground and overhead service upgrades. | D68: SUPENHU | E68: SUPENHS | F68: SUPENHL | G68: SUPENHI | H68: 8062 | I68: POA | K68: POA | M68: Quoted Service | N68: Price on application | O68: B2B Retailer only | P68: Yes
A69: 63 | B69: Provision of connection services above minimum requirements | C69: Customer requests increase in reliability or quality of supply beyond the standard, and/or above minimum regulatory requirements (e.g. reserve feeder) | D69: As Quoted | H69: 8063 | I69: POA | K69: POA | M69: Quoted Service | N69: Price on application | O69: Customer | P69: No
A70: 64 | B70: Upgrade from overhead to underground service | C70: Requests to convert an existing overhead service to an underground service | D70: As Quoted | H70: 8064 | I70: POA | K70: POA | M70: Quoted Service | N70: Price on application | O70: Customer | P70: Yes
A71: 65 | B71: Rectification of illegal connections or damage to overhead or underground service cables | C71: Repair works to re-establish a safe and legal connection due to customer or third party action | D71: As Quoted | H71: 8065 | I71: POA | K71: POA | M71: Quoted Service | N71: Price on application | O71: Customer | P71: No
A72: 66 | B72: De-energisation after business hours | C72: Retailer requests de-energisation of the customer's premises after business hours: - where the de-energisation can be performed (e.g. pole, pillar or meter). - Main switch sticker | D72: DEENAHU | E72: DEENAHS | F72: DEENAHL | G72: DEENAHI | H72: 8066 | I72: 0 | J72: =I72*1.1 -> 0 | K72: 0 | L72: =K72*1.1 -> 0 | M72: Quoted Service | N72: Fixed fee applies, capped to maximum specified in Schedule 8 of Electricity Regulation 2006 | O72: B2B Retailer only | P72: No
A73: 66-CF | B73: Call out fee for de-energisations after business hours | C73: Travel time to perform a de-energisation after business hours requested by a retailer, and the service is unable to be performed due to customer/retailer fault. Retailer requests de-energisation of the customer's premises after business hours: - where the de-energisation can be performed (e.g. pole, pillar or meter) - Main switch sticker. | D73: CFDEENAHU | E73: CFDEENAHS | F73: CFDEENAHL | G73: CFDEENAHI | H73: 8075 | I73: 0 | J73: =I73*1.1 -> 0 | K73: 0 | L73: =K73*1.1 -> 0 | M73: Quoted Service | N73: Fixed fee applies, capped to the maximum price of the associated service (to be consistent with Schedule 8 of Electricity Regulation 2006) | O73: B2B Retailer only | P73: N/A
A74: 67 | B74: Re-energisation after business hours | C74: Retailer requests re-energisation of a customer's premises after business hours: - after a physical disconnection and premises requires a visual examination - following a main switch sticker - where the customer has not paid their electricity account | D74: REENAHU | E74: REENAHS | F74: REENAHL | G74: REENAHI | H74: 8067 | I74: 109.9 | J74: =I74*1.1 -> 120.89 | K74: 109.9 | L74: =K74*1.1 -> 120.89 | M74: Quoted Service | N74: Fixed fee applies, capped to maximum specified in Schedule 8 of Electricity Regulation 2006 | O74: B2B Retailer only | P74: No
A75: 67-CF | B75: Call out fee for re-energisations after business hours | C75: Travel time to perform a re-energisation after business hours requested by a retailer, and the service is unable to be performed due to customer/retailer fault. Retailer requests re-energisation of a customer's premises after business hours: - after a physical disconnection and premises requires a visual examination - following a main switch sticker - where the customer has not paid their electricity account. | D75: CFREENAHU | E75: CFREENAHS | F75: CFREENAHL | G75: CFREENAHI | H75: 8076 | I75: 58.4 | J75: =I75*1.1 -> 64.24 | K75: 58.4 | L75: =K75*1.1 -> 64.24 | M75: Quoted Service | N75: Fixed fee applies (to be consistent with Schedule 8 of Electricity Regulation 2006) | O75: B2B Retailer only | P75: N/A
A76: 68 | B76: Accreditation of alternative service providers - major customer connections | C76: Accreditation of service providers that meet competency criteria. Applies to major customers classified as an Individually Calculated Customer (ICC), Connection Asset Customer (CAC) or Embedded Generator (EG) as per Ergon Energy's pricing proposal. | D76: As Quoted | H76: 8068 | I76: POA | K76: POA | M76: Quoted Service | N76: Price on application | O76: Customer | P76: No
A77: 18 | B77: Accreditation of alternative service providers - real estate developments | C77: Accreditation of service providers that meet competency criteria. Applies to real estate developments. | D77: ASPRED | H77: 8069 | I77: 903.5 | J77: =I77*1.1 -> 993.85 | K77: =I77 -> 903.5 | L77: =J77 -> 993.85 | M77: Fee Based Service | N77: Fixed fee applies | O77: Customer | P77: No
A78: 69 | B78: Approval of third party design - major customer connections | C78: Review, inspection and auditing of design carried out by an alternative service provider prior to energisation. Applies to major customers classified as an Individually Calculated Customer (ICC), Connection Asset Customer (CAC) or Embedded Generator (EG) as per Ergon Energy's pricing proposal. | D78: As Quoted | H78: 8070 | I78: POA | K78: POA | M78: Quoted Service | N78: Price on application | O78: Customer | P78: No
A79: 70 | B79: Approval of third party design - real estate developments | C79: Review, inspection and auditing of design carried out by an alternative service provider prior to energisation. Applies to real estate developments. | D79: As Quoted | H79: 8071 | I79: POA | K79: POA | M79: Quoted Service | N79: Price on application | O79: Customer | P79: No
A80: 71 | B80: Construction audit - major customer connections | C80: Review, inspection and auditing of construction works carried out by an alternative service provider prior to energisation. Applies to major customers classified as an Individually Calculated Customer (ICC), Connection Asset Customer (CAC) or Embedded Generator (EG) as per Ergon Energy's pricing proposal. | D80: As Quoted | H80: 8072 | I80: POA | K80: POA | M80: Quoted Service | N80: Price on application | O80: Customer | P80: No
A81: 72 | B81: Construction audit - real estate developments | C81: Review, inspection and auditing of construction works carried out by an alternative service provider prior to energisation. Applies to real estate developments. | D81: As Quoted | H81: 8073 | I81: POA | K81: POA | M81: Quoted Service | N81: Price on application | O81: Customer | P81: No
A82: 73 | B82: Approval of third party materials | C82: Certification of non-approved materials (i.e. approval of non-approved materials to be used on Ergon Energy's network). | D82: As Quoted | H82: 8074 | I82: POA | K82: POA | M82: Quoted Service | N82: Price on application | O82: Customer | P82: No
B83: Metering Services
B84: Meter replacements
A85: 19 | B85: Install replacement meter (Type 5 and 6) – Single phase – urban/short rural feeder | C85: Installation and provision during business hours of a single phase replacement meter | D85: MSNGLU | E85: MSNGLS | H85: 8193 | I85: 344.4 | J85: =I85*1.1 -> 378.84 | M85: Fee Based Service | N85: Fixed fee applies | O85: B2B Retailer only | P85: Depends on activity requested
A86: 19-CF | B86: Call out fee for installation of a replacement meter (Type 5 and 6) – Single phase – urban/short rural feeder | C86: Travel time to perform a fee based service requested by a retailer or customer, and the service is unable to be performed due to customer/retailer fault. Install replacement meter (Type 5 and 6) – Single phase – urban/short rural feeder. | D86: CFMSNGLU | E86: CFMSNGLS | H86: 8194 | I86: 63.4 | J86: =I86*1.1 -> 69.74 | M86: Fee Based Service | N86: Fixed fee applies | O86: B2B Retailer only | P86: N/A
A87: 20 | B87: Install replacement meter (Type 5 and 6) – Single phase – long rural/isolated feeder | C87: Installation and provision during business hours of a single phase replacement meter | F87: MSNGLL | G87: MSNGLI | H87: 8195 | K87: 344.4 | L87: =K87*1.1 -> 378.84 | M87: Fee Based Service | N87: Fixed fee applies, capped to UR/SR price as per Schedule 8 of Electricity Regulation 2006 | O87: B2B Retailer only | P87: Depends on activity requested
A88: 20-CF | B88: Call out fee for installation of a replacement meter (Type 5 and 6) – Single phase – long rural/isolated feeder | C88: Travel time to perform a fee based service requested by a retailer or customer, and the service is unable to be performed due to customer/retailer fault. Install replacement meter (Type 5 and 6) – Single phase – long rural/isolated feeder. | F88: CFMSNGLL | G88: CFMSNGLI | H88: 8196 | K88: 63.4 | L88: =K88*1.1 -> 69.74 | M88: Fee Based Service | N88: Fixed fee applies, capped to UR/SR price (to be consistent with Schedule 8 of Electricity Regulation 2006) | O88: B2B Retailer only | P88: N/A
A89: 21 | B89: Install replacement meter (Type 5 and 6) – Dual element – urban/short rural feeder | C89: Installation and provision during business hours of a dual element replacement meter | D89: MDUALU | E89: MDUALS | H89: 8197 | I89: 421.8 | J89: =I89*1.1 -> 463.98 | M89: Fee Based Service | N89: Fixed fee applies | O89: B2B Retailer only | P89: Depends on activity requested
A90: 21-CF | B90: Call out fee for installation of a replacement meter (Type 5 and 6) – Dual element – urban/short rural feeder | C90: Travel time to perform a fee based service requested by a retailer or customer, and the service is unable to be performed due to customer/retailer fault. Install replacement meter (Type 5 and 6) – Dual element – urban/short rural feeder. | D90: CFMDUALU | E90: CFMDUALS | H90: 8198 | I90: 63.4 | J90: =I90*1.1 -> 69.74 | M90: Fee Based Service | N90: Fixed fee applies | O90: B2B Retailer only | P90: N/A
A91: 22 | B91: Install replacement meter (Type 5 and 6) – Dual element – long rural/isolated feeder | C91: Installation and provision during business hours of a dual element replacement meter | F91: MDUALL | G91: MDUALI | H91: 8199 | K91: 421.8 | L91: =K91*1.1 -> 463.98 | M91: Fee Based Service | N91: Fixed fee applies, capped to UR/SR price as per Schedule 8 of Electricity Regulation 2006 | O91: B2B Retailer only | P91: Depends on activity requested
A92: 22-CF | B92: Call out fee for installation of a replacement meter (Type 5 and 6) – Dual element – long rural/isolated feeder | C92: Travel time to perform a fee based service requested by a retailer or customer, and the service is unable to be performed due to customer/retailer fault. Install replacement meter (Type 5 and 6) – Dual element – long rural/isolated feeder. | F92: CFMDUALL | G92: CFMDUALI | H92: 8200 | K92: 63.4 | L92: =K92*1.1 -> 69.74 | M92: Fee Based Service | N92: Fixed fee applies, capped to UR/SR price (to be consistent with Schedule 8 of Electricity Regulation 2006) | O92: B2B Retailer only | P92: N/A
A93: 23 | B93: Install replacement meter (Type 5 and 6) – Polyphase – urban/short rural feeder | C93: Installation and provision during business hours of a polyphase replacement meter | D93: MTHREU | E93: MTHRES | H93: 8201 | I93: 530.2 | J93: =I93*1.1 -> 583.22 | M93: Fee Based Service | N93: Fixed fee applies | O93: B2B Retailer only | P93: Depends on activity requested
A94: 23-CF | B94: Call out fee for installation of a replacement meter (Type 5 and 6) – Polyphase – urban/short rural feeder | C94: Travel time to perform a fee based service requested by a retailer or customer, and the service is unable to be performed due to customer/retailer fault. Install replacement meter (Type 5 and 6) – Polyphase – urban/short rural feeder. | D94: CFMTHREU | E94: CFMTHRES | H94: 8202 | I94: 63.4 | J94: =I94*1.1 -> 69.74 | M94: Fee Based Service | N94: Fixed fee applies | O94: B2B Retailer only | P94: N/A
A95: 24 | B95: Install replacement meter (Type 5 and 6) – Polyphase – long rural/isolated feeder | C95: Installation and provision during business hours of a polyphase replacement meter | F95: MTHREL | G95: MTHREI | H95: 8203 | K95: 530.2 | L95: =K95*1.1 -> 583.22 | M95: Fee Based Service | N95: Fixed fee applies, capped to UR/SR price as per Schedule 8 of Electricity Regulation 2006 | O95: B2B Retailer only | P95: Depends on activity requested
A96: 24-CF | B96: Call out fee for installation of a replacement meter (Type 5 and 6) – Polyphase – long rural/isolated feeder | C96: Travel time to perform a fee based service requested by a retailer or customer, and the service is unable to be performed due to customer/retailer fault. Install replacement meter (Type 5 and 6) – Polyphase – long rural/isolated feeder. | F96: CFMTHREL | G96: CFMTHREI | H96: 8204 | K96: 63.4 | L96: =K96*1.1 -> 69.74 | M96: Fee Based Service | N96: Fixed fee applies, capped to UR/SR price (to be consistent with Schedule 8 of Electricity Regulation 2006) | O96: B2B Retailer only | P96: N/A
A97: 25 | B97: Install replacement meter (CT) – urban/short rural feeder | C97: Installation and provision during business hours of a CT replacement meter | D97: MCTU | E97: MCTS | H97: 8205 | I97: 2519.1 | J97: =I97*1.1 -> 2771.01 | M97: Fee Based Service | N97: Fixed fee applies | O97: B2B Retailer only | P97: Depends on activity requested
A98: 25-CF | B98: Call out fee for installation of a replacement meter (CT) – urban/short rural feeder | C98: Travel time to perform a fee based service requested by a retailer or customer, and the service is unable to be performed due to customer/retailer fault. Install replacement meter (CT) – urban/short rural feeder. | D98: CFMCTU | E98: CFMCTS | H98: 8206 | I98: 121.3 | J98: =I98*1.1 -> 133.43 | M98: Fee Based Service | N98: Fixed fee applies | O98: B2B Retailer only | P98: N/A
A99: 26 | B99: Install replacement meter (CT) – long rural/isolated feeder | C99: Installation and provision during business hours of a CT replacement meter | F99: MCTL | G99: MCTI | H99: 8207 | K99: 2519.1 | L99: =K99*1.1 -> 2771.01 | M99: Fee Based Service | N99: Fixed fee applies, capped to UR/SR price as per Schedule 8 of Electricity Regulation 2006 | O99: B2B Retailer only | P99: Depends on activity requested
A100: 26-CF | B100: Call out fee for installation of a replacement meter (CT) – long rural/isolated feeder | C100: Travel time to perform a fee based service requested by a retailer or customer, and the service is unable to be performed due to customer/retailer fault. Install replacement meter (CT) – long rural/isolated feeder. | F100: CFMCTL | G100: CFMCTI | H100: 8208 | K100: 121.3 | L100: =K100*1.1 -> 133.43 | M100: Fee Based Service | N100: Fixed fee applies, capped to UR/SR price (to be consistent with Schedule 8 of Electricity Regulation 2006) | O100: B2B Retailer only | P100: N/A
B101: New meter installations
A102: 140 | B102: Install new meter (Type 5 and 6) – Single phase – Primary | C102: Installation and provision of a new single phase Type 5 or 6 meter. Applies where there is a primary metering service. | D102: NMSPU | E102: NMSPS | F102: NMSPL | G102: NMSPI | H102: 8172 | I102: 344.4 | J102: =I102*1.1 -> 378.84 | K102: 344.4 | L102: =K102*1.1 -> 378.84 | M102: Fee Based Service | N102: Fixed fee applies, capped to UR/SR price as per Schedule 8 of Electricity Regulation 2006 | O102: B2B Retailer only | P102: Depends on activity requested
A103: 141 | B103: Install new meter (Type 5 and 6) – Single phase – Primary plus embedded generation | C103: Installation and provision of a new single phase Type 5 or 6 meter. Applies where there is a primary metering service plus embedded generation. | D103: NMSPEGU | E103: NMSPEGS | F103: NMSPEGL | G103: NMSPEGI | H103: 8173 | I103: 344.4 | J103: =I103*1.1 -> 378.84 | K103: 344.4 | L103: =K103*1.1 -> 378.84 | M103: Fee Based Service | N103: Fixed fee applies, capped to UR/SR price as per Schedule 8 of Electricity Regulation 2006 | O103: B2B Retailer only | P103: Depends on activity requested
A104: 142 | B104: Install new meter (Type 5 and 6) – Dual element – Primary plus controlled load | C104: Installation and provision of a new dual element Type 5 or 6 meter. Applies where there is a primary metering service plus controlled load. | D104: NMDPCLU | E104: NMDPCLS | F104: NMDPCLL | G104: NMDPCLI | H104: 8174 | I104: 421.8 | J104: =I104*1.1 -> 463.98 | K104: 421.8 | L104: =K104*1.1 -> 463.98 | M104: Fee Based Service | N104: Fixed fee applies, capped to UR/SR price as per Schedule 8 of Electricity Regulation 2006 | O104: B2B Retailer only | P104: Depends on activity requested
A105: 143 | B105: Install new meter (Type 5 and 6) – Dual element – Primary plus controlled load plus embedded generation | C105: Installation and provision of a new dual element Type 5 or 6 meter. Applies where there is a primary metering service plus controlled load plus embedded generation. | D105: NMDPCLEGU | E105: NMDPCLEGS | F105: NMDPCLEGL | G105: NMDPCLEGI | H105: 8175 | I105: 421.8 | J105: =I105*1.1 -> 463.98 | K105: 421.8 | L105: =K105*1.1 -> 463.98 | M105: Fee Based Service | N105: Fixed fee applies, capped to UR/SR price as per Schedule 8 of Electricity Regulation 2006 | O105: B2B Retailer only | P105: Depends on activity requested
A106: 144 | B106: Install new meter (Type 5 and 6) – Polyphase – Primary | C106: Installation and provision of a new polyphase Type 5 or 6 meter. Applies where there is a primary metering service. | D106: NMPPU | E106: NMPPS | F106: NMPPL | G106: NMPPI | H106: 8176 | I106: 530.2 | J106: =I106*1.1 -> 583.22 | K106: 530.2 | L106: =K106*1.1 -> 583.22 | M106: Fee Based Service | N106: Fixed fee applies, capped to UR/SR price as per Schedule 8 of Electricity Regulation 2006 | O106: B2B Retailer only | P106: Depends on activity requested
A107: 145 | B107: Install new meter (Type 5 and 6) – Polyphase – Primary plus embedded generation | C107: Installation and provision of a new polyphase Type 5 or 6 meter. Applies where there is a primary metering service plus embedded generation. | D107: NMPPEGU | E107: NMPPEGS | F107: NMPPEGL | G107: NMPPEGI | H107: 8177 | I107: 530.2 | J107: =I107*1.1 -> 583.22 | K107: 530.2 | L107: =K107*1.1 -> 583.22 | M107: Fee Based Service | N107: Fixed fee applies, capped to UR/SR price as per Schedule 8 of Electricity Regulation 2006 | O107: B2B Retailer only | P107: Depends on activity requested
A108: 146 | B108: Install new meter (CT) – Primary | C108: Installation and provision of a new CT meter. Applies where there is a primary metering service. | D108: NMCTPU | E108: NMCTPS | F108: NMCTPL | G108: NMCTPI | H108: 8178 | I108: 2519.1 | J108: =I108*1.1 -> 2771.01 | K108: 2519.1 | L108: =K108*1.1 -> 2771.01 | M108: Fee Based Service | N108: Fixed fee applies, capped to UR/SR price as per Schedule 8 of Electricity Regulation 2006 | O108: B2B Retailer only | P108: Depends on activity requested
...

Sheet ACS Tariff classes & tariffs
F1: 4 | G1: 5 | H1: 6 | I1: 7
D3: Ergon Energy Corporation Limited
D4: 2017-18 ACS tariffs by tariff class
D8: Tariff class | E8: Tariff | F8: Product Codes
F9: Service undertaken | J9: No service undertaken due to customer/retailer fault (Call out fee)
B10: 1 | D10: Fee based services (urban/short rural) | E10: =VLOOKUP(B10,'EECL Price List'!$A$12:$P$172,2,FALSE) -> Application fee - Basic or standard connection | F10: =IF(VLOOKUP($B10,'EECL Price List'!$A$12:$P$172,F$1,FALSE)=0,"",VLOOKUP($B10,'EECL Price List'!$A$12:$P$172,F$1,FALSE)) -> APFSAC | G10: =IF(VLOOKUP($B10,'EECL Price List'!$A$12:$P$172,G$1,FALSE)=0,"",VLOOKUP($B10,'EECL Price List'!$A$12:$P$172,G$1,FALSE)) | J10: =IFERROR(IF(VLOOKUP($C10,'EECL Price List'!$A$12:$P$172,F$1,FALSE)=0,"",VLOOKUP($C10,'EECL Price List'!$A$12:$P$172,F$1,FALSE)),"") | K10: =IFERROR(IF(VLOOKUP($C10,'EECL Price List'!$A$12:$P$172,G$1,FALSE)=0,"",VLOOKUP($C10,'EECL Price List'!$A$12:$P$172,G$1,FALSE)),"")
B11: 2 | E11: =VLOOKUP(B11,'EECL Price List'!$A$12:$P$172,2,FALSE) -> Application fee - Basic or standard connection - Micro-embedded generators | F11: =IF(VLOOKUP($B11,'EECL Price List'!$A$12:$P$172,F$1,FALSE)=0,"",VLOOKUP($B11,'EECL Price List'!$A$12:$P$172,F$1,FALSE)) -> APFMEG | G11: =IF(VLOOKUP($B11,'EECL Price List'!$A$12:$P$172,G$1,FALSE)=0,"",VLOOKUP($B11,'EECL Price List'!$A$12:$P$172,G$1,FALSE)) | J11: =IFERROR(IF(VLOOKUP($C11,'EECL Price List'!$A$12:$P$172,F$1,FALSE)=0,"",VLOOKUP($C11,'EECL Price List'!$A$12:$P$172,F$1,FALSE)),"") | K11: =IFERROR(IF(VLOOKUP($C11,'EECL Price List'!$A$12:$P$172,G$1,FALSE)=0,"",VLOOKUP($C11,'EECL Price List'!$A$12:$P$172,G$1,FALSE)),"")
B12: 3 | E12: =VLOOKUP(B12,'EECL Price List'!$A$12:$P$172,2,FALSE) -> Application fee - Basic or standard connection - Micro-embedded generators - Technical assessment required | F12: =IF(VLOOKUP($B12,'EECL Price List'!$A$12:$P$172,F$1,FALSE)=0,"",VLOOKUP($B12,'EECL Price List'!$A$12:$P$172,F$1,FALSE)) -> APFMTA | G12: =IF(VLOOKUP($B12,'EECL Price List'!$A$12:$P$172,G$1,FALSE)=0,"",VLOOKUP($B12,'EECL Price List'!$A$12:$P$172,G$1,FALSE)) | J12: =IFERROR(IF(VLOOKUP($C12,'EECL Price List'!$A$12:$P$172,F$1,FALSE)=0,"",VLOOKUP($C12,'EECL Price List'!$A$12:$P$172,F$1,FALSE)),"") | K12: =IFERROR(IF(VLOOKUP($C12,'EECL Price List'!$A$12:$P$172,G$1,FALSE)=0,"",VLOOKUP($C12,'EECL Price List'!$A$12:$P$172,G$1,FALSE)),"")
B13: 4 | E13: =VLOOKUP(B13,'EECL Price List'!$A$12:$P$172,2,FALSE) -> Application fee - Real estate development connection | F13: =IF(VLOOKUP($B13,'EECL Price List'!$A$12:$P$172,F$1,FALSE)=0,"",VLOOKUP($B13,'EECL Price List'!$A$12:$P$172,F$1,FALSE)) -> APFRED | G13: =IF(VLOOKUP($B13,'EECL Price List'!$A$12:$P$172,G$1,FALSE)=0,"",VLOOKUP($B13,'EECL Price List'!$A$12:$P$172,G$1,FALSE)) | J13: =IFERROR(IF(VLOOKUP($C13,'EECL Price List'!$A$12:$P$172,F$1,FALSE)=0,"",VLOOKUP($C13,'EECL Price List'!$A$12:$P$172,F$1,FALSE)),"") | K13: =IFERROR(IF(VLOOKUP($C13,'EECL Price List'!$A$12:$P$172,G$1,FALSE)=0,"",VLOOKUP($C13,'EECL Price List'!$A$12:$P$172,G$1,FALSE)),"")
B14: 5 | E14: =VLOOKUP(B14,'EECL Price List'!$A$12:$P$172,2,FALSE) -> Protection and Power Quality assessment prior to connection | F14: =IF(VLOOKUP($B14,'EECL Price List'!$A$12:$P$172,F$1,FALSE)=0,"",VLOOKUP($B14,'EECL Price List'!$A$12:$P$172,F$1,FALSE)) -> PPQA | G14: =IF(VLOOKUP($B14,'EECL Price List'!$A$12:$P$172,G$1,FALSE)=0,"",VLOOKUP($B14,'EECL Price List'!$A$12:$P$172,G$1,FALSE)) | J14: =IFERROR(IF(VLOOKUP($C14,'EECL Price List'!$A$12:$P$172,F$1,FALSE)=0,"",VLOOKUP($C14,'EECL Price List'!$A$12:$P$172,F$1,FALSE)),"") | K14: =IFERROR(IF(VLOOKUP($C14,'EECL Price List'!$A$12:$P$172,G$1,FALSE)=0,"",VLOOKUP($C14,'EECL Price List'!$A$12:$P$172,G$1,FALSE)),"")
B15: 6 | C15: 6-CF | E15: =VLOOKUP(B15,'EECL Price List'!$A$12:$P$172,2,FALSE) -> Temporary connection, not in permanent position - single phase metered - urban/short rural feeders | F15: =IF(VLOOKUP($B15,'EECL Price List'!$A$12:$P$172,F$1,FALSE)=0,"",VLOOKUP($B15,'EECL Price List'!$A$12:$P$172,F$1,FALSE)) -> TBSSPU | G15: =IF(VLOOKUP($B15,'EECL Price List'!$A$12:$P$172,G$1,FALSE)=0,"",VLOOKUP($B15,'EECL Price List'!$A$12:$P$172,G$1,FALSE)) -> TBSSPS | J15: =IFERROR(IF(VLOOKUP($C15,'EECL Price List'!$A$12:$P$172,F$1,FALSE)=0,"",VLOOKUP($C15,'EECL Price List'!$A$12:$P$172,F$1,FALSE)),"") -> CFTBSSPU | K15: =IFERROR(IF(VLOOKUP($C15,'EECL Price List'!$A$12:$P$172,G$1,FALSE)=0,"",VLOOKUP($C15,'EECL Price List'!$A$12:$P$172,G$1,FALSE)),"") -> CFTBSSPS
B16: 8 | C16: 8-CF | E16: =VLOOKUP(B16,'EECL Price List'!$A$12:$P$172,2,FALSE) -> Temporary connection, not in permanent position - multi phase metered - urban/short rural feeders | F16: =IF(VLOOKUP($B16,'EECL Price List'!$A$12:$P$172,F$1,FALSE)=0,"",VLOOKUP($B16,'EECL Price List'!$A$12:$P$172,F$1,FALSE)) -> TBSMPU | G16: =IF(VLOOKUP($B16,'EECL Price List'!$A$12:$P$172,G$1,FALSE)=0,"",VLOOKUP($B16,'EECL Price List'!$A$12:$P$172,G$1,FALSE)) -> TBSMPS | J16: =IFERROR(IF(VLOOKUP($C16,'EECL Price List'!$A$12:$P$172,F$1,FALSE)=0,"",VLOOKUP($C16,'EECL Price List'!$A$12:$P$172,F$1,FALSE)),"") -> CFTBSMPU | K16: =IFERROR(IF(VLOOKUP($C16,'EECL Price List'!$A$12:$P$172,G$1,FALSE)=0,"",VLOOKUP($C16,'EECL Price List'!$A$12:$P$172,G$1,FALSE)),"") -> CFTBSMPS
B17: 10 | C17: 10-CF | E17: =VLOOKUP(B17,'EECL Price List'!$A$12:$P$172,2,FALSE) -> Supply abolishment during business hours - urban/short rural feeders | F17: =IF(VLOOKUP($B17,'EECL Price List'!$A$12:$P$172,F$1,FALSE)=0,"",VLOOKUP($B17,'EECL Price List'!$A$12:$P$172,F$1,FALSE)) -> SUPABOLU | G17: =IF(VLOOKUP($B17,'EECL Price List'!$A$12:$P$172,G$1,FALSE)=0,"",VLOOKUP($B17,'EECL Price List'!$A$12:$P$172,G$1,FALSE)) -> SUPABOLS | J17: =IFERROR(IF(VLOOKUP($C17,'EECL Price List'!$A$12:$P$172,F$1,FALSE)=0,"",VLOOKUP($C17,'EECL Price List'!$A$12:$P$172,F$1,FALSE)),"") -> CFSUPABOLU | K17: =IFERROR(IF(VLOOKUP($C17,'EECL Price List'!$A$12:$P$172,G$1,FALSE)=0,"",VLOOKUP($C17,'EECL Price List'!$A$12:$P$172,G$1,FALSE)),"") -> CFSUPABOLS
B18: 12 | C18: 12-CF | E18: =VLOOKUP(B18,'EECL Price List'!$A$12:$P$172,2,FALSE) -> De-energisation during business hours - urban/short rural feeders | F18: =IF(VLOOKUP($B18,'EECL Price List'!$A$12:$P$172,F$1,FALSE)=0,"",VLOOKUP($B18,'EECL Price List'!$A$12:$P$172,F$1,FALSE)) -> DEENBHU | G18: =IF(VLOOKUP($B18,'EECL Price List'!$A$12:$P$172,G$1,FALSE)=0,"",VLOOKUP($B18,'EECL Price List'!$A$12:$P$172,G$1,FALSE)) -> DEENBHS | J18: =IFERROR(IF(VLOOKUP($C18,'EECL Price List'!$A$12:$P$172,F$1,FALSE)=0,"",VLOOKUP($C18,'EECL Price List'!$A$12:$P$172,F$1,FALSE)),"") -> CFDEENBHU | K18: =IFERROR(IF(VLOOKUP($C18,'EECL Price List'!$A$12:$P$172,G$1,FALSE)=0,"",VLOOKUP($C18,'EECL Price List'!$A$12:$P$172,G$1,FALSE)),"") -> CFDEENBHS
B19: 14 | C19: 14-CF | E19: =VLOOKUP(B19,'EECL Price List'!$A$12:$P$172,2,FALSE) -> Re-energisation during business hours - urban/short rural feeders | F19: =IF(VLOOKUP($B19,'EECL Price List'!$A$12:$P$172,F$1,FALSE)=0,"",VLOOKUP($B19,'EECL Price List'!$A$12:$P$172,F$1,FALSE)) -> REENBHU | G19: =IF(VLOOKUP($B19,'EECL Price List'!$A$12:$P$172,G$1,FALSE)=0,"",VLOOKUP($B19,'EECL Price List'!$A$12:$P$172,G$1,FALSE)) -> REENBHS | J19: =IFERROR(IF(VLOOKUP($C19,'EECL Price List'!$A$12:$P$172,F$1,FALSE)=0,"",VLOOKUP($C19,'EECL Price List'!$A$12:$P$172,F$1,FALSE)),"") -> CFREENBHU | K19: =IFERROR(IF(VLOOKUP($C19,'EECL Price List'!$A$12:$P$172,G$1,FALSE)=0,"",VLOOKUP($C19,'EECL Price List'!$A$12:$P$172,G$1,FALSE)),"") -> CFREENBHS
B20: 16 | C20: 16-CF | E20: =VLOOKUP(B20,'EECL Price List'!$A$12:$P$172,2,FALSE) -> Re-energisation during business hours - after de-energisation for debt - urban/short rural feeders | F20: =IF(VLOOKUP($B20,'EECL Price List'!$A$12:$P$172,F$1,FALSE)=0,"",VLOOKUP($B20,'EECL Price List'!$A$12:$P$172,F$1,FALSE)) -> REDDBHU | G20: =IF(VLOOKUP($B20,'EECL Price List'!$A$12:$P$172,G$1,FALSE)=0,"",VLOOKUP($B20,'EECL Price List'!$A$12:$P$172,G$1,FALSE)) -> REDDBHS | J20: =IFERROR(IF(VLOOKUP($C20,'EECL Price List'!$A$12:$P$172,F$1,FALSE)=0,"",VLOOKUP($C20,'EECL Price List'!$A$12:$P$172,F$1,FALSE)),"") -> CFREDDBHU | K20: =IFERROR(IF(VLOOKUP($C20,'EECL Price List'!$A$12:$P$172,G$1,FALSE)=0,"",VLOOKUP($C20,'EECL Price List'!$A$12:$P$172,G$1,FALSE)),"") -> CFREDDBHS
B21: 18 | E21: =VLOOKUP(B21,'EECL Price List'!$A$12:$P$172,2,FALSE) -> Accreditation of alternative service providers - real estate developments | F21: =IF(VLOOKUP($B21,'EECL Price List'!$A$12:$P$172,F$1,FALSE)=0,"",VLOOKUP($B21,'EECL Price List'!$A$12:$P$172,F$1,FALSE)) -> ASPRED | G21: =IF(VLOOKUP($B21,'EECL Price List'!$A$12:$P$172,G$1,FALSE)=0,"",VLOOKUP($B21,'EECL Price List'!$A$12:$P$172,G$1,FALSE)) | J21: =IFERROR(IF(VLOOKUP($C21,'EECL Price List'!$A$12:$P$172,F$1,FALSE)=0,"",VLOOKUP($C21,'EECL Price List'!$A$12:$P$172,F$1,FALSE)),"") | K21: =IFERROR(IF(VLOOKUP($C21,'EECL Price List'!$A$12:$P$172,G$1,FALSE)=0,"",VLOOKUP($C21,'EECL Price List'!$A$12:$P$172,G$1,FALSE)),"")
B22: 19 | C22: 19-CF | E22: =VLOOKUP(B22,'EECL Price List'!$A$12:$P$172,2,FALSE) -> Install replacement meter (Type 5 and 6) – Single phase – urban/short rural feeder | F22: =IF(VLOOKUP($B22,'EECL Price List'!$A$12:$P$172,F$1,FALSE)=0,"",VLOOKUP($B22,'EECL Price List'!$A$12:$P$172,F$1,FALSE)) -> MSNGLU | G22: =IF(VLOOKUP($B22,'EECL Price List'!$A$12:$P$172,G$1,FALSE)=0,"",VLOOKUP($B22,'EECL Price List'!$A$12:$P$172,G$1,FALSE)) -> MSNGLS | J22: =IFERROR(IF(VLOOKUP($C22,'EECL Price List'!$A$12:$P$172,F$1,FALSE)=0,"",VLOOKUP($C22,'EECL Price List'!$A$12:$P$172,F$1,FALSE)),"") -> CFMSNGLU | K22: =IFERROR(IF(VLOOKUP($C22,'EECL Price List'!$A$12:$P$172,G$1,FALSE)=0,"",VLOOKUP($C22,'EECL Price List'!$A$12:$P$172,G$1,FALSE)),"") -> CFMSNGLS
B23: 21 | C23: 21-CF | E23: =VLOOKUP(B23,'EECL Price List'!$A$12:$P$172,2,FALSE) -> Install replacement meter (Type 5 and 6) – Dual element – urban/short rural feeder | F23: =IF(VLOOKUP($B23,'EECL Price List'!$A$12:$P$172,F$1,FALSE)=0,"",VLOOKUP($B23,'EECL Price List'!$A$12:$P$172,F$1,FALSE)) -> MDUALU | G23: =IF(VLOOKUP($B23,'EECL Price List'!$A$12:$P$172,G$1,FALSE)=0,"",VLOOKUP($B23,'EECL Price List'!$A$12:$P$172,G$1,FALSE)) -> MDUALS | J23: =IFERROR(IF(VLOOKUP($C23,'EECL Price List'!$A$12:$P$172,F$1,FALSE)=0,"",VLOOKUP($C23,'EECL Price List'!$A$12:$P$172,F$1,FALSE)),"") -> CFMDUALU | K23: =IFERROR(IF(VLOOKUP($C23,'EECL Price List'!$A$12:$P$172,G$1,FALSE)=0,"",VLOOKUP($C23,'EECL Price List'!$A$12:$P$172,G$1,FALSE)),"") -> CFMDUALS
B24: 23 | C24: 23-CF | E24: =VLOOKUP(B24,'EECL Price List'!$A$12:$P$172,2,FALSE) -> Install replacement meter (Type 5 and 6) – Polyphase – urban/short rural feeder | F24: =IF(VLOOKUP($B24,'EECL Price List'!$A$12:$P$172,F$1,FALSE)=0,"",VLOOKUP($B24,'EECL Price List'!$A$12:$P$172,F$1,FALSE)) -> MTHREU | G24: =IF(VLOOKUP($B24,'EECL Price List'!$A$12:$P$172,G$1,FALSE)=0,"",VLOOKUP($B24,'EECL Price List'!$A$12:$P$172,G$1,FALSE)) -> MTHRES | J24: =IFERROR(IF(VLOOKUP($C24,'EECL Price List'!$A$12:$P$172,F$1,FALSE)=0,"",VLOOKUP($C24,'EECL Price List'!$A$12:$P$172,F$1,FALSE)),"") -> CFMTHREU | K24: =IFERROR(IF(VLOOKUP($C24,'EECL Price List'!$A$12:$P$172,G$1,FALSE)=0,"",VLOOKUP($C24,'EECL Price List'!$A$12:$P$172,G$1,FALSE)),"") -> CFMTHRES
B25: 25 | C25: 25-CF | E25: =VLOOKUP(B25,'EECL Price List'!$A$12:$P$172,2,FALSE) -> Install replacement meter (CT) – urban/short rural feeder | F25: =IF(VLOOKUP($B25,'EECL Price List'!$A$12:$P$172,F$1,FALSE)=0,"",VLOOKUP($B25,'EECL Price List'!$A$12:$P$172,F$1,FALSE)) -> MCTU | G25: =IF(VLOOKUP($B25,'EECL Price List'!$A$12:$P$172,G$1,FALSE)=0,"",VLOOKUP($B25,'EECL Price List'!$A$12:$P$172,G$1,FALSE)) -> MCTS | J25: =IFERROR(IF(VLOOKUP($C25,'EECL Price List'!$A$12:$P$172,F$1,FALSE)=0,"",VLOOKUP($C25,'EECL Price List'!$A$12:$P$172,F$1,FALSE)),"") -> CFMCTU | K25: =IFERROR(IF(VLOOKUP($C25,'EECL Price List'!$A$12:$P$172,G$1,FALSE)=0,"",VLOOKUP($C25,'EECL Price List'!$A$12:$P$172,G$1,FALSE)),"") -> CFMCTS
B26: 140 | C26: 157-CF | E26: =VLOOKUP(B26,'EECL Price List'!$A$12:$P$172,2,FALSE) -> Install new meter (Type 5 and 6) – Single phase – Primary | F26: =IF(VLOOKUP($B26,'EECL Price List'!$A$12:$P$172,F$1,FALSE)=0,"",VLOOKUP($B26,'EECL Price List'!$A$12:$P$172,F$1,FALSE)) -> NMSPU | G26: =IF(VLOOKUP($B26,'EECL Price List'!$A$12:$P$172,G$1,FALSE)=0,"",VLOOKUP($B26,'EECL Price List'!$A$12:$P$172,G$1,FALSE)) -> NMSPS | J26: =IFERROR(IF(VLOOKUP($C26,'EECL Price List'!$A$12:$P$172,F$1,FALSE)=0,"",VLOOKUP($C26,'EECL Price List'!$A$12:$P$172,F$1,FALSE)),"") -> CFNMSPU | K26: =IFERROR(IF(VLOOKUP($C26,'EECL Price List'!$A$12:$P$172,G$1,FALSE)=0,"",VLOOKUP($C26,'EECL Price List'!$A$12:$P$172,G$1,FALSE)),"") -> CFNMSPS
B27: 141 | C27: 157-CF | E27: =VLOOKUP(B27,'EECL Price List'!$A$12:$P$172,2,FALSE) -> Install new meter (Type 5 and 6) – Single phase – Primary plus embedded generation | F27: =IF(VLOOKUP($B27,'EECL Price List'!$A$12:$P$172,F$1,FALSE)=0,"",VLOOKUP($B27,'EECL Price List'!$A$12:$P$172,F$1,FALSE)) -> NMSPEGU | G27: =IF(VLOOKUP($B27,'EECL Price List'!$A$12:$P$172,G$1,FALSE)=0,"",VLOOKUP($B27,'EECL Price List'!$A$12:$P$172,G$1,FALSE)) -> NMSPEGS | J27: =IFERROR(IF(VLOOKUP($C27,'EECL Price List'!$A$12:$P$172,F$1,FALSE)=0,"",VLOOKUP($C27,'EECL Price List'!$A$12:$P$172,F$1,FALSE)),"") -> CFNMSPU | K27: =IFERROR(IF(VLOOKUP($C27,'EECL Price List'!$A$12:$P$172,G$1,FALSE)=0,"",VLOOKUP($C27,'EECL Price List'!$A$12:$P$172,G$1,FALSE)),"") -> CFNMSPS
B28: 142 | C28: 158-CF | E28: =VLOOKUP(B28,'EECL Price List'!$A$12:$P$172,2,FALSE) -> Install new meter (Type 5 and 6) – Dual element – Primary plus controlled load | F28: =IF(VLOOKUP($B28,'EECL Price List'!$A$12:$P$172,F$1,FALSE)=0,"",VLOOKUP($B28,'EECL Price List'!$A$12:$P$172,F$1,FALSE)) -> NMDPCLU | G28: =IF(VLOOKUP($B28,'EECL Price List'!$A$12:$P$172,G$1,FALSE)=0,"",VLOOKUP($B28,'EECL Price List'!$A$12:$P$172,G$1,FALSE)) -> NMDPCLS | J28: =IFERROR(IF(VLOOKUP($C28,'EECL Price List'!$A$12:$P$172,F$1,FALSE)=0,"",VLOOKUP($C28,'EECL Price List'!$A$12:$P$172,F$1,FALSE)),"") -> CFNMDUALU | K28: =IFERROR(IF(VLOOKUP($C28,'EECL Price List'!$A$12:$P$172,G$1,FALSE)=0,"",VLOOKUP($C28,'EECL Price List'!$A$12:$P$172,G$1,FALSE)),"") -> CFNMDUALS
B29: 143 | C29: 158-CF | E29: =VLOOKUP(B29,'EECL Price List'!$A$12:$P$172,2,FALSE) -> Install new meter (Type 5 and 6) – Dual element – Primary plus controlled load plus embedded generation | F29: =IF(VLOOKUP($B29,'EECL Price List'!$A$12:$P$172,F$1,FALSE)=0,"",VLOOKUP($B29,'EECL Price List'!$A$12:$P$172,F$1,FALSE)) -> NMDPCLEGU | G29: =IF(VLOOKUP($B29,'EECL Price List'!$A$12:$P$172,G$1,FALSE)=0,"",VLOOKUP($B29,'EECL Price List'!$A$12:$P$172,G$1,FALSE)) -> NMDPCLEGS | J29: =IFERROR(IF(VLOOKUP($C29,'EECL Price List'!$A$12:$P$172,F$1,FALSE)=0,"",VLOOKUP($C29,'EECL Price List'!$A$12:$P$172,F$1,FALSE)),"") -> CFNMDUALU | K29: =IFERROR(IF(VLOOKUP($C29,'EECL Price List'!$A$12:$P$172,G$1,FALSE)=0,"",VLOOKUP($C29,'EECL Price List'!$A$12:$P$172,G$1,FALSE)),"") -> CFNMDUALS
B30: 144 | C30: 159-CF | E30: =VLOOKUP(B30,'EECL Price List'!$A$12:$P$172,2,FALSE) -> Install new meter (Type 5 and 6) – Polyphase – Primary | F30: =IF(VLOOKUP($B30,'EECL Price List'!$A$12:$P$172,F$1,FALSE)=0,"",VLOOKUP($B30,'EECL Price List'!$A$12:$P$172,F$1,FALSE)) -> NMPPU | G30: =IF(VLOOKUP($B30,'EECL Price List'!$A$12:$P$172,G$1,FALSE)=0,"",VLOOKUP($B30,'EECL Price List'!$A$12:$P$172,G$1,FALSE)) -> NMPPS | J30: =IFERROR(IF(VLOOKUP($C30,'EECL Price List'!$A$12:$P$172,F$1,FALSE)=0,"",VLOOKUP($C30,'EECL Price List'!$A$12:$P$172,F$1,FALSE)),"") -> CFNMTHREU | K30: =IFERROR(IF(VLOOKUP($C30,'EECL Price List'!$A$12:$P$172,G$1,FALSE)=0,"",VLOOKUP($C30,'EECL Price List'!$A$12:$P$172,G$1,FALSE)),"") -> CFNMTHRES
B31: 145 | C31: 159-CF | E31: =VLOOKUP(B31,'EECL Price List'!$A$12:$P$172,2,FALSE) -> Install new meter (Type 5 and 6) – Polyphase – Primary plus embedded generation | F31: =IF(VLOOKUP($B31,'EECL Price List'!$A$12:$P$172,F$1,FALSE)=0,"",VLOOKUP($B31,'EECL Price List'!$A$12:$P$172,F$1,FALSE)) -> NMPPEGU | G31: =IF(VLOOKUP($B31,'EECL Price List'!$A$12:$P$172,G$1,FALSE)=0,"",VLOOKUP($B31,'EECL Price List'!$A$12:$P$172,G$1,FALSE)) -> NMPPEGS | J31: =IFERROR(IF(VLOOKUP($C31,'EECL Price List'!$A$12:$P$172,F$1,FALSE)=0,"",VLOOKUP($C31,'EECL Price List'!$A$12:$P$172,F$1,FALSE)),"") -> CFNMTHREU | K31: =IFERROR(IF(VLOOKUP($C31,'EECL Price List'!$A$12:$P$172,G$1,FALSE)=0,"",VLOOKUP($C31,'EECL Price List'!$A$12:$P$172,G$1,FALSE)),"") -> CFNMTHRES
B32: 146 | C32: 160-CF | E32: =VLOOKUP(B32,'EECL Price List'!$A$12:$P$172,2,FALSE) -> Install new meter (CT) – Primary | F32: =IF(VLOOKUP($B32,'EECL Price List'!$A$12:$P$172,F$1,FALSE)=0,"",VLOOKUP($B32,'EECL Price List'!$A$12:$P$172,F$1,FALSE)) -> NMCTPU | G32: =IF(VLOOKUP($B32,'EECL Price List'!$A$12:$P$172,G$1,FALSE)=0,"",VLOOKUP($B32,'EECL Price List'!$A$12:$P$172,G$1,FALSE)) -> NMCTPS | J32: =IFERROR(IF(VLOOKUP($C32,'EECL Price List'!$A$12:$P$172,F$1,FALSE)=0,"",VLOOKUP($C32,'EECL Price List'!$A$12:$P$172,F$1,FALSE)),"") -> CFNMCTU | K32: =IFERROR(IF(VLOOKUP($C32,'EECL Price List'!$A$12:$P$172,G$1,FALSE)=0,"",VLOOKUP($C32,'EECL Price List'!$A$12:$P$172,G$1,FALSE)),"") -> CFNMCTS
B33: 147 | C33: 160-CF | E33: =VLOOKUP(B33,'EECL Price List'!$A$12:$P$172,2,FALSE) -> Install new meter (CT) – Primary plus embedded generation | F33: =IF(VLOOKUP($B33,'EECL Price List'!$A$12:$P$172,F$1,FALSE)=0,"",VLOOKUP($B33,'EECL Price List'!$A$12:$P$172,F$1,FALSE)) -> NMCTPEGU | G33: =IF(VLOOKUP($B33,'EECL Price List'!$A$12:$P$172,G$1,FALSE)=0,"",VLOOKUP($B33,'EECL Price List'!$A$12:$P$172,G$1,FALSE)) -> NMCTPEGS | J33: =IFERROR(IF(VLOOKUP($C33,'EECL Price List'!$A$12:$P$172,F$1,FALSE)=0,"",VLOOKUP($C33,'EECL Price List'!$A$12:$P$172,F$1,FALSE)),"") -> CFNMCTU | K33: =IFERROR(IF(VLOOKUP($C33,'EECL Price List'!$A$12:$P$172,G$1,FALSE)=0,"",VLOOKUP($C33,'EECL Price List'!$A$12:$P$172,G$1,FALSE)),"") -> CFNMCTS
... B42: 156 | C42: 160-CF | E42: =VLOOKUP(B42,'EECL Price List'!$A$12:$P$172,2,FALSE) -> Install new meter (CT) to accommodate embedded generation installation | F42: =IF(VLOOKUP($B42,'EECL Price List'!$A$12:$P$172,F$1,FALSE)=0,"",VLOOKUP($B42,'EECL Price List'!$A$12:$P$172,F$1,FALSE)) -> NCTAEGU | G42: =IF(VLOOKUP($B42,'EECL Price List'!$A$12:$P$172,G$1,FALSE)=0,"",VLOOKUP($B42,'EECL Price List'!$A$12:$P$172,G$1,FALSE)) -> NCTAEGS | J42: =IFERROR(IF(VLOOKUP($C42,'EECL Price List'!$A$12:$P$172,F$1,FALSE)=0,"",VLOOKUP($C42,'EECL Price List'!$A$12:$P$172,F$1,FALSE)),"") -> CFNMCTU | K42: =IFERROR(IF(VLOOKUP($C42,'EECL Price List'!$A$12:$P$172,G$1,FALSE)=0,"",VLOOKUP($C42,'EECL Price List'!$A$12:$P$172,G$1,FALSE)),"") -> CFNMCTS
B43: 1 | D43: Fee based services (long rural/isolated) | E43: =VLOOKUP(B43,'EECL Price List'!$A$12:$P$172,2,FALSE) -> Application fee - Basic or standard connection | F43: =IF(VLOOKUP($B43,'EECL Price List'!$A$12:$P$172,F$1,FALSE)=0,"",VLOOKUP($B43,'EECL Price List'!$A$12:$P$172,F$1,FALSE)) -> APFSAC | G43: =IF(VLOOKUP($B43,'EECL Price List'!$A$12:$P$172,I$1,FALSE)=0,"",VLOOKUP($B43,'EECL Price List'!$A$12:$P$172,I$1,FALSE))
B44: 2 | E44: =VLOOKUP(B44,'EECL Price List'!$A$12:$P$172,2,FALSE) -> Application fee - Basic or standard connection - Micro-embedded generators | F44: =IF(VLOOKUP($B44,'EECL Price List'!$A$12:$P$172,F$1,FALSE)=0,"",VLOOKUP($B44,'EECL Price List'!$A$12:$P$172,F$1,FALSE)) -> APFMEG | G44: =IF(VLOOKUP($B44,'EECL Price List'!$A$12:$P$172,I$1,FALSE)=0,"",VLOOKUP($B44,'EECL Price List'!$A$12:$P$172,I$1,FALSE))
B45: 3 | E45: =VLOOKUP(B45,'EECL Price List'!$A$12:$P$172,2,FALSE) -> Application fee - Basic or standard connection - Micro-embedded generators - Technical assessment required | F45: =IF(VLOOKUP($B45,'EECL Price List'!$A$12:$P$172,F$1,FALSE)=0,"",VLOOKUP($B45,'EECL Price List'!$A$12:$P$172,F$1,FALSE)) -> APFMTA | G45: =IF(VLOOKUP($B45,'EECL Price List'!$A$12:$P$172,I$1,FALSE)=0,"",VLOOKUP($B45,'EECL Price List'!$A$12:$P$172,I$1,FALSE))
B46: 4 | E46: =VLOOKUP(B46,'EECL Price List'!$A$12:$P$172,2,FALSE) -> Application fee - Real estate development connection | F46: =IF(VLOOKUP($B46,'EECL Price List'!$A$12:$P$172,F$1,FALSE)=0,"",VLOOKUP($B46,'EECL Price List'!$A$12:$P$172,F$1,FALSE)) -> APFRED | G46: =IF(VLOOKUP($B46,'EECL Price List'!$A$12:$P$172,I$1,FALSE)=0,"",VLOOKUP($B46,'EECL Price List'!$A$12:$P$172,I$1,FALSE))
B47: 5 | E47: =VLOOKUP(B47,'EECL Price List'!$A$12:$P$172,2,FALSE) -> Protection and Power Quality assessment prior to connection | F47: =IF(VLOOKUP($B47,'EECL Price List'!$A$12:$P$172,F$1,FALSE)=0,"",VLOOKUP($B47,'EECL Price List'!$A$12:$P$172,F$1,FALSE)) -> PPQA | G47: =IF(VLOOKUP($B47,'EECL Price List'!$A$12:$P$172,I$1,FALSE)=0,"",VLOOKUP($B47,'EECL Price List'!$A$12:$P$172,I$1,FALSE))
B48: 7 | C48: 7-CF | E48: =VLOOKUP(B48,'EECL Price List'!$A$12:$P$172,2,FALSE) -> Temporary connection, not in permanent position - single phase metered - long rural/isolated feeders | F48: =IF(VLOOKUP($B48,'EECL Price List'!$A$12:$P$172,H$1,FALSE)=0,"",VLOOKUP($B48,'EECL Price List'!$A$12:$P$172,H$1,FALSE)) -> TBSSPL | G48: =IF(VLOOKUP($B48,'EECL Price List'!$A$12:$P$172,I$1,FALSE)=0,"",VLOOKUP($B48,'EECL Price List'!$A$12:$P$172,I$1,FALSE)) -> TBSSPI | J48: =IF(VLOOKUP($C48,'EECL Price List'!$A$12:$P$172,H$1,FALSE)=0,"",VLOOKUP($C48,'EECL Price List'!$A$12:$P$172,H$1,FALSE)) -> CFTBSSPL | K48: =IF(VLOOKUP($C48,'EECL Price List'!$A$12:$P$172,I$1,FALSE)=0,"",VLOOKUP($C48,'EECL Price List'!$A$12:$P$172,I$1,FALSE)) -> CFTBSSPI
B49: 9 | C49: 9-CF | E49: =VLOOKUP(B49,'EECL Price List'!$A$12:$P$172,2,FALSE) -> Temporary connection, not in permanent position - multi phase metered - long rural/isolated feeders | F49: =IF(VLOOKUP($B49,'EECL Price List'!$A$12:$P$172,H$1,FALSE)=0,"",VLOOKUP($B49,'EECL Price List'!$A$12:$P$172,H$1,FALSE)) -> TBSMPL | G49: =IF(VLOOKUP($B49,'EECL Price List'!$A$12:$P$172,I$1,FALSE)=0,"",VLOOKUP($B49,'EECL Price List'!$A$12:$P$172,I$1,FALSE)) -> TBSMPI | J49: =IF(VLOOKUP($C49,'EECL Price List'!$A$12:$P$172,H$1,FALSE)=0,"",VLOOKUP($C49,'EECL Price List'!$A$12:$P$172,H$1,FALSE)) -> CFTBSMPL | K49: =IF(VLOOKUP($C49,'EECL Price List'!$A$12:$P$172,I$1,FALSE)=0,"",VLOOKUP($C49,'EECL Price List'!$A$12:$P$172,I$1,FALSE)) -> CFTBSMPI
B50: 11 | C50: 11-CF | E50: =VLOOKUP(B50,'EECL Price List'!$A$12:$P$172,2,FALSE) -> Supply abolishment during business hours - long rural/isolated feeders | F50: =IF(VLOOKUP($B50,'EECL Price List'!$A$12:$P$172,H$1,FALSE)=0,"",VLOOKUP($B50,'EECL Price List'!$A$12:$P$172,H$1,FALSE)) -> SUPABOLL | G50: =IF(VLOOKUP($B50,'EECL Price List'!$A$12:$P$172,I$1,FALSE)=0,"",VLOOKUP($B50,'EECL Price List'!$A$12:$P$172,I$1,FALSE)) -> SUPABOLI | J50: =IF(VLOOKUP($C50,'EECL Price List'!$A$12:$P$172,H$1,FALSE)=0,"",VLOOKUP($C50,'EECL Price List'!$A$12:$P$172,H$1,FALSE)) -> CFSUPABOLL | K50: =IF(VLOOKUP($C50,'EECL Price List'!$A$12:$P$172,I$1,FALSE)=0,"",VLOOKUP($C50,'EECL Price List'!$A$12:$P$172,I$1,FALSE)) -> CFSUPABOLI
B51: 13 | C51: 13-CF | E51: =VLOOKUP(B51,'EECL Price List'!$A$12:$P$172,2,FALSE) -> De-energisation during business hours - long rural/isolated feeders | F51: =IF(VLOOKUP($B51,'EECL Price List'!$A$12:$P$172,H$1,FALSE)=0,"",VLOOKUP($B51,'EECL Price List'!$A$12:$P$172,H$1,FALSE)) -> DEENBHL | G51: =IF(VLOOKUP($B51,'EECL Price List'!$A$12:$P$172,I$1,FALSE)=0,"",VLOOKUP($B51,'EECL Price List'!$A$12:$P$172,I$1,FALSE)) -> DEENBHI | J51: =IF(VLOOKUP($C51,'EECL Price List'!$A$12:$P$172,H$1,FALSE)=0,"",VLOOKUP($C51,'EECL Price List'!$A$12:$P$172,H$1,FALSE)) -> CFDEENBHL | K51: =IF(VLOOKUP($C51,'EECL Price List'!$A$12:$P$172,I$1,FALSE)=0,"",VLOOKUP($C51,'EECL Price List'!$A$12:$P$172,I$1,FALSE)) -> CFDEENBHI
B52: 15 | C52: 15-CF | E52: =VLOOKUP(B52,'EECL Price List'!$A$12:$P$172,2,FALSE) -> Re-energisation during business hours - long rural/isolated feeders | F52: =IF(VLOOKUP($B52,'EECL Price List'!$A$12:$P$172,H$1,FALSE)=0,"",VLOOKUP($B52,'EECL Price List'!$A$12:$P$172,H$1,FALSE)) -> REENBHL | G52: =IF(VLOOKUP($B52,'EECL Price List'!$A$12:$P$172,I$1,FALSE)=0,"",VLOOKUP($B52,'EECL Price List'!$A$12:$P$172,I$1,FALSE)) -> REENBHI | J52: =IF(VLOOKUP($C52,'EECL Price List'!$A$12:$P$172,H$1,FALSE)=0,"",VLOOKUP($C52,'EECL Price List'!$A$12:$P$172,H$1,FALSE)) -> CFREENBHL | K52: =IF(VLOOKUP($C52,'EECL Price List'!$A$12:$P$172,I$1,FALSE)=0,"",VLOOKUP($C52,'EECL Price List'!$A$12:$P$172,I$1,FALSE)) -> CFREENBHI
B53: 17 | C53: 17-CF | E53: =VLOOKUP(B53,'EECL Price List'!$A$12:$P$172,2,FALSE) -> Re-energisation during business hours - after de-energisation for debt - long rural/isolated feeders | F53: =IF(VLOOKUP($B53,'EECL Price List'!$A$12:$P$172,H$1,FALSE)=0,"",VLOOKUP($B53,'EECL Price List'!$A$12:$P$172,H$1,FALSE)) -> REDDBHL | G53: =IF(VLOOKUP($B53,'EECL Price List'!$A$12:$P$172,I$1,FALSE)=0,"",VLOOKUP($B53,'EECL Price List'!$A$12:$P$172,I$1,FALSE)) -> REDDBHI | J53: =IF(VLOOKUP($C53,'EECL Price List'!$A$12:$P$172,H$1,FALSE)=0,"",VLOOKUP($C53,'EECL Price List'!$A$12:$P$172,H$1,FALSE)) -> CFREDDBHL | K53: =IF(VLOOKUP($C53,'EECL Price List'!$A$12:$P$172,I$1,FALSE)=0,"",VLOOKUP($C53,'EECL Price List'!$A$12:$P$172,I$1,FALSE)) -> CFREDDBHI
B54: 18 | E54: =VLOOKUP(B54,'EECL Price List'!$A$12:$P$172,2,FALSE) -> Accreditation of alternative service providers - real estate developments | F54: =IF(VLOOKUP($B54,'EECL Price List'!$A$12:$P$172,F$1,FALSE)=0,"",VLOOKUP($B54,'EECL Price List'!$A$12:$P$172,F$1,FALSE)) -> ASPRED | G54: =IF(VLOOKUP($B54,'EECL Price List'!$A$12:$P$172,I$1,FALSE)=0,"",VLOOKUP($B54,'EECL Price List'!$A$12:$P$172,I$1,FALSE))
B55: 20 | C55: 20-CF | E55: =VLOOKUP(B55,'EECL Price List'!$A$12:$P$172,2,FALSE) -> Install replacement meter (Type 5 and 6) – Single phase – long rural/isolated feeder | F55: =IF(VLOOKUP($B55,'EECL Price List'!$A$12:$P$172,H$1,FALSE)=0,"",VLOOKUP($B55,'EECL Price List'!$A$12:$P$172,H$1,FALSE)) -> MSNGLL | G55: =IF(VLOOKUP($B55,'EECL Price List'!$A$12:$P$172,I$1,FALSE)=0,"",VLOOKUP($B55,'EECL Price List'!$A$12:$P$172,I$1,FALSE)) -> MSNGLI | J55: =IF(VLOOKUP($C55,'EECL Price List'!$A$12:$P$172,H$1,FALSE)=0,"",VLOOKUP($C55,'EECL Price List'!$A$12:$P$172,H$1,FALSE)) -> CFMSNGLL | K55: =IF(VLOOKUP($C55,'EECL Price List'!$A$12:$P$172,I$1,FALSE)=0,"",VLOOKUP($C55,'EECL Price List'!$A$12:$P$172,I$1,FALSE)) -> CFMSNGLI
B56: 22 | C56: 22-CF | E56: =VLOOKUP(B56,'EECL Price List'!$A$12:$P$172,2,FALSE) -> Install replacement meter (Type 5 and 6) – Dual element – long rural/isolated feeder | F56: =IF(VLOOKUP($B56,'EECL Price List'!$A$12:$P$172,H$1,FALSE)=0,"",VLOOKUP($B56,'EECL Price List'!$A$12:$P$172,H$1,FALSE)) -> MDUALL | G56: =IF(VLOOKUP($B56,'EECL Price List'!$A$12:$P$172,I$1,FALSE)=0,"",VLOOKUP($B56,'EECL Price List'!$A$12:$P$172,I$1,FALSE)) -> MDUALI | J56: =IF(VLOOKUP($C56,'EECL Price List'!$A$12:$P$172,H$1,FALSE)=0,"",VLOOKUP($C56,'EECL Price List'!$A$12:$P$172,H$1,FALSE)) -> CFMDUALL | K56: =IF(VLOOKUP($C56,'EECL Price List'!$A$12:$P$172,I$1,FALSE)=0,"",VLOOKUP($C56,'EECL Price List'!$A$12:$P$172,I$1,FALSE)) -> CFMDUALI
B57: 24 | C57: 24-CF | E57: =VLOOKUP(B57,'EECL Price List'!$A$12:$P$172,2,FALSE) -> Install replacement meter (Type 5 and 6) – Polyphase – long rural/isolated feeder | F57: =IF(VLOOKUP($B57,'EECL Price List'!$A$12:$P$172,H$1,FALSE)=0,"",VLOOKUP($B57,'EECL Price List'!$A$12:$P$172,H$1,FALSE)) -> MTHREL | G57: =IF(VLOOKUP($B57,'EECL Price List'!$A$12:$P$172,I$1,FALSE)=0,"",VLOOKUP($B57,'EECL Price List'!$A$12:$P$172,I$1,FALSE)) -> MTHREI | J57: =IF(VLOOKUP($C57,'EECL Price List'!$A$12:$P$172,H$1,FALSE)=0,"",VLOOKUP($C57,'EECL Price List'!$A$12:$P$172,H$1,FALSE)) -> CFMTHREL | K57: =IF(VLOOKUP($C57,'EECL Price List'!$A$12:$P$172,I$1,FALSE)=0,"",VLOOKUP($C57,'EECL Price List'!$A$12:$P$172,I$1,FALSE)) -> CFMTHREI
B58: 26 | C58: 26-CF | E58: =VLOOKUP(B58,'EECL Price List'!$A$12:$P$172,2,FALSE) -> Install replacement meter (CT) – long rural/isolated feeder | F58: =IF(VLOOKUP($B58,'EECL Price List'!$A$12:$P$172,H$1,FALSE)=0,"",VLOOKUP($B58,'EECL Price List'!$A$12:$P$172,H$1,FALSE)) -> MCTL | G58: =IF(VLOOKUP($B58,'EECL Price List'!$A$12:$P$172,I$1,FALSE)=0,"",VLOOKUP($B58,'EECL Price List'!$A$12:$P$172,I$1,FALSE)) -> MCTI | J58: =IF(VLOOKUP($C58,'EECL Price List'!$A$12:$P$172,H$1,FALSE)=0,"",VLOOKUP($C58,'EECL Price List'!$A$12:$P$172,H$1,FALSE)) -> CFMCTL | K58: =IF(VLOOKUP($C58,'EECL Price List'!$A$12:$P$172,I$1,FALSE)=0,"",VLOOKUP($C58,'EECL Price List'!$A$12:$P$172,I$1,FALSE)) -> CFMCTI
B59: 140 | C59: 157-CF | E59: =VLOOKUP(B59,'EECL Price List'!$A$12:$P$172,2,FALSE) -> Install new meter (Type 5 and 6) – Single phase – Primary | F59: =IF(VLOOKUP($B59,'EECL Price List'!$A$12:$P$172,H$1,FALSE)=0,"",VLOOKUP($B59,'EECL Price List'!$A$12:$P$172,H$1,FALSE)) -> NMSPL | G59: =IF(VLOOKUP($B59,'EECL Price List'!$A$12:$P$172,I$1,FALSE)=0,"",VLOOKUP($B59,'EECL Price List'!$A$12:$P$172,I$1,FALSE)) -> NMSPI | J59: =IF(VLOOKUP($C59,'EECL Price List'!$A$12:$P$172,H$1,FALSE)=0,"",VLOOKUP($C59,'EECL Price List'!$A$12:$P$172,H$1,FALSE)) -> CFNMSPL | K59: =IF(VLOOKUP($C59,'EECL Price List'!$A$12:$P$172,I$1,FALSE)=0,"",VLOOKUP($C59,'EECL Price List'!$A$12:$P$172,I$1,FALSE)) -> CFNMSPI
B60: 141 | C60: 157-CF | E60: =VLOOKUP(B60,'EECL Price List'!$A$12:$P$172,2,FALSE) -> Install new meter (Type 5 and 6) – Single phase – Primary plus embedded generation | F60: =IF(VLOOKUP($B60,'EECL Price List'!$A$12:$P$172,H$1,FALSE)=0,"",VLOOKUP($B60,'EECL Price List'!$A$12:$P$172,H$1,FALSE)) -> NMSPEGL | G60: =IF(VLOOKUP($B60,'EECL Price List'!$A$12:$P$172,I$1,FALSE)=0,"",VLOOKUP($B60,'EECL Price List'!$A$12:$P$172,I$1,FALSE)) -> NMSPEGI | J60: =IF(VLOOKUP($C60,'EECL Price List'!$A$12:$P$172,H$1,FALSE)=0,"",VLOOKUP($C60,'EECL Price List'!$A$12:$P$172,H$1,FALSE)) -> CFNMSPL | K60: =IF(VLOOKUP($C60,'EECL Price List'!$A$12:$P$172,I$1,FALSE)=0,"",VLOOKUP($C60,'EECL Price List'!$A$12:$P$172,I$1,FALSE)) -> CFNMSPI
B61: 142 | C61: 158-CF | E61: =VLOOKUP(B61,'EECL Price List'!$A$12:$P$172,2,FALSE) -> Install new meter (Type 5 and 6) – Dual element – Primary plus controlled load | F61: =IF(VLOOKUP($B61,'EECL Price List'!$A$12:$P$172,H$1,FALSE)=0,"",VLOOKUP($B61,'EECL Price List'!$A$12:$P$172,H$1,FALSE)) -> NMDPCLL | G61: =IF(VLOOKUP($B61,'EECL Price List'!$A$12:$P$172,I$1,FALSE)=0,"",VLOOKUP($B61,'EECL Price List'!$A$12:$P$172,I$1,FALSE)) -> NMDPCLI | J61: =IF(VLOOKUP($C61,'EECL Price List'!$A$12:$P$172,H$1,FALSE)=0,"",VLOOKUP($C61,'EECL Price List'!$A$12:$P$172,H$1,FALSE)) -> CFNMDUALL | K61: =IF(VLOOKUP($C61,'EECL Price List'!$A$12:$P$172,I$1,FALSE)=0,"",VLOOKUP($C61,'EECL Price List'!$A$12:$P$172,I$1,FALSE)) -> CFNMDUALI
B62: 143 | C62: 158-CF | E62: =VLOOKUP(B62,'EECL Price List'!$A$12:$P$172,2,FALSE) -> Install new meter (Type 5 and 6) – Dual element – Primary plus controlled load plus embedded generation | F62: =IF(VLOOKUP($B62,'EECL Price List'!$A$12:$P$172,H$1,FALSE)=0,"",VLOOKUP($B62,'EECL Price List'!$A$12:$P$172,H$1,FALSE)) -> NMDPCLEGL | G62: =IF(VLOOKUP($B62,'EECL Price List'!$A$12:$P$172,I$1,FALSE)=0,"",VLOOKUP($B62,'EECL Price List'!$A$12:$P$172,I$1,FALSE)) -> NMDPCLEGI | J62: =IF(VLOOKUP($C62,'EECL Price List'!$A$12:$P$172,H$1,FALSE)=0,"",VLOOKUP($C62,'EECL Price List'!$A$12:$P$172,H$1,FALSE)) -> CFNMDUALL | K62: =IF(VLOOKUP($C62,'EECL Price List'!$A$12:$P$172,I$1,FALSE)=0,"",VLOOKUP($C62,'EECL Price List'!$A$12:$P$172,I$1,FALSE)) -> CFNMDUALI
B63: 144 | C63: 159-CF | E63: =VLOOKUP(B63,'EECL Price List'!$A$12:$P$172,2,FALSE) -> Install new meter (Type 5 and 6) – Polyphase – Primary | F63: =IF(VLOOKUP($B63,'EECL Price List'!$A$12:$P$172,H$1,FALSE)=0,"",VLOOKUP($B63,'EECL Price List'!$A$12:$P$172,H$1,FALSE)) -> NMPPL | G63: =IF(VLOOKUP($B63,'EECL Price List'!$A$12:$P$172,I$1,FALSE)=0,"",VLOOKUP($B63,'EECL Price List'!$A$12:$P$172,I$1,FALSE)) -> NMPPI | J63: =IF(VLOOKUP($C63,'EECL Price List'!$A$12:$P$172,H$1,FALSE)=0,"",VLOOKUP($C63,'EECL Price List'!$A$12:$P$172,H$1,FALSE)) -> CFNMTHREL | K63: =IF(VLOOKUP($C63,'EECL Price List'!$A$12:$P$172,I$1,FALSE)=0,"",VLOOKUP($C63,'EECL Price List'!$A$12:$P$172,I$1,FALSE)) -> CFNMTHREI
B64: 145 | C64: 159-CF | E64: =VLOOKUP(B64,'EECL Price List'!$A$12:$P$172,2,FALSE) -> Install new meter (Type 5 and 6) – Polyphase – Primary plus embedded generation | F64: =IF(VLOOKUP($B64,'EECL Price List'!$A$12:$P$172,H$1,FALSE)=0,"",VLOOKUP($B64,'EECL Price List'!$A$12:$P$172,H$1,FALSE)) -> NMPPEGL | G64: =IF(VLOOKUP($B64,'EECL Price List'!$A$12:$P$172,I$1,FALSE)=0,"",VLOOKUP($B64,'EECL Price List'!$A$12:$P$172,I$1,FALSE)) -> NMPPEGI | J64: =IF(VLOOKUP($C64,'EECL Price List'!$A$12:$P$172,H$1,FALSE)=0,"",VLOOKUP($C64,'EECL Price List'!$A$12:$P$172,H$1,FALSE)) -> CFNMTHREL | K64: =IF(VLOOKUP($C64,'EECL Price List'!$A$12:$P$172,I$1,FALSE)=0,"",VLOOKUP($C64,'EECL Price List'!$A$12:$P$172,I$1,FALSE)) -> CFNMTHREI
B65: 146 | C65: 160-CF | E65: =VLOOKUP(B65,'EECL Price List'!$A$12:$P$172,2,FALSE) -> Install new meter (CT) – Primary | F65: =IF(VLOOKUP($B65,'EECL Price List'!$A$12:$P$172,H$1,FALSE)=0,"",VLOOKUP($B65,'EECL Price List'!$A$12:$P$172,H$1,FALSE)) -> NMCTPL | G65: =IF(VLOOKUP($B65,'EECL Price List'!$A$12:$P$172,I$1,FALSE)=0,"",VLOOKUP($B65,'EECL Price List'!$A$12:$P$172,I$1,FALSE)) -> NMCTPI | J65: =IF(VLOOKUP($C65,'EECL Price List'!$A$12:$P$172,H$1,FALSE)=0,"",VLOOKUP($C65,'EECL Price List'!$A$12:$P$172,H$1,FALSE)) -> CFNMCTL | K65: =IF(VLOOKUP($C65,'EECL Price List'!$A$12:$P$172,I$1,FALSE)=0,"",VLOOKUP($C65,'EECL Price List'!$A$12:$P$172,I$1,FALSE)) -> CFNMCTI
B66: 147 | C66: 160-CF | E66: =VLOOKUP(B66,'EECL Price List'!$A$12:$P$172,2,FALSE) -> Install new meter (CT) – Primary plus embedded generation | F66: =IF(VLOOKUP($B66,'EECL Price List'!$A$12:$P$172,H$1,FALSE)=0,"",VLOOKUP($B66,'EECL Price List'!$A$12:$P$172,H$1,FALSE)) -> NMCTPEGL | G66: =IF(VLOOKUP($B66,'EECL Price List'!$A$12:$P$172,I$1,FALSE)=0,"",VLOOKUP($B66,'EECL Price List'!$A$12:$P$172,I$1,FALSE)) -> NMCTPEGI | J66: =IF(VLOOKUP($C66,'EECL Price List'!$A$12:$P$172,H$1,FALSE)=0,"",VLOOKUP($C66,'EECL Price List'!$A$12:$P$172,H$1,FALSE)) -> CFNMCTL | K66: =IF(VLOOKUP($C66,'EECL Price List'!$A$12:$P$172,I$1,FALSE)=0,"",VLOOKUP($C66,'EECL Price List'!$A$12:$P$172,I$1,FALSE)) -> CFNMCTI
... B75: 156 | C75: 160-CF | E75: =VLOOKUP(B75,'EECL Price List'!$A$12:$P$172,2,FALSE) -> Install new meter (CT) to accommodate embedded generation installation | F75: =IF(VLOOKUP($B75,'EECL Price List'!$A$12:$P$172,H$1,FALSE)=0,"",VLOOKUP($B75,'EECL Price List'!$A$12:$P$172,H$1,FALSE)) -> NCTAEGL | G75: =IF(VLOOKUP($B75,'EECL Price List'!$A$12:$P$172,I$1,FALSE)=0,"",VLOOKUP($B75,'EECL Price List'!$A$12:$P$172,I$1,FALSE)) -> NCTAEGI | J75: =IF(VLOOKUP($C75,'EECL Price List'!$A$12:$P$172,H$1,FALSE)=0,"",VLOOKUP($C75,'EECL Price List'!$A$12:$P$172,H$1,FALSE)) -> CFNMCTL | K75: =IF(VLOOKUP($C75,'EECL Price List'!$A$12:$P$172,I$1,FALSE)=0,"",VLOOKUP($C75,'EECL Price List'!$A$12:$P$172,I$1,FALSE)) -> CFNMCTI
B76: 40 | D76: Quoted Services | E76: =VLOOKUP(B76,'EECL Price List'!$A$12:$P$172,2,FALSE) -> Application fee - Negotiated connection | F76: =IF(VLOOKUP($B76,'EECL Price List'!$A$12:$P$172,F$1,FALSE)=0,"",VLOOKUP($B76,'EECL Price List'!$A$12:$P$172,F$1,FALSE)) -> As Quoted | G76: =IF(VLOOKUP($B76,'EECL Price List'!$A$12:$P$172,G$1,FALSE)=0,"",VLOOKUP($B76,'EECL Price List'!$A$12:$P$172,G$1,FALSE)) | H76: =IF(VLOOKUP($B76,'EECL Price List'!$A$12:$P$172,H$1,FALSE)=0,"",VLOOKUP($B76,'EECL Price List'!$A$12:$P$172,H$1,FALSE)) | I76: =IF(VLOOKUP($B76,'EECL Price List'!$A$12:$P$172,I$1,FALSE)=0,"",VLOOKUP($B76,'EECL Price List'!$A$12:$P$172,I$1,FALSE)) | J76: GENCF* | L76: =IFERROR(IF(VLOOKUP($C76,'EECL Price List'!$A$12:$P$172,H$1,FALSE)=0,"",VLOOKUP($C76,'EECL Price List'!$A$12:$P$172,H$1,FALSE)),"") | M76: =IFERROR(IF(VLOOKUP($C76,'EECL Price List'!$A$12:$P$172,I$1,FALSE)=0,"",VLOOKUP($C76,'EECL Price List'!$A$12:$P$172,I$1,FALSE)),"")
B77: 41 | E77: =VLOOKUP(B77,'EECL Price List'!$A$12:$P$172,2,FALSE) -> Application fee - Negotiated connection - Micro-embedded generators | F77: =IF(VLOOKUP($B77,'EECL Price List'!$A$12:$P$172,F$1,FALSE)=0,"",VLOOKUP($B77,'EECL Price List'!$A$12:$P$172,F$1,FALSE)) -> As Quoted | G77: =IF(VLOOKUP($B77,'EECL Price List'!$A$12:$P$172,G$1,FALSE)=0,"",VLOOKUP($B77,'EECL Price List'!$A$12:$P$172,G$1,FALSE)) | H77: =IF(VLOOKUP($B77,'EECL Price List'!$A$12:$P$172,H$1,FALSE)=0,"",VLOOKUP($B77,'EECL Price List'!$A$12:$P$172,H$1,FALSE)) | I77: =IF(VLOOKUP($B77,'EECL Price List'!$A$12:$P$172,I$1,FALSE)=0,"",VLOOKUP($B77,'EECL Price List'!$A$12:$P$172,I$1,FALSE)) | J77: GENCF* | K77: =IFERROR(IF(VLOOKUP($C77,'EECL Price List'!$A$12:$P$172,G$1,FALSE)=0,"",VLOOKUP($C77,'EECL Price List'!$A$12:$P$172,G$1,FALSE)),"") | L77: =IFERROR(IF(VLOOKUP($C77,'EECL Price List'!$A$12:$P$172,H$1,FALSE)=0,"",VLOOKUP($C77,'EECL Price List'!$A$12:$P$172,H$1,FALSE)),"") | M77: =IFERROR(IF(VLOOKUP($C77,'EECL Price List'!$A$12:$P$172,I$1,FALSE)=0,"",VLOOKUP($C77,'EECL Price List'!$A$12:$P$172,I$1,FALSE)),"")
B78: 42 | E78: =VLOOKUP(B78,'EECL Price List'!$A$12:$P$172,2,FALSE) -> Application fee - Negotiated - Major customer connection | F78: =IF(VLOOKUP($B78,'EECL Price List'!$A$12:$P$172,F$1,FALSE)=0,"",VLOOKUP($B78,'EECL Price List'!$A$12:$P$172,F$1,FALSE)) -> As Quoted | G78: =IF(VLOOKUP($B78,'EECL Price List'!$A$12:$P$172,G$1,FALSE)=0,"",VLOOKUP($B78,'EECL Price List'!$A$12:$P$172,G$1,FALSE)) | H78: =IF(VLOOKUP($B78,'EECL Price List'!$A$12:$P$172,H$1,FALSE)=0,"",VLOOKUP($B78,'EECL Price List'!$A$12:$P$172,H$1,FALSE)) | I78: =IF(VLOOKUP($B78,'EECL Price List'!$A$12:$P$172,I$1,FALSE)=0,"",VLOOKUP($B78,'EECL Price List'!$A$12:$P$172,I$1,FALSE)) | J78: GENCF* | K78: =IFERROR(IF(VLOOKUP($C78,'EECL Price List'!$A$12:$P$172,G$1,FALSE)=0,"",VLOOKUP($C78,'EECL Price List'!$A$12:$P$172,G$1,FALSE)),"") | L78: =IFERROR(IF(VLOOKUP($C78,'EECL Price List'!$A$12:$P$172,H$1,FALSE)=0,"",VLOOKUP($C78,'EECL Price List'!$A$12:$P$172,H$1,FALSE)),"") | M78: =IFERROR(IF(VLOOKUP($C78,'EECL Price List'!$A$12:$P$172,I$1,FALSE)=0,"",VLOOKUP($C78,'EECL Price List'!$A$12:$P$172,I$1,FALSE)),"")
B79: 43 | E79: =VLOOKUP(B79,'EECL Price List'!$A$12:$P$172,2,FALSE) -> Carrying out planning studies and analysis relating to connection applications | F79: =IF(VLOOKUP($B79,'EECL Price List'!$A$12:$P$172,F$1,FALSE)=0,"",VLOOKUP($B79,'EECL Price List'!$A$12:$P$172,F$1,FALSE)) -> As Quoted | G79: =IF(VLOOKUP($B79,'EECL Price List'!$A$12:$P$172,G$1,FALSE)=0,"",VLOOKUP($B79,'EECL Price List'!$A$12:$P$172,G$1,FALSE)) | H79: =IF(VLOOKUP($B79,'EECL Price List'!$A$12:$P$172,H$1,FALSE)=0,"",VLOOKUP($B79,'EECL Price List'!$A$12:$P$172,H$1,FALSE)) | I79: =IF(VLOOKUP($B79,'EECL Price List'!$A$12:$P$172,I$1,FALSE)=0,"",VLOOKUP($B79,'EECL Price List'!$A$12:$P$172,I$1,FALSE)) | J79: GENCF* | K79: =IFERROR(IF(VLOOKUP($C79,'EECL Price List'!$A$12:$P$172,G$1,FALSE)=0,"",VLOOKUP($C79,'EECL Price List'!$A$12:$P$172,G$1,FALSE)),"") | L79: =IFERROR(IF(VLOOKUP($C79,'EECL Price List'!$A$12:$P$172,H$1,FALSE)=0,"",VLOOKUP($C79,'EECL Price List'!$A$12:$P$172,H$1,FALSE)),"") | M79: =IFERROR(IF(VLOOKUP($C79,'EECL Price List'!$A$12:$P$172,I$1,FALSE)=0,"",VLOOKUP($C79,'EECL Price List'!$A$12:$P$172,I$1,FALSE)),"")
B80: 44 | E80: =VLOOKUP(B80,'EECL Price List'!$A$12:$P$172,2,FALSE) -> Feasibility and concept scoping, including planning and design, for major customer connections | F80: =IF(VLOOKUP($B80,'EECL Price List'!$A$12:$P$172,F$1,FALSE)=0,"",VLOOKUP($B80,'EECL Price List'!$A$12:$P$172,F$1,FALSE)) -> As Quoted | G80: =IF(VLOOKUP($B80,'EECL Price List'!$A$12:$P$172,G$1,FALSE)=0,"",VLOOKUP($B80,'EECL Price List'!$A$12:$P$172,G$1,FALSE)) | H80: =IF(VLOOKUP($B80,'EECL Price List'!$A$12:$P$172,H$1,FALSE)=0,"",VLOOKUP($B80,'EECL Price List'!$A$12:$P$172,H$1,FALSE)) | I80: =IF(VLOOKUP($B80,'EECL Price List'!$A$12:$P$172,I$1,FALSE)=0,"",VLOOKUP($B80,'EECL Price List'!$A$12:$P$172,I$1,FALSE)) | J80: GENCF* | K80: =IFERROR(IF(VLOOKUP($C80,'EECL Price List'!$A$12:$P$172,G$1,FALSE)=0,"",VLOOKUP($C80,'EECL Price List'!$A$12:$P$172,G$1,FALSE)),"") | L80: =IFERROR(IF(VLOOKUP($C80,'EECL Price List'!$A$12:$P$172,H$1,FALSE)=0,"",VLOOKUP($C80,'EECL Price List'!$A$12:$P$172,H$1,FALSE)),"") | M80: =IFERROR(IF(VLOOKUP($C80,'EECL Price List'!$A$12:$P$172,I$1,FALSE)=0,"",VLOOKUP($C80,'EECL Price List'!$A$12:$P$172,I$1,FALSE)),"")
B81: 45 | E81: =VLOOKUP(B81,'EECL Price List'!$A$12:$P$172,2,FALSE) -> Tender process | F81: =IF(VLOOKUP($B81,'EECL Price List'!$A$12:$P$172,F$1,FALSE)=0,"",VLOOKUP($B81,'EECL Price List'!$A$12:$P$172,F$1,FALSE)) -> As Quoted | G81: =IF(VLOOKUP($B81,'EECL Price List'!$A$12:$P$172,G$1,FALSE)=0,"",VLOOKUP($B81,'EECL Price List'!$A$12:$P$172,G$1,FALSE)) | H81: =IF(VLOOKUP($B81,'EECL Price List'!$A$12:$P$172,H$1,FALSE)=0,"",VLOOKUP($B81,'EECL Price List'!$A$12:$P$172,H$1,FALSE)) | I81: =IF(VLOOKUP($B81,'EECL Price List'!$A$12:$P$172,I$1,FALSE)=0,"",VLOOKUP($B81,'EECL Price List'!$A$12:$P$172,I$1,FALSE)) | J81: GENCF* | K81: =IFERROR(IF(VLOOKUP($C81,'EECL Price List'!$A$12:$P$172,G$1,FALSE)=0,"",VLOOKUP($C81,'EECL Price List'!$A$12:$P$172,G$1,FALSE)),"") | L81: =IFERROR(IF(VLOOKUP($C81,'EECL Price List'!$A$12:$P$172,H$1,FALSE)=0,"",VLOOKUP($C81,'EECL Price List'!$A$12:$P$172,H$1,FALSE)),"") | M81: =IFERROR(IF(VLOOKUP($C81,'EECL Price List'!$A$12:$P$172,I$1,FALSE)=0,"",VLOOKUP($C81,'EECL Price List'!$A$12:$P$172,I$1,FALSE)),"")
B82: 46 | E82: =VLOOKUP(B82,'EECL Price List'!$A$12:$P$172,2,FALSE) -> Pre-connection site inspection | F82: =IF(VLOOKUP($B82,'EECL Price List'!$A$12:$P$172,F$1,FALSE)=0,"",VLOOKUP($B82,'EECL Price List'!$A$12:$P$172,F$1,FALSE)) -> As Quoted | G82: =IF(VLOOKUP($B82,'EECL Price List'!$A$12:$P$172,G$1,FALSE)=0,"",VLOOKUP($B82,'EECL Price List'!$A$12:$P$172,G$1,FALSE)) | H82: =IF(VLOOKUP($B82,'EECL Price List'!$A$12:$P$172,H$1,FALSE)=0,"",VLOOKUP($B82,'EECL Price List'!$A$12:$P$172,H$1,FALSE)) | I82: =IF(VLOOKUP($B82,'EECL Price List'!$A$12:$P$172,I$1,FALSE)=0,"",VLOOKUP($B82,'EECL Price List'!$A$12:$P$172,I$1,FALSE)) | J82: GENCF* | K82: =IFERROR(IF(VLOOKUP($C82,'EECL Price List'!$A$12:$P$172,G$1,FALSE)=0,"",VLOOKUP($C82,'EECL Price List'!$A$12:$P$172,G$1,FALSE)),"") | L82: =IFERROR(IF(VLOOKUP($C82,'EECL Price List'!$A$12:$P$172,H$1,FALSE)=0,"",VLOOKUP($C82,'EECL Price List'!$A$12:$P$172,H$1,FALSE)),"") | M82: =IFERROR(IF(VLOOKUP($C82,'EECL Price List'!$A$12:$P$172,I$1,FALSE)=0,"",VLOOKUP($C82,'EECL Price List'!$A$12:$P$172,I$1,FALSE)),"")
B83: 47 | E83: =VLOOKUP(B83,'EECL Price List'!$A$12:$P$172,2,FALSE) -> Provision of site-specific connection information and advice | F83: =IF(VLOOKUP($B83,'EECL Price List'!$A$12:$P$172,F$1,FALSE)=0,"",VLOOKUP($B83,'EECL Price List'!$A$12:$P$172,F$1,FALSE)) -> As Quoted | G83: =IF(VLOOKUP($B83,'EECL Price List'!$A$12:$P$172,G$1,FALSE)=0,"",VLOOKUP($B83,'EECL Price List'!$A$12:$P$172,G$1,FALSE)) | H83: =IF(VLOOKUP($B83,'EECL Price List'!$A$12:$P$172,H$1,FALSE)=0,"",VLOOKUP($B83,'EECL Price List'!$A$12:$P$172,H$1,FALSE)) | I83: =IF(VLOOKUP($B83,'EECL Price List'!$A$12:$P$172,I$1,FALSE)=0,"",VLOOKUP($B83,'EECL Price List'!$A$12:$P$172,I$1,FALSE)) | J83: GENCF* | K83: =IFERROR(IF(VLOOKUP($C83,'EECL Price List'!$A$12:$P$172,G$1,FALSE)=0,"",VLOOKUP($C83,'EECL Price List'!$A$12:$P$172,G$1,FALSE)),"") | L83: =IFERROR(IF(VLOOKUP($C83,'EECL Price List'!$A$12:$P$172,H$1,FALSE)=0,"",VLOOKUP($C83,'EECL Price List'!$A$12:$P$172,H$1,FALSE)),"") | M83: =IFERROR(IF(VLOOKUP($C83,'EECL Price List'!$A$12:$P$172,I$1,FALSE)=0,"",VLOOKUP($C83,'EECL Price List'!$A$12:$P$172,I$1,FALSE)),"")
B84: 48 | E84: =VLOOKUP(B84,'EECL Price List'!$A$12:$P$172,2,FALSE) -> Preparation of preliminary designs and planning reports for major customer connections, including project scopes and estimates | F84: =IF(VLOOKUP($B84,'EECL Price List'!$A$12:$P$172,F$1,FALSE)=0,"",VLOOKUP($B84,'EECL Price List'!$A$12:$P$172,F$1,FALSE)) -> As Quoted | G84: =IF(VLOOKUP($B84,'EECL Price List'!$A$12:$P$172,G$1,FALSE)=0,"",VLOOKUP($B84,'EECL Price List'!$A$12:$P$172,G$1,FALSE)) | H84: =IF(VLOOKUP($B84,'EECL Price List'!$A$12:$P$172,H$1,FALSE)=0,"",VLOOKUP($B84,'EECL Price List'!$A$12:$P$172,H$1,FALSE)) | I84: =IF(VLOOKUP($B84,'EECL Price List'!$A$12:$P$172,I$1,FALSE)=0,"",VLOOKUP($B84,'EECL Price List'!$A$12:$P$172,I$1,FALSE)) | J84: GENCF* | K84: =IFERROR(IF(VLOOKUP($C84,'EECL Price List'!$A$12:$P$172,G$1,FALSE)=0,"",VLOOKUP($C84,'EECL Price List'!$A$12:$P$172,G$1,FALSE)),"") | L84: =IFERROR(IF(VLOOKUP($C84,'EECL Price List'!$A$12:$P$172,H$1,FALSE)=0,"",VLOOKUP($C84,'EECL Price List'!$A$12:$P$172,H$1,FALSE)),"") | M84: =IFERROR(IF(VLOOKUP($C84,'EECL Price List'!$A$12:$P$172,I$1,FALSE)=0,"",VLOOKUP($C84,'EECL Price List'!$A$12:$P$172,I$1,FALSE)),"")
B85: 49 | E85: =VLOOKUP(B85,'EECL Price List'!$A$12:$P$172,2,FALSE) -> Customer build, own and operate consultation services | F85: =IF(VLOOKUP($B85,'EECL Price List'!$A$12:$P$172,F$1,FALSE)=0,"",VLOOKUP($B85,'EECL Price List'!$A$12:$P$172,F$1,FALSE)) -> As Quoted | G85: =IF(VLOOKUP($B85,'EECL Price List'!$A$12:$P$172,G$1,FALSE)=0,"",VLOOKUP($B85,'EECL Price List'!$A$12:$P$172,G$1,FALSE)) | H85: =IF(VLOOKUP($B85,'EECL Price List'!$A$12:$P$172,H$1,FALSE)=0,"",VLOOKUP($B85,'EECL Price List'!$A$12:$P$172,H$1,FALSE)) | I85: =IF(VLOOKUP($B85,'EECL Price List'!$A$12:$P$172,I$1,FALSE)=0,"",VLOOKUP($B85,'EECL Price List'!$A$12:$P$172,I$1,FALSE)) | J85: GENCF* | K85: =IFERROR(IF(VLOOKUP($C85,'EECL Price List'!$A$12:$P$172,G$1,FALSE)=0,"",VLOOKUP($C85,'EECL Price List'!$A$12:$P$172,G$1,FALSE)),"") | L85: =IFERROR(IF(VLOOKUP($C85,'EECL Price List'!$A$12:$P$172,H$1,FALSE)=0,"",VLOOKUP($C85,'EECL Price List'!$A$12:$P$172,H$1,FALSE)),"") | M85: =IFERROR(IF(VLOOKUP($C85,'EECL Price List'!$A$12:$P$172,I$1,FALSE)=0,"",VLOOKUP($C85,'EECL Price List'!$A$12:$P$172,I$1,FALSE)),"")
B86: 50 | E86: =VLOOKUP(B86,'EECL Price List'!$A$12:$P$172,2,FALSE) -> Detailed enquiry response fee - embedded generation | F86: =IF(VLOOKUP($B86,'EECL Price List'!$A$12:$P$172,F$1,FALSE)=0,"",VLOOKUP($B86,'EECL Price List'!$A$12:$P$172,F$1,FALSE)) -> As Quoted | G86: =IF(VLOOKUP($B86,'EECL Price List'!$A$12:$P$172,G$1,FALSE)=0,"",VLOOKUP($B86,'EECL Price List'!$A$12:$P$172,G$1,FALSE)) | H86: =IF(VLOOKUP($B86,'EECL Price List'!$A$12:$P$172,H$1,FALSE)=0,"",VLOOKUP($B86,'EECL Price List'!$A$12:$P$172,H$1,FALSE)) | I86: =IF(VLOOKUP($B86,'EECL Price List'!$A$12:$P$172,I$1,FALSE)=0,"",VLOOKUP($B86,'EECL Price List'!$A$12:$P$172,I$1,FALSE)) | J86: GENCF* | K86: =IFERROR(IF(VLOOKUP($C86,'EECL Price List'!$A$12:$P$172,G$1,FALSE)=0,"",VLOOKUP($C86,'EECL Price List'!$A$12:$P$172,G$1,FALSE)),"") | L86: =IFERROR(IF(VLOOKUP($C86,'EECL Price List'!$A$12:$P$172,H$1,FALSE)=0,"",VLOOKUP($C86,'EECL Price List'!$A$12:$P$172,H$1,FALSE)),"") | M86: =IFERROR(IF(VLOOKUP($C86,'EECL Price List'!$A$12:$P$172,I$1,FALSE)=0,"",VLOOKUP($C86,'EECL Price List'!$A$12:$P$172,I$1,FALSE)),"")
B87: 51 | E87: =VLOOKUP(B87,'EECL Price List'!$A$12:$P$172,2,FALSE) -> Design and construction of connection assets for major customers | F87: =IF(VLOOKUP($B87,'EECL Price List'!$A$12:$P$172,F$1,FALSE)=0,"",VLOOKUP($B87,'EECL Price List'!$A$12:$P$172,F$1,FALSE)) -> As Quoted | G87: =IF(VLOOKUP($B87,'EECL Price List'!$A$12:$P$172,G$1,FALSE)=0,"",VLOOKUP($B87,'EECL Price List'!$A$12:$P$172,G$1,FALSE)) | H87: =IF(VLOOKUP($B87,'EECL Price List'!$A$12:$P$172,H$1,FALSE)=0,"",VLOOKUP($B87,'EECL Price List'!$A$12:$P$172,H$1,FALSE)) | I87: =IF(VLOOKUP($B87,'EECL Price List'!$A$12:$P$172,I$1,FALSE)=0,"",VLOOKUP($B87,'EECL Price List'!$A$12:$P$172,I$1,FALSE)) | J87: GENCF* | K87: =IFERROR(IF(VLOOKUP($C87,'EECL Price List'!$A$12:$P$172,G$1,FALSE)=0,"",VLOOKUP($C87,'EECL Price List'!$A$12:$P$172,G$1,FALSE)),"") | L87: =IFERROR(IF(VLOOKUP($C87,'EECL Price List'!$A$12:$P$172,H$1,FALSE)=0,"",VLOOKUP($C87,'EECL Price List'!$A$12:$P$172,H$1,FALSE)),"") | M87: =IFERROR(IF(VLOOKUP($C87,'EECL Price List'!$A$12:$P$172,I$1,FALSE)=0,"",VLOOKUP($C87,'EECL Price List'!$A$12:$P$172,I$1,FALSE)),"")
B88: 52 | E88: =VLOOKUP(B88,'EECL Price List'!$A$12:$P$172,2,FALSE) -> Commissioning and energisation of major customer connections | F88: =IF(VLOOKUP($B88,'EECL Price List'!$A$12:$P$172,F$1,FALSE)=0,"",VLOOKUP($B88,'EECL Price List'!$A$12:$P$172,F$1,FALSE)) -> As Quoted | G88: =IF(VLOOKUP($B88,'EECL Price List'!$A$12:$P$172,G$1,FALSE)=0,"",VLOOKUP($B88,'EECL Price List'!$A$12:$P$172,G$1,FALSE)) | H88: =IF(VLOOKUP($B88,'EECL Price List'!$A$12:$P$172,H$1,FALSE)=0,"",VLOOKUP($B88,'EECL Price List'!$A$12:$P$172,H$1,FALSE)) | I88: =IF(VLOOKUP($B88,'EECL Price List'!$A$12:$P$172,I$1,FALSE)=0,"",VLOOKUP($B88,'EECL Price List'!$A$12:$P$172,I$1,FALSE)) | J88: GENCF* | K88: =IFERROR(IF(VLOOKUP($C88,'EECL Price List'!$A$12:$P$172,G$1,FALSE)=0,"",VLOOKUP($C88,'EECL Price List'!$A$12:$P$172,G$1,FALSE)),"") | L88: =IFERROR(IF(VLOOKUP($C88,'EECL Price List'!$A$12:$P$172,H$1,FALSE)=0,"",VLOOKUP($C88,'EECL Price List'!$A$12:$P$172,H$1,FALSE)),"") | M88: =IFERROR(IF(VLOOKUP($C88,'EECL Price List'!$A$12:$P$172,I$1,FALSE)=0,"",VLOOKUP($C88,'EECL Price List'!$A$12:$P$172,I$1,FALSE)),"")
... B101: 65 | E101: =VLOOKUP(B101,'EECL Price List'!$A$12:$P$172,2,FALSE) -> Rectification of illegal connections or damage to overhead or underground service cables | F101: =IF(VLOOKUP($B101,'EECL Price List'!$A$12:$P$172,F$1,FALSE)=0,"",VLOOKUP($B101,'EECL Price List'!$A$12:$P$172,F$1,FALSE)) -> As Quoted | G101: =IF(VLOOKUP($B101,'EECL Price List'!$A$12:$P$172,G$1,FALSE)=0,"",VLOOKUP($B101,'EECL Price List'!$A$12:$P$172,G$1,FALSE)) | H101: =IF(VLOOKUP($B101,'EECL Price List'!$A$12:$P$172,H$1,FALSE)=0,"",VLOOKUP($B101,'EECL Price List'!$A$12:$P$172,H$1,FALSE)) | I101: =IF(VLOOKUP($B101,'EECL Price List'!$A$12:$P$172,I$1,FALSE)=0,"",VLOOKUP($B101,'EECL Price List'!$A$12:$P$172,I$1,FALSE)) | J101: GENCF* | K101: =IFERROR(IF(VLOOKUP($C101,'EECL Price List'!$A$12:$P$172,G$1,FALSE)=0,"",VLOOKUP($C101,'EECL Price List'!$A$12:$P$172,G$1,FALSE)),"") | L101: =IFERROR(IF(VLOOKUP($C101,'EECL Price List'!$A$12:$P$172,H$1,FALSE)=0,"",VLOOKUP($C101,'EECL Price List'!$A$12:$P$172,H$1,FALSE)),"") | M101: =IFERROR(IF(VLOOKUP($C101,'EECL Price List'!$A$12:$P$172,I$1,FALSE)=0,"",VLOOKUP($C101,'EECL Price List'!$A$12:$P$172,I$1,FALSE)),"")
B102: 66 | C102: 66-CF | E102: =VLOOKUP(B102,'EECL Price List'!$A$12:$P$172,2,FALSE) -> De-energisation after business hours | F102: =IF(VLOOKUP($B102,'EECL Price List'!$A$12:$P$172,F$1,FALSE)=0,"",VLOOKUP($B102,'EECL Price List'!$A$12:$P$172,F$1,FALSE)) -> DEENAHU | G102: =IF(VLOOKUP($B102,'EECL Price List'!$A$12:$P$172,G$1,FALSE)=0,"",VLOOKUP($B102,'EECL Price List'!$A$12:$P$172,G$1,FALSE)) -> DEENAHS | H102: =IF(VLOOKUP($B102,'EECL Price List'!$A$12:$P$172,H$1,FALSE)=0,"",VLOOKUP($B102,'EECL Price List'!$A$12:$P$172,H$1,FALSE)) -> DEENAHL | I102: =IF(VLOOKUP($B102,'EECL Price List'!$A$12:$P$172,I$1,FALSE)=0,"",VLOOKUP($B102,'EECL Price List'!$A$12:$P$172,I$1,FALSE)) -> DEENAHI | J102: =IFERROR(IF(VLOOKUP($C102,'EECL Price List'!$A$12:$P$172,F$1,FALSE)=0,"",VLOOKUP($C102,'EECL Price List'!$A$12:$P$172,F$1,FALSE)),"") -> CFDEENAHU | K102: =IFERROR(IF(VLOOKUP($C102,'EECL Price List'!$A$12:$P$172,G$1,FALSE)=0,"",VLOOKUP($C102,'EECL Price List'!$A$12:$P$172,G$1,FALSE)),"") -> CFDEENAHS | L102: =IFERROR(IF(VLOOKUP($C102,'EECL Price List'!$A$12:$P$172,H$1,FALSE)=0,"",VLOOKUP($C102,'EECL Price List'!$A$12:$P$172,H$1,FALSE)),"") -> CFDEENAHL | M102: =IFERROR(IF(VLOOKUP($C102,'EECL Price List'!$A$12:$P$172,I$1,FALSE)=0,"",VLOOKUP($C102,'EECL Price List'!$A$12:$P$172,I$1,FALSE)),"") -> CFDEENAHI
B103: 67 | C103: 67-CF | E103: =VLOOKUP(B103,'EECL Price List'!$A$12:$P$172,2,FALSE) -> Re-energisation after business hours | F103: =IF(VLOOKUP($B103,'EECL Price List'!$A$12:$P$172,F$1,FALSE)=0,"",VLOOKUP($B103,'EECL Price List'!$A$12:$P$172,F$1,FALSE)) -> REENAHU | G103: =IF(VLOOKUP($B103,'EECL Price List'!$A$12:$P$172,G$1,FALSE)=0,"",VLOOKUP($B103,'EECL Price List'!$A$12:$P$172,G$1,FALSE)) -> REENAHS | H103: =IF(VLOOKUP($B103,'EECL Price List'!$A$12:$P$172,H$1,FALSE)=0,"",VLOOKUP($B103,'EECL Price List'!$A$12:$P$172,H$1,FALSE)) -> REENAHL | I103: =IF(VLOOKUP($B103,'EECL Price List'!$A$12:$P$172,I$1,FALSE)=0,"",VLOOKUP($B103,'EECL Price List'!$A$12:$P$172,I$1,FALSE)) -> REENAHI | J103: =IFERROR(IF(VLOOKUP($C103,'EECL Price List'!$A$12:$P$172,F$1,FALSE)=0,"",VLOOKUP($C103,'EECL Price List'!$A$12:$P$172,F$1,FALSE)),"") -> CFREENAHU | K103: =IFERROR(IF(VLOOKUP($C103,'EECL Price List'!$A$12:$P$172,G$1,FALSE)=0,"",VLOOKUP($C103,'EECL Price List'!$A$12:$P$172,G$1,FALSE)),"") -> CFREENAHS | L103: =IFERROR(IF(VLOOKUP($C103,'EECL Price List'!$A$12:$P$172,H$1,FALSE)=0,"",VLOOKUP($C103,'EECL Price List'!$A$12:$P$172,H$1,FALSE)),"") -> CFREENAHL | M103: =IFERROR(IF(VLOOKUP($C103,'EECL Price List'!$A$12:$P$172,I$1,FALSE)=0,"",VLOOKUP($C103,'EECL Price List'!$A$12:$P$172,I$1,FALSE)),"") -> CFREENAHI
B104: 68 | E104: =VLOOKUP(B104,'EECL Price List'!$A$12:$P$172,2,FALSE) -> Accreditation of alternative service providers - major customer connections | F104: =IF(VLOOKUP($B104,'EECL Price List'!$A$12:$P$172,F$1,FALSE)=0,"",VLOOKUP($B104,'EECL Price List'!$A$12:$P$172,F$1,FALSE)) -> As Quoted | G104: =IF(VLOOKUP($B104,'EECL Price List'!$A$12:$P$172,G$1,FALSE)=0,"",VLOOKUP($B104,'EECL Price List'!$A$12:$P$172,G$1,FALSE)) | H104: =IF(VLOOKUP($B104,'EECL Price List'!$A$12:$P$172,H$1,FALSE)=0,"",VLOOKUP($B104,'EECL Price List'!$A$12:$P$172,H$1,FALSE)) | I104: =IF(VLOOKUP($B104,'EECL Price List'!$A$12:$P$172,I$1,FALSE)=0,"",VLOOKUP($B104,'EECL Price List'!$A$12:$P$172,I$1,FALSE)) | J104: GENCF* | K104: =IFERROR(IF(VLOOKUP($C104,'EECL Price List'!$A$12:$P$172,G$1,FALSE)=0,"",VLOOKUP($C104,'EECL Price List'!$A$12:$P$172,G$1,FALSE)),"") | L104: =IFERROR(IF(VLOOKUP($C104,'EECL Price List'!$A$12:$P$172,H$1,FALSE)=0,"",VLOOKUP($C104,'EECL Price List'!$A$12:$P$172,H$1,FALSE)),"") | M104: =IFERROR(IF(VLOOKUP($C104,'EECL Price List'!$A$12:$P$172,I$1,FALSE)=0,"",VLOOKUP($C104,'EECL Price List'!$A$12:$P$172,I$1,FALSE)),"")
B105: 69 | E105: =VLOOKUP(B105,'EECL Price List'!$A$12:$P$172,2,FALSE) -> Approval of third party design - major customer connections | F105: =IF(VLOOKUP($B105,'EECL Price List'!$A$12:$P$172,F$1,FALSE)=0,"",VLOOKUP($B105,'EECL Price List'!$A$12:$P$172,F$1,FALSE)) -> As Quoted | G105: =IF(VLOOKUP($B105,'EECL Price List'!$A$12:$P$172,G$1,FALSE)=0,"",VLOOKUP($B105,'EECL Price List'!$A$12:$P$172,G$1,FALSE)) | H105: =IF(VLOOKUP($B105,'EECL Price List'!$A$12:$P$172,H$1,FALSE)=0,"",VLOOKUP($B105,'EECL Price List'!$A$12:$P$172,H$1,FALSE)) | I105: =IF(VLOOKUP($B105,'EECL Price List'!$A$12:$P$172,I$1,FALSE)=0,"",VLOOKUP($B105,'EECL Price List'!$A$12:$P$172,I$1,FALSE)) | J105: GENCF* | K105: =IFERROR(IF(VLOOKUP($C105,'EECL Price List'!$A$12:$P$172,G$1,FALSE)=0,"",VLOOKUP($C105,'EECL Price List'!$A$12:$P$172,G$1,FALSE)),"") | L105: =IFERROR(IF(VLOOKUP($C105,'EECL Price List'!$A$12:$P$172,H$1,FALSE)=0,"",VLOOKUP($C105,'EECL Price List'!$A$12:$P$172,H$1,FALSE)),"") | M105: =IFERROR(IF(VLOOKUP($C105,'EECL Price List'!$A$12:$P$172,I$1,FALSE)=0,"",VLOOKUP($C105,'EECL Price List'!$A$12:$P$172,I$1,FALSE)),"")
B106: 70 | E106: =VLOOKUP(B106,'EECL Price List'!$A$12:$P$172,2,FALSE) -> Approval of third party design - real estate developments | F106: =IF(VLOOKUP($B106,'EECL Price List'!$A$12:$P$172,F$1,FALSE)=0,"",VLOOKUP($B106,'EECL Price List'!$A$12:$P$172,F$1,FALSE)) -> As Quoted | G106: =IF(VLOOKUP($B106,'EECL Price List'!$A$12:$P$172,G$1,FALSE)=0,"",VLOOKUP($B106,'EECL Price List'!$A$12:$P$172,G$1,FALSE)) | H106: =IF(VLOOKUP($B106,'EECL Price List'!$A$12:$P$172,H$1,FALSE)=0,"",VLOOKUP($B106,'EECL Price List'!$A$12:$P$172,H$1,FALSE)) | I106: =IF(VLOOKUP($B106,'EECL Price List'!$A$12:$P$172,I$1,FALSE)=0,"",VLOOKUP($B106,'EECL Price List'!$A$12:$P$172,I$1,FALSE)) | J106: GENCF* | K106: =IFERROR(IF(VLOOKUP($C106,'EECL Price List'!$A$12:$P$172,G$1,FALSE)=0,"",VLOOKUP($C106,'EECL Price List'!$A$12:$P$172,G$1,FALSE)),"") | L106: =IFERROR(IF(VLOOKUP($C106,'EECL Price List'!$A$12:$P$172,H$1,FALSE)=0,"",VLOOKUP($C106,'EECL Price List'!$A$12:$P$172,H$1,FALSE)),"") | M106: =IFERROR(IF(VLOOKUP($C106,'EECL Price List'!$A$12:$P$172,I$1,FALSE)=0,"",VLOOKUP($C106,'EECL Price List'!$A$12:$P$172,I$1,FALSE)),"")
B107: 71 | E107: =VLOOKUP(B107,'EECL Price List'!$A$12:$P$172,2,FALSE) -> Construction audit - major customer connections | F107: =IF(VLOOKUP($B107,'EECL Price List'!$A$12:$P$172,F$1,FALSE)=0,"",VLOOKUP($B107,'EECL Price List'!$A$12:$P$172,F$1,FALSE)) -> As Quoted | G107: =IF(VLOOKUP($B107,'EECL Price List'!$A$12:$P$172,G$1,FALSE)=0,"",VLOOKUP($B107,'EECL Price List'!$A$12:$P$172,G$1,FALSE)) | H107: =IF(VLOOKUP($B107,'EECL Price List'!$A$12:$P$172,H$1,FALSE)=0,"",VLOOKUP($B107,'EECL Price List'!$A$12:$P$172,H$1,FALSE)) | I107: =IF(VLOOKUP($B107,'EECL Price List'!$A$12:$P$172,I$1,FALSE)=0,"",VLOOKUP($B107,'EECL Price List'!$A$12:$P$172,I$1,FALSE)) | J107: GENCF* | K107: =IFERROR(IF(VLOOKUP($C107,'EECL Price List'!$A$12:$P$172,G$1,FALSE)=0,"",VLOOKUP($C107,'EECL Price List'!$A$12:$P$172,G$1,FALSE)),"") | L107: =IFERROR(IF(VLOOKUP($C107,'EECL Price List'!$A$12:$P$172,H$1,FALSE)=0,"",VLOOKUP($C107,'EECL Price List'!$A$12:$P$172,H$1,FALSE)),"") | M107: =IFERROR(IF(VLOOKUP($C107,'EECL Price List'!$A$12:$P$172,I$1,FALSE)=0,"",VLOOKUP($C107,'EECL Price List'!$A$12:$P$172,I$1,FALSE)),"")
B108: 72 | E108: =VLOOKUP(B108,'EECL Price List'!$A$12:$P$172,2,FALSE) -> Construction audit - real estate developments | F108: =IF(VLOOKUP($B108,'EECL Price List'!$A$12:$P$172,F$1,FALSE)=0,"",VLOOKUP($B108,'EECL Price List'!$A$12:$P$172,F$1,FALSE)) -> As Quoted | G108: =IF(VLOOKUP($B108,'EECL Price List'!$A$12:$P$172,G$1,FALSE)=0,"",VLOOKUP($B108,'EECL Price List'!$A$12:$P$172,G$1,FALSE)) | H108: =IF(VLOOKUP($B108,'EECL Price List'!$A$12:$P$172,H$1,FALSE)=0,"",VLOOKUP($B108,'EECL Price List'!$A$12:$P$172,H$1,FALSE)) | I108: =IF(VLOOKUP($B108,'EECL Price List'!$A$12:$P$172,I$1,FALSE)=0,"",VLOOKUP($B108,'EECL Price List'!$A$12:$P$172,I$1,FALSE)) | J108: GENCF* | K108: =IFERROR(IF(VLOOKUP($C108,'EECL Price List'!$A$12:$P$172,G$1,FALSE)=0,"",VLOOKUP($C108,'EECL Price List'!$A$12:$P$172,G$1,FALSE)),"") | L108: =IFERROR(IF(VLOOKUP($C108,'EECL Price List'!$A$12:$P$172,H$1,FALSE)=0,"",VLOOKUP($C108,'EECL Price List'!$A$12:$P$172,H$1,FALSE)),"") | M108: =IFERROR(IF(VLOOKUP($C108,'EECL Price List'!$A$12:$P$172,I$1,FALSE)=0,"",VLOOKUP($C108,'EECL Price List'!$A$12:$P$172,I$1,FALSE)),"")
B109: 73 | E109: =VLOOKUP(B109,'EECL Price List'!$A$12:$P$172,2,FALSE) -> Approval of third party materials | F109: =IF(VLOOKUP($B109,'EECL Price List'!$A$12:$P$172,F$1,FALSE)=0,"",VLOOKUP($B109,'EECL Price List'!$A$12:$P$172,F$1,FALSE)) -> As Quoted | G109: =IF(VLOOKUP($B109,'EECL Price List'!$A$12:$P$172,G$1,FALSE)=0,"",VLOOKUP($B109,'EECL Price List'!$A$12:$P$172,G$1,FALSE)) | H109: =IF(VLOOKUP($B109,'EECL Price List'!$A$12:$P$172,H$1,FALSE)=0,"",VLOOKUP($B109,'EECL Price List'!$A$12:$P$172,H$1,FALSE)) | I109: =IF(VLOOKUP($B109,'EECL Price List'!$A$12:$P$172,I$1,FALSE)=0,"",VLOOKUP($B109,'EECL Price List'!$A$12:$P$172,I$1,FALSE)) | J109: GENCF* | K109: =IFERROR(IF(VLOOKUP($C109,'EECL Price List'!$A$12:$P$172,G$1,FALSE)=0,"",VLOOKUP($C109,'EECL Price List'!$A$12:$P$172,G$1,FALSE)),"") | L109: =IFERROR(IF(VLOOKUP($C109,'EECL Price List'!$A$12:$P$172,H$1,FALSE)=0,"",VLOOKUP($C109,'EECL Price List'!$A$12:$P$172,H$1,FALSE)),"") | M109: =IFERROR(IF(VLOOKUP($C109,'EECL Price List'!$A$12:$P$172,I$1,FALSE)=0,"",VLOOKUP($C109,'EECL Price List'!$A$12:$P$172,I$1,FALSE)),"")
B110: 74 | C110: 74-CF | E110: =VLOOKUP(B110,'EECL Price List'!$A$12:$P$172,2,FALSE) -> Special meter read | F110: =IF(VLOOKUP($B110,'EECL Price List'!$A$12:$P$172,F$1,FALSE)=0,"",VLOOKUP($B110,'EECL Price List'!$A$12:$P$172,F$1,FALSE)) -> SPMTRRDU | G110: =IF(VLOOKUP($B110,'EECL Price List'!$A$12:$P$172,G$1,FALSE)=0,"",VLOOKUP($B110,'EECL Price List'!$A$12:$P$172,G$1,FALSE)) -> SPMTRRDS | H110: =IF(VLOOKUP($B110,'EECL Price List'!$A$12:$P$172,H$1,FALSE)=0,"",VLOOKUP($B110,'EECL Price List'!$A$12:$P$172,H$1,FALSE)) -> SPMTRRDL | I110: =IF(VLOOKUP($B110,'EECL Price List'!$A$12:$P$172,I$1,FALSE)=0,"",VLOOKUP($B110,'EECL Price List'!$A$12:$P$172,I$1,FALSE)) -> SPMTRRDI | J110: =IFERROR(IF(VLOOKUP($C110,'EECL Price List'!$A$12:$P$172,F$1,FALSE)=0,"",VLOOKUP($C110,'EECL Price List'!$A$12:$P$172,F$1,FALSE)),"") -> CFSPMTRRDU | K110: =IFERROR(IF(VLOOKUP($C110,'EECL Price List'!$A$12:$P$172,G$1,FALSE)=0,"",VLOOKUP($C110,'EECL Price List'!$A$12:$P$172,G$1,FALSE)),"") -> CFSPMTRRDS | L110: =IFERROR(IF(VLOOKUP($C110,'EECL Price List'!$A$12:$P$172,H$1,FALSE)=0,"",VLOOKUP($C110,'EECL Price List'!$A$12:$P$172,H$1,FALSE)),"") -> CFSPMTRRDL | M110: =IFERROR(IF(VLOOKUP($C110,'EECL Price List'!$A$12:$P$172,I$1,FALSE)=0,"",VLOOKUP($C110,'EECL Price List'!$A$12:$P$172,I$1,FALSE)),"") -> CFSPMTRRDI
B111: 75 | C111: 75-CF | E111: =VLOOKUP(B111,'EECL Price List'!$A$12:$P$172,2,FALSE) -> Meter test | F111: =IF(VLOOKUP($B111,'EECL Price List'!$A$12:$P$172,F$1,FALSE)=0,"",VLOOKUP($B111,'EECL Price List'!$A$12:$P$172,F$1,FALSE)) -> MTRTESTU | G111: =IF(VLOOKUP($B111,'EECL Price List'!$A$12:$P$172,G$1,FALSE)=0,"",VLOOKUP($B111,'EECL Price List'!$A$12:$P$172,G$1,FALSE)) -> MTRTESTS | H111: =IF(VLOOKUP($B111,'EECL Price List'!$A$12:$P$172,H$1,FALSE)=0,"",VLOOKUP($B111,'EECL Price List'!$A$12:$P$172,H$1,FALSE)) -> MTRTESTL | I111: =IF(VLOOKUP($B111,'EECL Price List'!$A$12:$P$172,I$1,FALSE)=0,"",VLOOKUP($B111,'EECL Price List'!$A$12:$P$172,I$1,FALSE)) -> MTRTESTI | J111: =IFERROR(IF(VLOOKUP($C111,'EECL Price List'!$A$12:$P$172,F$1,FALSE)=0,"",VLOOKUP($C111,'EECL Price List'!$A$12:$P$172,F$1,FALSE)),"") -> CFMTRTESTU | K111: =IFERROR(IF(VLOOKUP($C111,'EECL Price List'!$A$12:$P$172,G$1,FALSE)=0,"",VLOOKUP($C111,'EECL Price List'!$A$12:$P$172,G$1,FALSE)),"") -> CFMTRTESTS | L111: =IFERROR(IF(VLOOKUP($C111,'EECL Price List'!$A$12:$P$172,H$1,FALSE)=0,"",VLOOKUP($C111,'EECL Price List'!$A$12:$P$172,H$1,FALSE)),"") -> CFMTRTESTL | M111: =IFERROR(IF(VLOOKUP($C111,'EECL Price List'!$A$12:$P$172,I$1,FALSE)=0,"",VLOOKUP($C111,'EECL Price List'!$A$12:$P$172,I$1,FALSE)),"") -> CFMTRTESTI
B112: 76 | E112: =VLOOKUP(B112,'EECL Price List'!$A$12:$P$172,2,FALSE) -> Meter inspection and investigation on request | F112: =IF(VLOOKUP($B112,'EECL Price List'!$A$12:$P$172,F$1,FALSE)=0,"",VLOOKUP($B112,'EECL Price List'!$A$12:$P$172,F$1,FALSE)) -> MTRINSPU | G112: =IF(VLOOKUP($B112,'EECL Price List'!$A$12:$P$172,G$1,FALSE)=0,"",VLOOKUP($B112,'EECL Price List'!$A$12:$P$172,G$1,FALSE)) -> MTRINSPS | H112: =IF(VLOOKUP($B112,'EECL Price List'!$A$12:$P$172,H$1,FALSE)=0,"",VLOOKUP($B112,'EECL Price List'!$A$12:$P$172,H$1,FALSE)) -> MTRINSPL | I112: =IF(VLOOKUP($B112,'EECL Price List'!$A$12:$P$172,I$1,FALSE)=0,"",VLOOKUP($B112,'EECL Price List'!$A$12:$P$172,I$1,FALSE)) -> MTRINSPI | J112: GENCF* | K112: =IFERROR(IF(VLOOKUP($C112,'EECL Price List'!$A$12:$P$172,G$1,FALSE)=0,"",VLOOKUP($C112,'EECL Price List'!$A$12:$P$172,G$1,FALSE)),"") | L112: =IFERROR(IF(VLOOKUP($C112,'EECL Price List'!$A$12:$P$172,H$1,FALSE)=0,"",VLOOKUP($C112,'EECL Price List'!$A$12:$P$172,H$1,FALSE)),"") | M112: =IFERROR(IF(VLOOKUP($C112,'EECL Price List'!$A$12:$P$172,I$1,FALSE)=0,"",VLOOKUP($C112,'EECL Price List'!$A$12:$P$172,I$1,FALSE)),"")
B113: 77 | E113: =VLOOKUP(B113,'EECL Price List'!$A$12:$P$172,2,FALSE) -> Metering alteration | F113: =IF(VLOOKUP($B113,'EECL Price List'!$A$12:$P$172,F$1,FALSE)=0,"",VLOOKUP($B113,'EECL Price List'!$A$12:$P$172,F$1,FALSE)) -> MOVEMTRU | G113: =IF(VLOOKUP($B113,'EECL Price List'!$A$12:$P$172,G$1,FALSE)=0,"",VLOOKUP($B113,'EECL Price List'!$A$12:$P$172,G$1,FALSE)) -> MOVEMTRS | H113: =IF(VLOOKUP($B113,'EECL Price List'!$A$12:$P$172,H$1,FALSE)=0,"",VLOOKUP($B113,'EECL Price List'!$A$12:$P$172,H$1,FALSE)) -> MOVEMTRL | I113: =IF(VLOOKUP($B113,'EECL Price List'!$A$12:$P$172,I$1,FALSE)=0,"",VLOOKUP($B113,'EECL Price List'!$A$12:$P$172,I$1,FALSE)) -> MOVEMTRI | J113: GENCF* | K113: =IFERROR(IF(VLOOKUP($C113,'EECL Price List'!$A$12:$P$172,G$1,FALSE)=0,"",VLOOKUP($C113,'EECL Price List'!$A$12:$P$172,G$1,FALSE)),"") | L113: =IFERROR(IF(VLOOKUP($C113,'EECL Price List'!$A$12:$P$172,H$1,FALSE)=0,"",VLOOKUP($C113,'EECL Price List'!$A$12:$P$172,H$1,FALSE)),"") | M113: =IFERROR(IF(VLOOKUP($C113,'EECL Price List'!$A$12:$P$172,I$1,FALSE)=0,"",VLOOKUP($C113,'EECL Price List'!$A$12:$P$172,I$1,FALSE)),"")
B114: 78 | E114: =VLOOKUP(B114,'EECL Price List'!$A$12:$P$172,2,FALSE) -> Exchange meter | F114: =IF(VLOOKUP($B114,'EECL Price List'!$A$12:$P$172,F$1,FALSE)=0,"",VLOOKUP($B114,'EECL Price List'!$A$12:$P$172,F$1,FALSE)) -> MTRREPU | G114: =IF(VLOOKUP($B114,'EECL Price List'!$A$12:$P$172,G$1,FALSE)=0,"",VLOOKUP($B114,'EECL Price List'!$A$12:$P$172,G$1,FALSE)) -> MTRREPS | H114: =IF(VLOOKUP($B114,'EECL Price List'!$A$12:$P$172,H$1,FALSE)=0,"",VLOOKUP($B114,'EECL Price List'!$A$12:$P$172,H$1,FALSE)) -> MTRREPL | I114: =IF(VLOOKUP($B114,'EECL Price List'!$A$12:$P$172,I$1,FALSE)=0,"",VLOOKUP($B114,'EECL Price List'!$A$12:$P$172,I$1,FALSE)) -> MTRREPI | J114: GENCF* | K114: =IFERROR(IF(VLOOKUP($C114,'EECL Price List'!$A$12:$P$172,G$1,FALSE)=0,"",VLOOKUP($C114,'EECL Price List'!$A$12:$P$172,G$1,FALSE)),"") | L114: =IFERROR(IF(VLOOKUP($C114,'EECL Price List'!$A$12:$P$172,H$1,FALSE)=0,"",VLOOKUP($C114,'EECL Price List'!$A$12:$P$172,H$1,FALSE)),"") | M114: =IFERROR(IF(VLOOKUP($C114,'EECL Price List'!$A$12:$P$172,I$1,FALSE)=0,"",VLOOKUP($C114,'EECL Price List'!$A$12:$P$172,I$1,FALSE)),"")
B115: 79 | E115: =VLOOKUP(B115,'EECL Price List'!$A$12:$P$172,2,FALSE) -> Type 5 to 7 non-standard metering services | F115: =IF(VLOOKUP($B115,'EECL Price List'!$A$12:$P$172,F$1,FALSE)=0,"",VLOOKUP($B115,'EECL Price List'!$A$12:$P$172,F$1,FALSE)) -> As Quoted | G115: =IF(VLOOKUP($B115,'EECL Price List'!$A$12:$P$172,G$1,FALSE)=0,"",VLOOKUP($B115,'EECL Price List'!$A$12:$P$172,G$1,FALSE)) | H115: =IF(VLOOKUP($B115,'EECL Price List'!$A$12:$P$172,H$1,FALSE)=0,"",VLOOKUP($B115,'EECL Price List'!$A$12:$P$172,H$1,FALSE)) | I115: =IF(VLOOKUP($B115,'EECL Price List'!$A$12:$P$172,I$1,FALSE)=0,"",VLOOKUP($B115,'EECL Price List'!$A$12:$P$172,I$1,FALSE)) | J115: GENCF* | K115: =IFERROR(IF(VLOOKUP($C115,'EECL Price List'!$A$12:$P$172,G$1,FALSE)=0,"",VLOOKUP($C115,'EECL Price List'!$A$12:$P$172,G$1,FALSE)),"") | L115: =IFERROR(IF(VLOOKUP($C115,'EECL Price List'!$A$12:$P$172,H$1,FALSE)=0,"",VLOOKUP($C115,'EECL Price List'!$A$12:$P$172,H$1,FALSE)),"") | M115: =IFERROR(IF(VLOOKUP($C115,'EECL Price List'!$A$12:$P$172,I$1,FALSE)=0,"",VLOOKUP($C115,'EECL Price List'!$A$12:$P$172,I$1,FALSE)),"")
B116: 80 | E116: =VLOOKUP(B116,'EECL Price List'!$A$12:$P$172,2,FALSE) -> Removal of a meter (Type 5 & 6) | F116: =IF(VLOOKUP($B116,'EECL Price List'!$A$12:$P$172,F$1,FALSE)=0,"",VLOOKUP($B116,'EECL Price List'!$A$12:$P$172,F$1,FALSE)) -> RMMTRU | G116: =IF(VLOOKUP($B116,'EECL Price List'!$A$12:$P$172,G$1,FALSE)=0,"",VLOOKUP($B116,'EECL Price List'!$A$12:$P$172,G$1,FALSE)) -> RMMTRS | H116: =IF(VLOOKUP($B116,'EECL Price List'!$A$12:$P$172,H$1,FALSE)=0,"",VLOOKUP($B116,'EECL Price List'!$A$12:$P$172,H$1,FALSE)) -> RMMTRL | I116: =IF(VLOOKUP($B116,'EECL Price List'!$A$12:$P$172,I$1,FALSE)=0,"",VLOOKUP($B116,'EECL Price List'!$A$12:$P$172,I$1,FALSE)) -> RMMTRI | J116: GENCF* | K116: =IFERROR(IF(VLOOKUP($C116,'EECL Price List'!$A$12:$P$172,G$1,FALSE)=0,"",VLOOKUP($C116,'EECL Price List'!$A$12:$P$172,G$1,FALSE)),"") | L116: =IFERROR(IF(VLOOKUP($C116,'EECL Price List'!$A$12:$P$172,H$1,FALSE)=0,"",VLOOKUP($C116,'EECL Price List'!$A$12:$P$172,H$1,FALSE)),"") | M116: =IFERROR(IF(VLOOKUP($C116,'EECL Price List'!$A$12:$P$172,I$1,FALSE)=0,"",VLOOKUP($C116,'EECL Price List'!$A$12:$P$172,I$1,FALSE)),"")
B117: 81 | E117: =VLOOKUP(B117,'EECL Price List'!$A$12:$P$172,2,FALSE) -> Meter re-seal | F117: =IF(VLOOKUP($B117,'EECL Price List'!$A$12:$P$172,F$1,FALSE)=0,"",VLOOKUP($B117,'EECL Price List'!$A$12:$P$172,F$1,FALSE)) -> MTRSEALU | G117: =IF(VLOOKUP($B117,'EECL Price List'!$A$12:$P$172,G$1,FALSE)=0,"",VLOOKUP($B117,'EECL Price List'!$A$12:$P$172,G$1,FALSE)) -> MTRSEALS | H117: =IF(VLOOKUP($B117,'EECL Price List'!$A$12:$P$172,H$1,FALSE)=0,"",VLOOKUP($B117,'EECL Price List'!$A$12:$P$172,H$1,FALSE)) -> MTRSEALL | I117: =IF(VLOOKUP($B117,'EECL Price List'!$A$12:$P$172,I$1,FALSE)=0,"",VLOOKUP($B117,'EECL Price List'!$A$12:$P$172,I$1,FALSE)) -> MTRSEALI | J117: GENCF* | K117: =IFERROR(IF(VLOOKUP($C117,'EECL Price List'!$A$12:$P$172,G$1,FALSE)=0,"",VLOOKUP($C117,'EECL Price List'!$A$12:$P$172,G$1,FALSE)),"") | L117: =IFERROR(IF(VLOOKUP($C117,'EECL Price List'!$A$12:$P$172,H$1,FALSE)=0,"",VLOOKUP($C117,'EECL Price List'!$A$12:$P$172,H$1,FALSE)),"") | M117: =IFERROR(IF(VLOOKUP($C117,'EECL Price List'!$A$12:$P$172,I$1,FALSE)=0,"",VLOOKUP($C117,'EECL Price List'!$A$12:$P$172,I$1,FALSE)),"")
B118: 82 | E118: =VLOOKUP(B118,'EECL Price List'!$A$12:$P$172,2,FALSE) -> Install new or replacement meter - after hours | F118: =IF(VLOOKUP($B118,'EECL Price List'!$A$12:$P$172,F$1,FALSE)=0,"",VLOOKUP($B118,'EECL Price List'!$A$12:$P$172,F$1,FALSE)) -> NRMAHU | G118: =IF(VLOOKUP($B118,'EECL Price List'!$A$12:$P$172,G$1,FALSE)=0,"",VLOOKUP($B118,'EECL Price List'!$A$12:$P$172,G$1,FALSE)) -> NRMAHS | H118: =IF(VLOOKUP($B118,'EECL Price List'!$A$12:$P$172,H$1,FALSE)=0,"",VLOOKUP($B118,'EECL Price List'!$A$12:$P$172,H$1,FALSE)) -> NRMAHL | I118: =IF(VLOOKUP($B118,'EECL Price List'!$A$12:$P$172,I$1,FALSE)=0,"",VLOOKUP($B118,'EECL Price List'!$A$12:$P$172,I$1,FALSE)) -> NRMAHI | J118: GENCF* | K118: =IFERROR(IF(VLOOKUP($C118,'EECL Price List'!$A$12:$P$172,G$1,FALSE)=0,"",VLOOKUP($C118,'EECL Price List'!$A$12:$P$172,G$1,FALSE)),"") | L118: =IFERROR(IF(VLOOKUP($C118,'EECL Price List'!$A$12:$P$172,H$1,FALSE)=0,"",VLOOKUP($C118,'EECL Price List'!$A$12:$P$172,H$1,FALSE)),"") | M118: =IFERROR(IF(VLOOKUP($C118,'EECL Price List'!$A$12:$P$172,I$1,FALSE)=0,"",VLOOKUP($C118,'EECL Price List'!$A$12:$P$172,I$1,FALSE)),"")
B119: 83 | E119: =VLOOKUP(B119,'EECL Price List'!$A$12:$P$172,2,FALSE) -> Change time switch | F119: =IF(VLOOKUP($B119,'EECL Price List'!$A$12:$P$172,F$1,FALSE)=0,"",VLOOKUP($B119,'EECL Price List'!$A$12:$P$172,F$1,FALSE)) -> CHTSRAU | G119: =IF(VLOOKUP($B119,'EECL Price List'!$A$12:$P$172,G$1,FALSE)=0,"",VLOOKUP($B119,'EECL Price List'!$A$12:$P$172,G$1,FALSE)) -> CHTSRAS | H119: =IF(VLOOKUP($B119,'EECL Price List'!$A$12:$P$172,H$1,FALSE)=0,"",VLOOKUP($B119,'EECL Price List'!$A$12:$P$172,H$1,FALSE)) -> CHTSRAL | I119: =IF(VLOOKUP($B119,'EECL Price List'!$A$12:$P$172,I$1,FALSE)=0,"",VLOOKUP($B119,'EECL Price List'!$A$12:$P$172,I$1,FALSE)) -> CHTSRAI | J119: GENCF* | K119: =IFERROR(IF(VLOOKUP($C119,'EECL Price List'!$A$12:$P$172,G$1,FALSE)=0,"",VLOOKUP($C119,'EECL Price List'!$A$12:$P$172,G$1,FALSE)),"") | L119: =IFERROR(IF(VLOOKUP($C119,'EECL Price List'!$A$12:$P$172,H$1,FALSE)=0,"",VLOOKUP($C119,'EECL Price List'!$A$12:$P$172,H$1,FALSE)),"") | M119: =IFERROR(IF(VLOOKUP($C119,'EECL Price List'!$A$12:$P$172,I$1,FALSE)=0,"",VLOOKUP($C119,'EECL Price List'!$A$12:$P$172,I$1,FALSE)),"")
B120: 84 | E120: =VLOOKUP(B120,'EECL Price List'!$A$12:$P$172,2,FALSE) -> Change tariff | F120: =IF(VLOOKUP($B120,'EECL Price List'!$A$12:$P$172,F$1,FALSE)=0,"",VLOOKUP($B120,'EECL Price List'!$A$12:$P$172,F$1,FALSE)) -> CHTARIFU | G120: =IF(VLOOKUP($B120,'EECL Price List'!$A$12:$P$172,G$1,FALSE)=0,"",VLOOKUP($B120,'EECL Price List'!$A$12:$P$172,G$1,FALSE)) -> CHTARIFS | H120: =IF(VLOOKUP($B120,'EECL Price List'!$A$12:$P$172,H$1,FALSE)=0,"",VLOOKUP($B120,'EECL Price List'!$A$12:$P$172,H$1,FALSE)) -> CHTARIFL | I120: =IF(VLOOKUP($B120,'EECL Price List'!$A$12:$P$172,I$1,FALSE)=0,"",VLOOKUP($B120,'EECL Price List'!$A$12:$P$172,I$1,FALSE)) -> CHTARIFI | J120: GENCF* | K120: =IFERROR(IF(VLOOKUP($C120,'EECL Price List'!$A$12:$P$172,G$1,FALSE)=0,"",VLOOKUP($C120,'EECL Price List'!$A$12:$P$172,G$1,FALSE)),"") | L120: =IFERROR(IF(VLOOKUP($C120,'EECL Price List'!$A$12:$P$172,H$1,FALSE)=0,"",VLOOKUP($C120,'EECL Price List'!$A$12:$P$172,H$1,FALSE)),"") | M120: =IFERROR(IF(VLOOKUP($C120,'EECL Price List'!$A$12:$P$172,I$1,FALSE)=0,"",VLOOKUP($C120,'EECL Price List'!$A$12:$P$172,I$1,FALSE)),"")
B121: 85 | E121: =VLOOKUP(B121,'EECL Price List'!$A$12:$P$172,2,FALSE) -> Reprogram card meters | F121: =IF(VLOOKUP($B121,'EECL Price List'!$A$12:$P$172,F$1,FALSE)=0,"",VLOOKUP($B121,'EECL Price List'!$A$12:$P$172,F$1,FALSE)) -> PRCDMTRU | G121: =IF(VLOOKUP($B121,'EECL Price List'!$A$12:$P$172,G$1,FALSE)=0,"",VLOOKUP($B121,'EECL Price List'!$A$12:$P$172,G$1,FALSE)) -> PRCDMTRS | H121: =IF(VLOOKUP($B121,'EECL Price List'!$A$12:$P$172,H$1,FALSE)=0,"",VLOOKUP($B121,'EECL Price List'!$A$12:$P$172,H$1,FALSE)) -> PRCDMTRL | I121: =IF(VLOOKUP($B121,'EECL Price List'!$A$12:$P$172,I$1,FALSE)=0,"",VLOOKUP($B121,'EECL Price List'!$A$12:$P$172,I$1,FALSE)) -> PRCDMTRI | J121: GENCF* | K121: =IFERROR(IF(VLOOKUP($C121,'EECL Price List'!$A$12:$P$172,G$1,FALSE)=0,"",VLOOKUP($C121,'EECL Price List'!$A$12:$P$172,G$1,FALSE)),"") | L121: =IFERROR(IF(VLOOKUP($C121,'EECL Price List'!$A$12:$P$172,H$1,FALSE)=0,"",VLOOKUP($C121,'EECL Price List'!$A$12:$P$172,H$1,FALSE)),"") | M121: =IFERROR(IF(VLOOKUP($C121,'EECL Price List'!$A$12:$P$172,I$1,FALSE)=0,"",VLOOKUP($C121,'EECL Price List'!$A$12:$P$172,I$1,FALSE)),"")
B122: 86 | E122: =VLOOKUP(B122,'EECL Price List'!$A$12:$P$172,2,FALSE) -> Install metering related load control | F122: =IF(VLOOKUP($B122,'EECL Price List'!$A$12:$P$172,F$1,FALSE)=0,"",VLOOKUP($B122,'EECL Price List'!$A$12:$P$172,F$1,FALSE)) -> INMTRLDCU | G122: =IF(VLOOKUP($B122,'EECL Price List'!$A$12:$P$172,G$1,FALSE)=0,"",VLOOKUP($B122,'EECL Price List'!$A$12:$P$172,G$1,FALSE)) -> INMTRLDCS | H122: =IF(VLOOKUP($B122,'EECL Price List'!$A$12:$P$172,H$1,FALSE)=0,"",VLOOKUP($B122,'EECL Price List'!$A$12:$P$172,H$1,FALSE)) -> INMTRLDCL | I122: =IF(VLOOKUP($B122,'EECL Price List'!$A$12:$P$172,I$1,FALSE)=0,"",VLOOKUP($B122,'EECL Price List'!$A$12:$P$172,I$1,FALSE)) -> INMTRLDCI | J122: GENCF* | K122: =IFERROR(IF(VLOOKUP($C122,'EECL Price List'!$A$12:$P$172,G$1,FALSE)=0,"",VLOOKUP($C122,'EECL Price List'!$A$12:$P$172,G$1,FALSE)),"") | L122: =IFERROR(IF(VLOOKUP($C122,'EECL Price List'!$A$12:$P$172,H$1,FALSE)=0,"",VLOOKUP($C122,'EECL Price List'!$A$12:$P$172,H$1,FALSE)),"") | M122: =IFERROR(IF(VLOOKUP($C122,'EECL Price List'!$A$12:$P$172,I$1,FALSE)=0,"",VLOOKUP($C122,'EECL Price List'!$A$12:$P$172,I$1,FALSE)),"")
B123: 87 | E123: =VLOOKUP(B123,'EECL Price List'!$A$12:$P$172,2,FALSE) -> Removal of load control device | F123: =IF(VLOOKUP($B123,'EECL Price List'!$A$12:$P$172,F$1,FALSE)=0,"",VLOOKUP($B123,'EECL Price List'!$A$12:$P$172,F$1,FALSE)) -> RMLDCRLU | G123: =IF(VLOOKUP($B123,'EECL Price List'!$A$12:$P$172,G$1,FALSE)=0,"",VLOOKUP($B123,'EECL Price List'!$A$12:$P$172,G$1,FALSE)) -> RMLDCRLS | H123: =IF(VLOOKUP($B123,'EECL Price List'!$A$12:$P$172,H$1,FALSE)=0,"",VLOOKUP($B123,'EECL Price List'!$A$12:$P$172,H$1,FALSE)) -> RMLDCRLL | I123: =IF(VLOOKUP($B123,'EECL Price List'!$A$12:$P$172,I$1,FALSE)=0,"",VLOOKUP($B123,'EECL Price List'!$A$12:$P$172,I$1,FALSE)) -> RMLDCRLI | J123: GENCF* | K123: =IFERROR(IF(VLOOKUP($C123,'EECL Price List'!$A$12:$P$172,G$1,FALSE)=0,"",VLOOKUP($C123,'EECL Price List'!$A$12:$P$172,G$1,FALSE)),"") | L123: =IFERROR(IF(VLOOKUP($C123,'EECL Price List'!$A$12:$P$172,H$1,FALSE)=0,"",VLOOKUP($C123,'EECL Price List'!$A$12:$P$172,H$1,FALSE)),"") | M123: =IFERROR(IF(VLOOKUP($C123,'EECL Price List'!$A$12:$P$172,I$1,FALSE)=0,"",VLOOKUP($C123,'EECL Price List'!$A$12:$P$172,I$1,FALSE)),"")
... B134: 98 | E134: =VLOOKUP(B134,'EECL Price List'!$A$12:$P$172,2,FALSE) -> Removal/rearrangement of public lighting assets | F134: =IF(VLOOKUP($B134,'EECL Price List'!$A$12:$P$172,F$1,FALSE)=0,"",VLOOKUP($B134,'EECL Price List'!$A$12:$P$172,F$1,FALSE)) -> As Quoted | G134: =IF(VLOOKUP($B134,'EECL Price List'!$A$12:$P$172,G$1,FALSE)=0,"",VLOOKUP($B134,'EECL Price List'!$A$12:$P$172,G$1,FALSE)) | H134: =IF(VLOOKUP($B134,'EECL Price List'!$A$12:$P$172,H$1,FALSE)=0,"",VLOOKUP($B134,'EECL Price List'!$A$12:$P$172,H$1,FALSE)) | I134: =IF(VLOOKUP($B134,'EECL Price List'!$A$12:$P$172,I$1,FALSE)=0,"",VLOOKUP($B134,'EECL Price List'!$A$12:$P$172,I$1,FALSE)) | J134: GENCF* | K134: =IFERROR(IF(VLOOKUP($C134,'EECL Price List'!$A$12:$P$172,G$1,FALSE)=0,"",VLOOKUP($C134,'EECL Price List'!$A$12:$P$172,G$1,FALSE)),"") | L134: =IFERROR(IF(VLOOKUP($C134,'EECL Price List'!$A$12:$P$172,H$1,FALSE)=0,"",VLOOKUP($C134,'EECL Price List'!$A$12:$P$172,H$1,FALSE)),"") | M134: =IFERROR(IF(VLOOKUP($C134,'EECL Price List'!$A$12:$P$172,I$1,FALSE)=0,"",VLOOKUP($C134,'EECL Price List'!$A$12:$P$172,I$1,FALSE)),"")
B135: 100 | D135: Default Metering Services | E135: =VLOOKUP(B135,'EECL Price List'!$A$12:$P$172,2,FALSE) -> Primary service - Non-capital | F135: =IF(VLOOKUP($B135,'EECL Price List'!$A$12:$P$172,F$1,FALSE)=0,"",VLOOKUP($B135,'EECL Price List'!$A$12:$P$172,F$1,FALSE)) -> ACSMNCC | G135: =IF(VLOOKUP($B135,'EECL Price List'!$A$12:$P$172,G$1,FALSE)=0,"",VLOOKUP($B135,'EECL Price List'!$A$12:$P$172,G$1,FALSE)) | H135: =IF(VLOOKUP($B135,'EECL Price List'!$A$12:$P$172,H$1,FALSE)=0,"",VLOOKUP($B135,'EECL Price List'!$A$12:$P$172,H$1,FALSE)) | I135: =IF(VLOOKUP($B135,'EECL Price List'!$A$12:$P$172,I$1,FALSE)=0,"",VLOOKUP($B135,'EECL Price List'!$A$12:$P$172,I$1,FALSE))
B136: 101 | E136: =VLOOKUP(B136,'EECL Price List'!$A$12:$P$172,2,FALSE) -> Primary service - Capital | F136: =IF(VLOOKUP($B136,'EECL Price List'!$A$12:$P$172,F$1,FALSE)=0,"",VLOOKUP($B136,'EECL Price List'!$A$12:$P$172,F$1,FALSE)) -> ACSMCC | G136: =IF(VLOOKUP($B136,'EECL Price List'!$A$12:$P$172,G$1,FALSE)=0,"",VLOOKUP($B136,'EECL Price List'!$A$12:$P$172,G$1,FALSE)) | H136: =IF(VLOOKUP($B136,'EECL Price List'!$A$12:$P$172,H$1,FALSE)=0,"",VLOOKUP($B136,'EECL Price List'!$A$12:$P$172,H$1,FALSE)) | I136: =IF(VLOOKUP($B136,'EECL Price List'!$A$12:$P$172,I$1,FALSE)=0,"",VLOOKUP($B136,'EECL Price List'!$A$12:$P$172,I$1,FALSE))
B137: 102 | E137: =VLOOKUP(B137,'EECL Price List'!$A$12:$P$172,2,FALSE) -> Controlled load - Non-capital | F137: =IF(VLOOKUP($B137,'EECL Price List'!$A$12:$P$172,F$1,FALSE)=0,"",VLOOKUP($B137,'EECL Price List'!$A$12:$P$172,F$1,FALSE)) -> ACSMNCC | G137: =IF(VLOOKUP($B137,'EECL Price List'!$A$12:$P$172,G$1,FALSE)=0,"",VLOOKUP($B137,'EECL Price List'!$A$12:$P$172,G$1,FALSE)) | H137: =IF(VLOOKUP($B137,'EECL Price List'!$A$12:$P$172,H$1,FALSE)=0,"",VLOOKUP($B137,'EECL Price List'!$A$12:$P$172,H$1,FALSE)) | I137: =IF(VLOOKUP($B137,'EECL Price List'!$A$12:$P$172,I$1,FALSE)=0,"",VLOOKUP($B137,'EECL Price List'!$A$12:$P$172,I$1,FALSE))
B138: 103 | E138: =VLOOKUP(B138,'EECL Price List'!$A$12:$P$172,2,FALSE) -> Controlled load - Capital | F138: =IF(VLOOKUP($B138,'EECL Price List'!$A$12:$P$172,F$1,FALSE)=0,"",VLOOKUP($B138,'EECL Price List'!$A$12:$P$172,F$1,FALSE)) -> ACSMCC | G138: =IF(VLOOKUP($B138,'EECL Price List'!$A$12:$P$172,G$1,FALSE)=0,"",VLOOKUP($B138,'EECL Price List'!$A$12:$P$172,G$1,FALSE)) | H138: =IF(VLOOKUP($B138,'EECL Price List'!$A$12:$P$172,H$1,FALSE)=0,"",VLOOKUP($B138,'EECL Price List'!$A$12:$P$172,H$1,FALSE)) | I138: =IF(VLOOKUP($B138,'EECL Price List'!$A$12:$P$172,I$1,FALSE)=0,"",VLOOKUP($B138,'EECL Price List'!$A$12:$P$172,I$1,FALSE))
B139: 104 | E139: =VLOOKUP(B139,'EECL Price List'!$A$12:$P$172,2,FALSE) -> Embedded generation - Non-capital | F139: =IF(VLOOKUP($B139,'EECL Price List'!$A$12:$P$172,F$1,FALSE)=0,"",VLOOKUP($B139,'EECL Price List'!$A$12:$P$172,F$1,FALSE)) -> ACSMNCC | G139: =IF(VLOOKUP($B139,'EECL Price List'!$A$12:$P$172,G$1,FALSE)=0,"",VLOOKUP($B139,'EECL Price List'!$A$12:$P$172,G$1,FALSE)) | H139: =IF(VLOOKUP($B139,'EECL Price List'!$A$12:$P$172,H$1,FALSE)=0,"",VLOOKUP($B139,'EECL Price List'!$A$12:$P$172,H$1,FALSE)) | I139: =IF(VLOOKUP($B139,'EECL Price List'!$A$12:$P$172,I$1,FALSE)=0,"",VLOOKUP($B139,'EECL Price List'!$A$12:$P$172,I$1,FALSE))
B140: 105 | E140: =VLOOKUP(B140,'EECL Price List'!$A$12:$P$172,2,FALSE) -> Embedded generation - Capital | F140: =IF(VLOOKUP($B140,'EECL Price List'!$A$12:$P$172,F$1,FALSE)=0,"",VLOOKUP($B140,'EECL Price List'!$A$12:$P$172,F$1,FALSE)) -> ACSMCC | G140: =IF(VLOOKUP($B140,'EECL Price List'!$A$12:$P$172,G$1,FALSE)=0,"",VLOOKUP($B140,'EECL Price List'!$A$12:$P$172,G$1,FALSE)) | H140: =IF(VLOOKUP($B140,'EECL Price List'!$A$12:$P$172,H$1,FALSE)=0,"",VLOOKUP($B140,'EECL Price List'!$A$12:$P$172,H$1,FALSE)) | I140: =IF(VLOOKUP($B140,'EECL Price List'!$A$12:$P$172,I$1,FALSE)=0,"",VLOOKUP($B140,'EECL Price List'!$A$12:$P$172,I$1,FALSE))
B141: 106-CF | E141: =VLOOKUP(B141,'EECL Price List'!$A$12:$P$172,2,FALSE) -> Call out fee for Final Meter Read – urban/short rural feeder | J141: =IF(VLOOKUP($B141,'EECL Price List'!$A$12:$P$172,F$1,FALSE)=0,"",VLOOKUP($B141,'EECL Price List'!$A$12:$P$172,F$1,FALSE)) -> CFFMTRRDU | K141: =IF(VLOOKUP($B141,'EECL Price List'!$A$12:$P$172,G$1,FALSE)=0,"",VLOOKUP($B141,'EECL Price List'!$A$12:$P$172,G$1,FALSE)) -> CFFMTRRDS | L141: =IF(VLOOKUP($B141,'EECL Price List'!$A$12:$P$172,H$1,FALSE)=0,"",VLOOKUP($B141,'EECL Price List'!$A$12:$P$172,H$1,FALSE)) | M141: =IF(VLOOKUP($B141,'EECL Price List'!$A$12:$P$172,I$1,FALSE)=0,"",VLOOKUP($B141,'EECL Price List'!$A$12:$P$172,I$1,FALSE))
B142: 107-CF | E142: =VLOOKUP(B142,'EECL Price List'!$A$12:$P$172,2,FALSE) -> Call out fee for Final Meter Read – long rural/isolated feeder | J142: =IF(VLOOKUP($B142,'EECL Price List'!$A$12:$P$172,F$1,FALSE)=0,"",VLOOKUP($B142,'EECL Price List'!$A$12:$P$172,F$1,FALSE)) | K142: =IF(VLOOKUP($B142,'EECL Price List'!$A$12:$P$172,G$1,FALSE)=0,"",VLOOKUP($B142,'EECL Price List'!$A$12:$P$172,G$1,FALSE)) | L142: =IF(VLOOKUP($B142,'EECL Price List'!$A$12:$P$172,H$1,FALSE)=0,"",VLOOKUP($B142,'EECL Price List'!$A$12:$P$172,H$1,FALSE)) -> CFFMTRRDL | M142: =IF(VLOOKUP($B142,'EECL Price List'!$A$12:$P$172,I$1,FALSE)=0,"",VLOOKUP($B142,'EECL Price List'!$A$12:$P$172,I$1,FALSE)) -> CFFMTRRDI
...
