Workbook
Name Base_Year: Lookup!$E$11
Name Cents_to_Dollars: Lookup!$D$33
Name Days_In_Wk: Lookup!$D$30
Name Days_In_Yr: Lookup!$D$31
Name Dollars: Lookup!$D$47
Name Dollars_to_Thousands: Lookup!$D$34
Name End_year: Lookup!$F$81
Name Error: Lookup!$D$37
Name Factor: Lookup!$D$50
Name Half: Lookup!$D$32
Name Kilometres: Lookup!$D$65
Name LU_Basis: Lookup!$D$70:$D$75
Name LU_Fee_Based_Services: Lookup!$D$102:$D$128
Name LU_Metering_Services: Lookup!$D$95:$D$97
Name LU_Quoted_Services: Lookup!$D$133:$D$148
Name LU_Revenue_Input: Lookup!$D$86:$D$88
Name LU_Service_Categories: Lookup!$D$153:$D$159
Name LU_Timing: Lookup!$D$79:$D$82
Name LU_Timing_Value: Lookup!$E$79:$E$82
Name LU_Units: Lookup!$D$46:$D$66
Name Mid_year: Lookup!$D$80
Name Millions: Lookup!$D$48
Name Model_Name: Cover!$B$3
Name Model_Start_Date: Lookup!$E$10
Name Mths_In_Mth: Lookup!$D$26
Name Mths_In_Qtr: Lookup!$D$27
Name Mths_In_Yr: Lookup!$D$29
Name NA: Lookup!$D$36
Name No: Lookup!$D$42
Name No_Input: Lookup!$D$88
Name Nominal: Lookup!$D$75
Name Number: Lookup!$D$51
Name Ok: Lookup!$D$35
Name Percent: Lookup!$D$46
Name Qtrs_In_Yr: Lookup!$D$28
Name Real2018: Lookup!$D$70
Name Real2019: Lookup!$D$71
Name Real2020: Lookup!$D$72
Name Start_year: Lookup!$D$79
Name Thousands: Lookup!$D$49
Name Title_Msg: Checks!$H$10
Name Yes: Lookup!$D$41
Name Yes_No: Lookup!$D$41:$D$42

Sheet Cover
B3: ACS Pricing Model - Power and Water Corporation
C11: Model Developer: | F11: Power and Water Corporation
C13: Purpose of the Model:
C14: The purpose of this model is to assesses tariffs for alternative control services (ACS) applicable to Power and Water Corporation customers and demonstrate compliance with AER requirements.
C16: Model Legend:
D19: Assumptions | F19: Cells containing assumptions intended to be manipulated by model users
D20: Drop Down | F20: Cells containing a drop down list for users to select inputs
D21: Input | F21: Cells containing input texts/numbers NOT intended to be changed by model users
D22: Output | F22: Cells containing formulae NOT intended to be changed by model users
D23: Heading 1 | F23: Level 1 heading NOT intended to be changed by model users
D24: Heading 2 | F24: Level 2 heading NOT intended to be changed by model users
F25: Cells where inputs or outputs are not applicable
D26: Hyperlink | F26: Cells containing a hyperlink to another part of the workbook
D27: Error | F27: Cells representing there is an error in the nominated area of the workbook
D28: Ok | F28: Cells representing there are no errors in the nominated area of the workbook
F29: Cells containing a link from external workbooks
C32: Disclaimer:
C33: This model is confidential information of, and is owned by, Power and Water Corporation ABN 15 947 352 360 (PWC). It may not be disclosed to, or used or relied on by, any person without the consent of PWC. PWC has not verified the inputs or the outputs of this model and makes no representation or warranty as to the completeness, accuracy, reliability or appropriateness of the model, its inputs and outputs (including any forward looking statements) or how it functions. To the extent permitted by law, any person using or relying on this model or its outputs does so at their own risk and agrees that PWC will not be liable to any person for any loss or damage of any kind arising out of or in any way connected with the use of this model (including negligence). The references to PWC in this disclaimer includes their respective directors, officers, employees, contractors, advisers or agents.

Sheet TOC
B1: Table of Contents
B2: =Title_Msg -> No Errors Found
B3: Go to Cover Sheet
B4: =Model_Name -> ACS Pricing Model - Power and Water Corporation
B6: =B1 -> Table of Contents
C8: Inputs
D10: =Inputs_Prices!$B$1 -> Inputs - Prices
C12: Calculations
D14: =Calculations_Price_Caps!$B$1 -> Calculation - Price Caps
C16: Outputs
D18: =Output_Compliance!$B$1 -> Output - Compliance
D19: =Output_Pricing_Proposal!B1 -> Output - Pricing Proposal
C21: Appendix
D23: =Lookup!B1 -> Model Lookups
D24: =Checks!B1 -> Checks
B26: End

Sheet Diagram
A1: =IF(SUM($A6:$A50)>0,1,0) -> 0 | B1: Model Diagram
B2: =Title_Msg -> No Errors Found
B3: =TOC!B1 -> Table of Contents
B4: =Model_Name -> ACS Pricing Model - Power and Water Corporation
B6: =B1 -> Model Diagram
B50: End

Sheet Inputs_Prices
A1: =IF(SUM($A11:$A261)>0,1,0) -> 0 | B1: Inputs - Prices
B2: =Title_Msg -> No Errors Found
B3: =TOC!B1 -> Table of Contents
B4: =Model_Name -> ACS Pricing Model - Power and Water Corporation
B5: =Lookup!B15 -> Period Start Date | M5: =Lookup!M15 -> 42917 | N5: =Lookup!N15 -> 43282 | O5: =Lookup!O15 -> 43647 | P5: =Lookup!P15 -> 44013 | Q5: =Lookup!Q15 -> 44378 | R5: =Lookup!R15 -> 44743 | S5: =Lookup!S15 -> 45108
B6: =Lookup!B16 -> Period End Date | M6: =Lookup!M16 -> 43281 | N6: =Lookup!N16 -> 43646 | O6: =Lookup!O16 -> 44012 | P6: =Lookup!P16 -> 44377 | Q6: =Lookup!Q16 -> 44742 | R6: =Lookup!R16 -> 45107 | S6: =Lookup!S16 -> 45473
B7: =Lookup!B17 -> Period Counter | M7: =Lookup!M17 -> 4 | N7: =Lookup!N17 -> 5 | O7: =Lookup!O17 -> 6 | P7: =Lookup!P17 -> 7 | Q7: =Lookup!Q17 -> 8 | R7: =Lookup!R17 -> 9 | S7: =Lookup!S17 -> 10
B8: =Lookup!B18 -> Year | M8: =Lookup!M18 -> 2018 | N8: =Lookup!N18 -> 2019 | O8: =Lookup!O18 -> 2020 | P8: =Lookup!P18 -> 2021 | Q8: =Lookup!Q18 -> 2022 | R8: =Lookup!R18 -> 2023 | S8: =Lookup!S18 -> 2024
B9: =Lookup!B19 -> Days In Year | M9: =Lookup!M19 -> 365 | N9: =Lookup!N19 -> 365 | O9: =Lookup!O19 -> 366 | P9: =Lookup!P19 -> 365 | Q9: =Lookup!Q19 -> 365 | R9: =Lookup!R19 -> 365 | S9: =Lookup!S19 -> 366
B10: =Lookup!B20 -> FY | D10: Tariff | E10: Service Category | H10: Source | I10: Unit | J10: =Lookup!G20 -> Basis | M10: =Lookup!M20 -> FY18 | N10: =Lookup!N20 -> FY19 | O10: =Lookup!O20 -> FY20 | P10: =Lookup!P20 -> FY21 | Q10: =Lookup!Q20 -> FY22 | R10: =Lookup!R20 -> FY23 | S10: =Lookup!S20 -> FY24
B12: Inputs
D14: This sheet inputs the proposed prices for each ACS service along with the data used to calculate the price caps included within the AER's revenue determination for the 2019-24 period.
B17: PWC Inputs (Years 2 to 5)
D19: This section inputs values provided by PWC. The first sub-section inputs the proposed prices for years 2 to 5 of the regulatory period. The second sub-section inputs any proposed annual adjustments (e.g. to cover pass-throughs).
D20: As per the AER's determination, annual adjustments are only allowed for ACS metering and ACS fee based services.
C23: Prices (Years 2 to 5)
D26: Service | E26: =E$10 -> Service Category | H26: =H$10 -> Source | I26: =I$10 -> Unit | J26: =J$10 -> Basis | P26: =P$10 -> FY21 | Q26: =Q$10 -> FY22 | R26: =R$10 -> FY23 | S26: =S$10 -> FY24
D28: Metering Services (Types 1 to 6)
D29: {=LU_Metering_Services} -> 1 Phase Meters (including Prepayment) | H29: PWC | I29: $/Year/Meter | J29: Nominal | P29: 64.66 | Q29: 68.39 | R29: 72.34 | S29: 76.52 | U29: Note: proposed prices are rounded to 2 decimal places
D30: 3 Phase Meters | H30: PWC | I30: $/Year/Meter | J30: Nominal | P30: 71.19 | Q30: 75.3 | R30: 79.65 | S30: 84.25
D31: Dedicated CT and VT meters | H31: PWC | I31: $/Year/Meter | J31: Nominal | P31: 120.58 | Q31: 127.54 | R31: 134.9 | S31: 142.69
D33: Fee Based Services
D34: {=LU_Fee_Based_Services} -> Disconnection (and final read) | E34: Connection Services | H34: PWC | I34: $/Request | J34: Nominal | P34: 65.35 | Q34: 64 | R34: 62.64 | S34: 61.24
D35: Reconnection | E35: Connection Services | H35: PWC | I35: $/Request | J35: Nominal | P35: 65.35 | Q35: 64 | R35: 62.64 | S35: 61.24
D36: Reconnection - after hours | E36: Connection Services | H36: PWC | I36: $/Request | J36: Nominal | P36: 121.39 | Q36: 118.88 | R36: 116.35 | S36: 113.75
D37: Temporary disconnection and reconnection - physical dismantling | E37: Connection Services | H37: PWC | I37: $/Request | J37: Nominal | P37: 755.16 | Q37: 779.8 | R37: 806.48 | S37: 834
D38: Provision of 3 phase service | E38: Connection Services | H38: PWC | I38: $/Request | J38: Nominal | P38: 1434.81 | Q38: 1481.63 | R38: 1532.31 | S38: 1584.6
D39: Standard temporary builder’s connection | E39: Connection Services | H39: PWC | I39: $/Request | J39: Nominal | P39: 673.61 | Q39: 695.59 | R39: 719.39 | S39: 743.94
D40: Temporary disconnection and reconnection - no dismantling | E40: De-energisation / Re-energisation | H40: PWC | I40: $/Request | J40: Nominal | P40: 293 | Q40: 302.56 | R40: 312.91 | S40: 323.59
D41: Complex disconnection | E41: De-energisation / Re-energisation | H41: PWC | I41: $/Request | J41: Nominal | P41: 320.19 | Q41: 330.64 | R41: 341.95 | S41: 353.62
D42: Wasted visit fee | E42: Connection Services | H42: PWC | I42: $/Request | J42: Nominal | P42: 157.07 | Q42: 162.2 | R42: 167.75 | S42: 173.47
D43: Special meter test | E43: Meter Servicing (Fee based) | H43: PWC | I43: $/Request | J43: Nominal | P43: 306.6 | Q43: 316.61 | R43: 327.44 | S43: 338.61
D44: Exchange or replace meter – three phase | E44: Meter Servicing (Fee based) | H44: PWC | I44: $/Request | J44: Nominal | P44: 676.38 | Q44: 698.45 | R44: 722.34 | S44: 746.99
D45: Exchange or replace meter - single phase | E45: Meter Servicing (Fee based) | H45: PWC | I45: $/Request | J45: Nominal | P45: 566.26 | Q45: 584.74 | R45: 604.74 | S45: 625.38
D46: Relocation of meter | E46: Meter Servicing (Fee based) | H46: PWC | I46: $/Request | J46: Nominal | P46: 320.19 | Q46: 330.64 | R46: 341.95 | S46: 353.62
... D60: Class 1 & 2 PV service | E60: Connection Services | H60: PWC | I60: $/Request | J60: Nominal | P60: 89.3 | Q60: 92.21 | R60: 95.36 | S60: 98.61
D62: Quoted Services | Labour Component
D63: {=LU_Quoted_Services} -> Design related services | E63: Not Applicable | H63: PWC | I63: $/Hour | J63: Nominal | P63: 159.39 | Q63: 164.59 | R63: 170.22 | S63: 176.03
D64: Connection applications | E64: Not Applicable | H64: PWC | I64: $/Hour | J64: Nominal | P64: 159.39 | Q64: 164.59 | R64: 170.22 | S64: 176.03
D65: Access permits, oversights and facilitation | E65: Not Applicable | H65: PWC | I65: $/Hour | J65: Nominal | P65: 159.39 | Q65: 164.59 | R65: 170.22 | S65: 176.03
D66: Notices of arrangement and completion notices | E66: Not Applicable | H66: PWC | I66: $/Hour | J66: Nominal | P66: 89.3 | Q66: 92.21 | R66: 95.36 | S66: 98.61
D67: Network related property services | E67: Not Applicable | H67: PWC | I67: $/Hour | J67: Nominal | P67: 89.3 | Q67: 92.21 | R67: 95.36 | S67: 98.61
D68: Site establishment services | E68: Not Applicable | H68: PWC | I68: $/Hour | J68: Nominal | P68: 89.3 | Q68: 92.21 | R68: 95.36 | S68: 98.61
D69: Network safety services | E69: Not Applicable | H69: PWC | I69: $/Hour | J69: Nominal | P69: 135.92 | Q69: 140.36 | R69: 145.16 | S69: 150.11
D70: Network tariff change request | E70: Not Applicable | H70: PWC | I70: $/Hour | J70: Nominal | P70: 89.3 | Q70: 92.21 | R70: 95.36 | S70: 98.61
D71: Planned interruption - customer request | E71: Not Applicable | H71: PWC | I71: $/Hour | J71: Nominal | P71: 135.92 | Q71: 140.36 | R71: 145.16 | S71: 150.11
D72: Performance of a statutory right (access prevented) | E72: Not Applicable | H72: PWC | I72: $/Hour | J72: Nominal | P72: 135.92 | Q72: 140.36 | R72: 145.16 | S72: 150.11
D73: Provision of network related training to third parties | E73: Not Applicable | H73: PWC | I73: $/Hour | J73: Nominal | P73: 89.3 | Q73: 92.21 | R73: 95.36 | S73: 98.61
D74: Non-standard reporting services | E74: Not Applicable | H74: PWC | I74: $/Hour | J74: Nominal | P74: 89.3 | Q74: 92.21 | R74: 95.36 | S74: 98.61
D75: Services provided for retailer of last resort event | E75: Not Applicable | H75: PWC | I75: $/Hour | J75: Nominal | P75: 89.3 | Q75: 92.21 | R75: 95.36 | S75: 98.61
... D78: Annual prepayment meter licensing fee * | E78: Not Applicable | H78: PWC | I78: $/Hour | J78: Nominal | P78: 89.3 | Q78: 92.21 | R78: 95.36 | S78: 98.61
A80: =IF(SUM($O80:$S80)=0,0,1) -> 0 | D80: Check for errors | P80: {=IF(SUMPRODUCT(--ISERROR(P29:P78*1))<>0,1,0)} -> 0 | Q80: {=IF(SUMPRODUCT(--ISERROR(Q29:Q78*1))<>0,1,0)} -> 0 | R80: {=IF(SUMPRODUCT(--ISERROR(R29:R78*1))<>0,1,0)} -> 0 | S80: {=IF(SUMPRODUCT(--ISERROR(S29:S78*1))<>0,1,0)} -> 0
C82: Annual Adjustments for ACS Metering and Fee-based Services (Years 2 to 5)
D85: Service | H85: =Lookup!E$20 -> Source | I85: =Lookup!F$20 -> Unit | J85: =Lookup!G$20 -> Basis | P85: =P$10 -> FY21 | Q85: =Q$10 -> FY22 | R85: =R$10 -> FY23 | S85: =S$10 -> FY24
D87: Metering Services (Types 1 to 6)
D88: {=LU_Metering_Services} -> 1 Phase Meters (including Prepayment) | H88: PWC | I88: $/Year/Meter | J88: Nominal | P88: 0 | Q88: 0 | R88: 0 | S88: 0
D89: 3 Phase Meters | H89: PWC | I89: $/Year/Meter | J89: Nominal | P89: 0 | Q89: 0 | R89: 0 | S89: 0
D90: Dedicated CT and VT meters | H90: PWC | I90: $/Year/Meter | J90: Nominal | P90: 0 | Q90: 0 | R90: 0 | S90: 0
D92: Fee Based Services
D93: {=LU_Fee_Based_Services} -> Disconnection (and final read) | H93: PWC | I93: $/Request | J93: Nominal | P93: 0 | Q93: 0 | R93: 0 | S93: 0
D94: Reconnection | H94: PWC | I94: $/Request | J94: Nominal | P94: 0 | Q94: 0 | R94: 0 | S94: 0
D95: Reconnection - after hours | H95: PWC | I95: $/Request | J95: Nominal | P95: 0 | Q95: 0 | R95: 0 | S95: 0
D96: Temporary disconnection and reconnection - physical dismantling | H96: PWC | I96: $/Request | J96: Nominal | P96: 0 | Q96: 0 | R96: 0 | S96: 0
D97: Provision of 3 phase service | H97: PWC | I97: $/Request | J97: Nominal | P97: 0 | Q97: 0 | R97: 0 | S97: 0
D98: Standard temporary builder’s connection | H98: PWC | I98: $/Request | J98: Nominal | P98: 0 | Q98: 0 | R98: 0 | S98: 0
D99: Temporary disconnection and reconnection - no dismantling | H99: PWC | I99: $/Request | J99: Nominal | P99: 0 | Q99: 0 | R99: 0 | S99: 0
D100: Complex disconnection | H100: PWC | I100: $/Request | J100: Nominal | P100: 0 | Q100: 0 | R100: 0 | S100: 0
D101: Wasted visit fee | H101: PWC | I101: $/Request | J101: Nominal | P101: 0 | Q101: 0 | R101: 0 | S101: 0
D102: Special meter test | H102: PWC | I102: $/Request | J102: Nominal | P102: 0 | Q102: 0 | R102: 0 | S102: 0
D103: Exchange or replace meter – three phase | H103: PWC | I103: $/Request | J103: Nominal | P103: 0 | Q103: 0 | R103: 0 | S103: 0
D104: Exchange or replace meter - single phase | H104: PWC | I104: $/Request | J104: Nominal | P104: 0 | Q104: 0 | R104: 0 | S104: 0
D105: Relocation of meter | H105: PWC | I105: $/Request | J105: Nominal | P105: 0 | Q105: 0 | R105: 0 | S105: 0
... D108: Special meter read - no appointment | H108: PWC | I108: $/Request | J108: Nominal | P108: 0 | Q108: 0 | R108: 0 | S108: 0
D109: Special meter read - appointment | H109: PWC | I109: $/Request | J109: Nominal | Q109: 0 | R109: 0 | S109: 0
D110: Class 3 PV Assessment | H110: PWC | I110: $/Request | J110: Nominal | P110: 0 | Q110: 0 | R110: 0 | S110: 0
D111: Meter program change | H111: PWC | I111: $/Request | J111: Nominal | P111: 0 | Q111: 0 | R111: 0 | S111: 0
D112: Historical data requests | H112: PWC | I112: $/Request | J112: Nominal | P112: 0 | Q112: 0 | R112: 0 | S112: 0
D113: Standing data requests | H113: PWC | I113: $/Request | J113: Nominal | P113: 0 | Q113: 0 | R113: 0 | S113: 0
D114: Customer transfers | H114: PWC | I114: $/Request | J114: Nominal | P114: 0 | Q114: 0 | R114: 0 | S114: 0
D115: Network tariff change request | H115: PWC | I115: $/Request | J115: Nominal | P115: 0 | Q115: 0 | R115: 0 | S115: 0
D116: Prepayment Vending Charge | H116: PWC | I116: $/Request | J116: Nominal | P116: 0 | Q116: 0 | R116: 0 | S116: 0
D117: Prepayment Meter Support Charge | H117: PWC | I117: $/Request | J117: Nominal | P117: 0 | Q117: 0 | R117: 0 | S117: 0
D118: Installation of Minor Apparatus | H118: PWC | I118: $/Request | J118: Nominal | P118: 0 | Q118: 0 | R118: 0 | S118: 0
D119: Class 1 & 2 PV service | H119: PWC | I119: $/Request | J119: Nominal | P119: 0 | Q119: 0 | R119: 0 | S119: 0
A121: =IF(SUM($O121:$S121)=0,0,1) -> 0 | D121: Check for errors | P121: {=IF(SUMPRODUCT(--ISERROR(P88:P119*1))<>0,1,0)} -> 0 | Q121: {=IF(SUMPRODUCT(--ISERROR(Q88:Q119*1))<>0,1,0)} -> 0 | R121: {=IF(SUMPRODUCT(--ISERROR(R88:R119*1))<>0,1,0)} -> 0 | S121: {=IF(SUMPRODUCT(--ISERROR(S88:S119*1))<>0,1,0)} -> 0
B123: Determination Values
D125: This section inputs values from relevant network price determinations, including for annual return on debt updates. The first sub-section inputs inflation inputs. The second sub-section inputs the year 1 tariffs for each service.
D126: The third sub-section inputs the X-factors for each service.
C129: Inflation
D132: Item | H132: =Lookup!E$20 -> Source | I132: =Lookup!F$20 -> Unit | J132: =Lookup!G$20 -> Basis | N132: =N$10 -> FY19 | O132: =O$10 -> FY20 | P132: =P$10 -> FY21 | Q132: =Q$10 -> FY22 | R132: =R$10 -> FY23 | S132: =S$10 -> FY24
D134: Forecast Inflation (from final decision) | H134: AER | I134: Percent | J134: N/A | O134: 0.024248747 | P134: 0.024248747 | Q134: 0.024248747 | R134: 0.024248747 | S134: 0.024248747
D135: Consumer Price Index
D136: Index (Weighted Average for the eight capital cities) | H136: ABS | I136: Factor | J136: N/A | N136: 112.1 | O136: 114.1 | P136: 116.2
D137: Quarter | H137: ABS | I137: N/A | J137: N/A | N137: 43070 | O137: 43435 | P137: 43800 | Q137: 44166 | R137: 44531 | S137: 44896
D139: Inflation rate | H139: ABS | I139: Percent | J139: N/A | O139: =IF(O136=0,O134,O136/N136-1) -> 0.017841213 | P139: =IF(P136=0,P134,P136/O136-1) -> 0.018404908 | Q139: =IF(Q136=0,Q134,Q136/P136-1) -> 0.024248747 | R139: =IF(R136=0,R134,R136/Q136-1) -> 0.024248747 | S139: =IF(S136=0,S134,S136/R136-1) -> 0.024248747
A141: =IF(SUM($O141:$S141)=0,0,1) -> 0 | D141: Check for errors | O141: =IF(ISERROR(O139),1,0) -> 0 | P141: =IF(ISERROR(P139),1,0) -> 0 | Q141: =IF(ISERROR(Q139),1,0) -> 0 | R141: =IF(ISERROR(R139),1,0) -> 0 | S141: =IF(ISERROR(S139),1,0) -> 0
C143: ="First Year Tariffs ("&O146&")" -> First Year Tariffs (FY20)
D146: Service | E146: =E$10 -> Service Category | H146: =H$10 -> Source | I146: =I$10 -> Unit | J146: =J$10 -> Basis | O146: =O$10 -> FY20
D148: Metering Services (Types 1 to 6)
D149: {=LU_Metering_Services} -> 1 Phase Meters (including Prepayment) | H149: AER | I149: $/Year/Meter | J149: Nominal | O149: 61.48
...

Sheet Calculations_Price_Caps
A1: =IF(SUM($A11:$A114)>0,1,0) -> 0 | B1: Calculation - Price Caps
B2: =Title_Msg -> No Errors Found
B3: =TOC!B1 -> Table of Contents
B4: =Model_Name -> ACS Pricing Model - Power and Water Corporation
B5: =Lookup!B15 -> Period Start Date | O5: =Lookup!O15 -> 43647 | P5: =Lookup!P15 -> 44013 | Q5: =Lookup!Q15 -> 44378 | R5: =Lookup!R15 -> 44743 | S5: =Lookup!S15 -> 45108
B6: =Lookup!B16 -> Period End Date | O6: =Lookup!O16 -> 44012 | P6: =Lookup!P16 -> 44377 | Q6: =Lookup!Q16 -> 44742 | R6: =Lookup!R16 -> 45107 | S6: =Lookup!S16 -> 45473
B7: =Lookup!B17 -> Period Counter | O7: =Lookup!O17 -> 6 | P7: =Lookup!P17 -> 7 | Q7: =Lookup!Q17 -> 8 | R7: =Lookup!R17 -> 9 | S7: =Lookup!S17 -> 10
B8: =Lookup!B18 -> Year | O8: =Lookup!O18 -> 2020 | P8: =Lookup!P18 -> 2021 | Q8: =Lookup!Q18 -> 2022 | R8: =Lookup!R18 -> 2023 | S8: =Lookup!S18 -> 2024
B9: =Lookup!B19 -> Days In Year | O9: =Lookup!O19 -> 366 | P9: =Lookup!P19 -> 365 | Q9: =Lookup!Q19 -> 365 | R9: =Lookup!R19 -> 365 | S9: =Lookup!S19 -> 366
B10: =Lookup!B20 -> FY | D10: Tariff | E10: Service Category | H10: Source | I10: Unit | J10: =Lookup!G20 -> Basis | M10: =Lookup!M20 -> FY18 | N10: =Lookup!N20 -> FY19 | O10: =Lookup!O20 -> FY20 | P10: =Lookup!P20 -> FY21 | Q10: =Lookup!Q20 -> FY22 | R10: =Lookup!R20 -> FY23 | S10: =Lookup!S20 -> FY24
B12: Price Caps by Service
D14: This sheet calculates the price caps for each alternative control service, split between metering services (types 1 to 6), fee based services and quoted services.
D15: The price caps are calculated as per the formulas included in Attachment 13 of the Australian Energy Regulator's draft revenue determination for the 2019-24 period (repeated below), which were adopted in the final determination.
D16: Only the price cap of the labour component for quoted services is calculated. The contractor services and materials components are simply included at cost at the time a service is quoted.
C55: Price Caps
D58: Service | H58: =Lookup!E$20 -> Source | I58: =Lookup!F$20 -> Unit | J58: =Lookup!G$20 -> Basis | O58: =O$10 -> FY20 | P58: =P$10 -> FY21 | Q58: =Q$10 -> FY22 | R58: =R$10 -> FY23 | S58: =S$10 -> FY24
D60: Metering Services (Types 1 to 6)
D61: {=LU_Metering_Services} -> 1 Phase Meters (including Prepayment) | H61: Calculated | I61: $/Year/Meter | J61: Nominal | O61: =Inputs_Prices!O149 -> 61.48 | P61: =ROUND(O61*(1+Inputs_Prices!P$139)*(1-Inputs_Prices!P208)+Inputs_Prices!P88,2) -> 64.66 | Q61: =ROUND(P61*(1+Inputs_Prices!Q$139)*(1-Inputs_Prices!Q208)+Inputs_Prices!Q88,2) -> 68.39 | R61: =ROUND(Q61*(1+Inputs_Prices!R$139)*(1-Inputs_Prices!R208)+Inputs_Prices!R88,2) -> 72.34 | S61: =ROUND(R61*(1+Inputs_Prices!S$139)*(1-Inputs_Prices!S208)+Inputs_Prices!S88,2) -> 76.52 | T61: Note: price caps are rounded to 2 decimal places
D62: 3 Phase Meters | H62: Calculated | I62: $/Year/Meter | J62: Nominal | O62: =Inputs_Prices!O150 -> 67.69 | P62: =ROUND(O62*(1+Inputs_Prices!P$139)*(1-Inputs_Prices!P209)+Inputs_Prices!P89,2) -> 71.19 | Q62: =ROUND(P62*(1+Inputs_Prices!Q$139)*(1-Inputs_Prices!Q209)+Inputs_Prices!Q89,2) -> 75.3 | R62: =ROUND(Q62*(1+Inputs_Prices!R$139)*(1-Inputs_Prices!R209)+Inputs_Prices!R89,2) -> 79.65 | S62: =ROUND(R62*(1+Inputs_Prices!S$139)*(1-Inputs_Prices!S209)+Inputs_Prices!S89,2) -> 84.25
D63: Dedicated CT and VT meters | H63: Calculated | I63: $/Year/Meter | J63: Nominal | O63: =Inputs_Prices!O151 -> 114.65 | P63: =ROUND(O63*(1+Inputs_Prices!P$139)*(1-Inputs_Prices!P210)+Inputs_Prices!P90,2) -> 120.58 | Q63: =ROUND(P63*(1+Inputs_Prices!Q$139)*(1-Inputs_Prices!Q210)+Inputs_Prices!Q90,2) -> 127.54 | R63: =ROUND(Q63*(1+Inputs_Prices!R$139)*(1-Inputs_Prices!R210)+Inputs_Prices!R90,2) -> 134.9 | S63: =ROUND(R63*(1+Inputs_Prices!S$139)*(1-Inputs_Prices!S210)+Inputs_Prices!S90,2) -> 142.69
D65: Fee Based Services
D66: {=LU_Fee_Based_Services} -> Disconnection (and final read) | H66: Calculated | I66: $/Request | J66: Nominal | O66: =Inputs_Prices!O154 -> 66.99 | P66: =ROUND(O66*(1+Inputs_Prices!P$139)*(1-Inputs_Prices!P213)+Inputs_Prices!P93,2) -> 65.35 | Q66: =ROUND(P66*(1+Inputs_Prices!Q$139)*(1-Inputs_Prices!Q213)+Inputs_Prices!Q93,2) -> 64 | R66: =ROUND(Q66*(1+Inputs_Prices!R$139)*(1-Inputs_Prices!R213)+Inputs_Prices!R93,2) -> 62.64 | S66: =ROUND(R66*(1+Inputs_Prices!S$139)*(1-Inputs_Prices!S213)+Inputs_Prices!S93,2) -> 61.24
D67: Reconnection | H67: Calculated | I67: $/Request | J67: Nominal | O67: =Inputs_Prices!O155 -> 66.99 | P67: =ROUND(O67*(1+Inputs_Prices!P$139)*(1-Inputs_Prices!P214)+Inputs_Prices!P94,2) -> 65.35 | Q67: =ROUND(P67*(1+Inputs_Prices!Q$139)*(1-Inputs_Prices!Q214)+Inputs_Prices!Q94,2) -> 64 | R67: =ROUND(Q67*(1+Inputs_Prices!R$139)*(1-Inputs_Prices!R214)+Inputs_Prices!R94,2) -> 62.64 | S67: =ROUND(R67*(1+Inputs_Prices!S$139)*(1-Inputs_Prices!S214)+Inputs_Prices!S94,2) -> 61.24
D68: Reconnection - after hours | H68: Calculated | I68: $/Request | J68: Nominal | O68: =Inputs_Prices!O156 -> 124.43 | P68: =ROUND(O68*(1+Inputs_Prices!P$139)*(1-Inputs_Prices!P215)+Inputs_Prices!P95,2) -> 121.39 | Q68: =ROUND(P68*(1+Inputs_Prices!Q$139)*(1-Inputs_Prices!Q215)+Inputs_Prices!Q95,2) -> 118.88 | R68: =ROUND(Q68*(1+Inputs_Prices!R$139)*(1-Inputs_Prices!R215)+Inputs_Prices!R95,2) -> 116.35 | S68: =ROUND(R68*(1+Inputs_Prices!S$139)*(1-Inputs_Prices!S215)+Inputs_Prices!S95,2) -> 113.75
D69: Temporary disconnection and reconnection - physical dismantling | H69: Calculated | I69: $/Request | J69: Nominal | O69: =Inputs_Prices!O157 -> 737.3 | P69: =ROUND(O69*(1+Inputs_Prices!P$139)*(1-Inputs_Prices!P216)+Inputs_Prices!P96,2) -> 755.16 | Q69: =ROUND(P69*(1+Inputs_Prices!Q$139)*(1-Inputs_Prices!Q216)+Inputs_Prices!Q96,2) -> 779.8 | R69: =ROUND(Q69*(1+Inputs_Prices!R$139)*(1-Inputs_Prices!R216)+Inputs_Prices!R96,2) -> 806.48 | S69: =ROUND(R69*(1+Inputs_Prices!S$139)*(1-Inputs_Prices!S216)+Inputs_Prices!S96,2) -> 834
D70: Provision of 3 phase service | H70: Calculated | I70: $/Request | J70: Nominal | O70: =Inputs_Prices!O158 -> 1400.88 | P70: =ROUND(O70*(1+Inputs_Prices!P$139)*(1-Inputs_Prices!P217)+Inputs_Prices!P97,2) -> 1434.81 | Q70: =ROUND(P70*(1+Inputs_Prices!Q$139)*(1-Inputs_Prices!Q217)+Inputs_Prices!Q97,2) -> 1481.63 | R70: =ROUND(Q70*(1+Inputs_Prices!R$139)*(1-Inputs_Prices!R217)+Inputs_Prices!R97,2) -> 1532.31 | S70: =ROUND(R70*(1+Inputs_Prices!S$139)*(1-Inputs_Prices!S217)+Inputs_Prices!S97,2) -> 1584.6
D71: Standard temporary builder’s connection | H71: Calculated | I71: $/Request | J71: Nominal | O71: =Inputs_Prices!O159 -> 657.68 | P71: =ROUND(O71*(1+Inputs_Prices!P$139)*(1-Inputs_Prices!P218)+Inputs_Prices!P98,2) -> 673.61 | Q71: =ROUND(P71*(1+Inputs_Prices!Q$139)*(1-Inputs_Prices!Q218)+Inputs_Prices!Q98,2) -> 695.59 | R71: =ROUND(Q71*(1+Inputs_Prices!R$139)*(1-Inputs_Prices!R218)+Inputs_Prices!R98,2) -> 719.39 | S71: =ROUND(R71*(1+Inputs_Prices!S$139)*(1-Inputs_Prices!S218)+Inputs_Prices!S98,2) -> 743.94
D72: Temporary disconnection and reconnection - no dismantling | H72: Calculated | I72: $/Request | J72: Nominal | O72: =Inputs_Prices!O160 -> 286.07 | P72: =ROUND(O72*(1+Inputs_Prices!P$139)*(1-Inputs_Prices!P219)+Inputs_Prices!P99,2) -> 293 | Q72: =ROUND(P72*(1+Inputs_Prices!Q$139)*(1-Inputs_Prices!Q219)+Inputs_Prices!Q99,2) -> 302.56 | R72: =ROUND(Q72*(1+Inputs_Prices!R$139)*(1-Inputs_Prices!R219)+Inputs_Prices!R99,2) -> 312.91 | S72: =ROUND(R72*(1+Inputs_Prices!S$139)*(1-Inputs_Prices!S219)+Inputs_Prices!S99,2) -> 323.59
D73: Complex disconnection | H73: Calculated | I73: $/Request | J73: Nominal | O73: =Inputs_Prices!O161 -> 312.62 | P73: =ROUND(O73*(1+Inputs_Prices!P$139)*(1-Inputs_Prices!P220)+Inputs_Prices!P100,2) -> 320.19 | Q73: =ROUND(P73*(1+Inputs_Prices!Q$139)*(1-Inputs_Prices!Q220)+Inputs_Prices!Q100,2) -> 330.64 | R73: =ROUND(Q73*(1+Inputs_Prices!R$139)*(1-Inputs_Prices!R220)+Inputs_Prices!R100,2) -> 341.95 | S73: =ROUND(R73*(1+Inputs_Prices!S$139)*(1-Inputs_Prices!S220)+Inputs_Prices!S100,2) -> 353.62
D74: Wasted visit fee | H74: Calculated | I74: $/Request | J74: Nominal | O74: =Inputs_Prices!O162 -> 153.36 | P74: =ROUND(O74*(1+Inputs_Prices!P$139)*(1-Inputs_Prices!P221)+Inputs_Prices!P101,2) -> 157.07 | Q74: =ROUND(P74*(1+Inputs_Prices!Q$139)*(1-Inputs_Prices!Q221)+Inputs_Prices!Q101,2) -> 162.2 | R74: =ROUND(Q74*(1+Inputs_Prices!R$139)*(1-Inputs_Prices!R221)+Inputs_Prices!R101,2) -> 167.75 | S74: =ROUND(R74*(1+Inputs_Prices!S$139)*(1-Inputs_Prices!S221)+Inputs_Prices!S101,2) -> 173.47
D75: Special meter test | H75: Calculated | I75: $/Request | J75: Nominal | O75: =Inputs_Prices!O163 -> 299.35 | P75: =ROUND(O75*(1+Inputs_Prices!P$139)*(1-Inputs_Prices!P222)+Inputs_Prices!P102,2) -> 306.6 | Q75: =ROUND(P75*(1+Inputs_Prices!Q$139)*(1-Inputs_Prices!Q222)+Inputs_Prices!Q102,2) -> 316.61 | R75: =ROUND(Q75*(1+Inputs_Prices!R$139)*(1-Inputs_Prices!R222)+Inputs_Prices!R102,2) -> 327.44 | S75: =ROUND(R75*(1+Inputs_Prices!S$139)*(1-Inputs_Prices!S222)+Inputs_Prices!S102,2) -> 338.61
D76: Exchange or replace meter – three phase | H76: Calculated | I76: $/Request | J76: Nominal | O76: =Inputs_Prices!O164 -> 660.39 | P76: =ROUND(O76*(1+Inputs_Prices!P$139)*(1-Inputs_Prices!P223)+Inputs_Prices!P103,2) -> 676.38 | Q76: =ROUND(P76*(1+Inputs_Prices!Q$139)*(1-Inputs_Prices!Q223)+Inputs_Prices!Q103,2) -> 698.45 | R76: =ROUND(Q76*(1+Inputs_Prices!R$139)*(1-Inputs_Prices!R223)+Inputs_Prices!R103,2) -> 722.34 | S76: =ROUND(R76*(1+Inputs_Prices!S$139)*(1-Inputs_Prices!S223)+Inputs_Prices!S103,2) -> 746.99
D77: Exchange or replace meter - single phase | H77: Calculated | I77: $/Request | J77: Nominal | O77: =Inputs_Prices!O165 -> 552.87 | P77: =ROUND(O77*(1+Inputs_Prices!P$139)*(1-Inputs_Prices!P224)+Inputs_Prices!P104,2) -> 566.26 | Q77: =ROUND(P77*(1+Inputs_Prices!Q$139)*(1-Inputs_Prices!Q224)+Inputs_Prices!Q104,2) -> 584.74 | R77: =ROUND(Q77*(1+Inputs_Prices!R$139)*(1-Inputs_Prices!R224)+Inputs_Prices!R104,2) -> 604.74 | S77: =ROUND(R77*(1+Inputs_Prices!S$139)*(1-Inputs_Prices!S224)+Inputs_Prices!S104,2) -> 625.38
D78: Relocation of meter | H78: Calculated | I78: $/Request | J78: Nominal | O78: =Inputs_Prices!O166 -> 312.62 | P78: =ROUND(O78*(1+Inputs_Prices!P$139)*(1-Inputs_Prices!P225)+Inputs_Prices!P105,2) -> 320.19 | Q78: =ROUND(P78*(1+Inputs_Prices!Q$139)*(1-Inputs_Prices!Q225)+Inputs_Prices!Q105,2) -> 330.64 | R78: =ROUND(Q78*(1+Inputs_Prices!R$139)*(1-Inputs_Prices!R225)+Inputs_Prices!R105,2) -> 341.95 | S78: =ROUND(R78*(1+Inputs_Prices!S$139)*(1-Inputs_Prices!S225)+Inputs_Prices!S105,2) -> 353.62
... D92: Class 1 & 2 PV service | H92: Calculated | I92: $/Request | J92: Nominal | O92: =Inputs_Prices!O180 -> 87.19 | P92: =ROUND(O92*(1+Inputs_Prices!P$139)*(1-Inputs_Prices!P239)+Inputs_Prices!P119,2) -> 89.3 | Q92: =ROUND(P92*(1+Inputs_Prices!Q$139)*(1-Inputs_Prices!Q239)+Inputs_Prices!Q119,2) -> 92.21 | R92: =ROUND(Q92*(1+Inputs_Prices!R$139)*(1-Inputs_Prices!R239)+Inputs_Prices!R119,2) -> 95.36 | S92: =ROUND(R92*(1+Inputs_Prices!S$139)*(1-Inputs_Prices!S239)+Inputs_Prices!S119,2) -> 98.61
D94: Quoted Services | Labour Component
D95: {=LU_Quoted_Services} -> Design related services | H95: Calculated | I95: $/Hour | J95: Nominal | O95: =Inputs_Prices!O183 -> 155.62 | P95: =ROUND(O95*(1+Inputs_Prices!P$139)*(1-Inputs_Prices!P242),2) -> 159.39 | Q95: =ROUND(P95*(1+Inputs_Prices!Q$139)*(1-Inputs_Prices!Q242),2) -> 164.59 | R95: =ROUND(Q95*(1+Inputs_Prices!R$139)*(1-Inputs_Prices!R242),2) -> 170.22 | S95: =ROUND(R95*(1+Inputs_Prices!S$139)*(1-Inputs_Prices!S242),2) -> 176.03
D96: Connection applications | H96: Calculated | I96: $/Hour | J96: Nominal | O96: =Inputs_Prices!O184 -> 155.62 | P96: =ROUND(O96*(1+Inputs_Prices!P$139)*(1-Inputs_Prices!P243),2) -> 159.39 | Q96: =ROUND(P96*(1+Inputs_Prices!Q$139)*(1-Inputs_Prices!Q243),2) -> 164.59 | R96: =ROUND(Q96*(1+Inputs_Prices!R$139)*(1-Inputs_Prices!R243),2) -> 170.22 | S96: =ROUND(R96*(1+Inputs_Prices!S$139)*(1-Inputs_Prices!S243),2) -> 176.03
D97: Access permits, oversights and facilitation | H97: Calculated | I97: $/Hour | J97: Nominal | O97: =Inputs_Prices!O185 -> 155.62 | P97: =ROUND(O97*(1+Inputs_Prices!P$139)*(1-Inputs_Prices!P244),2) -> 159.39 | Q97: =ROUND(P97*(1+Inputs_Prices!Q$139)*(1-Inputs_Prices!Q244),2) -> 164.59 | R97: =ROUND(Q97*(1+Inputs_Prices!R$139)*(1-Inputs_Prices!R244),2) -> 170.22 | S97: =ROUND(R97*(1+Inputs_Prices!S$139)*(1-Inputs_Prices!S244),2) -> 176.03
D98: Notices of arrangement and completion notices | H98: Calculated | I98: $/Hour | J98: Nominal | O98: =Inputs_Prices!O186 -> 87.19 | P98: =ROUND(O98*(1+Inputs_Prices!P$139)*(1-Inputs_Prices!P245),2) -> 89.3 | Q98: =ROUND(P98*(1+Inputs_Prices!Q$139)*(1-Inputs_Prices!Q245),2) -> 92.21 | R98: =ROUND(Q98*(1+Inputs_Prices!R$139)*(1-Inputs_Prices!R245),2) -> 95.36 | S98: =ROUND(R98*(1+Inputs_Prices!S$139)*(1-Inputs_Prices!S245),2) -> 98.61
D99: Network related property services | H99: Calculated | I99: $/Hour | J99: Nominal | O99: =Inputs_Prices!O187 -> 87.19 | P99: =ROUND(O99*(1+Inputs_Prices!P$139)*(1-Inputs_Prices!P246),2) -> 89.3 | Q99: =ROUND(P99*(1+Inputs_Prices!Q$139)*(1-Inputs_Prices!Q246),2) -> 92.21 | R99: =ROUND(Q99*(1+Inputs_Prices!R$139)*(1-Inputs_Prices!R246),2) -> 95.36 | S99: =ROUND(R99*(1+Inputs_Prices!S$139)*(1-Inputs_Prices!S246),2) -> 98.61
D100: Site establishment services | H100: Calculated | I100: $/Hour | J100: Nominal | O100: =Inputs_Prices!O188 -> 87.19 | P100: =ROUND(O100*(1+Inputs_Prices!P$139)*(1-Inputs_Prices!P247),2) -> 89.3 | Q100: =ROUND(P100*(1+Inputs_Prices!Q$139)*(1-Inputs_Prices!Q247),2) -> 92.21 | R100: =ROUND(Q100*(1+Inputs_Prices!R$139)*(1-Inputs_Prices!R247),2) -> 95.36 | S100: =ROUND(R100*(1+Inputs_Prices!S$139)*(1-Inputs_Prices!S247),2) -> 98.61
D101: Network safety services | H101: Calculated | I101: $/Hour | J101: Nominal | O101: =Inputs_Prices!O189 -> 132.71 | P101: =ROUND(O101*(1+Inputs_Prices!P$139)*(1-Inputs_Prices!P248),2) -> 135.92 | Q101: =ROUND(P101*(1+Inputs_Prices!Q$139)*(1-Inputs_Prices!Q248),2) -> 140.36 | R101: =ROUND(Q101*(1+Inputs_Prices!R$139)*(1-Inputs_Prices!R248),2) -> 145.16 | S101: =ROUND(R101*(1+Inputs_Prices!S$139)*(1-Inputs_Prices!S248),2) -> 150.11
D102: Network tariff change request | H102: Calculated | I102: $/Hour | J102: Nominal | O102: =Inputs_Prices!O190 -> 87.19 | P102: =ROUND(O102*(1+Inputs_Prices!P$139)*(1-Inputs_Prices!P249),2) -> 89.3 | Q102: =ROUND(P102*(1+Inputs_Prices!Q$139)*(1-Inputs_Prices!Q249),2) -> 92.21 | R102: =ROUND(Q102*(1+Inputs_Prices!R$139)*(1-Inputs_Prices!R249),2) -> 95.36 | S102: =ROUND(R102*(1+Inputs_Prices!S$139)*(1-Inputs_Prices!S249),2) -> 98.61
D103: Planned interruption - customer request | H103: Calculated | I103: $/Hour | J103: Nominal | O103: =Inputs_Prices!O191 -> 132.71 | P103: =ROUND(O103*(1+Inputs_Prices!P$139)*(1-Inputs_Prices!P250),2) -> 135.92 | Q103: =ROUND(P103*(1+Inputs_Prices!Q$139)*(1-Inputs_Prices!Q250),2) -> 140.36 | R103: =ROUND(Q103*(1+Inputs_Prices!R$139)*(1-Inputs_Prices!R250),2) -> 145.16 | S103: =ROUND(R103*(1+Inputs_Prices!S$139)*(1-Inputs_Prices!S250),2) -> 150.11
D104: Performance of a statutory right (access prevented) | H104: Calculated | I104: $/Hour | J104: Nominal | O104: =Inputs_Prices!O192 -> 132.71 | P104: =ROUND(O104*(1+Inputs_Prices!P$139)*(1-Inputs_Prices!P251),2) -> 135.92 | Q104: =ROUND(P104*(1+Inputs_Prices!Q$139)*(1-Inputs_Prices!Q251),2) -> 140.36 | R104: =ROUND(Q104*(1+Inputs_Prices!R$139)*(1-Inputs_Prices!R251),2) -> 145.16 | S104: =ROUND(R104*(1+Inputs_Prices!S$139)*(1-Inputs_Prices!S251),2) -> 150.11
D105: Provision of network related training to third parties | H105: Calculated | I105: $/Hour | J105: Nominal | O105: =Inputs_Prices!O193 -> 87.19 | P105: =ROUND(O105*(1+Inputs_Prices!P$139)*(1-Inputs_Prices!P252),2) -> 89.3 | Q105: =ROUND(P105*(1+Inputs_Prices!Q$139)*(1-Inputs_Prices!Q252),2) -> 92.21 | R105: =ROUND(Q105*(1+Inputs_Prices!R$139)*(1-Inputs_Prices!R252),2) -> 95.36 | S105: =ROUND(R105*(1+Inputs_Prices!S$139)*(1-Inputs_Prices!S252),2) -> 98.61
D106: Non-standard reporting services | H106: Calculated | I106: $/Hour | J106: Nominal | O106: =Inputs_Prices!O194 -> 87.19 | P106: =ROUND(O106*(1+Inputs_Prices!P$139)*(1-Inputs_Prices!P253),2) -> 89.3 | Q106: =ROUND(P106*(1+Inputs_Prices!Q$139)*(1-Inputs_Prices!Q253),2) -> 92.21 | R106: =ROUND(Q106*(1+Inputs_Prices!R$139)*(1-Inputs_Prices!R253),2) -> 95.36 | S106: =ROUND(R106*(1+Inputs_Prices!S$139)*(1-Inputs_Prices!S253),2) -> 98.61
D107: Services provided for retailer of last resort event | H107: Calculated | I107: $/Hour | J107: Nominal | O107: =Inputs_Prices!O195 -> 87.19 | P107: =ROUND(O107*(1+Inputs_Prices!P$139)*(1-Inputs_Prices!P254),2) -> 89.3 | Q107: =ROUND(P107*(1+Inputs_Prices!Q$139)*(1-Inputs_Prices!Q254),2) -> 92.21 | R107: =ROUND(Q107*(1+Inputs_Prices!R$139)*(1-Inputs_Prices!R254),2) -> 95.36 | S107: =ROUND(R107*(1+Inputs_Prices!S$139)*(1-Inputs_Prices!S254),2) -> 98.61
... D110: Annual prepayment meter licensing fee * | H110: Calculated | I110: $/Hour | J110: Nominal | O110: =Inputs_Prices!O198 -> 87.19 | P110: =ROUND(O110*(1+Inputs_Prices!P$139)*(1-Inputs_Prices!P257),2) -> 89.3 | Q110: =ROUND(P110*(1+Inputs_Prices!Q$139)*(1-Inputs_Prices!Q257),2) -> 92.21 | R110: =ROUND(Q110*(1+Inputs_Prices!R$139)*(1-Inputs_Prices!R257),2) -> 95.36 | S110: =ROUND(R110*(1+Inputs_Prices!S$139)*(1-Inputs_Prices!S257),2) -> 98.61
A112: =IF(SUM($O112:$S112)=0,0,1) -> 0 | D112: Check for errors | O112: {=IF(SUMPRODUCT(--ISERROR(O61:O110))<>0,1,0)} -> 0 | P112: {=IF(SUMPRODUCT(--ISERROR(P61:P110))<>0,1,0)} -> 0 | Q112: {=IF(SUMPRODUCT(--ISERROR(Q61:Q110))<>0,1,0)} -> 0 | R112: {=IF(SUMPRODUCT(--ISERROR(R61:R110))<>0,1,0)} -> 0 | S112: {=IF(SUMPRODUCT(--ISERROR(S61:S110))<>0,1,0)} -> 0
B114: End

Sheet Output_Compliance
A1: =IF(SUM($A11:$A84)>0,1,0) -> 0 | B1: Output - Compliance
B2: =Title_Msg -> No Errors Found
B3: =TOC!B1 -> Table of Contents
B4: =Model_Name -> ACS Pricing Model - Power and Water Corporation
B5: =Lookup!B15 -> Period Start Date | M5: =Lookup!M15 -> 42917 | N5: =Lookup!N15 -> 43282 | O5: =Lookup!O15 -> 43647 | P5: =Lookup!P15 -> 44013 | Q5: =Lookup!Q15 -> 44378 | R5: =Lookup!R15 -> 44743 | S5: =Lookup!S15 -> 45108
B6: =Lookup!B16 -> Period End Date | M6: =Lookup!M16 -> 43281 | N6: =Lookup!N16 -> 43646 | O6: =Lookup!O16 -> 44012 | P6: =Lookup!P16 -> 44377 | Q6: =Lookup!Q16 -> 44742 | R6: =Lookup!R16 -> 45107 | S6: =Lookup!S16 -> 45473
B7: =Lookup!B17 -> Period Counter | M7: =Lookup!M17 -> 4 | N7: =Lookup!N17 -> 5 | O7: =Lookup!O17 -> 6 | P7: =Lookup!P17 -> 7 | Q7: =Lookup!Q17 -> 8 | R7: =Lookup!R17 -> 9 | S7: =Lookup!S17 -> 10
B8: =Lookup!B18 -> Year | M8: =Lookup!M18 -> 2018 | N8: =Lookup!N18 -> 2019 | O8: =Lookup!O18 -> 2020 | P8: =Lookup!P18 -> 2021 | Q8: =Lookup!Q18 -> 2022 | R8: =Lookup!R18 -> 2023 | S8: =Lookup!S18 -> 2024
B9: =Lookup!B19 -> Days In Year | M9: =Lookup!M19 -> 365 | N9: =Lookup!N19 -> 365 | O9: =Lookup!O19 -> 366 | P9: =Lookup!P19 -> 365 | Q9: =Lookup!Q19 -> 365 | R9: =Lookup!R19 -> 365 | S9: =Lookup!S19 -> 366
B10: =Lookup!B20 -> FY | D10: Tariff Class | H10: =Lookup!E20 -> Source | I10: =Lookup!F20 -> Unit | J10: =Lookup!G20 -> Basis | M10: =Lookup!M20 -> FY18 | N10: =Lookup!N20 -> FY19 | O10: =Lookup!O20 -> FY20 | P10: =Lookup!P20 -> FY21 | Q10: =Lookup!Q20 -> FY22 | R10: =Lookup!R20 -> FY23 | S10: =Lookup!S20 -> FY24
B12: Compliance Checks
D14: This sheet tests whether the proposed prices fall within the calculated price caps. The checks are
D16: Tariff Compliance Year: | H16: FY21 | I16: ="Note: years prior to "&H16&" are ignored from the checks" -> Note: years prior to FY21 are ignored from the checks
D18: Summary
D19: Metering Services (Types 1 to 6) | H19: =IF(COUNTIF(OFFSET($P$31:$P$33,0,MATCH($H$16,$P$10:$S$10)-1,COUNTA($P$31:$P$33),COUNTA($P$10:$S$10)-MATCH($H$16,$P$10:$S$10)+1),"Fail")>0,"Fail","Pass") -> Pass
D20: Fee Based Services | H20: =IF(COUNTIF(OFFSET($P$36:$P$62,0,MATCH($H$16,$P$10:$S$10)-1,COUNTA($P$36:$P$62),COUNTA($P$10:$S$10)-MATCH($H$16,$P$10:$S$10)+1),"Fail")>0,"Fail","Pass") -> Pass
D21: Quoted Services (Labour Component Only) | H21: =IF(COUNTIF(OFFSET($P$65:$P$80,0,MATCH($H$16,$P$10:$S$10)-1,COUNTA($P$65:$P$80),COUNTA($P$10:$S$10)-MATCH($H$16,$P$10:$S$10)+1),"Fail")>0,"Fail","Pass") -> Pass | I21: =IF(H21="NA","Note: The side constraint only applies from year 2 of the regulatory period","")
A23: =IF(SUM($H23)=0,0,1) -> 0 | D23: Check for errors | H23: =COUNTIF(H19:H21,"Fail") -> 0
C25: Price Caps
D28: Service | H28: =Lookup!E$20 -> Source | I28: =Lookup!F$20 -> Unit | J28: =Lookup!G$20 -> Basis | P28: =P$10 -> FY21 | Q28: =Q$10 -> FY22 | R28: =R$10 -> FY23 | S28: =S$10 -> FY24
D30: Metering Services (Types 1 to 6)
D31: {=LU_Metering_Services} -> 1 Phase Meters (including Prepayment) | H31: Calculated | I31: $/Year/Meter | J31: Nominal | P31: =IF(Inputs_Prices!P29>Calculations_Price_Caps!P61,"Fail","Pass") -> Pass | Q31: =IF(Inputs_Prices!Q29>Calculations_Price_Caps!Q61,"Fail","Pass") -> Pass | R31: =IF(Inputs_Prices!R29>Calculations_Price_Caps!R61,"Fail","Pass") -> Pass | S31: =IF(Inputs_Prices!S29>Calculations_Price_Caps!S61,"Fail","Pass") -> Pass
D32: 3 Phase Meters | H32: Calculated | I32: $/Year/Meter | J32: Nominal | P32: =IF(Inputs_Prices!P30>Calculations_Price_Caps!P62,"Fail","Pass") -> Pass | Q32: =IF(Inputs_Prices!Q30>Calculations_Price_Caps!Q62,"Fail","Pass") -> Pass | R32: =IF(Inputs_Prices!R30>Calculations_Price_Caps!R62,"Fail","Pass") -> Pass | S32: =IF(Inputs_Prices!S30>Calculations_Price_Caps!S62,"Fail","Pass") -> Pass
D33: Dedicated CT and VT meters | H33: Calculated | I33: $/Year/Meter | J33: Nominal | P33: =IF(Inputs_Prices!P31>Calculations_Price_Caps!P63,"Fail","Pass") -> Pass | Q33: =IF(Inputs_Prices!Q31>Calculations_Price_Caps!Q63,"Fail","Pass") -> Pass | R33: =IF(Inputs_Prices!R31>Calculations_Price_Caps!R63,"Fail","Pass") -> Pass | S33: =IF(Inputs_Prices!S31>Calculations_Price_Caps!S63,"Fail","Pass") -> Pass
D35: Fee Based Services
D36: {=LU_Fee_Based_Services} -> Disconnection (and final read) | H36: Calculated | I36: $/Request | J36: Nominal | P36: =IF(Inputs_Prices!P34>Calculations_Price_Caps!P66,"Fail","Pass") -> Pass | Q36: =IF(Inputs_Prices!Q34>Calculations_Price_Caps!Q66,"Fail","Pass") -> Pass | R36: =IF(Inputs_Prices!R34>Calculations_Price_Caps!R66,"Fail","Pass") -> Pass | S36: =IF(Inputs_Prices!S34>Calculations_Price_Caps!S66,"Fail","Pass") -> Pass
D37: Reconnection | H37: Calculated | I37: $/Request | J37: Nominal | P37: =IF(Inputs_Prices!P35>Calculations_Price_Caps!P67,"Fail","Pass") -> Pass | Q37: =IF(Inputs_Prices!Q35>Calculations_Price_Caps!Q67,"Fail","Pass") -> Pass | R37: =IF(Inputs_Prices!R35>Calculations_Price_Caps!R67,"Fail","Pass") -> Pass | S37: =IF(Inputs_Prices!S35>Calculations_Price_Caps!S67,"Fail","Pass") -> Pass
D38: Reconnection - after hours | H38: Calculated | I38: $/Request | J38: Nominal | P38: =IF(Inputs_Prices!P36>Calculations_Price_Caps!P68,"Fail","Pass") -> Pass | Q38: =IF(Inputs_Prices!Q36>Calculations_Price_Caps!Q68,"Fail","Pass") -> Pass | R38: =IF(Inputs_Prices!R36>Calculations_Price_Caps!R68,"Fail","Pass") -> Pass | S38: =IF(Inputs_Prices!S36>Calculations_Price_Caps!S68,"Fail","Pass") -> Pass
D39: Temporary disconnection and reconnection - physical dismantling | H39: Calculated | I39: $/Request | J39: Nominal | P39: =IF(Inputs_Prices!P37>Calculations_Price_Caps!P69,"Fail","Pass") -> Pass | Q39: =IF(Inputs_Prices!Q37>Calculations_Price_Caps!Q69,"Fail","Pass") -> Pass | R39: =IF(Inputs_Prices!R37>Calculations_Price_Caps!R69,"Fail","Pass") -> Pass | S39: =IF(Inputs_Prices!S37>Calculations_Price_Caps!S69,"Fail","Pass") -> Pass
D40: Provision of 3 phase service | H40: Calculated | I40: $/Request | J40: Nominal | P40: =IF(Inputs_Prices!P38>Calculations_Price_Caps!P70,"Fail","Pass") -> Pass | Q40: =IF(Inputs_Prices!Q38>Calculations_Price_Caps!Q70,"Fail","Pass") -> Pass | R40: =IF(Inputs_Prices!R38>Calculations_Price_Caps!R70,"Fail","Pass") -> Pass | S40: =IF(Inputs_Prices!S38>Calculations_Price_Caps!S70,"Fail","Pass") -> Pass
D41: Standard temporary builder’s connection | H41: Calculated | I41: $/Request | J41: Nominal | P41: =IF(Inputs_Prices!P39>Calculations_Price_Caps!P71,"Fail","Pass") -> Pass | Q41: =IF(Inputs_Prices!Q39>Calculations_Price_Caps!Q71,"Fail","Pass") -> Pass | R41: =IF(Inputs_Prices!R39>Calculations_Price_Caps!R71,"Fail","Pass") -> Pass | S41: =IF(Inputs_Prices!S39>Calculations_Price_Caps!S71,"Fail","Pass") -> Pass
D42: Temporary disconnection and reconnection - no dismantling | H42: Calculated | I42: $/Request | J42: Nominal | P42: =IF(Inputs_Prices!P40>Calculations_Price_Caps!P72,"Fail","Pass") -> Pass | Q42: =IF(Inputs_Prices!Q40>Calculations_Price_Caps!Q72,"Fail","Pass") -> Pass | R42: =IF(Inputs_Prices!R40>Calculations_Price_Caps!R72,"Fail","Pass") -> Pass | S42: =IF(Inputs_Prices!S40>Calculations_Price_Caps!S72,"Fail","Pass") -> Pass
D43: Complex disconnection | H43: Calculated | I43: $/Request | J43: Nominal | P43: =IF(Inputs_Prices!P41>Calculations_Price_Caps!P73,"Fail","Pass") -> Pass | Q43: =IF(Inputs_Prices!Q41>Calculations_Price_Caps!Q73,"Fail","Pass") -> Pass | R43: =IF(Inputs_Prices!R41>Calculations_Price_Caps!R73,"Fail","Pass") -> Pass | S43: =IF(Inputs_Prices!S41>Calculations_Price_Caps!S73,"Fail","Pass") -> Pass
D44: Wasted visit fee | H44: Calculated | I44: $/Request | J44: Nominal | P44: =IF(Inputs_Prices!P42>Calculations_Price_Caps!P74,"Fail","Pass") -> Pass | Q44: =IF(Inputs_Prices!Q42>Calculations_Price_Caps!Q74,"Fail","Pass") -> Pass | R44: =IF(Inputs_Prices!R42>Calculations_Price_Caps!R74,"Fail","Pass") -> Pass | S44: =IF(Inputs_Prices!S42>Calculations_Price_Caps!S74,"Fail","Pass") -> Pass
D45: Special meter test | H45: Calculated | I45: $/Request | J45: Nominal | P45: =IF(Inputs_Prices!P43>Calculations_Price_Caps!P75,"Fail","Pass") -> Pass | Q45: =IF(Inputs_Prices!Q43>Calculations_Price_Caps!Q75,"Fail","Pass") -> Pass | R45: =IF(Inputs_Prices!R43>Calculations_Price_Caps!R75,"Fail","Pass") -> Pass | S45: =IF(Inputs_Prices!S43>Calculations_Price_Caps!S75,"Fail","Pass") -> Pass
D46: Exchange or replace meter – three phase | H46: Calculated | I46: $/Request | J46: Nominal | P46: =IF(Inputs_Prices!P44>Calculations_Price_Caps!P76,"Fail","Pass") -> Pass | Q46: =IF(Inputs_Prices!Q44>Calculations_Price_Caps!Q76,"Fail","Pass") -> Pass | R46: =IF(Inputs_Prices!R44>Calculations_Price_Caps!R76,"Fail","Pass") -> Pass | S46: =IF(Inputs_Prices!S44>Calculations_Price_Caps!S76,"Fail","Pass") -> Pass
D47: Exchange or replace meter - single phase | H47: Calculated | I47: $/Request | J47: Nominal | P47: =IF(Inputs_Prices!P45>Calculations_Price_Caps!P77,"Fail","Pass") -> Pass | Q47: =IF(Inputs_Prices!Q45>Calculations_Price_Caps!Q77,"Fail","Pass") -> Pass | R47: =IF(Inputs_Prices!R45>Calculations_Price_Caps!R77,"Fail","Pass") -> Pass | S47: =IF(Inputs_Prices!S45>Calculations_Price_Caps!S77,"Fail","Pass") -> Pass
D48: Relocation of meter | H48: Calculated | I48: $/Request | J48: Nominal | P48: =IF(Inputs_Prices!P46>Calculations_Price_Caps!P78,"Fail","Pass") -> Pass | Q48: =IF(Inputs_Prices!Q46>Calculations_Price_Caps!Q78,"Fail","Pass") -> Pass | R48: =IF(Inputs_Prices!R46>Calculations_Price_Caps!R78,"Fail","Pass") -> Pass | S48: =IF(Inputs_Prices!S46>Calculations_Price_Caps!S78,"Fail","Pass") -> Pass
... D62: Class 1 & 2 PV service | H62: Calculated | I62: $/Request | J62: Nominal | P62: =IF(Inputs_Prices!P60>Calculations_Price_Caps!P92,"Fail","Pass") -> Pass | Q62: =IF(Inputs_Prices!Q60>Calculations_Price_Caps!Q92,"Fail","Pass") -> Pass | R62: =IF(Inputs_Prices!R60>Calculations_Price_Caps!R92,"Fail","Pass") -> Pass | S62: =IF(Inputs_Prices!S60>Calculations_Price_Caps!S92,"Fail","Pass") -> Pass
D64: Quoted Services | Labour Component
D65: {=LU_Quoted_Services} -> Design related services | H65: Calculated | I65: $/Hour | J65: Nominal | P65: =IF(Inputs_Prices!P63>Calculations_Price_Caps!P95,"Fail","Pass") -> Pass | Q65: =IF(Inputs_Prices!Q63>Calculations_Price_Caps!Q95,"Fail","Pass") -> Pass | R65: =IF(Inputs_Prices!R63>Calculations_Price_Caps!R95,"Fail","Pass") -> Pass | S65: =IF(Inputs_Prices!S63>Calculations_Price_Caps!S95,"Fail","Pass") -> Pass
D66: Connection applications | H66: Calculated | I66: $/Hour | J66: Nominal | P66: =IF(Inputs_Prices!P64>Calculations_Price_Caps!P96,"Fail","Pass") -> Pass | Q66: =IF(Inputs_Prices!Q64>Calculations_Price_Caps!Q96,"Fail","Pass") -> Pass | R66: =IF(Inputs_Prices!R64>Calculations_Price_Caps!R96,"Fail","Pass") -> Pass | S66: =IF(Inputs_Prices!S64>Calculations_Price_Caps!S96,"Fail","Pass") -> Pass
D67: Access permits, oversights and facilitation | H67: Calculated | I67: $/Hour | J67: Nominal | P67: =IF(Inputs_Prices!P65>Calculations_Price_Caps!P97,"Fail","Pass") -> Pass | Q67: =IF(Inputs_Prices!Q65>Calculations_Price_Caps!Q97,"Fail","Pass") -> Pass | R67: =IF(Inputs_Prices!R65>Calculations_Price_Caps!R97,"Fail","Pass") -> Pass | S67: =IF(Inputs_Prices!S65>Calculations_Price_Caps!S97,"Fail","Pass") -> Pass
D68: Notices of arrangement and completion notices | H68: Calculated | I68: $/Hour | J68: Nominal | P68: =IF(Inputs_Prices!P66>Calculations_Price_Caps!P98,"Fail","Pass") -> Pass | Q68: =IF(Inputs_Prices!Q66>Calculations_Price_Caps!Q98,"Fail","Pass") -> Pass | R68: =IF(Inputs_Prices!R66>Calculations_Price_Caps!R98,"Fail","Pass") -> Pass | S68: =IF(Inputs_Prices!S66>Calculations_Price_Caps!S98,"Fail","Pass") -> Pass
D69: Network related property services | H69: Calculated | I69: $/Hour | J69: Nominal | P69: =IF(Inputs_Prices!P67>Calculations_Price_Caps!P99,"Fail","Pass") -> Pass | Q69: =IF(Inputs_Prices!Q67>Calculations_Price_Caps!Q99,"Fail","Pass") -> Pass | R69: =IF(Inputs_Prices!R67>Calculations_Price_Caps!R99,"Fail","Pass") -> Pass | S69: =IF(Inputs_Prices!S67>Calculations_Price_Caps!S99,"Fail","Pass") -> Pass
D70: Site establishment services | H70: Calculated | I70: $/Hour | J70: Nominal | P70: =IF(Inputs_Prices!P68>Calculations_Price_Caps!P100,"Fail","Pass") -> Pass | Q70: =IF(Inputs_Prices!Q68>Calculations_Price_Caps!Q100,"Fail","Pass") -> Pass | R70: =IF(Inputs_Prices!R68>Calculations_Price_Caps!R100,"Fail","Pass") -> Pass | S70: =IF(Inputs_Prices!S68>Calculations_Price_Caps!S100,"Fail","Pass") -> Pass
D71: Network safety services | H71: Calculated | I71: $/Hour | J71: Nominal | P71: =IF(Inputs_Prices!P69>Calculations_Price_Caps!P101,"Fail","Pass") -> Pass | Q71: =IF(Inputs_Prices!Q69>Calculations_Price_Caps!Q101,"Fail","Pass") -> Pass | R71: =IF(Inputs_Prices!R69>Calculations_Price_Caps!R101,"Fail","Pass") -> Pass | S71: =IF(Inputs_Prices!S69>Calculations_Price_Caps!S101,"Fail","Pass") -> Pass
D72: Network tariff change request | H72: Calculated | I72: $/Hour | J72: Nominal | P72: =IF(Inputs_Prices!P70>Calculations_Price_Caps!P102,"Fail","Pass") -> Pass | Q72: =IF(Inputs_Prices!Q70>Calculations_Price_Caps!Q102,"Fail","Pass") -> Pass | R72: =IF(Inputs_Prices!R70>Calculations_Price_Caps!R102,"Fail","Pass") -> Pass | S72: =IF(Inputs_Prices!S70>Calculations_Price_Caps!S102,"Fail","Pass") -> Pass
D73: Planned interruption - customer request | H73: Calculated | I73: $/Hour | J73: Nominal | P73: =IF(Inputs_Prices!P71>Calculations_Price_Caps!P103,"Fail","Pass") -> Pass | Q73: =IF(Inputs_Prices!Q71>Calculations_Price_Caps!Q103,"Fail","Pass") -> Pass | R73: =IF(Inputs_Prices!R71>Calculations_Price_Caps!R103,"Fail","Pass") -> Pass | S73: =IF(Inputs_Prices!S71>Calculations_Price_Caps!S103,"Fail","Pass") -> Pass
D74: Performance of a statutory right (access prevented) | H74: Calculated | I74: $/Hour | J74: Nominal | P74: =IF(Inputs_Prices!P72>Calculations_Price_Caps!P104,"Fail","Pass") -> Pass | Q74: =IF(Inputs_Prices!Q72>Calculations_Price_Caps!Q104,"Fail","Pass") -> Pass | R74: =IF(Inputs_Prices!R72>Calculations_Price_Caps!R104,"Fail","Pass") -> Pass | S74: =IF(Inputs_Prices!S72>Calculations_Price_Caps!S104,"Fail","Pass") -> Pass
D75: Provision of network related training to third parties | H75: Calculated | I75: $/Hour | J75: Nominal | P75: =IF(Inputs_Prices!P73>Calculations_Price_Caps!P105,"Fail","Pass") -> Pass | Q75: =IF(Inputs_Prices!Q73>Calculations_Price_Caps!Q105,"Fail","Pass") -> Pass | R75: =IF(Inputs_Prices!R73>Calculations_Price_Caps!R105,"Fail","Pass") -> Pass | S75: =IF(Inputs_Prices!S73>Calculations_Price_Caps!S105,"Fail","Pass") -> Pass
D76: Non-standard reporting services | H76: Calculated | I76: $/Hour | J76: Nominal | P76: =IF(Inputs_Prices!P74>Calculations_Price_Caps!P106,"Fail","Pass") -> Pass | Q76: =IF(Inputs_Prices!Q74>Calculations_Price_Caps!Q106,"Fail","Pass") -> Pass | R76: =IF(Inputs_Prices!R74>Calculations_Price_Caps!R106,"Fail","Pass") -> Pass | S76: =IF(Inputs_Prices!S74>Calculations_Price_Caps!S106,"Fail","Pass") -> Pass
D77: Services provided for retailer of last resort event | H77: Calculated | I77: $/Hour | J77: Nominal | P77: =IF(Inputs_Prices!P75>Calculations_Price_Caps!P107,"Fail","Pass") -> Pass | Q77: =IF(Inputs_Prices!Q75>Calculations_Price_Caps!Q107,"Fail","Pass") -> Pass | R77: =IF(Inputs_Prices!R75>Calculations_Price_Caps!R107,"Fail","Pass") -> Pass | S77: =IF(Inputs_Prices!S75>Calculations_Price_Caps!S107,"Fail","Pass") -> Pass
... D80: Annual prepayment meter licensing fee * | H80: Calculated | I80: $/Hour | J80: Nominal | P80: =IF(Inputs_Prices!P78>Calculations_Price_Caps!P110,"Fail","Pass") -> Pass | Q80: =IF(Inputs_Prices!Q78>Calculations_Price_Caps!Q110,"Fail","Pass") -> Pass | R80: =IF(Inputs_Prices!R78>Calculations_Price_Caps!R110,"Fail","Pass") -> Pass | S80: =IF(Inputs_Prices!S78>Calculations_Price_Caps!S110,"Fail","Pass") -> Pass
A82: =IF(SUM($O82:$S82)=0,0,1) -> 0 | D82: Check for errors | P82: {=IF(SUMPRODUCT(--ISERROR(P31:P80))<>0,1,0)} -> 0 | Q82: {=IF(SUMPRODUCT(--ISERROR(Q31:Q80))<>0,1,0)} -> 0 | R82: {=IF(SUMPRODUCT(--ISERROR(R31:R80))<>0,1,0)} -> 0 | S82: {=IF(SUMPRODUCT(--ISERROR(S31:S80))<>0,1,0)} -> 0
B84: End

Sheet Output_Pricing_Proposal
A1: =IF(SUM($A23:$A152)>0,1,0) -> 0 | B1: Output - Pricing Proposal
B2: No Errors Found
B3: Go to Cover Sheet
B4: =Model_Name -> ACS Pricing Model - Power and Water Corporation
B6: Tariff Year
D8: This sheet outputs tables for the pricing proposal. The prices reflect the tariff year selected below.
D10: Tariff Year: | H10: FY21 | I10: ← Nominate year
D11: Days In Year: | H11: =INDEX(Lookup!$P$19:$S$19,MATCH($H$10,Lookup!$P$20:$S$20,0)) -> 365
B14: ACS pricing parameters
D16: Terms | E16: Input | F16: Source
D17: Inflation update | E17: =INDEX(Inputs_Prices!O139:S139,MATCH($H$10,Lookup!$O$20:$S$20,0)) -> 0.018404908 | F17: Consistent with AER prescribed method we have updated inflation forecasts for 2020-21 to reflect the December 2019 ABS updates. Note this is consistent with SCS.
D18: X-factor for metering services (Type 1 to 6) | E18: =INDEX(Inputs_Prices!P208:S208,MATCH($H$10,Lookup!$P$20:$S$20,0)) -> -0.0327 | F18: Consistent with AER final decision on page 21 of Attachment 15 (Table 15.7)
D19: X-factor re-connection, disconnection and final read | E19: =INDEX(Inputs_Prices!P213:S213,MATCH($H$10,Lookup!$P$20:$S$20,0)) -> 0.042045 | F19: Consistent with AER final decision on page 20 of Attachment 15 (Table 15.6)
D20: X-factor for all other services to apply to 2020-21 | E20: =INDEX(Inputs_Prices!P216:S216,MATCH($H$10,Lookup!$P$20:$S$20,0)) -> -0.005708 | F20: Consistent with AER final decision on page on page 20 of Attachment 15 (Table 15.6)
B23: ACS Metering Services Pricing Parameters
F25: Excluding GST
D26: Metering service provision charges (for Types 1 – 6 meters) | E26: Basis of charging | F26: Price | G26: Annual Charge
D27: 1 Phase Meters (including Prepayment) | E27: $/day/meter | F27: =G27/$H$11 -> 0.17715068 | G27: =INDEX(Inputs_Prices!P29:S29,MATCH($H$10,Lookup!$P$20:$S$20,0)) -> 64.66
D28: 3 Phase Meters | E28: $/day/meter | F28: =G28/$H$11 -> 0.1950411 | G28: =INDEX(Inputs_Prices!P30:S30,MATCH($H$10,Lookup!$P$20:$S$20,0)) -> 71.19
D29: Dedicated CT and VT meters | E29: $/day/meter | F29: =G29/$H$11 -> 0.33035616 | G29: =INDEX(Inputs_Prices!P31:S31,MATCH($H$10,Lookup!$P$20:$S$20,0)) -> 120.58 | H29: Note: Consistent with the process used for FY20 tariffs, the annual metering charges have been converted to daily charges by dividing them by the number of days in the year.
B32: ACS Quoted Services Pricing Parameters (Labour Component Only)
F34: Price | K34: GST Adjustment | L34: 1.1
D35: Quoted services provision charges | E35: Basis of charging | F35: Excluding GST | G35: Including GST
D36: {=LU_Quoted_Services} -> Design related services | E36: $/hour | F36: =INDEX(Inputs_Prices!$P63:$S63,MATCH($H$10,Lookup!$P$20:$S$20,0)) -> 159.39 | G36: =F36*$L$34 -> 175.329
D37: Connection applications | E37: $/hour | F37: =INDEX(Inputs_Prices!$P64:$S64,MATCH($H$10,Lookup!$P$20:$S$20,0)) -> 159.39 | G37: =F37*$L$34 -> 175.329
D38: Access permits, oversights and facilitation | E38: $/hour | F38: =INDEX(Inputs_Prices!$P65:$S65,MATCH($H$10,Lookup!$P$20:$S$20,0)) -> 159.39 | G38: =F38*$L$34 -> 175.329
D39: Notices of arrangement and completion notices | E39: $/hour | F39: =INDEX(Inputs_Prices!$P66:$S66,MATCH($H$10,Lookup!$P$20:$S$20,0)) -> 89.3 | G39: =F39*$L$34 -> 98.23
D40: Network related property services | E40: $/hour | F40: =INDEX(Inputs_Prices!$P67:$S67,MATCH($H$10,Lookup!$P$20:$S$20,0)) -> 89.3 | G40: =F40*$L$34 -> 98.23
D41: Site establishment services | E41: $/hour | F41: =INDEX(Inputs_Prices!$P68:$S68,MATCH($H$10,Lookup!$P$20:$S$20,0)) -> 89.3 | G41: =F41*$L$34 -> 98.23
D42: Network safety services | E42: $/hour | F42: =INDEX(Inputs_Prices!$P69:$S69,MATCH($H$10,Lookup!$P$20:$S$20,0)) -> 135.92 | G42: =F42*$L$34 -> 149.512
D43: Network tariff change request | E43: $/hour | F43: =INDEX(Inputs_Prices!$P70:$S70,MATCH($H$10,Lookup!$P$20:$S$20,0)) -> 89.3 | G43: =F43*$L$34 -> 98.23
D44: Planned interruption - customer request | E44: $/hour | F44: =INDEX(Inputs_Prices!$P71:$S71,MATCH($H$10,Lookup!$P$20:$S$20,0)) -> 135.92 | G44: =F44*$L$34 -> 149.512
D45: Performance of a statutory right (access prevented) | E45: $/hour | F45: =INDEX(Inputs_Prices!$P72:$S72,MATCH($H$10,Lookup!$P$20:$S$20,0)) -> 135.92 | G45: =F45*$L$34 -> 149.512
D46: Provision of network related training to third parties | E46: $/hour | F46: =INDEX(Inputs_Prices!$P73:$S73,MATCH($H$10,Lookup!$P$20:$S$20,0)) -> 89.3 | G46: =F46*$L$34 -> 98.23
D47: Non-standard reporting services | E47: $/hour | F47: =INDEX(Inputs_Prices!$P74:$S74,MATCH($H$10,Lookup!$P$20:$S$20,0)) -> 89.3 | G47: =F47*$L$34 -> 98.23
D48: Services provided for retailer of last resort event | E48: $/hour | F48: =INDEX(Inputs_Prices!$P75:$S75,MATCH($H$10,Lookup!$P$20:$S$20,0)) -> 89.3 | G48: =F48*$L$34 -> 98.23
... D51: Annual prepayment meter licensing fee * | E51: $/hour | F51: =INDEX(Inputs_Prices!$P78:$S78,MATCH($H$10,Lookup!$P$20:$S$20,0)) -> 89.3 | G51: =F51*$L$34 -> 98.23
D52: * Cost of Prepayment meter software will be on charged according to customer requirements. Admin rate to be used to process cost recovery.
B54: ACS Fee Based Services Pricing Parameters
F56: Price
D57: Fee based service provision charges | E57: Basis of charging | F57: Excluding GST | G57: Including GST
D58: {=LU_Fee_Based_Services} -> Disconnection (and final read) | E58: $/request | F58: =INDEX(Inputs_Prices!$P34:$S34,MATCH($H$10,Lookup!$P$20:$S$20,0)) -> 65.35 | G58: =F58*$L$34 -> 71.885
D59: Reconnection | E59: $/request | F59: =INDEX(Inputs_Prices!$P35:$S35,MATCH($H$10,Lookup!$P$20:$S$20,0)) -> 65.35 | G59: =F59*$L$34 -> 71.885
D60: Reconnection - after hours | E60: $/request | F60: =INDEX(Inputs_Prices!$P36:$S36,MATCH($H$10,Lookup!$P$20:$S$20,0)) -> 121.39 | G60: =F60*$L$34 -> 133.529
D61: Temporary disconnection and reconnection - physical dismantling | E61: $/request | F61: =INDEX(Inputs_Prices!$P37:$S37,MATCH($H$10,Lookup!$P$20:$S$20,0)) -> 755.16 | G61: =F61*$L$34 -> 830.676
D62: Provision of 3 phase service | E62: $/request | F62: =INDEX(Inputs_Prices!$P38:$S38,MATCH($H$10,Lookup!$P$20:$S$20,0)) -> 1434.81 | G62: =F62*$L$34 -> 1578.291
D63: Standard temporary builder’s connection | E63: $/request | F63: =INDEX(Inputs_Prices!$P39:$S39,MATCH($H$10,Lookup!$P$20:$S$20,0)) -> 673.61 | G63: =F63*$L$34 -> 740.971
D64: Temporary disconnection and reconnection - no dismantling | E64: $/request | F64: =INDEX(Inputs_Prices!$P40:$S40,MATCH($H$10,Lookup!$P$20:$S$20,0)) -> 293 | G64: =F64*$L$34 -> 322.3
D65: Complex disconnection | E65: $/request | F65: =INDEX(Inputs_Prices!$P41:$S41,MATCH($H$10,Lookup!$P$20:$S$20,0)) -> 320.19 | G65: =F65*$L$34 -> 352.209
D66: Wasted visit fee | E66: $/request | F66: =INDEX(Inputs_Prices!$P42:$S42,MATCH($H$10,Lookup!$P$20:$S$20,0)) -> 157.07 | G66: =F66*$L$34 -> 172.777
D67: Special meter test | E67: $/request | F67: =INDEX(Inputs_Prices!$P43:$S43,MATCH($H$10,Lookup!$P$20:$S$20,0)) -> 306.6 | G67: =F67*$L$34 -> 337.26
D68: Exchange or replace meter – three phase | E68: $/request | F68: =INDEX(Inputs_Prices!$P44:$S44,MATCH($H$10,Lookup!$P$20:$S$20,0)) -> 676.38 | G68: =F68*$L$34 -> 744.018
D69: Exchange or replace meter - single phase | E69: $/request | F69: =INDEX(Inputs_Prices!$P45:$S45,MATCH($H$10,Lookup!$P$20:$S$20,0)) -> 566.26 | G69: =F69*$L$34 -> 622.886
D70: Relocation of meter | E70: $/request | F70: =INDEX(Inputs_Prices!$P46:$S46,MATCH($H$10,Lookup!$P$20:$S$20,0)) -> 320.19 | G70: =F70*$L$34 -> 352.209
... D84: Class 1 & 2 PV service | E84: $/request | F84: =INDEX(Inputs_Prices!$P60:$S60,MATCH($H$10,Lookup!$P$20:$S$20,0)) -> 89.3 | G84: =F84*$L$34 -> 98.23
B87: Indicative price schedule for ACS Metering services (nominal $, excluding GST)
D89: Charge | E89: Basis of charging | F89: Charge | G89: Charge | H89: Indicative | I89: Indicative | J89: Indicative
F90: 2019‐20 | G90: 2020‐21 | H90: 2021‐22 | I90: 2022‐23 | J90: 2023‐24
D91: 1 Phase Meters (including Prepayment) | E91: $/Year/Meter | F91: =Inputs_Prices!O149 -> 61.48 | G91: =Inputs_Prices!P29 -> 64.66 | H91: =Inputs_Prices!Q29 -> 68.39 | I91: =Inputs_Prices!R29 -> 72.34 | J91: =Inputs_Prices!S29 -> 76.52
D92: 3 Phase Meters | E92: $/Year/Meter | F92: =Inputs_Prices!O150 -> 67.69 | G92: =Inputs_Prices!P30 -> 71.19 | H92: =Inputs_Prices!Q30 -> 75.3 | I92: =Inputs_Prices!R30 -> 79.65 | J92: =Inputs_Prices!S30 -> 84.25
D93: Dedicated CT and VT meters | E93: $/Year/Meter | F93: =Inputs_Prices!O151 -> 114.65 | G93: =Inputs_Prices!P31 -> 120.58 | H93: =Inputs_Prices!Q31 -> 127.54 | I93: =Inputs_Prices!R31 -> 134.9 | J93: =Inputs_Prices!S31 -> 142.69
B96: Indicative price schedule for ACS Metering services (nominal $, excluding GST)
D98: Charge | E98: Basis of charging | F98: Charge | G98: Charge | H98: Indicative | I98: Indicative | J98: Indicative
F99: 2019‐20 | G99: 2020‐21 | H99: 2021‐22 | I99: 2022‐23 | J99: 2023‐24
D100: {=LU_Quoted_Services} -> Design related services | E100: $/hour | F100: =Inputs_Prices!O183 -> 155.62 | G100: =Inputs_Prices!P63 -> 159.39 | H100: =Inputs_Prices!Q63 -> 164.59 | I100: =Inputs_Prices!R63 -> 170.22 | J100: =Inputs_Prices!S63 -> 176.03
D101: Connection applications | E101: $/hour | F101: =Inputs_Prices!O184 -> 155.62 | G101: =Inputs_Prices!P64 -> 159.39 | H101: =Inputs_Prices!Q64 -> 164.59 | I101: =Inputs_Prices!R64 -> 170.22 | J101: =Inputs_Prices!S64 -> 176.03
D102: Access permits, oversights and facilitation | E102: $/hour | F102: =Inputs_Prices!O185 -> 155.62 | G102: =Inputs_Prices!P65 -> 159.39 | H102: =Inputs_Prices!Q65 -> 164.59 | I102: =Inputs_Prices!R65 -> 170.22 | J102: =Inputs_Prices!S65 -> 176.03
D103: Notices of arrangement and completion notices | E103: $/hour | F103: =Inputs_Prices!O186 -> 87.19 | G103: =Inputs_Prices!P66 -> 89.3 | H103: =Inputs_Prices!Q66 -> 92.21 | I103: =Inputs_Prices!R66 -> 95.36 | J103: =Inputs_Prices!S66 -> 98.61
D104: Network related property services | E104: $/hour | F104: =Inputs_Prices!O187 -> 87.19 | G104: =Inputs_Prices!P67 -> 89.3 | H104: =Inputs_Prices!Q67 -> 92.21 | I104: =Inputs_Prices!R67 -> 95.36 | J104: =Inputs_Prices!S67 -> 98.61
D105: Site establishment services | E105: $/hour | F105: =Inputs_Prices!O188 -> 87.19 | G105: =Inputs_Prices!P68 -> 89.3 | H105: =Inputs_Prices!Q68 -> 92.21 | I105: =Inputs_Prices!R68 -> 95.36 | J105: =Inputs_Prices!S68 -> 98.61
D106: Network safety services | E106: $/hour | F106: =Inputs_Prices!O189 -> 132.71 | G106: =Inputs_Prices!P69 -> 135.92 | H106: =Inputs_Prices!Q69 -> 140.36 | I106: =Inputs_Prices!R69 -> 145.16 | J106: =Inputs_Prices!S69 -> 150.11
D107: Network tariff change request | E107: $/hour | F107: =Inputs_Prices!O190 -> 87.19 | G107: =Inputs_Prices!P70 -> 89.3 | H107: =Inputs_Prices!Q70 -> 92.21 | I107: =Inputs_Prices!R70 -> 95.36 | J107: =Inputs_Prices!S70 -> 98.61
D108: Planned interruption - customer request | E108: $/hour | F108: =Inputs_Prices!O191 -> 132.71 | G108: =Inputs_Prices!P71 -> 135.92 | H108: =Inputs_Prices!Q71 -> 140.36 | I108: =Inputs_Prices!R71 -> 145.16 | J108: =Inputs_Prices!S71 -> 150.11
D109: Performance of a statutory right (access prevented) | E109: $/hour | F109: =Inputs_Prices!O192 -> 132.71 | G109: =Inputs_Prices!P72 -> 135.92 | H109: =Inputs_Prices!Q72 -> 140.36 | I109: =Inputs_Prices!R72 -> 145.16 | J109: =Inputs_Prices!S72 -> 150.11
D110: Provision of network related training to third parties | E110: $/hour | F110: =Inputs_Prices!O193 -> 87.19 | G110: =Inputs_Prices!P73 -> 89.3 | H110: =Inputs_Prices!Q73 -> 92.21 | I110: =Inputs_Prices!R73 -> 95.36 | J110: =Inputs_Prices!S73 -> 98.61
D111: Non-standard reporting services | E111: $/hour | F111: =Inputs_Prices!O194 -> 87.19 | G111: =Inputs_Prices!P74 -> 89.3 | H111: =Inputs_Prices!Q74 -> 92.21 | I111: =Inputs_Prices!R74 -> 95.36 | J111: =Inputs_Prices!S74 -> 98.61
D112: Services provided for retailer of last resort event | E112: $/hour | F112: =Inputs_Prices!O195 -> 87.19 | G112: =Inputs_Prices!P75 -> 89.3 | H112: =Inputs_Prices!Q75 -> 92.21 | I112: =Inputs_Prices!R75 -> 95.36 | J112: =Inputs_Prices!S75 -> 98.61
... D115: Annual prepayment meter licensing fee * | E115: $/hour | F115: =Inputs_Prices!O198 -> 87.19 | G115: =Inputs_Prices!P78 -> 89.3 | H115: =Inputs_Prices!Q78 -> 92.21 | I115: =Inputs_Prices!R78 -> 95.36 | J115: =Inputs_Prices!S78 -> 98.61
D116: * Cost of Prepayment meter software will be on charged according to customer requirements. Admin rate to be used to process cost recovery.
B119: Table 22: Indicative price schedule for ACS Fee based services (nominal $, excluding GST)
D121: Charge | E121: Basis of charging | F121: Charge | G121: Charge | H121: Indicative | I121: Indicative | J121: Indicative
F122: 2019‐20 | G122: 2020‐21 | H122: 2021‐22 | I122: 2022‐23 | J122: 2023‐24
D123: {=LU_Fee_Based_Services} -> Disconnection (and final read) | E123: $/request | F123: =Inputs_Prices!O154 -> 66.99 | G123: =Inputs_Prices!P34 -> 65.35 | H123: =Inputs_Prices!Q34 -> 64 | I123: =Inputs_Prices!R34 -> 62.64 | J123: =Inputs_Prices!S34 -> 61.24
D124: Reconnection | E124: $/request | F124: =Inputs_Prices!O155 -> 66.99 | G124: =Inputs_Prices!P35 -> 65.35 | H124: =Inputs_Prices!Q35 -> 64 | I124: =Inputs_Prices!R35 -> 62.64 | J124: =Inputs_Prices!S35 -> 61.24
D125: Reconnection - after hours | E125: $/request | F125: =Inputs_Prices!O156 -> 124.43 | G125: =Inputs_Prices!P36 -> 121.39 | H125: =Inputs_Prices!Q36 -> 118.88 | I125: =Inputs_Prices!R36 -> 116.35 | J125: =Inputs_Prices!S36 -> 113.75
D126: Temporary disconnection and reconnection - physical dismantling | E126: $/request | F126: =Inputs_Prices!O157 -> 737.3 | G126: =Inputs_Prices!P37 -> 755.16 | H126: =Inputs_Prices!Q37 -> 779.8 | I126: =Inputs_Prices!R37 -> 806.48 | J126: =Inputs_Prices!S37 -> 834
D127: Provision of 3 phase service | E127: $/request | F127: =Inputs_Prices!O158 -> 1400.88 | G127: =Inputs_Prices!P38 -> 1434.81 | H127: =Inputs_Prices!Q38 -> 1481.63 | I127: =Inputs_Prices!R38 -> 1532.31 | J127: =Inputs_Prices!S38 -> 1584.6
D128: Standard temporary builder’s connection | E128: $/request | F128: =Inputs_Prices!O159 -> 657.68 | G128: =Inputs_Prices!P39 -> 673.61 | H128: =Inputs_Prices!Q39 -> 695.59 | I128: =Inputs_Prices!R39 -> 719.39 | J128: =Inputs_Prices!S39 -> 743.94
D129: Temporary disconnection and reconnection - no dismantling | E129: $/request | F129: =Inputs_Prices!O160 -> 286.07 | G129: =Inputs_Prices!P40 -> 293 | H129: =Inputs_Prices!Q40 -> 302.56 | I129: =Inputs_Prices!R40 -> 312.91 | J129: =Inputs_Prices!S40 -> 323.59
D130: Complex disconnection | E130: $/request | F130: =Inputs_Prices!O161 -> 312.62 | G130: =Inputs_Prices!P41 -> 320.19 | H130: =Inputs_Prices!Q41 -> 330.64 | I130: =Inputs_Prices!R41 -> 341.95 | J130: =Inputs_Prices!S41 -> 353.62
D131: Wasted visit fee | E131: $/request | F131: =Inputs_Prices!O162 -> 153.36 | G131: =Inputs_Prices!P42 -> 157.07 | H131: =Inputs_Prices!Q42 -> 162.2 | I131: =Inputs_Prices!R42 -> 167.75 | J131: =Inputs_Prices!S42 -> 173.47
D132: Special meter test | E132: $/request | F132: =Inputs_Prices!O163 -> 299.35 | G132: =Inputs_Prices!P43 -> 306.6 | H132: =Inputs_Prices!Q43 -> 316.61 | I132: =Inputs_Prices!R43 -> 327.44 | J132: =Inputs_Prices!S43 -> 338.61
D133: Exchange or replace meter – three phase | E133: $/request | F133: =Inputs_Prices!O164 -> 660.39 | G133: =Inputs_Prices!P44 -> 676.38 | H133: =Inputs_Prices!Q44 -> 698.45 | I133: =Inputs_Prices!R44 -> 722.34 | J133: =Inputs_Prices!S44 -> 746.99
D134: Exchange or replace meter - single phase | E134: $/request | F134: =Inputs_Prices!O165 -> 552.87 | G134: =Inputs_Prices!P45 -> 566.26 | H134: =Inputs_Prices!Q45 -> 584.74 | I134: =Inputs_Prices!R45 -> 604.74 | J134: =Inputs_Prices!S45 -> 625.38
D135: Relocation of meter | E135: $/request | F135: =Inputs_Prices!O166 -> 312.62 | G135: =Inputs_Prices!P46 -> 320.19 | H135: =Inputs_Prices!Q46 -> 330.64 | I135: =Inputs_Prices!R46 -> 341.95 | J135: =Inputs_Prices!S46 -> 353.62
... D149: Class 1 & 2 PV service | E149: $/request | F149: =Inputs_Prices!O180 -> 87.19 | G149: =Inputs_Prices!P60 -> 89.3 | H149: =Inputs_Prices!Q60 -> 92.21 | I149: =Inputs_Prices!R60 -> 95.36 | J149: =Inputs_Prices!S60 -> 98.61
B152: End

Sheet Lookup
A1: =IF(SUM($A6:$A162)>0,1,0) -> 0 | B1: Model Lookups
B2: =Title_Msg -> No Errors Found
B3: =TOC!B1 -> Table of Contents
B4: =Model_Name -> ACS Pricing Model - Power and Water Corporation
B6: Model Settings
C8: Periodicity Inputs
D10: Model Start Date | E10: 41821
D11: Base Year | E11: 2018
C13: Time Series Headings
B15: Period Start Date | J15: =IF(J17=1,Model_Start_Date,I16+1) -> 41821 | K15: =IF(K17=1,Model_Start_Date,J16+1) -> 42186 | L15: =IF(L17=1,Model_Start_Date,K16+1) -> 42552 | M15: =IF(M17=1,Model_Start_Date,L16+1) -> 42917 | N15: =IF(N17=1,Model_Start_Date,M16+1) -> 43282 | O15: =IF(O17=1,Model_Start_Date,N16+1) -> 43647 | P15: =IF(P17=1,Model_Start_Date,O16+1) -> 44013 | Q15: =IF(Q17=1,Model_Start_Date,P16+1) -> 44378 | ... S15: =IF(S17=1,Model_Start_Date,R16+1) -> 45108
B16: Period End Date | J16: =EOMONTH(J15,Mths_In_Yr-1) -> 42185 | K16: =EOMONTH(K15,Mths_In_Yr-1) -> 42551 | L16: =EOMONTH(L15,Mths_In_Yr-1) -> 42916 | M16: =EOMONTH(M15,Mths_In_Yr-1) -> 43281 | N16: =EOMONTH(N15,Mths_In_Yr-1) -> 43646 | O16: =EOMONTH(O15,Mths_In_Yr-1) -> 44012 | P16: =EOMONTH(P15,Mths_In_Yr-1) -> 44377 | Q16: =EOMONTH(Q15,Mths_In_Yr-1) -> 44742 | ... S16: =EOMONTH(S15,Mths_In_Yr-1) -> 45473
B17: Period Counter | J17: =N(I17)+1 -> 1 | K17: =N(J17)+1 -> 2 | L17: =N(K17)+1 -> 3 | M17: =N(L17)+1 -> 4 | N17: =N(M17)+1 -> 5 | O17: =N(N17)+1 -> 6 | P17: =N(O17)+1 -> 7 | Q17: =N(P17)+1 -> 8 | ... S17: =N(R17)+1 -> 10
B18: Year | J18: =YEAR(J16) -> 2015 | K18: =YEAR(K16) -> 2016 | L18: =YEAR(L16) -> 2017 | M18: =YEAR(M16) -> 2018 | N18: =YEAR(N16) -> 2019 | O18: =YEAR(O16) -> 2020 | P18: =YEAR(P16) -> 2021 | Q18: =YEAR(Q16) -> 2022 | ... S18: =YEAR(S16) -> 2024
B19: Days In Year | J19: =J16-J15+1 -> 365 | K19: =K16-K15+1 -> 366 | L19: =L16-L15+1 -> 365 | M19: =M16-M15+1 -> 365 | N19: =N16-N15+1 -> 365 | O19: =O16-O15+1 -> 366 | P19: =P16-P15+1 -> 365 | Q19: =Q16-Q15+1 -> 365 | ... S19: =S16-S15+1 -> 366
B20: FY | E20: Source | F20: Unit | G20: Basis | H20: Timing | J20: ="FY"&RIGHT(J18,2) -> FY15 | K20: ="FY"&RIGHT(K18,2) -> FY16 | L20: ="FY"&RIGHT(L18,2) -> FY17 | M20: ="FY"&RIGHT(M18,2) -> FY18 | N20: ="FY"&RIGHT(N18,2) -> FY19 | O20: ="FY"&RIGHT(O18,2) -> FY20 | P20: ="FY"&RIGHT(P18,2) -> FY21 | Q20: ="FY"&RIGHT(Q18,2) -> FY22 | ... S20: ="FY"&RIGHT(S18,2) -> FY24
B22: Model Lookups
C24: General Model Constant | E24: Name
D26: 1 | E26: Mths_In_Mth
D27: 3 | E27: Mths_In_Qtr
D28: 4 | E28: Qtrs_In_Yr
D29: 12 | E29: Mths_In_Yr
D30: 7 | E30: Days_In_Wk
D31: 365 | E31: Days_In_Yr
D32: 0.5 | E32: Half
D33: 0.01 | E33: Cents_to_Dollars
D34: 0.001 | E34: Dollars_to_Thousands
D35: Ok | E35: Ok
D36: N/A | E36: NA
D37: Error | E37: Error
C39: General Model Constant | E39: Name
E40: Yes_No
D41: Yes | E41: Yes
D42: No | E42: No
C44: Units | E44: Name
E45: LU_Units
D46: Percent | E46: Percent
D47: Dollars | E47: Dollars
D48: $Millions | E48: Millions
D49: $000's | E49: Thousands
D50: Factor | E50: Factor
D51: Number | E51: Number
D52: ¢/day/NMI | E52: =NA -> N/A
D53: $/month/meter | E53: =NA -> N/A
D54: $/day/per NMI | E54: =NA -> N/A
D55: ¢/kWh | E55: =NA -> N/A
D56: $/kVA | E56: =NA -> N/A
D57: $/Year/Meter | E57: =NA -> N/A
D58: $/Request | E58: =NA -> N/A
D59: $/Hour | E59: =NA -> N/A
D60: NMI-days | E60: =NA -> N/A
D61: Meter-month | E61: =NA -> N/A
D62: kWh | E62: =NA -> N/A
D63: kVA | E63: =NA -> N/A
D64: NMI | E64: =NA -> N/A
D65: Km | E65: Kilometres
D66: =NA -> N/A | E66: Not Applicable
C68: Basis | E68: Name
E69: LU_Basis
D70: Real $2018 | E70: Real2018
D71: Real $2019 | E71: Real2019
D72: Real $2020 | E72: Real2020
D73: Real
D74: =NA -> N/A | E74: Not Applicable
D75: Nominal | E75: Nominal
C77: Timing | F77: Name
D78: LU_Timing | E78: LU_Timing_Value
D79: Start year | E79: 0 | F79: Start_year
D80: Mid year | E80: 0.5 | F80: Mid_year
D81: End year | E81: 1 | F81: End_year
D82: =NA -> N/A | E82: =NA -> N/A
C84: Revenue Input Type | E84: Name
E85: LU_Revenue_Input
D86: Actual
D87: Estimate
D88: No Input | E88: No_Input
C91: Client Lookups
C93: Metering Services | E93: Name
E94: LU_Metering_Services
D95: 1 Phase Meters (including Prepayment)
D96: 3 Phase Meters
D97: Dedicated CT and VT meters
C100: Fee Based Services | E100: Name
E101: LU_Fee_Based_Services
D102: Disconnection (and final read)
D103: Reconnection
D104: Reconnection - after hours
D105: Temporary disconnection and reconnection - physical dismantling
D106: Provision of 3 phase service
D107: Standard temporary builder’s connection
D108: Temporary disconnection and reconnection - no dismantling
D109: Complex disconnection
D110: Wasted visit fee
D111: Special meter test
D112: Exchange or replace meter – three phase
D113: Exchange or replace meter - single phase
... D128: Class 1 & 2 PV service
C131: Quoted Services | E131: Name
E132: LU_Quoted_Services
D133: Design related services
D134: Connection applications
...

Sheet Checks
B1: Checks
B2: =Title_Msg -> No Errors Found
B3: =TOC!B1 -> Table of Contents
B4: =Model_Name -> ACS Pricing Model - Power and Water Corporation
B6: Model Title Message
D8: Error Message | H8: =IF(H21=0,"No Errors Found","Errors Found") -> No Errors Found
D9: Alert Message
D10: Model Message | H10: =H8&IF(H9="","",", " &H9) -> No Errors Found
B12: Model Checks
C14: Error Checks
D16: =Inputs_Prices!$B$1 -> Inputs - Prices | H16: =Inputs_Prices!$A$1 -> 0
D17: =Calculations_Price_Caps!$B$1 -> Calculation - Price Caps | H17: =Calculations_Price_Caps!$A$1 -> 0
D18: =Output_Compliance!$B$1 -> Output - Compliance | H18: =Output_Compliance!$A$1 -> 0
D19: =Output_Pricing_Proposal!$B$1 -> Output - Pricing Proposal | H19: =Output_Pricing_Proposal!$A$1 -> 0
C21: Total Errors | H21: =IF(SUM($H$16:$H$19)>0,1,0) -> 0
B23: End
